Workbook
Name LucroLiquido: ALLCOOK!#REF!
Name LucroLiquido: ESPECIARYA!#REF!
Name LucroLiquido: PALATO!#REF!
Name LucroLiquido: #REF!

Sheet MANUAL
C4: Manual
D5: 1 | E5: Relatório de Movimento | G5: Cadastro de Usuário
D6: 2 | E6: Verificara se o final do Mês é o inicial do seguinte
D7: 3

Sheet PALATO
B2: =G42+M42+T42+AA42 -> 14869988 | C2: JANEIRO | I2: FEVEREIRO | P2: MARÇO | W2: ABRIL | AD2: MAIO | AK2: JUNHO | AR2: JULHO | AY2: AGOSTO | BF2: SETEMBRO | BM2: OUTUBRO | BT2: NOVEMBRO | CA2: DEZEMBRO | CH2: 2026
B3: DEMONSTRAÇÃO FINANCEIRA | C3: ESPECIARYA | E3: ALL COOK | G3: PALATO | I3: ESPECIARYA | K3: ALL COOK | M3: PALATO | O3: Δ | P3: ESPECIARYA | R3: ALL COOK | T3: PALATO | V3: Δ | W3: ESPECIARYA | Y3: ALL COOK | AA3: PALATO | AC3: Δ | AD3: ESPECIARYA | AF3: ALL COOK | AH3: PALATO | AJ3: Δ | AK3: ESPECIARYA | AM3: ALL COOK | AO3: PALATO | AQ3: Δ | AR3: ESPECIARYA | AT3: ALL COOK | AV3: PALATO | AX3: Δ | AY3: ESPECIARYA | BA3: ALL COOK | BC3: PALATO | BE3: Δ | BF3: ESPECIARYA | BH3: ALL COOK | BJ3: PALATO | BL3: Δ | BM3: ESPECIARYA | BO3: ALL COOK | BQ3: PALATO | BS3: Δ | BT3: ESPECIARYA | BV3: ALL COOK | BX3: PALATO | BZ3: Δ | CA3: ESPECIARYA | CC3: ALL COOK | CE3: PALATO | CG3: Δ | CH3: ESPECIARYA | CJ3: ALL COOK | CL3: PALATO
B4: Vendas Dinheiro | C4: =SUMIF('MVTO E'!$C$3:$C$240,"Vda_Din",'MVTO E'!$G$3:$G$240)-SUMIF('MVTO E'!$C$3:$C$240,"Vda_S_Din",'MVTO E'!$G$3:$G$240) -> 1612193.8 | D4: =C4/$C$10 -> 0.04900135 | E4: =SUMIF('MVTO A'!$C$3:$C$184,"Vda_Din",'MVTO A'!$G$3:$G$184)-SUMIF('MVTO A'!$C$3:$C$184,"Vda_S_Din",'MVTO A'!$G$3:$G$184) -> 0 | F4: =E4/$E$10 -> 0 | G4: =C4+E4 -> 1612193.8 | H4: =G4/$G$10 -> 0.043746924 | I4: =SUMIF('MVTO E'!$C$3:$C$240,"Vda_Din",'MVTO E'!$H$3:$H$240)-SUMIF('MVTO E'!$C$3:$C$240,"Vda_S_Din",'MVTO E'!$H$3:$H$240) -> 1483685.4 | J4: =I4/$I$10 -> 0.069886187 | K4: =SUMIF('MVTO A'!$C$3:$C$184,"Vda_Din",'MVTO A'!$H$3:$H$184)-SUMIF('MVTO A'!$C$3:$C$184,"Vda_S_Din",'MVTO A'!$H$3:$H$184) -> 0 | L4: =K4/$K$10 -> 0 | M4: =I4+K4 -> 1483685.4 | N4: =M4/$M$10 -> 0.060191888 | O4: =M4-G4 -> -128508.45 | P4: =SUMIF('MVTO E'!$C$3:$C$240,"Vda_Din",'MVTO E'!$I$3:$I$240)-SUMIF('MVTO E'!$C$3:$C$240,"Vda_S_Din",'MVTO E'!$I$3:$I$240) -> 1481071.3 | Q4: =P4/$I$10 -> 0.069763058 | R4: =SUMIF('MVTO A'!$C$3:$C$184,"Vda_Din",'MVTO A'!$I$3:$I$184)-SUMIF('MVTO A'!$C$3:$C$184,"Vda_S_Din",'MVTO A'!$I$3:$I$184) -> 0 | S4: =R4/$K$10 -> 0 | T4: =P4+R4 -> 1481071.3 | U4: =T4/$T$10 -> 0.053939707 | V4: =T4-M4 -> -2614.04 | W4: =SUMIF('MVTO E'!$C$3:$C$240,"Vda_Din",'MVTO E'!$J$3:$J$240)-SUMIF('MVTO E'!$C$3:$C$240,"Vda_S_Din",'MVTO E'!$J$3:$J$240) -> 1430187.4 | X4: =W4/$I$10 -> 0.067366265 | Y4: =SUMIF('MVTO A'!$C$3:$C$184,"Vda_Din",'MVTO A'!$J$3:$J$184)-SUMIF('MVTO A'!$C$3:$C$184,"Vda_S_Din",'MVTO A'!$J$3:$J$184) -> 0 | Z4: =Y4/$K$10 -> 0 | AA4: =W4+Y4 -> 1430187.4 | AB4: =AA4/$AA$10 -> 0.056404765 | AC4: =AA4-T4 -> -50883.96 | AD4: =SUMIF('MVTO E'!$C$3:$C$240,"Vda_Din",'MVTO E'!$K$3:$K$240)-SUMIF('MVTO E'!$C$3:$C$240,"Vda_S_Din",'MVTO E'!$K$3:$K$240) -> 0 | AE4: =AD4/$I$10 -> 0 | AF4: =SUMIF('MVTO A'!$C$3:$C$184,"Vda_Din",'MVTO A'!$K$3:$K$184)-SUMIF('MVTO A'!$C$3:$C$184,"Vda_S_Din",'MVTO A'!$K$3:$K$184) -> 0 | AG4: =AF4/$K$10 -> 0 | AH4: =AD4+AF4 -> 0 | AI4: =AH4/$AA$10 -> 0 | AJ4: =AH4-AA4 -> -1430187.4 | AK4: =SUMIF('MVTO E'!$C$3:$C$240,"Vda_Din",'MVTO E'!$L$3:$L$240)-SUMIF('MVTO E'!$C$3:$C$240,"Vda_S_Din",'MVTO E'!$L$3:$L$240) -> 0 | AL4: =AK4/$I$10 -> 0 | AM4: =SUMIF('MVTO A'!$C$3:$C$184,"Vda_Din",'MVTO A'!$L$3:$L$184)-SUMIF('MVTO A'!$C$3:$C$184,"Vda_S_Din",'MVTO A'!$L$3:$L$184) -> 0 | AN4: =AM4/$K$10 -> 0 | AO4: =AK4+AM4 -> 0 | AP4: =AO4/$AA$10 -> 0 | AQ4: =AO4-AH4 -> 0 | AR4: =SUMIF('MVTO E'!$C$3:$C$240,"Vda_Din",'MVTO E'!$M$3:$M$240)-SUMIF('MVTO E'!$C$3:$C$240,"Vda_S_Din",'MVTO E'!$M$3:$M$240) -> 0 | AS4: =AR4/$I$10 -> 0 | AT4: =SUMIF('MVTO A'!$C$3:$C$184,"Vda_Din",'MVTO A'!$M$3:$M$184)-SUMIF('MVTO A'!$C$3:$C$184,"Vda_S_Din",'MVTO A'!$M$3:$M$184) -> 0 | AU4: =AT4/$K$10 -> 0 | AV4: =AR4+AT4 -> 0 | AW4: =AV4/$AA$10 -> 0 | AX4: =AV4-AO4 -> 0 | AY4: =SUMIF('MVTO E'!$C$3:$C$240,"Vda_Din",'MVTO E'!$N$3:$N$240)-SUMIF('MVTO E'!$C$3:$C$240,"Vda_S_Din",'MVTO E'!$N$3:$N$240) -> 0 | AZ4: =AY4/$I$10 -> 0 | BA4: =SUMIF('MVTO A'!$C$3:$C$184,"Vda_Din",'MVTO A'!$N$3:$N$184)-SUMIF('MVTO A'!$C$3:$C$184,"Vda_S_Din",'MVTO A'!$N$3:$N$184) -> 0 | BB4: =BA4/$K$10 -> 0 | BC4: =AY4+BA4 -> 0 | BD4: =BC4/$AA$10 -> 0 | BE4: =BC4-AV4 -> 0 | BF4: =SUMIF('MVTO E'!$C$3:$C$240,"Vda_Din",'MVTO E'!$O$3:$O$240)-SUMIF('MVTO E'!$C$3:$C$240,"Vda_S_Din",'MVTO E'!$O$3:$O$240) -> 0 | BG4: =BF4/$I$10 -> 0 | BH4: =SUMIF('MVTO A'!$C$3:$C$184,"Vda_Din",'MVTO A'!$O$3:$O$184)-SUMIF('MVTO A'!$C$3:$C$184,"Vda_S_Din",'MVTO A'!$O$3:$O$184) -> 0 | BI4: =BH4/$K$10 -> 0 | BJ4: =BF4+BH4 -> 0 | BK4: =BJ4/$AA$10 -> 0 | BL4: =BJ4-BC4 -> 0 | BM4: =SUMIF('MVTO E'!$C$3:$C$240,"Vda_Din",'MVTO E'!$P$3:$P$240)-SUMIF('MVTO E'!$C$3:$C$240,"Vda_S_Din",'MVTO E'!$P$3:$P$240) -> 0 | BN4: =BM4/$I$10 -> 0 | BO4: =SUMIF('MVTO A'!$C$3:$C$184,"Vda_Din",'MVTO A'!$P$3:$P$184)-SUMIF('MVTO A'!$C$3:$C$184,"Vda_S_Din",'MVTO A'!$P$3:$P$184) -> 0 | BP4: =BO4/$K$10 -> 0 | BQ4: =BM4+BO4 -> 0 | BR4: =BQ4/$AA$10 -> 0 | BS4: =BQ4-BJ4 -> 0 | BT4: =SUMIF('MVTO E'!$C$3:$C$240,"Vda_Din",'MVTO E'!$Q$3:$Q$240)-SUMIF('MVTO E'!$C$3:$C$240,"Vda_S_Din",'MVTO E'!$Q$3:$Q$240) -> 0 | BU4: =BT4/$I$10 -> 0 | BV4: =SUMIF('MVTO A'!$C$3:$C$184,"Vda_Din",'MVTO A'!$Q$3:$Q$184)-SUMIF('MVTO A'!$C$3:$C$184,"Vda_S_Din",'MVTO A'!$Q$3:$Q$184) -> 0 | BW4: =BV4/$K$10 -> 0 | BX4: =BT4+BV4 -> 0 | BY4: =BX4/$AA$10 -> 0 | BZ4: =BX4-BQ4 -> 0 | CA4: =SUMIF('MVTO E'!$C$3:$C$240,"Vda_Din",'MVTO E'!$R$3:$R$240)-SUMIF('MVTO E'!$C$3:$C$240,"Vda_S_Din",'MVTO E'!$R$3:$R$240) -> 0 | CB4: =CA4/$I$10 -> 0 | CC4: =SUMIF('MVTO A'!$C$3:$C$184,"Vda_Din",'MVTO A'!$R$3:$R$184)-SUMIF('MVTO A'!$C$3:$C$184,"Vda_S_Din",'MVTO A'!$R$3:$R$184) -> 0 | CD4: =CC4/$K$10 -> 0 | CE4: =CA4+CC4 -> 0 | CF4: =CE4/$AA$10 -> 0 | CG4: =CE4-BX4 -> 0 | CH4: =SUM(C4,I4,P4,W4,AD4,AK4,AR4,AY4,BF4,BM4,BT4,CA4) -> 6007137.8 | CI4: =CH4/$CH$10 -> 0.059988986 | CJ4: =SUM(E4,K4,R4,Y4,AF4,AM4,AT4,BA4,BH4,BO4,BV4,CC4) -> 0 | CK4: =CJ4/$CJ$10 -> 0 | CL4: =SUM(G4,M4,T4,AA4,AH4,AO4,AV4,BC4,BJ4,BQ4,BX4,CE4) -> 6007137.8 | CM4: =CL4/$CL$10 -> 0.052548675
B5: Vendas - PIX | C5: =SUMIF('MVTO E'!$C$3:$C$240,"Vda_PIX",'MVTO E'!$G$3:$G$240)-SUMIF('MVTO E'!$C$3:$C$240,"Vda_S_PIX",'MVTO E'!$G$3:$G$240) -> 27676.12 | D5: =C5/$C$10 -> 0.00084119369 | E5: =SUMIF('MVTO A'!$C$3:$C$184,"Vda_PIX",'MVTO A'!$G$3:$G$184)-SUMIF('MVTO A'!$C$3:$C$184,"Vda_S_PIX",'MVTO A'!$G$3:$G$184) -> 230404.64 | F5: =E5/$E$10 -> 0.058304786 | G5: =C5+E5 -> 258080.76 | H5: =G5/$G$10 -> 0.0070030286 | I5: =SUMIF('MVTO E'!$C$3:$C$240,"Vda_PIX",'MVTO E'!$H$3:$H$240)-SUMIF('MVTO E'!$C$3:$C$240,"Vda_S_PIX",'MVTO E'!$H$3:$H$240) -> 19035.57 | J5: =I5/$I$10 -> 0.00089663445 | K5: =SUMIF('MVTO A'!$C$3:$C$184,"Vda_PIX",'MVTO A'!$H$3:$H$184)-SUMIF('MVTO A'!$C$3:$C$184,"Vda_S_PIX",'MVTO A'!$H$3:$H$184) -> 185954.55 | L5: =K5/$K$10 -> 0.054384848 | M5: =I5+K5 -> 204990.12 | N5: =M5/$M$10 -> 0.0083162797 | O5: =M5-G5 -> -53090.64 | P5: =SUMIF('MVTO E'!$C$3:$C$240,"Vda_PIX",'MVTO E'!$I$3:$I$240)-SUMIF('MVTO E'!$C$3:$C$240,"Vda_S_PIX",'MVTO E'!$I$3:$I$240) -> 19965.39 | Q5: =P5/$I$10 -> 0.00094043186 | R5: =SUMIF('MVTO A'!$C$3:$C$184,"Vda_PIX",'MVTO A'!$I$3:$I$184)-SUMIF('MVTO A'!$C$3:$C$184,"Vda_S_PIX",'MVTO A'!$I$3:$I$184) -> 208795.25 | S5: =R5/$K$10 -> 0.061064911 | T5: =P5+R5 -> 228760.64 | U5: =T5/$T$10 -> 0.0083313219 | V5: =T5-M5 -> 23770.52 | W5: =SUMIF('MVTO E'!$C$3:$C$240,"Vda_PIX",'MVTO E'!$J$3:$J$240)-SUMIF('MVTO E'!$C$3:$C$240,"Vda_S_PIX",'MVTO E'!$J$3:$J$240) -> 34126.54 | X5: =W5/$I$10 -> 0.001607466 | Y5: =SUMIF('MVTO A'!$C$3:$C$184,"Vda_PIX",'MVTO A'!$J$3:$J$184)-SUMIF('MVTO A'!$C$3:$C$184,"Vda_S_PIX",'MVTO A'!$J$3:$J$184) -> 164338.74 | Z5: =Y5/$K$10 -> 0.048063021 | AA5: =W5+Y5 -> 198465.28 | AB5: =AA5/$AA$10 -> 0.0078272176 | AC5: =AA5-T5 -> -30295.36 | AD5: =SUMIF('MVTO E'!$C$3:$C$240,"Vda_PIX",'MVTO E'!$K$3:$K$240)-SUMIF('MVTO E'!$C$3:$C$240,"Vda_S_PIX",'MVTO E'!$K$3:$K$240) -> 0 | AE5: =AD5/$I$10 -> 0 | AF5: =SUMIF('MVTO A'!$C$3:$C$184,"Vda_PIX",'MVTO A'!$K$3:$K$184)-SUMIF('MVTO A'!$C$3:$C$184,"Vda_S_PIX",'MVTO A'!$K$3:$K$184) -> 0 | AG5: =AF5/$K$10 -> 0 | AH5: =AD5+AF5 -> 0 | AI5: =AH5/$AA$10 -> 0 | AJ5: =AH5-AA5 -> -198465.28 | AK5: =SUMIF('MVTO E'!$C$3:$C$240,"Vda_PIX",'MVTO E'!$L$3:$L$240)-SUMIF('MVTO E'!$C$3:$C$240,"Vda_S_PIX",'MVTO E'!$L$3:$L$240) -> 0 | AL5: =AK5/$I$10 -> 0 | AM5: =SUMIF('MVTO A'!$C$3:$C$184,"Vda_PIX",'MVTO A'!$L$3:$L$184)-SUMIF('MVTO A'!$C$3:$C$184,"Vda_S_PIX",'MVTO A'!$L$3:$L$184) -> 0 | AN5: =AM5/$K$10 -> 0 | AO5: =AK5+AM5 -> 0 | AP5: =AO5/$AA$10 -> 0 | AQ5: =AO5-AH5 -> 0 | AR5: =SUMIF('MVTO E'!$C$3:$C$240,"Vda_PIX",'MVTO E'!$M$3:$M$240)-SUMIF('MVTO E'!$C$3:$C$240,"Vda_S_PIX",'MVTO E'!$M$3:$M$240) -> 0 | AS5: =AR5/$I$10 -> 0 | AT5: =SUMIF('MVTO A'!$C$3:$C$184,"Vda_PIX",'MVTO A'!$M$3:$M$184)-SUMIF('MVTO A'!$C$3:$C$184,"Vda_S_PIX",'MVTO A'!$M$3:$M$184) -> 0 | AU5: =AT5/$K$10 -> 0 | AV5: =AR5+AT5 -> 0 | AW5: =AV5/$AA$10 -> 0 | AX5: =AV5-AO5 -> 0 | AY5: =SUMIF('MVTO E'!$C$3:$C$240,"Vda_PIX",'MVTO E'!$N$3:$N$240)-SUMIF('MVTO E'!$C$3:$C$240,"Vda_S_PIX",'MVTO E'!$N$3:$N$240) -> 0 | AZ5: =AY5/$I$10 -> 0 | BA5: =SUMIF('MVTO A'!$C$3:$C$184,"Vda_PIX",'MVTO A'!$N$3:$N$184)-SUMIF('MVTO A'!$C$3:$C$184,"Vda_S_PIX",'MVTO A'!$N$3:$N$184) -> 0 | BB5: =BA5/$K$10 -> 0 | BC5: =AY5+BA5 -> 0 | BD5: =BC5/$AA$10 -> 0 | BE5: =BC5-AV5 -> 0 | BF5: =SUMIF('MVTO E'!$C$3:$C$240,"Vda_PIX",'MVTO E'!$O$3:$O$240)-SUMIF('MVTO E'!$C$3:$C$240,"Vda_S_PIX",'MVTO E'!$O$3:$O$240) -> 0 | BG5: =BF5/$I$10 -> 0 | BH5: =SUMIF('MVTO A'!$C$3:$C$184,"Vda_PIX",'MVTO A'!$O$3:$O$184)-SUMIF('MVTO A'!$C$3:$C$184,"Vda_S_PIX",'MVTO A'!$O$3:$O$184) -> 0 | BI5: =BH5/$K$10 -> 0 | BJ5: =BF5+BH5 -> 0 | BK5: =BJ5/$AA$10 -> 0 | BL5: =BJ5-BC5 -> 0 | BM5: =SUMIF('MVTO E'!$C$3:$C$240,"Vda_PIX",'MVTO E'!$P$3:$P$240)-SUMIF('MVTO E'!$C$3:$C$240,"Vda_S_PIX",'MVTO E'!$P$3:$P$240) -> 0 | BN5: =BM5/$I$10 -> 0 | BO5: =SUMIF('MVTO A'!$C$3:$C$184,"Vda_PIX",'MVTO A'!$P$3:$P$184)-SUMIF('MVTO A'!$C$3:$C$184,"Vda_S_PIX",'MVTO A'!$P$3:$P$184) -> 0 | BP5: =BO5/$K$10 -> 0 | BQ5: =BM5+BO5 -> 0 | BR5: =BQ5/$AA$10 -> 0 | BS5: =BQ5-BJ5 -> 0 | BT5: =SUMIF('MVTO E'!$C$3:$C$240,"Vda_PIX",'MVTO E'!$Q$3:$Q$240)-SUMIF('MVTO E'!$C$3:$C$240,"Vda_S_PIX",'MVTO E'!$Q$3:$Q$240) -> 0 | BU5: =BT5/$I$10 -> 0 | BV5: =SUMIF('MVTO A'!$C$3:$C$184,"Vda_PIX",'MVTO A'!$Q$3:$Q$184)-SUMIF('MVTO A'!$C$3:$C$184,"Vda_S_PIX",'MVTO A'!$Q$3:$Q$184) -> 0 | BW5: =BV5/$K$10 -> 0 | BX5: =BT5+BV5 -> 0 | BY5: =BX5/$AA$10 -> 0 | BZ5: =BX5-BQ5 -> 0 | CA5: =SUMIF('MVTO E'!$C$3:$C$240,"Vda_PIX",'MVTO E'!$R$3:$R$240)-SUMIF('MVTO E'!$C$3:$C$240,"Vda_S_PIX",'MVTO E'!$R$3:$R$240) -> 0 | CB5: =CA5/$I$10 -> 0 | CC5: =SUMIF('MVTO A'!$C$3:$C$184,"Vda_PIX",'MVTO A'!$R$3:$R$184)-SUMIF('MVTO A'!$C$3:$C$184,"Vda_S_PIX",'MVTO A'!$R$3:$R$184) -> 0 | CD5: =CC5/$K$10 -> 0 | CE5: =CA5+CC5 -> 0 | CF5: =CE5/$AA$10 -> 0 | CG5: =CE5-BX5 -> 0 | CH5: =SUM(C5,I5,P5,W5,AD5,AK5,AR5,AY5,BF5,BM5,BT5,CA5) -> 100803.62 | CI5: =CH5/$CH$10 -> 0.0010066536 | CJ5: =SUM(E5,K5,R5,Y5,AF5,AM5,AT5,BA5,BH5,BO5,BV5,CC5) -> 789493.18 | CK5: =CJ5/$CJ$10 -> 0.055683045 | CL5: =SUM(G5,M5,T5,AA5,AH5,AO5,AV5,BC5,BJ5,BQ5,BX5,CE5) -> 890296.8 | CM5: =CL5/$CL$10 -> 0.0077880545
B6: Vendas - Débito | C6: =SUMIF('MVTO E'!$C$3:$C$240,"Vda_Debito",'MVTO E'!$G$3:$G$240)-SUMIF('MVTO E'!$C$3:$C$240,"Vda_S_Deb",'MVTO E'!$G$3:$G$240) -> 5599965.6 | D6: =C6/$C$10 -> 0.17020651 | E6: =SUMIF('MVTO A'!$C$3:$C$184,"Vda_Debito",'MVTO A'!$G$3:$G$184)-SUMIF('MVTO A'!$C$3:$C$184,"Vda_S_Deb",'MVTO A'!$G$3:$G$184) -> 991436.74 | F6: =E6/$E$10 -> 0.2508869 | G6: =C6+E6 -> 6591402.3 | H6: =G6/$G$10 -> 0.17885788 | I6: =SUMIF('MVTO E'!$C$3:$C$240,"Vda_Debito",'MVTO E'!$H$3:$H$240)-SUMIF('MVTO E'!$C$3:$C$240,"Vda_S_Deb",'MVTO E'!$H$3:$H$240) -> 4567047.7 | J6: =I6/$I$10 -> 0.21512213 | K6: =SUMIF('MVTO A'!$C$3:$C$184,"Vda_Debito",'MVTO A'!$H$3:$H$184)-SUMIF('MVTO A'!$C$3:$C$184,"Vda_S_Deb",'MVTO A'!$H$3:$H$184) -> 776917.09 | L6: =K6/$K$10 -> 0.2272196 | M6: =I6+K6 -> 5343964.8 | N6: =M6/$M$10 -> 0.21680024 | O6: =M6-G6 -> -1247437.5 | P6: =SUMIF('MVTO E'!$C$3:$C$240,"Vda_Debito",'MVTO E'!$I$3:$I$240)-SUMIF('MVTO E'!$C$3:$C$240,"Vda_S_Deb",'MVTO E'!$I$3:$I$240) -> 5183789.5 | Q6: =P6/$I$10 -> 0.24417258 | R6: =SUMIF('MVTO A'!$C$3:$C$184,"Vda_Debito",'MVTO A'!$I$3:$I$184)-SUMIF('MVTO A'!$C$3:$C$184,"Vda_S_Deb",'MVTO A'!$I$3:$I$184) -> 903793.71 | S6: =R6/$K$10 -> 0.26432633 | T6: =P6+R6 -> 6087583.2 | U6: =T6/$T$10 -> 0.22170604 | V6: =T6-M6 -> 743618.37 | W6: =SUMIF('MVTO E'!$C$3:$C$240,"Vda_Debito",'MVTO E'!$J$3:$J$240)-SUMIF('MVTO E'!$C$3:$C$240,"Vda_S_Deb",'MVTO E'!$J$3:$J$240) -> 4670126.4 | X6: =W6/$I$10 -> 0.21997746 | Y6: =SUMIF('MVTO A'!$C$3:$C$184,"Vda_Debito",'MVTO A'!$J$3:$J$184)-SUMIF('MVTO A'!$C$3:$C$184,"Vda_S_Deb",'MVTO A'!$J$3:$J$184) -> 770320.33 | Z6: =Y6/$K$10 -> 0.22529029 | AA6: =W6+Y6 -> 5440446.7 | AB6: =AA6/$AA$10 -> 0.21456428 | AC6: =AA6-T6 -> -647136.45 | AD6: =SUMIF('MVTO E'!$C$3:$C$240,"Vda_Debito",'MVTO E'!$K$3:$K$240)-SUMIF('MVTO E'!$C$3:$C$240,"Vda_S_Deb",'MVTO E'!$K$3:$K$240) -> 0 | AE6: =AD6/$I$10 -> 0 | AF6: =SUMIF('MVTO A'!$C$3:$C$184,"Vda_Debito",'MVTO A'!$K$3:$K$184)-SUMIF('MVTO A'!$C$3:$C$184,"Vda_S_Deb",'MVTO A'!$K$3:$K$184) -> 0 | AG6: =AF6/$K$10 -> 0 | AH6: =AD6+AF6 -> 0 | AI6: =AH6/$AA$10 -> 0 | AJ6: =AH6-AA6 -> -5440446.7 | AK6: =SUMIF('MVTO E'!$C$3:$C$240,"Vda_Debito",'MVTO E'!$L$3:$L$240)-SUMIF('MVTO E'!$C$3:$C$240,"Vda_S_Deb",'MVTO E'!$L$3:$L$240) -> 0 | AL6: =AK6/$I$10 -> 0 | AM6: =SUMIF('MVTO A'!$C$3:$C$184,"Vda_Debito",'MVTO A'!$L$3:$L$184)-SUMIF('MVTO A'!$C$3:$C$184,"Vda_S_Deb",'MVTO A'!$L$3:$L$184) -> 0 | AN6: =AM6/$K$10 -> 0 | AO6: =AK6+AM6 -> 0 | AP6: =AO6/$AA$10 -> 0 | AQ6: =AO6-AH6 -> 0 | AR6: =SUMIF('MVTO E'!$C$3:$C$240,"Vda_Debito",'MVTO E'!$M$3:$M$240)-SUMIF('MVTO E'!$C$3:$C$240,"Vda_S_Deb",'MVTO E'!$M$3:$M$240) -> 0 | AS6: =AR6/$I$10 -> 0 | AT6: =SUMIF('MVTO A'!$C$3:$C$184,"Vda_Debito",'MVTO A'!$M$3:$M$184)-SUMIF('MVTO A'!$C$3:$C$184,"Vda_S_Deb",'MVTO A'!$M$3:$M$184) -> 0 | AU6: =AT6/$K$10 -> 0 | AV6: =AR6+AT6 -> 0 | AW6: =AV6/$AA$10 -> 0 | AX6: =AV6-AO6 -> 0 | AY6: =SUMIF('MVTO E'!$C$3:$C$240,"Vda_Debito",'MVTO E'!$N$3:$N$240)-SUMIF('MVTO E'!$C$3:$C$240,"Vda_S_Deb",'MVTO E'!$N$3:$N$240) -> 0 | AZ6: =AY6/$I$10 -> 0 | BA6: =SUMIF('MVTO A'!$C$3:$C$184,"Vda_Debito",'MVTO A'!$N$3:$N$184)-SUMIF('MVTO A'!$C$3:$C$184,"Vda_S_Deb",'MVTO A'!$N$3:$N$184) -> 0 | BB6: =BA6/$K$10 -> 0 | BC6: =AY6+BA6 -> 0 | BD6: =BC6/$AA$10 -> 0 | BE6: =BC6-AV6 -> 0 | BF6: =SUMIF('MVTO E'!$C$3:$C$240,"Vda_Debito",'MVTO E'!$O$3:$O$240)-SUMIF('MVTO E'!$C$3:$C$240,"Vda_S_Deb",'MVTO E'!$O$3:$O$240) -> 0 | BG6: =BF6/$I$10 -> 0 | BH6: =SUMIF('MVTO A'!$C$3:$C$184,"Vda_Debito",'MVTO A'!$O$3:$O$184)-SUMIF('MVTO A'!$C$3:$C$184,"Vda_S_Deb",'MVTO A'!$O$3:$O$184) -> 0 | BI6: =BH6/$K$10 -> 0 | BJ6: =BF6+BH6 -> 0 | BK6: =BJ6/$AA$10 -> 0 | BL6: =BJ6-BC6 -> 0 | BM6: =SUMIF('MVTO E'!$C$3:$C$240,"Vda_Debito",'MVTO E'!$P$3:$P$240)-SUMIF('MVTO E'!$C$3:$C$240,"Vda_S_Deb",'MVTO E'!$P$3:$P$240) -> 0 | BN6: =BM6/$I$10 -> 0 | BO6: =SUMIF('MVTO A'!$C$3:$C$184,"Vda_Debito",'MVTO A'!$P$3:$P$184)-SUMIF('MVTO A'!$C$3:$C$184,"Vda_S_Deb",'MVTO A'!$P$3:$P$184) -> 0 | BP6: =BO6/$K$10 -> 0 | BQ6: =BM6+BO6 -> 0 | BR6: =BQ6/$AA$10 -> 0 | BS6: =BQ6-BJ6 -> 0 | BT6: =SUMIF('MVTO E'!$C$3:$C$240,"Vda_Debito",'MVTO E'!$Q$3:$Q$240)-SUMIF('MVTO E'!$C$3:$C$240,"Vda_S_Deb",'MVTO E'!$Q$3:$Q$240) -> 0 | BU6: =BT6/$I$10 -> 0 | BV6: =SUMIF('MVTO A'!$C$3:$C$184,"Vda_Debito",'MVTO A'!$Q$3:$Q$184)-SUMIF('MVTO A'!$C$3:$C$184,"Vda_S_Deb",'MVTO A'!$Q$3:$Q$184) -> 0 | BW6: =BV6/$K$10 -> 0 | BX6: =BT6+BV6 -> 0 | BY6: =BX6/$AA$10 -> 0 | BZ6: =BX6-BQ6 -> 0 | CA6: =SUMIF('MVTO E'!$C$3:$C$240,"Vda_Debito",'MVTO E'!$R$3:$R$240)-SUMIF('MVTO E'!$C$3:$C$240,"Vda_S_Deb",'MVTO E'!$R$3:$R$240) -> 0 | CB6: =CA6/$I$10 -> 0 | CC6: =SUMIF('MVTO A'!$C$3:$C$184,"Vda_Debito",'MVTO A'!$R$3:$R$184)-SUMIF('MVTO A'!$C$3:$C$184,"Vda_S_Deb",'MVTO A'!$R$3:$R$184) -> 0 | CD6: =CC6/$K$10 -> 0 | CE6: =CA6+CC6 -> 0 | CF6: =CE6/$AA$10 -> 0 | CG6: =CE6-BX6 -> 0 | CH6: =SUM(C6,I6,P6,W6,AD6,AK6,AR6,AY6,BF6,BM6,BT6,CA6) -> 20020929 | CI6: =CH6/$CH$10 -> 0.19993469 | CJ6: =SUM(E6,K6,R6,Y6,AF6,AM6,AT6,BA6,BH6,BO6,BV6,CC6) -> 3442467.9 | CK6: =CJ6/$CJ$10 -> 0.24279766 | CL6: =SUM(G6,M6,T6,AA6,AH6,AO6,AV6,BC6,BJ6,BQ6,BX6,CE6) -> 23463397 | CM6: =CL6/$CL$10 -> 0.2052509
B7: Vendas - Crédito | C7: =SUMIF('MVTO E'!$C$3:$C$240,"Vda_Credito",'MVTO E'!$G$3:$G$240)-SUMIF('MVTO E'!$C$3:$C$240,"Vda_S_Cre",'MVTO E'!$G$3:$G$240) -> 20084101 | D7: =C7/$C$10 -> 0.61044029 | E7: =SUMIF('MVTO A'!$C$3:$C$184,"Vda_Credito",'MVTO A'!$G$3:$G$184)-SUMIF('MVTO A'!$C$3:$C$184,"Vda_S_Cre",'MVTO A'!$G$3:$G$184) -> 2297155.8 | F7: =E7/$E$10 -> 0.58130416 | G7: =C7+E7 -> 22381256 | H7: =G7/$G$10 -> 0.60731601 | I7: =SUMIF('MVTO E'!$C$3:$C$240,"Vda_Credito",'MVTO E'!$H$3:$H$240)-SUMIF('MVTO E'!$C$3:$C$240,"Vda_S_Cre",'MVTO E'!$H$3:$H$240) -> 10918480 | J7: =I7/$I$10 -> 0.51429433 | K7: =SUMIF('MVTO A'!$C$3:$C$184,"Vda_Credito",'MVTO A'!$H$3:$H$184)-SUMIF('MVTO A'!$C$3:$C$184,"Vda_S_Cre",'MVTO A'!$H$3:$H$184) -> 2042355.7 | L7: =K7/$K$10 -> 0.59731373 | M7: =I7+K7 -> 12960836 | N7: =M7/$M$10 -> 0.52581041 | O7: =M7-G7 -> -9420420.3 | P7: =SUMIF('MVTO E'!$C$3:$C$240,"Vda_Credito",'MVTO E'!$I$3:$I$240)-SUMIF('MVTO E'!$C$3:$C$240,"Vda_S_Cre",'MVTO E'!$I$3:$I$240) -> 12259326 | Q7: =P7/$I$10 -> 0.57745234 | R7: =SUMIF('MVTO A'!$C$3:$C$184,"Vda_Credito",'MVTO A'!$I$3:$I$184)-SUMIF('MVTO A'!$C$3:$C$184,"Vda_S_Cre",'MVTO A'!$I$3:$I$184) -> 2074024.7 | S7: =R7/$K$10 -> 0.60657573 | T7: =P7+R7 -> 14333351 | U7: =T7/$T$10 -> 0.52201184 | V7: =T7-M7 -> 1372515 | W7: =SUMIF('MVTO E'!$C$3:$C$240,"Vda_Credito",'MVTO E'!$J$3:$J$240)-SUMIF('MVTO E'!$C$3:$C$240,"Vda_S_Cre",'MVTO E'!$J$3:$J$240) -> 10963833 | X7: =W7/$I$10 -> 0.51643056 | Y7: =SUMIF('MVTO A'!$C$3:$C$184,"Vda_Credito",'MVTO A'!$J$3:$J$184)-SUMIF('MVTO A'!$C$3:$C$184,"Vda_S_Cre",'MVTO A'!$J$3:$J$184) -> 1957630.4 | Z7: =Y7/$K$10 -> 0.57253469 | AA7: =W7+Y7 -> 12921463 | AB7: =AA7/$AA$10 -> 0.50960603 | AC7: =AA7-T7 -> -1411888 | AD7: =SUMIF('MVTO E'!$C$3:$C$240,"Vda_Credito",'MVTO E'!$K$3:$K$240)-SUMIF('MVTO E'!$C$3:$C$240,"Vda_S_Cre",'MVTO E'!$K$3:$K$240) -> 0 | AE7: =AD7/$I$10 -> 0 | AF7: =SUMIF('MVTO A'!$C$3:$C$184,"Vda_Credito",'MVTO A'!$K$3:$K$184)-SUMIF('MVTO A'!$C$3:$C$184,"Vda_S_Cre",'MVTO A'!$K$3:$K$184) -> 0 | AG7: =AF7/$K$10 -> 0 | AH7: =AD7+AF7 -> 0 | AI7: =AH7/$AA$10 -> 0 | AJ7: =AH7-AA7 -> -12921463 | AK7: =SUMIF('MVTO E'!$C$3:$C$240,"Vda_Credito",'MVTO E'!$L$3:$L$240)-SUMIF('MVTO E'!$C$3:$C$240,"Vda_S_Cre",'MVTO E'!$L$3:$L$240) -> 0 | AL7: =AK7/$I$10 -> 0 | AM7: =SUMIF('MVTO A'!$C$3:$C$184,"Vda_Credito",'MVTO A'!$L$3:$L$184)-SUMIF('MVTO A'!$C$3:$C$184,"Vda_S_Cre",'MVTO A'!$L$3:$L$184) -> 0 | AN7: =AM7/$K$10 -> 0 | AO7: =AK7+AM7 -> 0 | AP7: =AO7/$AA$10 -> 0 | AQ7: =AO7-AH7 -> 0 | AR7: =SUMIF('MVTO E'!$C$3:$C$240,"Vda_Credito",'MVTO E'!$M$3:$M$240)-SUMIF('MVTO E'!$C$3:$C$240,"Vda_S_Cre",'MVTO E'!$M$3:$M$240) -> 0 | AS7: =AR7/$I$10 -> 0 | AT7: =SUMIF('MVTO A'!$C$3:$C$184,"Vda_Credito",'MVTO A'!$M$3:$M$184)-SUMIF('MVTO A'!$C$3:$C$184,"Vda_S_Cre",'MVTO A'!$M$3:$M$184) -> 0 | AU7: =AT7/$K$10 -> 0 | AV7: =AR7+AT7 -> 0 | AW7: =AV7/$AA$10 -> 0 | AX7: =AV7-AO7 -> 0 | AY7: =SUMIF('MVTO E'!$C$3:$C$240,"Vda_Credito",'MVTO E'!$N$3:$N$240)-SUMIF('MVTO E'!$C$3:$C$240,"Vda_S_Cre",'MVTO E'!$N$3:$N$240) -> 0 | AZ7: =AY7/$I$10 -> 0 | BA7: =SUMIF('MVTO A'!$C$3:$C$184,"Vda_Credito",'MVTO A'!$N$3:$N$184)-SUMIF('MVTO A'!$C$3:$C$184,"Vda_S_Cre",'MVTO A'!$N$3:$N$184) -> 0 | BB7: =BA7/$K$10 -> 0 | BC7: =AY7+BA7 -> 0 | BD7: =BC7/$AA$10 -> 0 | BE7: =BC7-AV7 -> 0 | BF7: =SUMIF('MVTO E'!$C$3:$C$240,"Vda_Credito",'MVTO E'!$O$3:$O$240)-SUMIF('MVTO E'!$C$3:$C$240,"Vda_S_Cre",'MVTO E'!$O$3:$O$240) -> 0 | BG7: =BF7/$I$10 -> 0 | BH7: =SUMIF('MVTO A'!$C$3:$C$184,"Vda_Credito",'MVTO A'!$O$3:$O$184)-SUMIF('MVTO A'!$C$3:$C$184,"Vda_S_Cre",'MVTO A'!$O$3:$O$184) -> 0 | BI7: =BH7/$K$10 -> 0 | BJ7: =BF7+BH7 -> 0 | BK7: =BJ7/$AA$10 -> 0 | BL7: =BJ7-BC7 -> 0 | BM7: =SUMIF('MVTO E'!$C$3:$C$240,"Vda_Credito",'MVTO E'!$P$3:$P$240)-SUMIF('MVTO E'!$C$3:$C$240,"Vda_S_Cre",'MVTO E'!$P$3:$P$240) -> 0 | BN7: =BM7/$I$10 -> 0 | BO7: =SUMIF('MVTO A'!$C$3:$C$184,"Vda_Credito",'MVTO A'!$P$3:$P$184)-SUMIF('MVTO A'!$C$3:$C$184,"Vda_S_Cre",'MVTO A'!$P$3:$P$184) -> 0 | BP7: =BO7/$K$10 -> 0 | BQ7: =BM7+BO7 -> 0 | BR7: =BQ7/$AA$10 -> 0 | BS7: =BQ7-BJ7 -> 0 | BT7: =SUMIF('MVTO E'!$C$3:$C$240,"Vda_Credito",'MVTO E'!$Q$3:$Q$240)-SUMIF('MVTO E'!$C$3:$C$240,"Vda_S_Cre",'MVTO E'!$Q$3:$Q$240) -> 0 | BU7: =BT7/$I$10 -> 0 | BV7: =SUMIF('MVTO A'!$C$3:$C$184,"Vda_Credito",'MVTO A'!$Q$3:$Q$184)-SUMIF('MVTO A'!$C$3:$C$184,"Vda_S_Cre",'MVTO A'!$Q$3:$Q$184) -> 0 | BW7: =BV7/$K$10 -> 0 | BX7: =BT7+BV7 -> 0 | BY7: =BX7/$AA$10 -> 0 | BZ7: =BX7-BQ7 -> 0 | CA7: =SUMIF('MVTO E'!$C$3:$C$240,"Vda_Credito",'MVTO E'!$R$3:$R$240)-SUMIF('MVTO E'!$C$3:$C$240,"Vda_S_Cre",'MVTO E'!$R$3:$R$240) -> 0 | CB7: =CA7/$I$10 -> 0 | CC7: =SUMIF('MVTO A'!$C$3:$C$184,"Vda_Credito",'MVTO A'!$R$3:$R$184)-SUMIF('MVTO A'!$C$3:$C$184,"Vda_S_Cre",'MVTO A'!$R$3:$R$184) -> 0 | CD7: =CC7/$K$10 -> 0 | CE7: =CA7+CC7 -> 0 | CF7: =CE7/$AA$10 -> 0 | CG7: =CE7-BX7 -> 0 | CH7: =SUM(C7,I7,P7,W7,AD7,AK7,AR7,AY7,BF7,BM7,BT7,CA7) -> 54225740 | CI7: =CH7/$CH$10 -> 0.54151366 | CJ7: =SUM(E7,K7,R7,Y7,AF7,AM7,AT7,BA7,BH7,BO7,BV7,CC7) -> 8371166.5 | CK7: =CJ7/$CJ$10 -> 0.59041934 | CL7: =SUM(G7,M7,T7,AA7,AH7,AO7,AV7,BC7,BJ7,BQ7,BX7,CE7) -> 62596907 | CM7: =CL7/$CL$10 -> 0.54757933
B8: Vendas - Ticket | C8: =SUMIF('MVTO E'!$C$3:$C$240,"Vda_Ticket",'MVTO E'!$G$3:$G$240)-SUMIF('MVTO E'!$C$3:$C$240,"Vda_S_Ticket",'MVTO E'!$G$3:$G$240) -> 4601459 | D8: =C8/$C$10 -> 0.13985769 | E8: =SUMIF('MVTO A'!$C$3:$C$184,"Vda_Ticket",'MVTO A'!$G$3:$G$184)-SUMIF('MVTO A'!$C$3:$C$184,"Vda_S_Ticket",'MVTO A'!$G$3:$G$184) -> 11369.36 | F8: =E8/$E$10 -> 0.0028770606 | G8: =C8+E8 -> 4612828.4 | H8: =G8/$G$10 -> 0.12516923 | I8: =SUMIF('MVTO E'!$C$3:$C$240,"Vda_Ticket",'MVTO E'!$H$3:$H$240)-SUMIF('MVTO E'!$C$3:$C$240,"Vda_S_Ticket",'MVTO E'!$H$3:$H$240) -> 3733267.5 | J8: =I8/$I$10 -> 0.17584849 | K8: =SUMIF('MVTO A'!$C$3:$C$184,"Vda_Ticket",'MVTO A'!$H$3:$H$184)-SUMIF('MVTO A'!$C$3:$C$184,"Vda_S_Ticket",'MVTO A'!$H$3:$H$184) -> 7082.82 | L8: =K8/$K$10 -> 0.0020714637 | M8: =I8+K8 -> 3740350.4 | N8: =M8/$M$10 -> 0.15174292 | O8: =M8-G8 -> -872478.04 | P8: =SUMIF('MVTO E'!$C$3:$C$240,"Vda_Ticket",'MVTO E'!$I$3:$I$240)-SUMIF('MVTO E'!$C$3:$C$240,"Vda_S_Ticket",'MVTO E'!$I$3:$I$240) -> 4398041.3 | Q8: =P8/$I$10 -> 0.2071614 | R8: =SUMIF('MVTO A'!$C$3:$C$184,"Vda_Ticket",'MVTO A'!$I$3:$I$184)-SUMIF('MVTO A'!$C$3:$C$184,"Vda_S_Ticket",'MVTO A'!$I$3:$I$184) -> 15070.53 | S8: =R8/$K$10 -> 0.0044075743 | T8: =P8+R8 -> 4413111.8 | U8: =T8/$T$10 -> 0.16072282 | V8: =T8-M8 -> 672761.45 | W8: =SUMIF('MVTO E'!$C$3:$C$240,"Vda_Ticket",'MVTO E'!$J$3:$J$240)-SUMIF('MVTO E'!$C$3:$C$240,"Vda_S_Ticket",'MVTO E'!$J$3:$J$240) -> 3932518.1 | X8: =W8/$I$10 -> 0.18523381 | Y8: =SUMIF('MVTO A'!$C$3:$C$184,"Vda_Ticket",'MVTO A'!$J$3:$J$184)-SUMIF('MVTO A'!$C$3:$C$184,"Vda_S_Ticket",'MVTO A'!$J$3:$J$184) -> 10029.76 | Z8: =Y8/$K$10 -> 0.0029333349 | AA8: =W8+Y8 -> 3942547.8 | AB8: =AA8/$AA$10 -> 0.15548906 | AC8: =AA8-T8 -> -470563.99 | AD8: =SUMIF('MVTO E'!$C$3:$C$240,"Vda_Ticket",'MVTO E'!$K$3:$K$240)-SUMIF('MVTO E'!$C$3:$C$240,"Vda_S_Ticket",'MVTO E'!$K$3:$K$240) -> 0 | AE8: =AD8/$I$10 -> 0 | AF8: =SUMIF('MVTO A'!$C$3:$C$184,"Vda_Ticket",'MVTO A'!$K$3:$K$184)-SUMIF('MVTO A'!$C$3:$C$184,"Vda_S_Ticket",'MVTO A'!$K$3:$K$184) -> 0 | AG8: =AF8/$K$10 -> 0 | AH8: =AD8+AF8 -> 0 | AI8: =AH8/$AA$10 -> 0 | AJ8: =AH8-AA8 -> -3942547.8 | AK8: =SUMIF('MVTO E'!$C$3:$C$240,"Vda_Ticket",'MVTO E'!$L$3:$L$240)-SUMIF('MVTO E'!$C$3:$C$240,"Vda_S_Ticket",'MVTO E'!$L$3:$L$240) -> 0 | AL8: =AK8/$I$10 -> 0 | AM8: =SUMIF('MVTO A'!$C$3:$C$184,"Vda_Ticket",'MVTO A'!$L$3:$L$184)-SUMIF('MVTO A'!$C$3:$C$184,"Vda_S_Ticket",'MVTO A'!$L$3:$L$184) -> 0 | AN8: =AM8/$K$10 -> 0 | AO8: =AK8+AM8 -> 0 | AP8: =AO8/$AA$10 -> 0 | AQ8: =AO8-AH8 -> 0 | AR8: =SUMIF('MVTO E'!$C$3:$C$240,"Vda_Ticket",'MVTO E'!$M$3:$M$240)-SUMIF('MVTO E'!$C$3:$C$240,"Vda_S_Ticket",'MVTO E'!$M$3:$M$240) -> 0 | AS8: =AR8/$I$10 -> 0 | AT8: =SUMIF('MVTO A'!$C$3:$C$184,"Vda_Ticket",'MVTO A'!$M$3:$M$184)-SUMIF('MVTO A'!$C$3:$C$184,"Vda_S_Ticket",'MVTO A'!$M$3:$M$184) -> 0 | AU8: =AT8/$K$10 -> 0 | AV8: =AR8+AT8 -> 0 | AW8: =AV8/$AA$10 -> 0 | AX8: =AV8-AO8 -> 0 | AY8: =SUMIF('MVTO E'!$C$3:$C$240,"Vda_Ticket",'MVTO E'!$N$3:$N$240)-SUMIF('MVTO E'!$C$3:$C$240,"Vda_S_Ticket",'MVTO E'!$N$3:$N$240) -> 0 | AZ8: =AY8/$I$10 -> 0 | BA8: =SUMIF('MVTO A'!$C$3:$C$184,"Vda_Ticket",'MVTO A'!$N$3:$N$184)-SUMIF('MVTO A'!$C$3:$C$184,"Vda_S_Ticket",'MVTO A'!$N$3:$N$184) -> 0 | BB8: =BA8/$K$10 -> 0 | BC8: =AY8+BA8 -> 0 | BD8: =BC8/$AA$10 -> 0 | BE8: =BC8-AV8 -> 0 | BF8: =SUMIF('MVTO E'!$C$3:$C$240,"Vda_Ticket",'MVTO E'!$O$3:$O$240)-SUMIF('MVTO E'!$C$3:$C$240,"Vda_S_Ticket",'MVTO E'!$O$3:$O$240) -> 0 | BG8: =BF8/$I$10 -> 0 | BH8: =SUMIF('MVTO A'!$C$3:$C$184,"Vda_Ticket",'MVTO A'!$O$3:$O$184)-SUMIF('MVTO A'!$C$3:$C$184,"Vda_S_Ticket",'MVTO A'!$O$3:$O$184) -> 0 | BI8: =BH8/$K$10 -> 0 | BJ8: =BF8+BH8 -> 0 | BK8: =BJ8/$AA$10 -> 0 | BL8: =BJ8-BC8 -> 0 | BM8: =SUMIF('MVTO E'!$C$3:$C$240,"Vda_Ticket",'MVTO E'!$P$3:$P$240)-SUMIF('MVTO E'!$C$3:$C$240,"Vda_S_Ticket",'MVTO E'!$P$3:$P$240) -> 0 | BN8: =BM8/$I$10 -> 0 | BO8: =SUMIF('MVTO A'!$C$3:$C$184,"Vda_Ticket",'MVTO A'!$P$3:$P$184)-SUMIF('MVTO A'!$C$3:$C$184,"Vda_S_Ticket",'MVTO A'!$P$3:$P$184) -> 0 | BP8: =BO8/$K$10 -> 0 | BQ8: =BM8+BO8 -> 0 | BR8: =BQ8/$AA$10 -> 0 | BS8: =BQ8-BJ8 -> 0 | BT8: =SUMIF('MVTO E'!$C$3:$C$240,"Vda_Ticket",'MVTO E'!$Q$3:$Q$240)-SUMIF('MVTO E'!$C$3:$C$240,"Vda_S_Ticket",'MVTO E'!$Q$3:$Q$240) -> 0 | BU8: =BT8/$I$10 -> 0 | BV8: =SUMIF('MVTO A'!$C$3:$C$184,"Vda_Ticket",'MVTO A'!$Q$3:$Q$184)-SUMIF('MVTO A'!$C$3:$C$184,"Vda_S_Ticket",'MVTO A'!$Q$3:$Q$184) -> 0 | BW8: =BV8/$K$10 -> 0 | BX8: =BT8+BV8 -> 0 | BY8: =BX8/$AA$10 -> 0 | BZ8: =BX8-BQ8 -> 0 | CA8: =SUMIF('MVTO E'!$C$3:$C$240,"Vda_Ticket",'MVTO E'!$R$3:$R$240)-SUMIF('MVTO E'!$C$3:$C$240,"Vda_S_Ticket",'MVTO E'!$R$3:$R$240) -> 0 | CB8: =CA8/$I$10 -> 0 | CC8: =SUMIF('MVTO A'!$C$3:$C$184,"Vda_Ticket",'MVTO A'!$R$3:$R$184)-SUMIF('MVTO A'!$C$3:$C$184,"Vda_S_Ticket",'MVTO A'!$R$3:$R$184) -> 0 | CD8: =CC8/$K$10 -> 0 | CE8: =CA8+CC8 -> 0 | CF8: =CE8/$AA$10 -> 0 | CG8: =CE8-BX8 -> 0 | CH8: =SUM(C8,I8,P8,W8,AD8,AK8,AR8,AY8,BF8,BM8,BT8,CA8) -> 16665286 | CI8: =CH8/$CH$10 -> 0.16642428 | CJ8: =SUM(E8,K8,R8,Y8,AF8,AM8,AT8,BA8,BH8,BO8,BV8,CC8) -> 43552.47 | CK8: =CJ8/$CJ$10 -> 0.0030717607 | CL8: =SUM(G8,M8,T8,AA8,AH8,AO8,AV8,BC8,BJ8,BQ8,BX8,CE8) -> 16708838 | CM8: =CL8/$CL$10 -> 0.146164
B9: Vendas - Clientes | C9: =SUMIF('MVTO E'!$C$3:$C$240,"Vda_Prazo",'MVTO E'!$G$3:$G$240)-SUMIF('MVTO E'!$C$3:$C$240,"Vda_S_Pz",'MVTO E'!$G$3:$G$240) -> 975612.51 | D9: =C9/$C$10 -> 0.029652967 | E9: =SUMIF('MVTO A'!$C$3:$C$184,"Vda_Prazo",'MVTO A'!$G$3:$G$184)-SUMIF('MVTO A'!$C$3:$C$184,"Vda_S_Pz",'MVTO A'!$G$3:$G$184) -> 421361.23 | F9: =E9/$E$10 -> 0.10662709 | G9: =C9+E9 -> 1396973.7 | H9: =G9/$G$10 -> 0.037906921 | I9: =SUMIF('MVTO E'!$C$3:$C$240,"Vda_Prazo",'MVTO E'!$H$3:$H$240)-SUMIF('MVTO E'!$C$3:$C$240,"Vda_S_Pz",'MVTO E'!$H$3:$H$240) -> 508506.3 | J9: =I9/$I$10 -> 0.023952226 | K9: =SUMIF('MVTO A'!$C$3:$C$184,"Vda_Prazo",'MVTO A'!$H$3:$H$184)-SUMIF('MVTO A'!$C$3:$C$184,"Vda_S_Pz",'MVTO A'!$H$3:$H$184) -> 406924.34 | L9: =K9/$K$10 -> 0.11901036 | M9: =I9+K9 -> 915430.64 | N9: =M9/$M$10 -> 0.037138264 | O9: =M9-G9 -> -481543.1 | P9: =SUMIF('MVTO E'!$C$3:$C$240,"Vda_Prazo",'MVTO E'!$I$3:$I$240)-SUMIF('MVTO E'!$C$3:$C$240,"Vda_S_Pz",'MVTO E'!$I$3:$I$240) -> 465125.84 | Q9: =P9/$I$10 -> 0.021908871 | R9: =SUMIF('MVTO A'!$C$3:$C$184,"Vda_Prazo",'MVTO A'!$I$3:$I$184)-SUMIF('MVTO A'!$C$3:$C$184,"Vda_S_Pz",'MVTO A'!$I$3:$I$184) -> 448900.38 | S9: =R9/$K$10 -> 0.13128681 | T9: =P9+R9 -> 914026.22 | U9: =T9/$T$10 -> 0.033288273 | V9: =T9-M9 -> -1404.42 | W9: =SUMIF('MVTO E'!$C$3:$C$240,"Vda_Prazo",'MVTO E'!$J$3:$J$240)-SUMIF('MVTO E'!$C$3:$C$240,"Vda_S_Pz",'MVTO E'!$J$3:$J$240) -> 1168204.4 | X9: =W9/$I$10 -> 0.055026056 | Y9: =SUMIF('MVTO A'!$C$3:$C$184,"Vda_Prazo",'MVTO A'!$J$3:$J$184)-SUMIF('MVTO A'!$C$3:$C$184,"Vda_S_Pz",'MVTO A'!$J$3:$J$184) -> 254474.69 | Z9: =Y9/$K$10 -> 0.074424463 | AA9: =W9+Y9 -> 1422679.1 | AB9: =AA9/$AA$10 -> 0.05610865 | AC9: =AA9-T9 -> 508652.9 | AD9: =SUMIF('MVTO E'!$C$3:$C$240,"Vda_Prazo",'MVTO E'!$K$3:$K$240)-SUMIF('MVTO E'!$C$3:$C$240,"Vda_S_Pz",'MVTO E'!$K$3:$K$240) -> 0 | AE9: =AD9/$I$10 -> 0 | AF9: =SUMIF('MVTO A'!$C$3:$C$184,"Vda_Prazo",'MVTO A'!$K$3:$K$184)-SUMIF('MVTO A'!$C$3:$C$184,"Vda_S_Pz",'MVTO A'!$K$3:$K$184) -> 0 | AG9: =AF9/$K$10 -> 0 | AH9: =AD9+AF9 -> 0 | AI9: =AH9/$AA$10 -> 0 | AJ9: =AH9-AA9 -> -1422679.1 | AK9: =SUMIF('MVTO E'!$C$3:$C$240,"Vda_Prazo",'MVTO E'!$L$3:$L$240)-SUMIF('MVTO E'!$C$3:$C$240,"Vda_S_Pz",'MVTO E'!$L$3:$L$240) -> 0 | AL9: =AK9/$I$10 -> 0 | AM9: =SUMIF('MVTO A'!$C$3:$C$184,"Vda_Prazo",'MVTO A'!$L$3:$L$184)-SUMIF('MVTO A'!$C$3:$C$184,"Vda_S_Pz",'MVTO A'!$L$3:$L$184) -> 0 | AN9: =AM9/$K$10 -> 0 | AO9: =AK9+AM9 -> 0 | AP9: =AO9/$AA$10 -> 0 | AQ9: =AO9-AH9 -> 0 | AR9: =SUMIF('MVTO E'!$C$3:$C$240,"Vda_Prazo",'MVTO E'!$M$3:$M$240)-SUMIF('MVTO E'!$C$3:$C$240,"Vda_S_Pz",'MVTO E'!$M$3:$M$240) -> 0 | AS9: =AR9/$I$10 -> 0 | AT9: =SUMIF('MVTO A'!$C$3:$C$184,"Vda_Prazo",'MVTO A'!$M$3:$M$184)-SUMIF('MVTO A'!$C$3:$C$184,"Vda_S_Pz",'MVTO A'!$M$3:$M$184) -> 0 | AU9: =AT9/$K$10 -> 0 | AV9: =AR9+AT9 -> 0 | AW9: =AV9/$AA$10 -> 0 | AX9: =AV9-AO9 -> 0 | AY9: =SUMIF('MVTO E'!$C$3:$C$240,"Vda_Prazo",'MVTO E'!$N$3:$N$240)-SUMIF('MVTO E'!$C$3:$C$240,"Vda_S_Pz",'MVTO E'!$N$3:$N$240) -> 0 | AZ9: =AY9/$I$10 -> 0 | BA9: =SUMIF('MVTO A'!$C$3:$C$184,"Vda_Prazo",'MVTO A'!$N$3:$N$184)-SUMIF('MVTO A'!$C$3:$C$184,"Vda_S_Pz",'MVTO A'!$N$3:$N$184) -> 0 | BB9: =BA9/$K$10 -> 0 | BC9: =AY9+BA9 -> 0 | BD9: =BC9/$AA$10 -> 0 | BE9: =BC9-AV9 -> 0 | BF9: =SUMIF('MVTO E'!$C$3:$C$240,"Vda_Prazo",'MVTO E'!$O$3:$O$240)-SUMIF('MVTO E'!$C$3:$C$240,"Vda_S_Pz",'MVTO E'!$O$3:$O$240) -> 0 | BG9: =BF9/$I$10 -> 0 | BH9: =SUMIF('MVTO A'!$C$3:$C$184,"Vda_Prazo",'MVTO A'!$O$3:$O$184)-SUMIF('MVTO A'!$C$3:$C$184,"Vda_S_Pz",'MVTO A'!$O$3:$O$184) -> 0 | BI9: =BH9/$K$10 -> 0 | BJ9: =BF9+BH9 -> 0 | BK9: =BJ9/$AA$10 -> 0 | BL9: =BJ9-BC9 -> 0 | BM9: =SUMIF('MVTO E'!$C$3:$C$240,"Vda_Prazo",'MVTO E'!$P$3:$P$240)-SUMIF('MVTO E'!$C$3:$C$240,"Vda_S_Pz",'MVTO E'!$P$3:$P$240) -> 0 | BN9: =BM9/$I$10 -> 0 | BO9: =SUMIF('MVTO A'!$C$3:$C$184,"Vda_Prazo",'MVTO A'!$P$3:$P$184)-SUMIF('MVTO A'!$C$3:$C$184,"Vda_S_Pz",'MVTO A'!$P$3:$P$184) -> 0 | BP9: =BO9/$K$10 -> 0 | BQ9: =BM9+BO9 -> 0 | BR9: =BQ9/$AA$10 -> 0 | BS9: =BQ9-BJ9 -> 0 | BT9: =SUMIF('MVTO E'!$C$3:$C$240,"Vda_Prazo",'MVTO E'!$Q$3:$Q$240)-SUMIF('MVTO E'!$C$3:$C$240,"Vda_S_Pz",'MVTO E'!$Q$3:$Q$240) -> 0 | BU9: =BT9/$I$10 -> 0 | BV9: =SUMIF('MVTO A'!$C$3:$C$184,"Vda_Prazo",'MVTO A'!$Q$3:$Q$184)-SUMIF('MVTO A'!$C$3:$C$184,"Vda_S_Pz",'MVTO A'!$Q$3:$Q$184) -> 0 | BW9: =BV9/$K$10 -> 0 | BX9: =BT9+BV9 -> 0 | BY9: =BX9/$AA$10 -> 0 | BZ9: =BX9-BQ9 -> 0 | CA9: =SUMIF('MVTO E'!$C$3:$C$240,"Vda_Prazo",'MVTO E'!$R$3:$R$240)-SUMIF('MVTO E'!$C$3:$C$240,"Vda_S_Pz",'MVTO E'!$R$3:$R$240) -> 0 | CB9: =CA9/$I$10 -> 0 | CC9: =SUMIF('MVTO A'!$C$3:$C$184,"Vda_Prazo",'MVTO A'!$R$3:$R$184)-SUMIF('MVTO A'!$C$3:$C$184,"Vda_S_Pz",'MVTO A'!$R$3:$R$184) -> 0 | CD9: =CC9/$K$10 -> 0 | CE9: =CA9+CC9 -> 0 | CF9: =CE9/$AA$10 -> 0 | CG9: =CE9-BX9 -> 0 | CH9: =SUM(C9,I9,P9,W9,AD9,AK9,AR9,AY9,BF9,BM9,BT9,CA9) -> 3117449.1 | CI9: =CH9/$CH$10 -> 0.031131733 | CJ9: =SUM(E9,K9,R9,Y9,AF9,AM9,AT9,BA9,BH9,BO9,BV9,CC9) -> 1531660.6 | CK9: =CJ9/$CJ$10 -> 0.1080282 | CL9: =SUM(G9,M9,T9,AA9,AH9,AO9,AV9,BC9,BJ9,BQ9,BX9,CE9) -> 4649109.7 | CM9: =CL9/$CL$10 -> 0.040669044
B10: Vendas - Total | C10: =SUM(C4:C9) -> 32901008 | D10: =SUM(D4:D9) -> 1 | E10: =SUM(E4:E9) -> 3951727.7 | F10: =SUM(F4:F9) -> 1 | G10: =C10+E10 -> 36852735 | H10: =SUM(H4:H9) -> 1 | I10: =SUM(I4:I9) -> 21230023 | J10: =SUM(J4:J9) -> 1 | K10: =SUM(K4:K9) -> 3419234.5 | L10: =SUM(L4:L9) -> 1 | M10: =I10+K10 -> 24649257 | N10: =SUM(N4:N9) -> 1 | O10: =M10-G10 -> -12203478 | P10: =SUM(P4:P9) -> 23807320 | Q10: =SUM(Q4:Q9) -> 1.1213987 | R10: =SUM(R4:R9) -> 3650584.5 | S10: =SUM(S4:S9) -> 1.0676614 | T10: =P10+R10 -> 27457904 | U10: =SUM(U4:U9) -> 1 | V10: =T10-M10 -> 2808646.8 | W10: =SUM(W4:W9) -> 22198995 | X10: =W10/$W$10 -> 1 | Y10: =SUM(Y4:Y9) -> 3156793.9 | Z10: =Y10/$Y$10 -> 1 | AA10: =W10+Y10 -> 25355789 | AB10: =SUM(AB4:AB9) -> 1 | AC10: =AA10-T10 -> -2102114.9 | AD10: =SUM(AD4:AD9) -> 0 | AE10: =AD10/$AD$10 -> #DIV/0! | AF10: =SUM(AF4:AF9) -> 0 | AG10: =AF10/$AF$10 -> #DIV/0! | AH10: =AD10+AF10 -> 0 | AI10: =SUM(AI4:AI9) -> 0 | AJ10: =AH10-AA10 -> -25355789 | AK10: =SUM(AK4:AK9) -> 0 | AL10: =AK10/$AK$10 -> #DIV/0! | AM10: =SUM(AM4:AM9) -> 0 | AN10: =AM10/$AM$10 -> #DIV/0! | AO10: =AK10+AM10 -> 0 | AP10: =SUM(AP4:AP9) -> 0 | AQ10: =AO10-AH10 -> 0 | AR10: =SUM(AR4:AR9) -> 0 | AS10: =AR10/$AR$10 -> #DIV/0! | AT10: =SUM(AT4:AT9) -> 0 | AU10: =AT10/$AT$10 -> #DIV/0! | AV10: =AR10+AT10 -> 0 | AW10: =SUM(AW4:AW9) -> 0 | AX10: =AV10-AO10 -> 0 | AY10: =SUM(AY4:AY9) -> 0 | AZ10: =AY10/$AY$10 -> #DIV/0! | BA10: =SUM(BA4:BA9) -> 0 | BB10: =BA10/$BA$10 -> #DIV/0! | BC10: =AY10+BA10 -> 0 | BD10: =SUM(BD4:BD9) -> 0 | BE10: =BC10-AV10 -> 0 | BF10: =SUM(BF4:BF9) -> 0 | BG10: =BF10/$BF$10 -> #DIV/0! | BH10: =SUM(BH4:BH9) -> 0 | BI10: =BH10/$BH$10 -> #DIV/0! | BJ10: =BF10+BH10 -> 0 | BK10: =SUM(BK4:BK9) -> 0 | BL10: =BJ10-BC10 -> 0 | BM10: =SUM(BM4:BM9) -> 0 | BN10: =BM10/$BF$10 -> #DIV/0! | BO10: =SUM(BO4:BO9) -> 0 | BP10: =BO10/$BH$10 -> #DIV/0! | BQ10: =BM10+BO10 -> 0 | BR10: =SUM(BR4:BR9) -> 0 | BS10: =BQ10-BJ10 -> 0 | BT10: =SUM(BT4:BT9) -> 0 | BU10: =BT10/$BF$10 -> #DIV/0! | BV10: =SUM(BV4:BV9) -> 0 | BW10: =BV10/$BH$10 -> #DIV/0! | BX10: =BT10+BV10 -> 0 | BY10: =SUM(BY4:BY9) -> 0 | BZ10: =BX10-BQ10 -> 0 | CA10: =SUM(CA4:CA9) -> 0 | CB10: =CA10/$BF$10 -> #DIV/0! | CC10: =SUM(CC4:CC9) -> 0 | CD10: =CC10/$BH$10 -> #DIV/0! | CE10: =CA10+CC10 -> 0 | CF10: =SUM(CF4:CF9) -> 0 | CG10: =CE10-BX10 -> 0 | CH10: =SUM(C10,I10,P10,W10,AD10,AK10,AR10,AY10,BF10,BM10,BT10,CA10) -> 1.0013735e+08 | CI10: =CH10/$CH$10 -> 1 | CJ10: =SUM(E10,K10,R10,Y10,AF10,AM10,AT10,BA10,BH10,BO10,BV10,CC10) -> 14178341 | CK10: =CJ10/$CJ$10 -> 1 | CL10: =SUM(G10,M10,T10,AA10,AH10,AO10,AV10,BC10,BJ10,BQ10,BX10,CE10) -> 1.1431569e+08 | CM10: =CL10/$CL$10 -> 1
B11: ( - ) Deduções | C11: =SUMIF('MVTO E'!$C$3:$C$240,"S_Deduções",'MVTO E'!$G$3:$G$240) -> 65385 | D11: =C11/$C$10 -> 0.0019873252 | E11: =SUMIF('MVTO A'!$C$3:$C$184,"S_Deduções",'MVTO A'!$G$3:$G$184) -> 185.5 | F11: =E11/$E$10 -> 4.6941493e-05 | G11: =C11+E11 -> 65570.5 | H11: =G11/$G$10 -> 0.0017792573 | I11: =SUMIF('MVTO E'!$C$3:$C$240,"S_Deduções",'MVTO E'!$H$3:$H$240) -> 43517.62 | J11: =I11/$I$10 -> 0.002049815 | K11: =SUMIF('MVTO A'!$C$3:$C$184,"S_Deduções",'MVTO A'!$H$3:$H$184) -> 0 | L11: =K11/$K$10 -> 0 | M11: =I11+K11 -> 43517.62 | N11: =M11/$M$10 -> 0.0017654739 | O11: =M11-G11 -> -22052.88 | P11: =SUMIF('MVTO E'!$C$3:$C$240,"S_Deduções",'MVTO E'!$I$3:$I$240) -> 372509.19 | Q11: =P11/$P$10 -> 0.015646834 | R11: =SUMIF('MVTO A'!$C$3:$C$184,"S_Deduções",'MVTO A'!$I$3:$I$184) -> 0 | S11: =R11/$R$10 -> 0 | T11: =P11+R11 -> 372509.19 | U11: =T11/$T$10 -> 0.013566556 | V11: =T11-M11 -> 328991.57 | W11: =SUMIF('MVTO E'!$C$3:$C$240,"S_Deduções",'MVTO E'!$J$3:$J$240) -> 64143.51 | X11: =W11/$W$10 -> 0.002889478 | Y11: =SUMIF('MVTO A'!$C$3:$C$184,"S_Deduções",'MVTO A'!$J$3:$J$184) -> 0 | Z11: =Y11/$Y$10 -> 0 | AA11: =W11+Y11 -> 64143.51 | AB11: =AA11/$AA$10 -> 0.0025297382 | AC11: =AA11-T11 -> -308365.68 | AD11: =SUMIF('MVTO E'!$C$3:$C$240,"S_Deduções",'MVTO E'!$K$3:$K$240) -> 0 | AE11: =AD11/$AD$10 -> #DIV/0! | AF11: =SUMIF('MVTO A'!$C$3:$C$184,"S_Deduções",'MVTO A'!$K$3:$K$184) -> 0 | AG11: =AF11/$AF$10 -> #DIV/0! | AH11: =AD11+AF11 -> 0 | AI11: =AH11/$AH$10 -> #DIV/0! | AJ11: =AH11-AA11 -> -64143.51 | AK11: =SUMIF('MVTO E'!$C$3:$C$240,"S_Deduções",'MVTO E'!$L$3:$L$240) -> 0 | AL11: =AK11/$AK$10 -> #DIV/0! | AM11: =SUMIF('MVTO A'!$C$3:$C$184,"S_Deduções",'MVTO A'!$L$3:$L$184) -> 0 | AN11: =AM11/$AM$10 -> #DIV/0! | AO11: =AK11+AM11 -> 0 | AP11: =AO11/$AO$10 -> #DIV/0! | AQ11: =AO11-AH11 -> 0 | AR11: =SUMIF('MVTO E'!$C$3:$C$240,"S_Deduções",'MVTO E'!$M$3:$M$240) -> 0 | AS11: =AR11/$AR$10 -> #DIV/0! | AT11: =SUMIF('MVTO A'!$C$3:$C$184,"S_Deduções",'MVTO A'!$M$3:$M$189) -> 0 | AU11: =AT11/$AT$10 -> #DIV/0! | AV11: =AR11+AT11 -> 0 | AW11: =AV11/$AV$10 -> #DIV/0! | AX11: =AV11-AO11 -> 0 | AY11: =SUMIF('MVTO E'!$C$3:$C$240,"S_Deduções",'MVTO E'!$N$3:$N$240) -> 0 | AZ11: =AY11/$AY$10 -> #DIV/0! | BA11: =SUMIF('MVTO A'!$C$3:$C$184,"S_Deduções",'MVTO A'!$N$3:$N$189) -> 0 | BB11: =BA11/$BA$10 -> #DIV/0! | BC11: =AY11+BA11 -> 0 | BD11: =BC11/$BC$10 -> #DIV/0! | BE11: =BC11-AV11 -> 0 | BF11: =SUMIF('MVTO E'!$C$3:$C$240,"S_Deduções",'MVTO E'!$O$3:$O$240) -> 0 | BG11: =BF11/$BF$10 -> #DIV/0! | BH11: =SUMIF('MVTO A'!$C$3:$C$195,"S_Deduções",'MVTO A'!$O$3:$O$195) -> 0 | BI11: =BH11/$BH$10 -> #DIV/0! | BJ11: =BF11+BH11 -> 0 | BK11: =BJ11/$BJ$10 -> #DIV/0! | BL11: =BJ11-BC11 -> 0 | BM11: =SUMIF('MVTO E'!$C$3:$C$240,"S_Deduções",'MVTO E'!$P$3:$P$240) -> 0 | BN11: =BM11/$BF$10 -> #DIV/0! | BO11: =SUMIF('MVTO A'!$C$3:$C$184,"S_Deduções",'MVTO A'!$P$3:$P$189) -> 0 | BP11: =BO11/$BH$10 -> #DIV/0! | BQ11: =BM11+BO11 -> 0 | BR11: =BQ11/$BJ$10 -> #DIV/0! | BS11: =BQ11-BJ11 -> 0 | BT11: =SUMIF('MVTO E'!$C$3:$C$240,"S_Deduções",'MVTO E'!$Q$3:$Q$240) -> 0 | BU11: =BT11/$BF$10 -> #DIV/0! | BV11: =SUMIF('MVTO A'!$C$3:$C$184,"S_Deduções",'MVTO A'!$Q$3:$Q$189) -> 0 | BW11: =BV11/$BH$10 -> #DIV/0! | BX11: =BT11+BV11 -> 0 | BY11: =BX11/$BJ$10 -> #DIV/0! | BZ11: =BX11-BQ11 -> 0 | CA11: =SUMIF('MVTO E'!$C$3:$C$240,"S_Deduções",'MVTO E'!$R$3:$R$240) -> 0 | CB11: =CA11/$BF$10 -> #DIV/0! | CC11: =SUMIF('MVTO A'!$C$3:$C$184,"S_Deduções",'MVTO A'!$R$3:$R$189) -> 0 | CD11: =CC11/$BH$10 -> #DIV/0! | CE11: =CA11+CC11 -> 0 | CF11: =CE11/$BJ$10 -> #DIV/0! | CG11: =CE11-BX11 -> 0 | CH11: =SUM(C11,I11,P11,W11,AD11,AK11,AR11,AY11,BF11,BM11,BT11,CA11) -> 545555.32 | CI11: =CH11/$CH$10 -> 0.0054480705 | CJ11: =SUM(E11,K11,R11,Y11,AF11,AM11,AT11,BA11,BH11,BO11,BV11,CC11) -> 185.5 | CK11: =CJ11/$CJ$10 -> 1.3083336e-05 | CL11: =SUM(G11,M11,T11,AA11,AH11,AO11,AV11,BC11,BJ11,BQ11,BX11,CE11) -> 545740.82 | CM11: =CL11/$CL$10 -> 0.0047739802
B12: ( - ) COMPRAS | C12: =SUMIF('MVTO E'!$C$3:$C$240,"Compras",'MVTO E'!$G$3:$G$240)+SUMIF('DESP E'!$D$3:$D$146,"Compras",'DESP E'!$G$3:$G$146) -> 22556749 | D12: =C12/$C$10 -> 0.68559447 | E12: =SUMIF('MVTO A'!$C$3:$C$184,"Compras",'MVTO A'!$G$3:$G$184)+SUMIF('DESP A'!$D$3:$D$129,"Compras",'DESP A'!$G$3:$G$129) -> 182167.49 | F12: =E12/$E$10 -> 0.046098188 | G12: =C12+E12 -> 22738916 | H12: =G12/$G$10 -> 0.61702113 | I12: =SUMIF('MVTO E'!$C$3:$C$240,"Compras",'MVTO E'!$H$3:$H$240)+SUMIF('DESP E'!$D$3:$D$146,"Compras",'DESP E'!$H$3:$H$146) -> 12804108 | J12: =I12/$I$10 -> 0.60311325 | K12: =SUMIF('MVTO A'!$C$3:$C$184,"Compras",'MVTO A'!$H$3:$H$184)+SUMIF('DESP A'!$D$3:$D$129,"Compras",'DESP A'!$H$3:$H$129) -> 121690.06 | L12: =K12/$K$10 -> 0.035589855 | M12: =I12+K12 -> 12925798 | N12: =M12/$M$10 -> 0.52438895 | O12: =M12-G12 -> -9813118.3 | P12: =SUMIF('MVTO E'!$C$3:$C$240,"Compras",'MVTO E'!$I$3:$I$240)+SUMIF('DESP E'!$D$3:$D$146,"Compras",'DESP E'!$I$3:$I$146) -> 15196261 | Q12: =P12/$P$10 -> 0.63830204 | R12: =SUMIF('MVTO A'!$C$3:$C$184,"Compras",'MVTO A'!$I$3:$I$184)+SUMIF('DESP A'!$D$3:$D$129,"Compras",'DESP A'!$I$3:$I$129) -> 141505.6 | S12: =R12/$R$10 -> 0.03876245 | T12: =P12+R12 -> 15337766 | U12: =T12/$T$10 -> 0.55859202 | V12: =T12-M12 -> 2411968.1 | W12: =SUMIF('MVTO E'!$C$3:$C$240,"Compras",'MVTO E'!$J$3:$J$240)+SUMIF('DESP E'!$D$3:$D$146,"Compras",'DESP E'!$J$3:$J$146) -> 14769758 | X12: =W12/$P$10 -> 0.62038725 | Y12: =SUMIF('MVTO A'!$C$3:$C$184,"Compras",'MVTO A'!$J$3:$J$184)+SUMIF('DESP A'!$D$3:$D$129,"Compras",'DESP A'!$J$3:$J$129) -> 112457.25 | Z12: =Y12/$Y$10 -> 0.035623881 | AA12: =W12+Y12 -> 14882215 | AB12: =AA12/$AA$10 -> 0.58693558 | AC12: =AA12-T12 -> -455551.4 | AD12: =SUMIF('MVTO E'!$C$3:$C$240,"Compras",'MVTO E'!$K$3:$K$240)+SUMIF('DESP E'!$D$3:$D$146,"Compras",'DESP E'!$K$3:$K$146) -> 0 | AE12: =AD12/$P$10 -> 0 | AF12: =SUMIF('MVTO A'!$C$3:$C$184,"Compras",'MVTO A'!$K$3:$K$184)+SUMIF('DESP A'!$D$3:$D$129,"Compras",'DESP A'!$K$3:$K$129) -> 0 | AG12: =AF12/$AF$10 -> #DIV/0! | AH12: =AD12+AF12 -> 0 | AI12: =AH12/$AH$10 -> #DIV/0! | AJ12: =AH12-AA12 -> -14882215 | AK12: =SUMIF('MVTO E'!$C$3:$C$240,"Compras",'MVTO E'!$L$3:$L$240)+SUMIF('DESP E'!$D$3:$D$146,"Compras",'DESP E'!$L$3:$L$146) -> 0 | AL12: =AK12/$P$10 -> 0 | AM12: =SUMIF('MVTO A'!$C$3:$C$184,"Compras",'MVTO A'!$L$3:$L$184)+SUMIF('DESP A'!$D$3:$D$129,"Compras",'DESP A'!$L$3:$L$129) -> 0 | AN12: =AM12/$AM$10 -> #DIV/0! | AO12: =AK12+AM12 -> 0 | AP12: =AO12/$AO$10 -> #DIV/0! | AQ12: =AO12-AH12 -> 0 | AR12: =SUMIF('MVTO E'!$C$3:$C$240,"Compras",'MVTO E'!$M$3:$M$240)+SUMIF('DESP E'!$D$3:$D$146,"Compras",'DESP E'!$M$3:$M$146) -> 0 | AS12: =AR12/$P$10 -> 0 | AT12: =SUMIF('MVTO A'!$C$3:$C$184,"Compras",'MVTO A'!$M$3:$M$189)+SUMIF('DESP A'!$D$3:$D$129,"Compras",'DESP A'!$M$3:$M$129) -> 0 | AU12: =AT12/$AT$10 -> #DIV/0! | AV12: =AR12+AT12 -> 0 | AW12: =AV12/$AV$10 -> #DIV/0! | AX12: =AV12-AO12 -> 0 | AY12: =SUMIF('MVTO E'!$C$3:$C$240,"Compras",'MVTO E'!$N$3:$N$240)+SUMIF('DESP E'!$D$3:$D$146,"Compras",'DESP E'!$N$3:$N$146) -> 0 | AZ12: =AY12/$P$10 -> 0 | BA12: =SUMIF('MVTO A'!$C$3:$C$184,"Compras",'MVTO A'!$N$3:$N$189)+SUMIF('DESP A'!$D$3:$D$129,"Compras",'DESP A'!$N$3:$N$129) -> 0 | BB12: =BA12/$BA$10 -> #DIV/0! | BC12: =AY12+BA12 -> 0 | BD12: =BC12/$BC$10 -> #DIV/0! | BE12: =BC12-AV12 -> 0 | BF12: =SUMIF('MVTO E'!$C$3:$C$240,"Compras",'MVTO E'!$O$3:$O$240)+SUMIF('DESP E'!$D$3:$D$146,"Compras",'DESP E'!$O$3:$O$146) -> 0 | BG12: =BF12/$P$10 -> 0 | BH12: =SUMIF('MVTO A'!$C$3:$C$195,"Compras",'MVTO A'!$O$3:$O$195)+SUMIF('DESP A'!$D$3:$D$144,"Compras",'DESP A'!$O$3:$O$185) -> 0 | BI12: =BH12/$BH$10 -> #DIV/0! | BJ12: =BF12+BH12 -> 0 | BK12: =BJ12/$BJ$10 -> #DIV/0! | BL12: =BJ12-BC12 -> 0 | BM12: =SUMIF('MVTO E'!$C$3:$C$240,"Compras",'MVTO E'!$P$3:$P$240)+SUMIF('DESP E'!$D$3:$D$146,"Compras",'DESP E'!$P$3:$P$146) -> 0 | BN12: =BM12/$P$10 -> 0 | BO12: =SUMIF('MVTO A'!$C$3:$C$195,"Compras",'MVTO A'!$P$3:$P$195)+SUMIF('DESP A'!$D$3:$D$129,"Compras",'DESP A'!$P$3:$P$129) -> 0 | BP12: =BO12/$BH$10 -> #DIV/0! | BQ12: =BM12+BO12 -> 0 | BR12: =BQ12/$BJ$10 -> #DIV/0! | BS12: =BQ12-BJ12 -> 0 | BT12: =SUMIF('MVTO E'!$C$3:$C$240,"Compras",'MVTO E'!$Q$3:$Q$240)+SUMIF('DESP E'!$D$3:$D$146,"Compras",'DESP E'!$Q$3:$Q$146) -> 0 | BU12: =BT12/$P$10 -> 0 | BV12: =SUMIF('MVTO A'!$C$3:$C$184,"Compras",'MVTO A'!$Q$3:$Q$189)+SUMIF('DESP A'!$D$3:$D$129,"Compras",'DESP A'!$Q$3:$Q$129) -> 0 | BW12: =BV12/$BH$10 -> #DIV/0! | BX12: =BT12+BV12 -> 0 | BY12: =BX12/$BJ$10 -> #DIV/0! | BZ12: =BX12-BQ12 -> 0 | CA12: =SUMIF('MVTO E'!$C$3:$C$240,"Compras",'MVTO E'!$R$3:$R$240)+SUMIF('DESP E'!$D$3:$D$146,"Compras",'DESP E'!$R$3:$R$146) -> 0 | CB12: =CA12/$P$10 -> 0 | CC12: =SUMIF('MVTO A'!$C$3:$C$184,"Compras",'MVTO A'!$R$3:$R$189)+SUMIF('DESP A'!$D$3:$D$174,"Compras",'DESP A'!$R$3:$R$174) -> 0 | CD12: =CC12/$BH$10 -> #DIV/0! | CE12: =CA12+CC12 -> 0 | CF12: =CE12/$BJ$10 -> #DIV/0! | CG12: =CE12-BX12 -> 0 | CH12: =SUM(C12,I12,P12,W12,AD12,AK12,AR12,AY12,BF12,BM12,BT12,CA12) -> 65326876 | CI12: =CH12/$CH$10 -> 0.65237275 | CJ12: =SUM(E12,K12,R12,Y12,AF12,AM12,AT12,BA12,BH12,BO12,BV12,CC12) -> 557820.4 | CK12: =CJ12/$CJ$10 -> 0.039343137 | CL12: =SUM(G12,M12,T12,AA12,AH12,AO12,AV12,BC12,BJ12,BQ12,BX12,CE12) -> 65884696 | CM12: =CL12/$CL$10 -> 0.57633994
B13: ( = ) Margem de Venda | C13: =C10-C11-C12 -> 10278874 | D13: =D10-D11-D12 -> 0.3124182 | E13: =E10-E11-E12 -> 3769374.8 | F13: =F10-F11-F12 -> 0.95385487 | G13: =C13+E13 -> 14048248 | H13: =H10-H11-H12 -> 0.38119961 | I13: =I10-I11-I12 -> 8382397.1 | J13: =J10-J11-J12 -> 0.39483693 | K13: =K10-K11-K12 -> 3297544.4 | L13: =L10-L11-L12 -> 0.96441015 | M13: =I13+K13 -> 11679942 | N13: =N10-N11-N12 -> 0.47384558 | O13: =M13-G13 -> -2368306.8 | P13: =P10-P11-P12 -> 8238549.8 | Q13: =Q10-Q11-Q12 -> 0.46744981 | R13: =R10-R11-R12 -> 3509078.9 | S13: =S10-S11-S12 -> 1.0288989 | T13: =P13+R13 -> 11747629 | U13: =U10-U11-U12 -> 0.42784142 | V13: =T13-M13 -> 67687.2 | W13: =W10-W11-W12 -> 7365094.3 | X13: =X10-X11-X12 -> 0.37672327 | Y13: =Y10-Y11-Y12 -> 3044336.6 | Z13: =Z10-Z11-Z12 -> 0.96437612 | AA13: =W13+Y13 -> 10409431 | AB13: =AB10-AB11-AB12 -> 0.41053468 | AC13: =AA13-T13 -> -1338197.8 | AD13: =AD10-AD11-AD12 -> 0 | AE13: =AE10-AE11-AE12 -> #DIV/0! | AF13: =AF10-AF11-AF12 -> 0 | AG13: =AG10-AG11-AG12 -> #DIV/0! | AH13: =AD13+AF13 -> 0 | AI13: =AI10-AI11-AI12 -> #DIV/0! | AJ13: =AH13-AA13 -> -10409431 | AK13: =AK10-AK11-AK12 -> 0 | AL13: =AL10-AL11-AL12 -> #DIV/0! | AM13: =AM10-AM11-AM12 -> 0 | AN13: =AN10-AN11-AN12 -> #DIV/0! | AO13: =AK13+AM13 -> 0 | AP13: =AP10-AP11-AP12 -> #DIV/0! | AQ13: =AO13-AH13 -> 0 | AR13: =AR10-AR11-AR12 -> 0 | AS13: =AS10-AS11-AS12 -> #DIV/0! | AT13: =AT10-AT11-AT12 -> 0 | AU13: =AU10-AU11-AU12 -> #DIV/0! | AV13: =AR13+AT13 -> 0 | AW13: =AW10-AW11-AW12 -> #DIV/0! | AX13: =AV13-AO13 -> 0 | AY13: =AY10-AY11-AY12 -> 0 | AZ13: =AZ10-AZ11-AZ12 -> #DIV/0! | BA13: =BA10-BA11-BA12 -> 0 | BB13: =BB10-BB11-BB12 -> #DIV/0! | BC13: =AY13+BA13 -> 0 | BD13: =BD10-BD11-BD12 -> #DIV/0! | BE13: =BC13-AV13 -> 0 | BF13: =BF10-BF11-BF12 -> 0 | BG13: =BG10-BG11-BG12 -> #DIV/0! | BH13: =BH10-BH11-BH12 -> 0 | BI13: =BI10-BI11-BI12 -> #DIV/0! | BJ13: =BF13+BH13 -> 0 | BK13: =BK10-BK11-BK12 -> #DIV/0! | BL13: =BJ13-BC13 -> 0 | BM13: =BM10-BM11-BM12 -> 0 | BN13: =BN10-BN11-BN12 -> #DIV/0! | BO13: =BO10-BO11-BO12 -> 0 | BP13: =BP10-BP11-BP12 -> #DIV/0! | BQ13: =BM13+BO13 -> 0 | BR13: =BR10-BR11-BR12 -> #DIV/0! | BS13: =BQ13-BJ13 -> 0 | BT13: =BT10-BT11-BT12 -> 0 | BU13: =BU10-BU11-BU12 -> #DIV/0! | BV13: =BV10-BV11-BV12 -> 0 | BW13: =BW10-BW11-BW12 -> #DIV/0! | BX13: =BT13+BV13 -> 0 | BY13: =BY10-BY11-BY12 -> #DIV/0! | BZ13: =BX13-BQ13 -> 0 | CA13: =CA10-CA11-CA12 -> 0 | CB13: =CB10-CB11-CB12 -> #DIV/0! | CC13: =CC10-CC11-CC12 -> 0 | CD13: =CD10-CD11-CD12 -> #DIV/0! | CE13: =CA13+CC13 -> 0 | CF13: =CF10-CF11-CF12 -> #DIV/0! | CG13: =CE13-BX13 -> 0 | CH13: =CH10-CH11-CH12 -> 34264915 | CI13: =CH13/$CH$10 -> 0.34217918 | CJ13: =CJ10-CJ11-CJ12 -> 13620335 | CK13: =CJ13/$CJ$10 -> 0.96064378 | CL13: =CL10-CL11-CL12 -> 47885250 | CM13: =CL13/$CL$10 -> 0.41888608
B14: ( - ) Impostos Sobre Vendas | C14: =SUMIF('MVTO E'!$C$3:$C$240,"Imp_Vda",'MVTO E'!$G$3:$G$240) -> 4511859.1 | D14: =C14/$C$10 -> 0.13713438 | E14: =SUMIF('MVTO A'!$C$3:$C$184,"Imp_Vda",'MVTO A'!$G$3:$G$184) -> 295759.72 | F14: =E14/$E$10 -> 0.074843142 | G14: =C14+E14 -> 4807618.8 | H14: =G14/$G$10 -> 0.13045487 | I14: =SUMIF('MVTO E'!$C$3:$C$240,"Imp_Vda",'MVTO E'!$H$3:$H$240) -> 2213354.6 | J14: =I14/$I$10 -> 0.10425588 | K14: =SUMIF('MVTO A'!$C$3:$C$184,"Imp_Vda",'MVTO A'!$H$3:$H$184) -> 282321.16 | L14: =K14/$K$10 -> 0.082568528 | M14: =I14+K14 -> 2495675.8 | N14: =M14/$M$10 -> 0.1012475 | O14: =M14-G14 -> -2311943.1 | P14: =SUMIF('MVTO E'!$C$3:$C$240,"Imp_Vda",'MVTO E'!$I$3:$I$240) -> 2370780.4 | Q14: =P14/$P$10 -> 0.099581996 | R14: =SUMIF('MVTO A'!$C$3:$C$184,"Imp_Vda",'MVTO A'!$I$3:$I$184) -> 144833.21 | S14: =R14/$R$10 -> 0.039673978 | T14: =P14+R14 -> 2515613.6 | U14: =T14/$T$10 -> 0.091617102 | V14: =T14-M14 -> 19937.83 | W14: =SUMIF('MVTO E'!$C$3:$C$240,"Imp_Vda",'MVTO E'!$J$3:$J$240) -> 2203266.9 | X14: =W14/$W$10 -> 0.099250746 | Y14: =SUMIF('MVTO A'!$C$3:$C$184,"Imp_Vda",'MVTO A'!$J$3:$J$184) -> 248869.95 | Z14: =Y14/$Y$10 -> 0.0788363 | AA14: =W14+Y14 -> 2452136.8 | AB14: =AA14/$AA$10 -> 0.096709149 | AC14: =AA14-T14 -> -63476.82 | AD14: =SUMIF('MVTO E'!$C$3:$C$240,"Imp_Vda",'MVTO E'!$K$3:$K$240) -> 0 | AE14: =AD14/$AD$10 -> #DIV/0! | AF14: =SUMIF('MVTO A'!$C$3:$C$184,"Imp_Vda",'MVTO A'!$K$3:$K$184) -> 0 | AG14: =AF14/$AF$10 -> #DIV/0! | AH14: =AD14+AF14 -> 0 | AI14: =AH14/$AH$10 -> #DIV/0! | AJ14: =AH14-AA14 -> -2452136.8 | AK14: =SUMIF('MVTO E'!$C$3:$C$240,"Imp_Vda",'MVTO E'!$L$3:$L$240) -> 0 | AL14: =AK14/$AK$10 -> #DIV/0! | AM14: =SUMIF('MVTO A'!$C$3:$C$184,"Imp_Vda",'MVTO A'!$L$3:$L$184) -> 0 | AN14: =AM14/$AM$10 -> #DIV/0! | AO14: =AK14+AM14 -> 0 | AP14: =AO14/$AO$10 -> #DIV/0! | AQ14: =AO14-AH14 -> 0 | AR14: =SUMIF('MVTO E'!$C$3:$C$240,"Imp_Vda",'MVTO E'!$M$3:$M$240) -> 0 | AS14: =AR14/$AR$10 -> #DIV/0! | AT14: =SUMIF('MVTO A'!$C$3:$C$184,"Imp_Vda",'MVTO A'!$M$3:$M$189) -> 0 | AU14: =AT14/$AT$10 -> #DIV/0! | AV14: =AR14+AT14 -> 0 | AW14: =AV14/$AV$10 -> #DIV/0! | AX14: =AV14-AO14 -> 0 | AY14: =SUMIF('MVTO E'!$C$3:$C$240,"Imp_Vda",'MVTO E'!$N$3:$N$240) -> 0 | AZ14: =AY14/$AY$10 -> #DIV/0! | BA14: =SUMIF('MVTO A'!$C$3:$C$184,"Imp_Vda",'MVTO A'!$N$3:$N$189) -> 0 | BB14: =BA14/$BA$10 -> #DIV/0! | BC14: =AY14+BA14 -> 0 | BD14: =BC14/$BC$10 -> #DIV/0! | BE14: =BC14-AV14 -> 0 | BF14: =SUMIF('MVTO E'!$C$3:$C$240,"Imp_Vda",'MVTO E'!$O$3:$O$240) -> 0 | BG14: =BF14/$BF$10 -> #DIV/0! | BH14: =SUMIF('MVTO A'!$C$3:$C$195,"Imp_Vda",'MVTO A'!$O$3:$O$195) -> 0 | BI14: =BH14/$BH$10 -> #DIV/0! | BJ14: =BF14+BH14 -> 0 | BK14: =BJ14/$BJ$10 -> #DIV/0! | BL14: =BJ14-BC14 -> 0 | BM14: =SUMIF('MVTO E'!$C$3:$C$240,"Imp_Vda",'MVTO E'!$P$3:$P$240) -> 0 | BN14: =BM14/$BF$10 -> #DIV/0! | BO14: =SUMIF('MVTO A'!$C$3:$C$184,"Imp_Vda",'MVTO A'!$P$3:$P$189) -> 0 | BP14: =BO14/$BH$10 -> #DIV/0! | BQ14: =BM14+BO14 -> 0 | BR14: =BQ14/$BJ$10 -> #DIV/0! | BS14: =BQ14-BJ14 -> 0 | BT14: =SUMIF('MVTO E'!$C$3:$C$240,"Imp_Vda",'MVTO E'!$Q$3:$Q$240) -> 0 | BU14: =BT14/$BF$10 -> #DIV/0! | BV14: =SUMIF('MVTO A'!$C$3:$C$184,"Imp_Vda",'MVTO A'!$Q$3:$Q$189) -> 0 | BW14: =BV14/$BH$10 -> #DIV/0! | BX14: =BT14+BV14 -> 0 | BY14: =BX14/$BJ$10 -> #DIV/0! | BZ14: =BX14-BQ14 -> 0 | CA14: =SUMIF('MVTO E'!$C$3:$C$240,"Imp_Vda",'MVTO E'!$R$3:$R$240) -> 0 | CB14: =CA14/$BF$10 -> #DIV/0! | CC14: =SUMIF('MVTO A'!$C$3:$C$184,"Imp_Vda",'MVTO A'!$R$3:$R$189) -> 0 | CD14: =CC14/$BH$10 -> #DIV/0! | CE14: =CA14+CC14 -> 0 | CF14: =CE14/$BJ$10 -> #DIV/0! | CG14: =CE14-BX14 -> 0 | CH14: =SUM(C14,I14,P14,W14,AD14,AK14,AR14,AY14,BF14,BM14,BT14,CA14) -> 11299261 | CI14: =CH14/$CH$10 -> 0.11283763 | CJ14: =SUM(E14,K14,R14,Y14,AF14,AM14,AT14,BA14,BH14,BO14,BV14,CC14) -> 971784.04 | CK14: =CJ14/$CJ$10 -> 0.06854004 | CL14: =SUM(G14,M14,T14,AA14,AH14,AO14,AV14,BC14,BJ14,BQ14,BX14,CE14) -> 12271045 | CM14: =CL14/$CL$10 -> 0.10734349
B15: ( + ) Adiantamentos de Clientes/Outras Receitas | C15: =SUMIF('MVTO E'!$C$3:$C$240,"Outros_Creditos",'MVTO E'!$G$3:$G$240) -> 73614.99 | D15: =C15/$C$10 -> 0.0022374692 | E15: =SUMIF('MVTO A'!$C$3:$C$184,"Outros_Creditos",'MVTO A'!$G$3:$G$184) -> 4773.84 | F15: =E15/$E$10 -> 0.0012080387 | G15: =C15+E15 -> 78388.83 | H15: =G15/$G$10 -> 0.0021270831 | I15: =SUMIF('MVTO E'!$C$3:$C$240,"Outros_Creditos",'MVTO E'!$H$3:$H$240) -> 112375.92 | J15: =I15/$I$10 -> 0.0052932548 | K15: =SUMIF('MVTO A'!$C$3:$C$184,"Outros_Creditos",'MVTO A'!$H$3:$H$184) -> 12404.57 | L15: =K15/$K$10 -> 0.0036278793 | M15: =I15+K15 -> 124780.49 | N15: =M15/$M$10 -> 0.0050622413 | O15: =M15-G15 -> 46391.66 | P15: =SUMIF('MVTO E'!$C$3:$C$240,"Outros_Creditos",'MVTO E'!$I$3:$I$240) -> 70164.12 | Q15: =P15/$P$10 -> 0.0029471659 | R15: =SUMIF('MVTO A'!$C$3:$C$184,"Outros_Creditos",'MVTO A'!$I$3:$I$184) -> 21701.73 | S15: =R15/$R$10 -> 0.0059447274 | T15: =P15+R15 -> 91865.85 | U15: =T15/$T$10 -> 0.0033456978 | V15: =T15-M15 -> -32914.64 | W15: =SUMIF('MVTO E'!$C$3:$C$240,"Outros_Creditos",'MVTO E'!$J$3:$J$240) -> 39439.29 | X15: =W15/$W$10 -> 0.001776625 | Y15: =SUMIF('MVTO A'!$C$3:$C$184,"Outros_Creditos",'MVTO A'!$J$3:$J$184) -> 16268.44 | Z15: =Y15/$Y$10 -> 0.0051534692 | AA15: =W15+Y15 -> 55707.73 | AB15: =AA15/$AA$10 -> 0.0021970418 | AC15: =AA15-T15 -> -36158.12 | AD15: =SUMIF('MVTO E'!$C$3:$C$240,"Outros_Creditos",'MVTO E'!$K$3:$K$240) -> 0 | AE15: =AD15/$AD$10 -> #DIV/0! | AF15: =SUMIF('MVTO A'!$C$3:$C$184,"Outros_Creditos",'MVTO A'!$K$3:$K$184) -> 0 | AG15: =AF15/$AF$10 -> #DIV/0! | AH15: =AD15+AF15 -> 0 | AI15: =AH15/$AH$10 -> #DIV/0! | AJ15: =AH15-AA15 -> -55707.73 | AK15: =SUMIF('MVTO E'!$C$3:$C$240,"Outros_Creditos",'MVTO E'!$L$3:$L$240) -> 0 | AL15: =AK15/$AK$10 -> #DIV/0! | AM15: =SUMIF('MVTO A'!$C$3:$C$184,"Outros_Creditos",'MVTO A'!$L$3:$L$184) -> 0 | AN15: =AM15/$AM$10 -> #DIV/0! | AO15: =AK15+AM15 -> 0 | AP15: =AO15/$AO$10 -> #DIV/0! | AQ15: =AO15-AH15 -> 0 | AR15: =SUMIF('MVTO E'!$C$3:$C$240,"Outros_Creditos",'MVTO E'!$M$3:$M$240) -> 0 | AS15: =AR15/$AR$10 -> #DIV/0! | AT15: =SUMIF('MVTO A'!$C$3:$C$184,"Outros_Creditos",'MVTO A'!$M$3:$M$189) -> 0 | AU15: =AT15/$AT$10 -> #DIV/0! | AV15: =AR15+AT15 -> 0 | AW15: =AV15/$AV$10 -> #DIV/0! | AX15: =AV15-AO15 -> 0 | AY15: =SUMIF('MVTO E'!$C$3:$C$240,"Outros_Creditos",'MVTO E'!$N$3:$N$240) -> 0 | AZ15: =AY15/$AY$10 -> #DIV/0! | BA15: =SUMIF('MVTO A'!$C$3:$C$184,"Outros_Creditos",'MVTO A'!$N$3:$N$189) -> 0 | BB15: =BA15/$BA$10 -> #DIV/0! | BC15: =AY15+BA15 -> 0 | BD15: =BC15/$BC$10 -> #DIV/0! | BE15: =BC15-AV15 -> 0 | BF15: =SUMIF('MVTO E'!$C$3:$C$240,"Outros_Creditos",'MVTO E'!$O$3:$O$240) -> 0 | BG15: =BF15/$BF$10 -> #DIV/0! | BH15: =SUMIF('MVTO A'!$C$3:$C$195,"Outros_Creditos",'MVTO A'!$O$3:$O$195) -> 0 | BI15: =BH15/$BH$10 -> #DIV/0! | BJ15: =BF15+BH15 -> 0 | BK15: =BJ15/$BJ$10 -> #DIV/0! | BL15: =BJ15-BC15 -> 0 | BM15: =SUMIF('MVTO E'!$C$3:$C$240,"Outros_Creditos",'MVTO E'!$P$3:$P$240) -> 0 | BN15: =BM15/$BF$10 -> #DIV/0! | BO15: =SUMIF('MVTO A'!$C$3:$C$184,"Outros_Creditos",'MVTO A'!$P$3:$P$189) -> 0 | BP15: =BO15/$BH$10 -> #DIV/0! | BQ15: =BM15+BO15 -> 0 | BR15: =BQ15/$BJ$10 -> #DIV/0! | BS15: =BQ15-BJ15 -> 0 | BT15: =SUMIF('MVTO E'!$C$3:$C$240,"Outros_Creditos",'MVTO E'!$Q$3:$Q$240) -> 0 | BU15: =BT15/$BF$10 -> #DIV/0! | BV15: =SUMIF('MVTO A'!$C$3:$C$184,"Outros_Creditos",'MVTO A'!$Q$3:$Q$189) -> 0 | BW15: =BV15/$BH$10 -> #DIV/0! | BX15: =BT15+BV15 -> 0 | BY15: =BX15/$BJ$10 -> #DIV/0! | BZ15: =BX15-BQ15 -> 0 | CA15: =SUMIF('MVTO E'!$C$3:$C$240,"Outros_Creditos",'MVTO E'!$R$3:$R$240) -> 0 | CB15: =CA15/$BF$10 -> #DIV/0! | CC15: =SUMIF('MVTO A'!$C$3:$C$184,"Outros_Creditos",'MVTO A'!$R$3:$R$189) -> 0 | CD15: =CC15/$BH$10 -> #DIV/0! | CE15: =CA15+CC15 -> 0 | CF15: =CE15/$BJ$10 -> #DIV/0! | CG15: =CE15-BX15 -> 0 | CH15: =SUM(C15,I15,P15,W15,AD15,AK15,AR15,AY15,BF15,BM15,BT15,CA15) -> 295594.32 | CI15: =CH15/$CH$10 -> 0.0029518889 | CJ15: =SUM(E15,K15,R15,Y15,AF15,AM15,AT15,BA15,BH15,BO15,BV15,CC15) -> 55148.58 | CK15: =CJ15/$CJ$10 -> 0.0038896357 | CL15: =SUM(G15,M15,T15,AA15,AH15,AO15,AV15,BC15,BJ15,BQ15,BX15,CE15) -> 350742.9 | CM15: =CL15/$CL$10 -> 0.0030681957
B16: ( - ) Adiantamentos Utilizados | C16: =SUMIF('MVTO E'!$C$3:$C$240,"Outros_Debitos",'MVTO E'!$G$3:$G$240)+SUMIF('DESP E'!$D$3:$D$146,"S_Fornec",'DESP E'!$G$3:$G$146) -> 1280.29 | D16: =C16/$C$10 -> 3.8913398e-05 | E16: =SUMIF('MVTO A'!$C$3:$C$184,"Outros_Debitos",'MVTO A'!$G$3:$G$184)+SUMIF('DESP A'!$D$3:$D$129,"S_Fornec",'DESP A'!$G$3:$G$129) -> 0 | F16: =E16/$E$10 -> 0 | G16: =C16+E16 -> 1280.29 | H16: =G16/$G$10 -> 3.4740705e-05 | I16: =SUMIF('MVTO E'!$C$3:$C$240,"Outros_Debitos",'MVTO E'!$H$3:$H$240)+SUMIF('DESP E'!$D$3:$D$146,"S_Fornec",'DESP E'!$H$3:$H$146) -> 688.64 | J16: =I16/$I$10 -> 3.2437082e-05 | K16: =SUMIF('MVTO A'!$C$3:$C$184,"Outros_Debitos",'MVTO A'!$H$3:$H$184)+SUMIF('DESP A'!$D$3:$D$129,"S_Fornec",'DESP A'!$H$3:$H$129) -> 0 | L16: =K16/$K$10 -> 0 | M16: =I16+K16 -> 688.64 | N16: =M16/$M$10 -> 2.7937556e-05 | O16: =M16-G16 -> -591.65 | P16: =SUMIF('MVTO E'!$C$3:$C$240,"Outros_Debitos",'MVTO E'!$I$3:$I$240)+SUMIF('DESP E'!$D$3:$D$146,"S_Fornec",'DESP E'!$I$3:$I$146) -> 234.92 | Q16: =P16/$P$10 -> 9.8675535e-06 | R16: =SUMIF('MVTO A'!$C$3:$C$184,"Outros_Debitos",'MVTO A'!$I$3:$I$184)+SUMIF('DESP A'!$D$3:$D$129,"S_Fornec",'DESP A'!$I$3:$I$129) -> 166.98 | S16: =R16/$R$10 -> 4.574062e-05 | T16: =P16+R16 -> 401.9 | U16: =T16/$T$10 -> 1.4636951e-05 | V16: =T16-M16 -> -286.74 | W16: =SUMIF('MVTO E'!$C$3:$C$240,"Outros_Debitos",'MVTO E'!$J$3:$J$240)+SUMIF('DESP E'!$D$3:$D$146,"S_Fornec",'DESP E'!$J$3:$J$146) -> 216.79 | X16: =W16/$W$10 -> 9.7657572e-06 | Y16: =SUMIF('MVTO A'!$C$3:$C$184,"Outros_Debitos",'MVTO A'!$J$3:$J$184)+SUMIF('DESP A'!$D$3:$D$129,"S_Fornec",'DESP A'!$J$3:$J$129) -> 0 | Z16: =Y16/$Y$10 -> 0 | AA16: =W16+Y16 -> 216.79 | AB16: =AA16/$AA$10 -> 8.5499212e-06 | AC16: =AA16-T16 -> -185.11 | AD16: =SUMIF('MVTO E'!$C$3:$C$240,"Outros_Debitos",'MVTO E'!$K$3:$K$240)+SUMIF('DESP E'!$D$3:$D$146,"S_Fornec",'DESP E'!$K$3:$K$146) -> 0 | AE16: =AD16/$AD$10 -> #DIV/0! | AF16: =SUMIF('MVTO A'!$C$3:$C$184,"Outros_Debitos",'MVTO A'!$K$3:$K$184)+SUMIF('DESP A'!$D$3:$D$129,"S_Fornec",'DESP A'!$K$3:$K$129) -> 0 | AG16: =AF16/$AF$10 -> #DIV/0! | AH16: =AD16+AF16 -> 0 | AI16: =AH16/$AH$10 -> #DIV/0! | AJ16: =AH16-AA16 -> -216.79 | AK16: =SUMIF('MVTO E'!$C$3:$C$240,"Outros_Debitos",'MVTO E'!$L$3:$L$240)+SUMIF('DESP E'!$D$3:$D$146,"S_Fornec",'DESP E'!$L$3:$L$146) -> 0 | AL16: =AK16/$AK$10 -> #DIV/0! | AM16: =SUMIF('MVTO A'!$C$3:$C$184,"Outros_Debitos",'MVTO A'!$L$3:$L$184)+SUMIF('DESP A'!$D$3:$D$129,"S_Fornec",'DESP A'!$L$3:$L$129) -> 0 | AN16: =AM16/$AM$10 -> #DIV/0! | AO16: =AK16+AM16 -> 0 | AP16: =AO16/$AO$10 -> #DIV/0! | AQ16: =AO16-AH16 -> 0 | AR16: =SUMIF('MVTO E'!$C$3:$C$240,"Outros_Debitos",'MVTO E'!$M$3:$M$240)+SUMIF('DESP E'!$D$3:$D$146,"S_Fornec",'DESP E'!$M$3:$M$146) -> 0 | AS16: =AR16/$AR$10 -> #DIV/0! | AT16: =SUMIF('MVTO A'!$C$3:$C$184,"Outros_Debitos",'MVTO A'!$M$3:$M$189)+SUMIF('DESP A'!$D$3:$D$129,"S_Fornec",'DESP A'!$M$3:$M$129) -> 0 | AU16: =AT16/$AT$10 -> #DIV/0! | AV16: =AR16+AT16 -> 0 | AW16: =AV16/$AV$10 -> #DIV/0! | AX16: =AV16-AO16 -> 0 | AY16: =SUMIF('MVTO E'!$C$3:$C$240,"Outros_Debitos",'MVTO E'!$N$3:$N$240)+SUMIF('DESP E'!$D$3:$D$146,"S_Fornec",'DESP E'!$N$3:$N$146) -> 0 | AZ16: =AY16/$AY$10 -> #DIV/0! | BA16: =SUMIF('MVTO A'!$C$3:$C$184,"Outros_Debitos",'MVTO A'!$N$3:$N$189)+SUMIF('DESP A'!$D$3:$D$129,"S_Fornec",'DESP A'!$N$3:$N$129) -> 0 | BB16: =BA16/$BA$10 -> #DIV/0! | BC16: =AY16+BA16 -> 0 | BD16: =BC16/$BC$10 -> #DIV/0! | BE16: =BC16-AV16 -> 0 | BF16: =SUMIF('MVTO E'!$C$3:$C$240,"Outros_Debitos",'MVTO E'!$O$3:$O$240)+SUMIF('DESP E'!$D$3:$D$146,"S_Fornec",'DESP E'!$O$3:$O$146) -> 0 | BG16: =BF16/$BF$10 -> #DIV/0! | BH16: =SUMIF('MVTO A'!$C$3:$C$195,"Outros_Debitos",'MVTO A'!$O$3:$O$195)+SUMIF('DESP A'!$D$3:$D$144,"S_Fornec",'DESP A'!$O$3:$O$144) -> 0 | BI16: =BH16/$BH$10 -> #DIV/0! | BJ16: =BF16+BH16 -> 0 | BK16: =BJ16/$BJ$10 -> #DIV/0! | BL16: =BJ16-BC16 -> 0 | BM16: =SUMIF('MVTO E'!$C$3:$C$240,"Outros_Debitos",'MVTO E'!$P$3:$P$240)+SUMIF('DESP E'!$D$3:$D$146,"S_Fornec",'DESP E'!$P$3:$P$146) -> 0 | BN16: =BM16/$BF$10 -> #DIV/0! | BO16: =SUMIF('MVTO A'!$C$3:$C$184,"Outros_Debitos",'MVTO A'!$P$3:$P$189)+SUMIF('DESP A'!$D$3:$D$129,"S_Fornec",'DESP A'!$P$3:$P$129) -> 0 | BP16: =BO16/$BH$10 -> #DIV/0! | BQ16: =BM16+BO16 -> 0 | BR16: =BQ16/$BJ$10 -> #DIV/0! | BS16: =BQ16-BJ16 -> 0 | BT16: =SUMIF('MVTO E'!$C$3:$C$240,"Outros_Debitos",'MVTO E'!$Q$3:$Q$240)+SUMIF('DESP E'!$D$3:$D$146,"S_Fornec",'DESP E'!$Q$3:$Q$146) -> 0 | BU16: =BT16/$BF$10 -> #DIV/0! | BV16: =SUMIF('MVTO A'!$C$3:$C$184,"Outros_Debitos",'MVTO A'!$Q$3:$Q$189)+SUMIF('DESP A'!$D$3:$D$129,"S_Fornec",'DESP A'!$Q$3:$Q$129) -> 0 | BW16: =BV16/$BH$10 -> #DIV/0! | BX16: =BT16+BV16 -> 0 | BY16: =BX16/$BJ$10 -> #DIV/0! | BZ16: =BX16-BQ16 -> 0 | CA16: =SUMIF('MVTO E'!$C$3:$C$240,"Outros_Debitos",'MVTO E'!$R$3:$R$240)+SUMIF('DESP E'!$D$3:$D$146,"S_Fornec",'DESP E'!$R$3:$R$146) -> 0 | CB16: =CA16/$BF$10 -> #DIV/0! | CC16: =SUMIF('MVTO A'!$C$3:$C$184,"Outros_Debitos",'MVTO A'!$R$3:$R$189)+SUMIF('DESP A'!$D$3:$D$129,"S_Fornec",'DESP A'!$R$3:$R$129) -> 0 | CD16: =CC16/$BH$10 -> #DIV/0! | CE16: =CA16+CC16 -> 0 | CF16: =CE16/$BJ$10 -> #DIV/0! | CG16: =CE16-BX16 -> 0 | CH16: =SUM(C16,I16,P16,W16,AD16,AK16,AR16,AY16,BF16,BM16,BT16,CA16) -> 2420.64 | CI16: =CH16/$CH$10 -> 2.4173199e-05 | CJ16: =SUM(E16,K16,R16,Y16,AF16,AM16,AT16,BA16,BH16,BO16,BV16,CC16) -> 166.98 | CK16: =CJ16/$CJ$10 -> 1.1777119e-05 | CL16: =SUM(G16,M16,T16,AA16,AH16,AO16,AV16,BC16,BJ16,BQ16,BX16,CE16) -> 2587.62 | CM16: =CL16/$CL$10 -> 2.2635739e-05
B17: ( + ) Entradas de Fornecedores | C17: =SUMIF('MVTO E'!$C$3:$C$240,"E_Fornec",'MVTO E'!$G$3:$G$240) -> 796075.4 | D17: =C17/$C$10 -> 0.02419608 | E17: =SUMIF('MVTO A'!$C$3:$C$177,"E_Fornec",'MVTO A'!$G$3:$G$177) -> 0 | F17: =E17/$E$10 -> 0 | G17: =C17+E17 -> 796075.4 | H17: =G17/$G$10 -> 0.021601528 | I17: =SUMIF('MVTO E'!$C$3:$C$240,"E_Fornec",'MVTO E'!$H$3:$H$240) -> 1178828.3 | J17: =I17/$I$10 -> 0.055526474 | K17: =SUMIF('MVTO A'!$C$3:$C$177,"E_Fornec",'MVTO A'!$H$3:$H$177) -> 0 | L17: =K17/$K$10 -> 0 | M17: =I17+K17 -> 1178828.3 | N17: =M17/$M$10 -> 0.047824091 | O17: =M17-G17 -> 382752.92 | P17: =SUMIF('MVTO E'!$C$3:$C$240,"E_Fornec",'MVTO E'!$I$3:$I$240) -> 660281.49 | Q17: =P17/$P$10 -> 0.02773439 | R17: =SUMIF('MVTO A'!$C$3:$C$177,"E_Fornec",'MVTO A'!$I$3:$I$177) -> 0 | S17: =R17/$R$10 -> 0 | T17: =P17+R17 -> 660281.49 | U17: =T17/$T$10 -> 0.024047046 | V17: =T17-M17 -> -518546.83 | W17: =SUMIF('MVTO E'!$C$3:$C$240,"E_Fornec",'MVTO E'!$J$3:$J$240) -> 554889.82 | X17: =W17/$W$10 -> 0.024996168 | Y17: =SUMIF('MVTO A'!$C$3:$C$177,"E_Fornec",'MVTO A'!$J$3:$J$184) -> 0 | Z17: =Y17/$Y$10 -> 0 | AA17: =W17+Y17 -> 554889.82 | AB17: =AA17/$AA$10 -> 0.021884147 | AC17: =AA17-T17 -> -105391.67 | AD17: =SUMIF('MVTO E'!$C$3:$C$240,"E_Fornec",'MVTO E'!$K$3:$K$240) -> 0 | AE17: =AD17/$AD$10 -> #DIV/0! | AF17: =SUMIF('MVTO A'!$C$3:$C$177,"E_Fornec",'MVTO A'!$K$3:$K$177) -> 0 | AG17: =AF17/$AF$10 -> #DIV/0! | AH17: =AD17+AF17 -> 0 | AI17: =AH17/$AH$10 -> #DIV/0! | AJ17: =AH17-AA17 -> -554889.82 | AK17: =SUMIF('MVTO E'!$C$3:$C$240,"E_Fornec",'MVTO E'!$L$3:$L$240) -> 0 | AL17: =AK17/$AK$10 -> #DIV/0! | AM17: =SUMIF('MVTO A'!$C$3:$C$177,"E_Fornec",'MVTO A'!$I$3:$I$177) -> 0 | AN17: =AM17/$AM$10 -> #DIV/0! | AO17: =AK17+AM17 -> 0 | AP17: =AO17/$AO$10 -> #DIV/0! | AQ17: =AO17-AH17 -> 0 | AR17: =SUMIF('MVTO E'!$C$3:$C$240,"E_Fornec",'MVTO E'!$M$3:$M$240) -> 0 | AS17: =AR17/$AR$10 -> #DIV/0! | AT17: =SUMIF('MVTO A'!$C$3:$C$177,"E_Fornec",'MVTO A'!$M$3:$M$189) -> 0 | AU17: =AT17/$AT$10 -> #DIV/0! | AV17: =AR17+AT17 -> 0 | AW17: =AV17/$AV$10 -> #DIV/0! | AX17: =AV17-AO17 -> 0 | AY17: =SUMIF('MVTO E'!$C$3:$C$240,"E_Fornec",'MVTO E'!$N$3:$N$240) -> 0 | AZ17: =AY17/$AY$10 -> #DIV/0! | BA17: =SUMIF('MVTO A'!$C$3:$C$177,"E_Fornec",'MVTO A'!$I$3:$I$177) -> 0 | BB17: =BA17/$BA$10 -> #DIV/0! | BC17: =AY17+BA17 -> 0 | BD17: =BC17/$BC$10 -> #DIV/0! | BE17: =BC17-AV17 -> 0 | BF17: =SUMIF('MVTO E'!$C$3:$C$240,"E_Fornec",'MVTO E'!$O$3:$O$240) -> 0 | BG17: =BF17/$BF$10 -> #DIV/0! | BH17: =SUMIF('MVTO A'!$C$3:$C$177,"E_Fornec",'MVTO A'!$I$3:$I$195) -> 0 | BI17: =BH17/$BH$10 -> #DIV/0! | BJ17: =BF17+BH17 -> 0 | BK17: =BJ17/$BJ$10 -> #DIV/0! | BL17: =BJ17-BC17 -> 0 | BM17: =SUMIF('MVTO E'!$C$3:$C$240,"E_Fornec",'MVTO E'!$P$3:$P$240) -> 0 | BN17: =BM17/$BF$10 -> #DIV/0! | BO17: =SUMIF('MVTO A'!$C$3:$C$177,"E_Fornec",'MVTO A'!$I$3:$I$177) -> 0 | BP17: =BO17/$BH$10 -> #DIV/0! | BQ17: =BM17+BO17 -> 0 | BR17: =BQ17/$BJ$10 -> #DIV/0! | BS17: =BQ17-BJ17 -> 0 | BT17: =SUMIF('MVTO E'!$C$3:$C$240,"E_Fornec",'MVTO E'!$Q$3:$Q$240) -> 0 | BU17: =BT17/$BF$10 -> #DIV/0! | BV17: =SUMIF('MVTO A'!$C$3:$C$177,"E_Fornec",'MVTO A'!$I$3:$I$177) -> 0 | BW17: =BV17/$BH$10 -> #DIV/0! | BX17: =BT17+BV17 -> 0 | BY17: =BX17/$BJ$10 -> #DIV/0! | BZ17: =BX17-BQ17 -> 0 | CA17: =SUMIF('MVTO E'!$C$3:$C$240,"E_Fornec",'MVTO E'!$R$3:$R$240) -> 0 | CB17: =CA17/$BF$10 -> #DIV/0! | CC17: =SUMIF('MVTO A'!$C$3:$C$177,"E_Fornec",'MVTO A'!$I$3:$I$177) -> 0 | CD17: =CC17/$BH$10 -> #DIV/0! | CE17: =CA17+CC17 -> 0 | CF17: =CE17/$BJ$10 -> #DIV/0! | CG17: =CE17-BX17 -> 0 | CH17: =SUM(C17,I17,P17,W17,AD17,AK17,AR17,AY17,BF17,BM17,BT17,CA17) -> 3190075 | CI17: =CH17/$CH$10 -> 0.031856996 | CJ17: =SUM(E17,K17,R17,Y17,AF17,AM17,AT17,BA17,BH17,BO17,BV17,CC17) -> 0 | CK17: =CJ17/$CJ$10 -> 0 | CL17: =SUM(G17,M17,T17,AA17,AH17,AO17,AV17,BC17,BJ17,BQ17,BX17,CE17) -> 3190075 | CM17: =CL17/$CL$10 -> 0.027905838
B19: Lucro Bruto | C19: =C13-C14+C15-C16+C17 -> 6635424.6 | D19: =C19/$C$10 -> 0.20167846 | E19: =E13-E14+E15-E16+E17 -> 3478388.9 | F19: =E19/$C$10 -> 0.10572287 | G19: =C19+E19 -> 10113813 | H19: =G19/$C$10 -> 0.30740133 | I19: =I13-I14+I15-I16+I17 -> 7459558.1 | J19: =I19/$I$10 -> 0.35136835 | K19: =K13-K14+K15-K16+K17 -> 3027627.8 | L19: =K19/$K$10 -> 0.8854695 | M19: =I19+K19 -> 10487186 | N19: =M19/$M$10 -> 0.42545647 | O19: =M19-G19 -> 373372.45 | P19: =P13-P14+P15-P16+P17 -> 6597980.1 | Q19: =P19/$P$10 -> 0.27714082 | R19: =R13-R14+R15-R16+R17 -> 3385780.5 | S19: =R19/$C$10 -> 0.10290811 | T19: =P19+R19 -> 9983760.6 | U19: =T19/$C$10 -> 0.30344847 | V19: =T19-M19 -> -503425.36 | W19: =W13-W14+W15-W16+W17 -> 5755939.8 | X19: =W19/$W$10 -> 0.2592883 | Y19: =Y13-Y14+Y15-Y16+Y17 -> 2811735.1 | Z19: =Y19/$C$10 -> 0.085460456 | AA19: =W19+Y19 -> 8567674.9 | AB19: =AA19/$C$10 -> 0.26040768 | AC19: =AA19-T19 -> -1416085.7 | AD19: =AD13-AD14+AD15-AD16+AD17 -> 0 | AE19: =AD19/$AD$10 -> #DIV/0! | AF19: =AF13-AF14+AF15-AF16+AF17 -> 0 | AG19: =AF19/$C$10 -> 0 | AH19: =AD19+AF19 -> 0 | AI19: =AH19/$C$10 -> 0 | AJ19: =AH19-AA19 -> -8567674.9 | AK19: =AK13-AK14+AK15-AK16+AK17 -> 0 | AL19: =AK19/$AK$10 -> #DIV/0! | AM19: =AM13-AM14+AM15-AM16+AM17 -> 0 | AN19: =AM19/$C$10 -> 0 | AO19: =AK19+AM19 -> 0 | AP19: =AO19/$C$10 -> 0 | AQ19: =AO19-AH19 -> 0 | AR19: =AR13-AR14+AR15-AR16+AR17 -> 0 | AS19: =AR19/$AR$10 -> #DIV/0! | AT19: =AT13-AT14+AT15-AT16+AT17 -> 0 | AU19: =AT19/$C$10 -> 0 | AV19: =AR19+AT19 -> 0 | AW19: =AV19/$C$10 -> 0 | AX19: =AV19-AO19 -> 0 | AY19: =AY13-AY14+AY15-AY16+AY17 -> 0 | AZ19: =AY19/$AY$10 -> #DIV/0! | BA19: =BA13-BA14+BA15-BA16+BA17 -> 0 | BB19: =BA19/$C$10 -> 0 | BC19: =AY19+BA19 -> 0 | BD19: =BC19/$C$10 -> 0 | BE19: =BC19-AV19 -> 0 | BF19: =BF13-BF14+BF15-BF16+BF17 -> 0 | BG19: =BF19/$BF$10 -> #DIV/0! | BH19: =BH13-BH14+BH15-BH16+BH17 -> 0 | BI19: =BH19/$C$10 -> 0 | BJ19: =BF19+BH19 -> 0 | BK19: =BJ19/$C$10 -> 0 | BL19: =BJ19-BC19 -> 0 | BM19: =BM13-BM14+BM15-BM16+BM17 -> 0 | BN19: =BM19/$BF$10 -> #DIV/0! | BO19: =BO13-BO14+BO15-BO16+BO17 -> 0 | BP19: =BO19/$C$10 -> 0 | BQ19: =BM19+BO19 -> 0 | BR19: =BQ19/$C$10 -> 0 | BS19: =BQ19-BJ19 -> 0 | BT19: =BT13-BT14+BT15-BT16+BT17 -> 0 | BU19: =BT19/$BF$10 -> #DIV/0! | BV19: =BV13-BV14+BV15-BV16+BV17 -> 0 | BW19: =BV19/$C$10 -> 0 | BX19: =BT19+BV19 -> 0 | BY19: =BX19/$C$10 -> 0 | BZ19: =BX19-BQ19 -> 0 | CA19: =CA13-CA14+CA15-CA16+CA17 -> 0 | CB19: =CA19/$BF$10 -> #DIV/0! | CC19: =CC13-CC14+CC15-CC16+CC17 -> 0 | CD19: =CC19/$C$10 -> 0 | CE19: =CA19+CC19 -> 0 | CF19: =CE19/$C$10 -> 0 | CG19: =CE19-BX19 -> 0 | CH19: =CH13-CH14+CH15-CH16+CH17 -> 26448903 | CI19: =CH19/$CH$10 -> 0.26412626 | CJ19: =CJ13-CJ14+CJ15-CJ16+CJ17 -> 12703532 | CK19: =CJ19/$CJ$10 -> 0.8959816 | CL19: =CL13-CL14+CL15-CL16+CL17 -> 39152435 | CM19: =CL19/$CL$10 -> 0.34249398
B20: Total de custos operacionais | C20: =SUM(C21:C41) -> 5596371 | D20: =C20/$C$10 -> 0.17009725 | E20: =SUM(E21:E41) -> 1195319.5 | F20: =E20/$E$10 -> 0.30248022 | G20: =C20+E20 -> 6791690.5 | H20: =G20/$G$10 -> 0.18429271 | I20: =SUM(I21:I41) -> 4644621.5 | J20: =I20/$I$10 -> 0.2187761 | K20: =SUM(K21:K41) -> 1207389.8 | L20: =K20/$K$10 -> 0.353117 | M20: =I20+K20 -> 5852011.4 | N20: =M20/$M$10 -> 0.23741126 | O20: =M20-G20 -> -939679.13 | P20: =SUM(P21:P41) -> 4747249.9 | Q20: =P20/$P$10 -> 0.19940296 | R20: =SUM(R21:R41) -> 1143000.8 | S20: =R20/$R$10 -> 0.31310077 | T20: =P20+R20 -> 5890250.8 | U20: =T20/$T$10 -> 0.21451931 | V20: =T20-M20 -> 38239.39 | W20: =SUM(W21:W41) -> 4767282.2 | X20: =W20/$W$10 -> 0.21475216 | Y20: =SUM(Y21:Y41) -> 981211.62 | Z20: =Y20/$Y$10 -> 0.31082537 | AA20: =W20+Y20 -> 5748493.8 | AB20: =AA20/$AA$10 -> 0.22671327 | AC20: =AA20-T20 -> -141756.93 | AD20: =SUM(AD21:AD41) -> 0 | AE20: =AD20/$AD$10 -> #DIV/0! | AF20: =SUM(AF21:AF41) -> 0 | AG20: =AF20/$AF$10 -> #DIV/0! | AH20: =AD20+AF20 -> 0 | AI20: =AH20/$AH$10 -> #DIV/0! | AJ20: =AH20-AA20 -> -5748493.8 | AK20: =SUM(AK21:AK41) -> 0 | AL20: =AK20/$AK$10 -> #DIV/0! | AM20: =SUM(AM21:AM41) -> 0 | AN20: =AM20/$AM$10 -> #DIV/0! | AO20: =AK20+AM20 -> 0 | AP20: =AO20/$AO$10 -> #DIV/0! | AQ20: =AO20-AH20 -> 0 | AR20: =SUM(AR21:AR41) -> 0 | AS20: =AR20/$AR$10 -> #DIV/0! | AT20: =SUM(AT21:AT41) -> 0 | AU20: =AT20/$AT$10 -> #DIV/0! | AV20: =AR20+AT20 -> 0 | AW20: =AV20/$AV$10 -> #DIV/0! | AX20: =AV20-AO20 -> 0 | AY20: =SUM(AY21:AY41) -> 0 | AZ20: =AY20/$AY$10 -> #DIV/0! | BA20: =SUM(BA21:BA41) -> 0 | BB20: =BA20/$BA$10 -> #DIV/0! | BC20: =AY20+BA20 -> 0 | BD20: =BC20/$BC$10 -> #DIV/0! | BE20: =BC20-AV20 -> 0 | BF20: =SUM(BF21:BF41) -> 0 | BG20: =BF20/$BF$10 -> #DIV/0! | BH20: =SUM(BH21:BH41) -> 0 | BI20: =BH20/$BH$10 -> #DIV/0! | BJ20: =BF20+BH20 -> 0 | BK20: =BJ20/$BJ$10 -> #DIV/0! | BL20: =BJ20-BC20 -> 0 | BM20: =SUM(BM21:BM41) -> 0 | BN20: =BM20/$BF$10 -> #DIV/0! | BO20: =SUM(BO21:BO41) -> 0 | BP20: =BO20/$BH$10 -> #DIV/0! | BQ20: =BM20+BO20 -> 0 | BR20: =BQ20/$BJ$10 -> #DIV/0! | BS20: =BQ20-BJ20 -> 0 | BT20: =SUM(BT21:BT41) -> 0 | BU20: =BT20/$BF$10 -> #DIV/0! | BV20: =SUM(BV21:BV41) -> 0 | BW20: =BV20/$BH$10 -> #DIV/0! | BX20: =BT20+BV20 -> 0 | BY20: =BX20/$BJ$10 -> #DIV/0! | BZ20: =BX20-BQ20 -> 0 | CA20: =SUM(CA21:CA41) -> 0 | CB20: =CA20/$BF$10 -> #DIV/0! | CC20: =SUM(CC21:CC41) -> 0 | CD20: =CC20/$BH$10 -> #DIV/0! | CE20: =CA20+CC20 -> 0 | CF20: =CE20/$BJ$10 -> #DIV/0! | CG20: =CE20-BX20 -> 0 | CH20: =IF(SUM(CH21:CH41)=0,"",SUM(CH21:CH41)) -> 19755525 | CI20: =CH20/$CH$10 -> 0.19728429 | CJ20: =IF(SUM(CJ21:CJ41)=0,"",SUM(CJ21:CJ41)) -> 4526921.8 | CK20: =CJ20/$CJ$10 -> 0.31928431 | CL20: =IF(SUM(CL21:CL41)=0,"",SUM(CL21:CL41)) -> 24282446 | CM20: =CL20/$CL$10 -> 0.2124157
B21: Tributárias | C21: =SUMIF('MVTO E'!$C$3:$C$240,"Tributárias",'MVTO E'!$G$3:$G$240)+SUMIF('DESP E'!$D$3:$D$146,"Tributárias",'DESP E'!$G$3:$G$146) -> 482658.05 | D21: =C21/$C$10 -> 0.014670008 | E21: =SUMIF('MVTO A'!$C$3:$C$184,"Tributárias",'MVTO A'!$G$3:$G$184)+SUMIF('DESP A'!$D$3:$D$129,"Tributárias",'DESP A'!$G$3:$G$129) -> 128279.22 | F21: =E21/$E$10 -> 0.032461553 | G21: =C21+E21 -> 610937.27 | H21: =G21/$G$10 -> 0.0165778 | I21: =SUMIF('MVTO E'!$C$3:$C$240,"Tributárias",'MVTO E'!$H$3:$H$240)+SUMIF('DESP E'!$D$3:$D$146,"Tributárias",'DESP E'!$H$3:$H$146) -> 189509.72 | J21: =I21/$I$10 -> 0.0089264963 | K21: =SUMIF('MVTO A'!$C$3:$C$184,"Tributárias",'MVTO A'!$H$3:$H$184)+SUMIF('DESP A'!$D$3:$D$129,"Tributárias",'DESP A'!$H$3:$H$129) -> 131214.43 | L21: =K21/$K$10 -> 0.038375382 | M21: =I21+K21 -> 320724.15 | N21: =M21/$M$10 -> 0.013011514 | O21: =M21-G21 -> -290213.12 | P21: =SUMIF('MVTO E'!$C$3:$C$240,"Tributárias",'MVTO E'!$I$3:$I$240)+SUMIF('DESP E'!$D$3:$D$146,"Tributárias",'DESP E'!$I$3:$I$146) -> 234705.19 | Q21: =P21/$P$10 -> 0.0098585306 | R21: =SUMIF('MVTO A'!$C$3:$C$184,"Tributárias",'MVTO A'!$I$3:$I$184)+SUMIF('DESP A'!$D$3:$D$129,"Tributárias",'DESP A'!$I$3:$I$129) -> 113935.58 | S21: =R21/$R$10 -> 0.031210229 | T21: =P21+R21 -> 348640.77 | U21: =T21/$T$10 -> 0.012697283 | V21: =T21-M21 -> 27916.62 | W21: =SUMIF('MVTO E'!$C$3:$C$240,"Tributárias",'MVTO E'!$J$3:$J$240)+SUMIF('DESP E'!$D$3:$D$146,"Tributárias",'DESP E'!$J$3:$J$146) -> 129263.85 | X21: =W21/$W$10 -> 0.0058229594 | Y21: =SUMIF('MVTO A'!$C$3:$C$184,"Tributárias",'MVTO A'!$J$3:$J$184)+SUMIF('DESP A'!$D$3:$D$129,"Tributárias",'DESP A'!$J$3:$J$129) -> 115962.81 | Z21: =Y21/$Y$10 -> 0.036734362 | AA21: =W21+Y21 -> 245226.66 | AB21: =AA21/$AA$10 -> 0.0096714268 | AC21: =AA21-T21 -> -103414.11 | AD21: =SUMIF('MVTO E'!$C$3:$C$240,"Tributárias",'MVTO E'!$K$3:$K$240)+SUMIF('DESP E'!$D$3:$D$146,"Tributárias",'DESP E'!$K$3:$K$146) -> 0 | AE21: =AD21/$AD$10 -> #DIV/0! | AF21: =SUMIF('MVTO A'!$C$3:$C$184,"Tributárias",'MVTO A'!$K$3:$K$184)+SUMIF('DESP A'!$D$3:$D$129,"Tributárias",'DESP A'!$K$3:$K$129) -> 0 | AG21: =AF21/$AF$10 -> #DIV/0! | AH21: =AD21+AF21 -> 0 | AI21: =AH21/$AH$10 -> #DIV/0! | AJ21: =AH21-AA21 -> -245226.66 | AK21: =SUMIF('MVTO E'!$C$3:$C$240,"Tributárias",'MVTO E'!$L$3:$L$240)+SUMIF('DESP E'!$D$3:$D$146,"Tributárias",'DESP E'!$L$3:$L$146) -> 0 | AL21: =AK21/$AK$10 -> #DIV/0! | AM21: =SUMIF('MVTO A'!$C$3:$C$184,"Tributárias",'MVTO A'!$L$3:$L$184)+SUMIF('DESP A'!$D$3:$D$129,"Tributárias",'DESP A'!$L$3:$L$129) -> 0 | AN21: =AM21/$AM$10 -> #DIV/0! | AO21: =AK21+AM21 -> 0 | AP21: =AO21/$AO$10 -> #DIV/0! | AQ21: =AO21-AH21 -> 0 | AR21: =SUMIF('MVTO E'!$C$3:$C$240,"Tributárias",'MVTO E'!$M$3:$M$240)+SUMIF('DESP E'!$D$3:$D$146,"Tributárias",'DESP E'!$M$3:$M$146) -> 0 | AS21: =AR21/$AR$10 -> #DIV/0! | AT21: =SUMIF('MVTO A'!$C$3:$C$184,"Tributárias",'MVTO A'!$M$3:$M$189)+SUMIF('DESP A'!$D$3:$D$129,"Tributárias",'DESP A'!$M$3:$M$129) -> 0 | AU21: =AT21/$AT$10 -> #DIV/0! | AV21: =AR21+AT21 -> 0 | AW21: =AV21/$AV$10 -> #DIV/0! | AX21: =AV21-AO21 -> 0 | AY21: =SUMIF('MVTO E'!$C$3:$C$240,"Tributárias",'MVTO E'!$N$3:$N$240)+SUMIF('DESP E'!$D$3:$D$146,"Tributárias",'DESP E'!$N$3:$N$146) -> 0 | AZ21: =AY21/$AY$10 -> #DIV/0! | BA21: =SUMIF('MVTO A'!$C$3:$C$184,"Tributárias",'MVTO A'!$N$3:$N$189)+SUMIF('DESP A'!$D$3:$D$129,"Tributárias",'DESP A'!$N$3:$N$129) -> 0 | BB21: =BA21/$BA$10 -> #DIV/0! | BC21: =AY21+BA21 -> 0 | BD21: =BC21/$BC$10 -> #DIV/0! | BE21: =BC21-AV21 -> 0 | BF21: =SUMIF('MVTO E'!$C$3:$C$240,"Tributárias",'MVTO E'!$O$3:$O$240)+SUMIF('DESP E'!$D$3:$D$146,"Tributárias",'DESP E'!$O$3:$O$146) -> 0 | BG21: =BF21/$BF$10 -> #DIV/0! | BH21: =SUMIF('MVTO A'!$C$3:$C$195,"Tributárias",'MVTO A'!$O$3:$O$195)+SUMIF('DESP A'!$D$3:$D$144,"Tributárias",'DESP A'!$O$3:$O$144) -> 0 | BI21: =BH21/$BH$10 -> #DIV/0! | BJ21: =BF21+BH21 -> 0 | BK21: =BJ21/$BJ$10 -> #DIV/0! | BL21: =BJ21-BC21 -> 0 | BM21: =SUMIF('MVTO E'!$C$3:$C$240,"Tributárias",'MVTO E'!$P$3:$P$240)+SUMIF('DESP E'!$D$3:$D$146,"Tributárias",'DESP E'!$P$3:$P$146) -> 0 | BN21: =BM21/$BF$10 -> #DIV/0! | BO21: =SUMIF('MVTO A'!$C$3:$C$184,"Tributárias",'MVTO A'!$P$3:$P$189)+SUMIF('DESP A'!$D$3:$D$129,"Tributárias",'DESP A'!$P$3:$P$129) -> 0 | BP21: =BO21/$BH$10 -> #DIV/0! | BQ21: =BM21+BO21 -> 0 | BR21: =BQ21/$BJ$10 -> #DIV/0! | BS21: =BQ21-BJ21 -> 0 | BT21: =SUMIF('MVTO E'!$C$3:$C$240,"Tributárias",'MVTO E'!$Q$3:$Q$240)+SUMIF('DESP E'!$D$3:$D$146,"Tributárias",'DESP E'!$Q$3:$Q$146) -> 0 | BU21: =BT21/$BF$10 -> #DIV/0! | BV21: =SUMIF('MVTO A'!$C$3:$C$184,"Tributárias",'MVTO A'!$Q$3:$Q$189)+SUMIF('DESP A'!$D$3:$D$129,"Tributárias",'DESP A'!$Q$3:$Q$129) -> 0 | BW21: =BV21/$BH$10 -> #DIV/0! | BX21: =BT21+BV21 -> 0 | BY21: =BX21/$BJ$10 -> #DIV/0! | BZ21: =BX21-BQ21 -> 0 | CA21: =SUMIF('MVTO E'!$C$3:$C$240,"Tributárias",'MVTO E'!$R$3:$R$240)+SUMIF('DESP E'!$D$3:$D$146,"Tributárias",'DESP E'!$R$3:$R$146) -> 0 | CB21: =CA21/$BF$10 -> #DIV/0! | CC21: =SUMIF('MVTO A'!$C$3:$C$184,"Tributárias",'MVTO A'!$R$3:$R$189)+SUMIF('DESP A'!$D$3:$D$129,"Tributárias",'DESP A'!$R$3:$R$129) -> 0 | CD21: =CC21/$BH$10 -> #DIV/0! | CE21: =CA21+CC21 -> 0 | CF21: =CE21/$BJ$10 -> #DIV/0! | CG21: =CE21-BX21 -> 0 | CH21: =SUM(C21,I21,P21,W21,AD21,AK21,AR21,AY21,BF21,BM21,BT21,CA21) -> 1036136.8 | CI21: =CH21/$CH$10 -> 0.010347157 | CJ21: =SUM(E21,K21,R21,Y21,AF21,AM21,AT21,BA21,BH21,BO21,BV21,CC21) -> 489392.04 | CK21: =CJ21/$CJ$10 -> 0.034516877 | CL21: =SUM(G21,M21,T21,AA21,AH21,AO21,AV21,BC21,BJ21,BQ21,BX21,CE21) -> 1525528.9 | CM21: =CL21/$CL$10 -> 0.013344878
B22: Almoxarifado | C22: =SUMIF('DESP E'!$D$3:$D$146,"Almoxarifado",'DESP E'!$G$3:$G$146) -> 214871.96 | D22: =C22/$C$10 -> 0.0065308626 | E22: =SUMIF('DESP A'!$D$3:$D$129,"Almoxarifado",'DESP A'!$G$3:$G$129) -> 0 | F22: =E22/$E$10 -> 0 | G22: =C22+E22 -> 214871.96 | H22: =G22/$G$10 -> 0.0058305566 | I22: =SUMIF('DESP E'!$D$3:$D$146,"Almoxarifado",'DESP E'!$H$3:$H$146) -> 159181.85 | J22: =I22/$I$10 -> 0.0074979594 | K22: =SUMIF('DESP A'!$D$3:$D$129,"Almoxarifado",'DESP A'!$H$3:$H$129) -> 0 | L22: =K22/$K$10 -> 0 | M22: =I22+K22 -> 159181.85 | N22: =M22/$M$10 -> 0.0064578761 | O22: =M22-G22 -> -55690.11 | P22: =SUMIF('DESP E'!$D$3:$D$146,"Almoxarifado",'DESP E'!$I$3:$I$146) -> 183249.46 | Q22: =P22/$P$10 -> 0.0076971899 | R22: =SUMIF('DESP A'!$D$3:$D$129,"Almoxarifado",'DESP A'!$I$3:$I$129) -> 0 | S22: =R22/$R$10 -> 0 | T22: =P22+R22 -> 183249.46 | U22: =T22/$T$10 -> 0.0066738327 | V22: =T22-M22 -> 24067.61 | W22: =SUMIF('DESP E'!$D$3:$D$146,"Almoxarifado",'DESP E'!$J$3:$J$146) -> 151331.75 | X22: =W22/$W$10 -> 0.006817054 | Y22: =SUMIF('DESP A'!$D$3:$D$129,"Almoxarifado",'DESP A'!$J$3:$J$129) -> 0 | Z22: =Y22/$Y$10 -> 0 | AA22: =W22+Y22 -> 151331.75 | AB22: =AA22/$AA$10 -> 0.0059683312 | AC22: =AA22-T22 -> -31917.71 | AD22: =SUMIF('DESP E'!$D$3:$D$146,"Almoxarifado",'DESP E'!$K$3:$K$146) -> 0 | AE22: =AD22/$AD$10 -> #DIV/0! | AF22: =SUMIF('DESP A'!$D$3:$D$129,"Almoxarifado",'DESP A'!$K$3:$K$129) -> 0 | AG22: =AF22/$AF$10 -> #DIV/0! | AH22: =AD22+AF22 -> 0 | AI22: =AH22/$AH$10 -> #DIV/0! | AJ22: =AH22-AA22 -> -151331.75 | AK22: =SUMIF('DESP E'!$D$3:$D$146,"Almoxarifado",'DESP E'!$L$3:$L$146) -> 0 | AL22: =AK22/$AK$10 -> #DIV/0! | AM22: =SUMIF('DESP A'!$D$3:$D$129,"Almoxarifado",'DESP A'!$L$3:$L$129) -> 0 | AN22: =AM22/$AM$10 -> #DIV/0! | AO22: =AK22+AM22 -> 0 | AP22: =AO22/$AO$10 -> #DIV/0! | AQ22: =AO22-AH22 -> 0 | AR22: =SUMIF('DESP E'!$D$3:$D$146,"Almoxarifado",'DESP E'!$M$3:$M$146) -> 0 | AS22: =AR22/$AR$10 -> #DIV/0! | AT22: =SUMIF('DESP A'!$D$3:$D$129,"Almoxarifado",'DESP A'!$M$3:$M$129) -> 0 | AU22: =AT22/$AT$10 -> #DIV/0! | AV22: =AR22+AT22 -> 0 | AW22: =AV22/$AV$10 -> #DIV/0! | AX22: =AV22-AO22 -> 0 | AY22: =SUMIF('DESP E'!$D$3:$D$146,"Almoxarifado",'DESP E'!$N$3:$N$146) -> 0 | AZ22: =AY22/$AY$10 -> #DIV/0! | BA22: =SUMIF('DESP A'!$D$3:$D$129,"Almoxarifado",'DESP A'!$N$3:$N$129) -> 0 | BB22: =BA22/$BA$10 -> #DIV/0! | BC22: =AY22+BA22 -> 0 | BD22: =BC22/$BC$10 -> #DIV/0! | BE22: =BC22-AV22 -> 0 | BF22: =SUMIF('DESP E'!$D$3:$D$146,"Almoxarifado",'DESP E'!$O$3:$O$146) -> 0 | BG22: =BF22/$BF$10 -> #DIV/0! | BH22: =SUMIF('DESP A'!$D$3:$D$144,"Almoxarifado",'DESP A'!$O$3:$O$144) -> 0 | BI22: =BH22/$BH$10 -> #DIV/0! | BJ22: =BF22+BH22 -> 0 | BK22: =BJ22/$BJ$10 -> #DIV/0! | BL22: =BJ22-BC22 -> 0 | BM22: =SUMIF('DESP E'!$D$3:$D$146,"Almoxarifado",'DESP E'!$P$3:$P$146) -> 0 | BN22: =BM22/$BF$10 -> #DIV/0! | BO22: =SUMIF('DESP A'!$D$3:$D$129,"Almoxarifado",'DESP A'!$P$3:$P$129) -> 0 | BP22: =BO22/$BH$10 -> #DIV/0! | BQ22: =BM22+BO22 -> 0 | BR22: =BQ22/$BJ$10 -> #DIV/0! | BS22: =BQ22-BJ22 -> 0 | BT22: =SUMIF('DESP E'!$D$3:$D$146,"Almoxarifado",'DESP E'!$Q$3:$Q$146) -> 0 | BU22: =BT22/$BF$10 -> #DIV/0! | BV22: =SUMIF('DESP A'!$D$3:$D$129,"Almoxarifado",'DESP A'!$Q$3:$Q$129) -> 0 | BW22: =BV22/$BH$10 -> #DIV/0! | BX22: =BT22+BV22 -> 0 | BY22: =BX22/$BJ$10 -> #DIV/0! | BZ22: =BX22-BQ22 -> 0 | CA22: =SUMIF('DESP E'!$D$3:$D$146,"Almoxarifado",'DESP E'!$R$3:$R$146) -> 0 | CB22: =CA22/$BF$10 -> #DIV/0! | CC22: =SUMIF('DESP A'!$D$3:$D$129,"Almoxarifado",'DESP A'!$R$3:$R$129) -> 0 | CD22: =CC22/$BH$10 -> #DIV/0! | CE22: =CA22+CC22 -> 0 | CF22: =CE22/$BJ$10 -> #DIV/0! | CG22: =CE22-BX22 -> 0 | CH22: =SUM(C22,I22,P22,W22,AD22,AK22,AR22,AY22,BF22,BM22,BT22,CA22) -> 708635.02 | CI22: =CH22/$CH$10 -> 0.0070766307 | CJ22: =SUM(E22,K22,R22,Y22,AF22,AM22,AT22,BA22,BH22,BO22,BV22,CC22) -> 0 | CK22: =CJ22/$CJ$10 -> 0 | CL22: =SUM(G22,M22,T22,AA22,AH22,AO22,AV22,BC22,BJ22,BQ22,BX22,CE22) -> 708635.02 | CM22: =CL22/$CL$10 -> 0.0061989307
B23: Outras (119103/215323) | C23: =SUMIF('MVTO E'!$C$3:$C$240,"Outras",'MVTO E'!$G$3:$G$240)+SUMIF('DESP E'!$D$3:$D$146,"Outras",'DESP E'!$G$3:$G$146) -> 302265 | D23: =C23/$C$10 -> 0.0091871046 | E23: =SUMIF('MVTO A'!$C$3:$C$184,"Outras",'MVTO A'!$G$3:$G$184)+SUMIF('DESP A'!$D$3:$D$129,"Outras",'DESP A'!$G$3:$G$129) -> 65091.75 | F23: =E23/$E$10 -> 0.016471719 | G23: =C23+E23 -> 367356.75 | H23: =G23/$G$10 -> 0.0099682356 | I23: =SUMIF('MVTO E'!$C$3:$C$240,"Outras",'MVTO E'!$H$3:$H$240)+SUMIF('DESP E'!$D$3:$D$146,"Outras",'DESP E'!$H$3:$H$146) -> 259031.43 | J23: =I23/$I$10 -> 0.012201185 | K23: =SUMIF('MVTO A'!$C$3:$C$184,"Outras",'MVTO A'!$H$3:$H$184)+SUMIF('DESP A'!$D$3:$D$129,"Outras",'DESP A'!$H$3:$H$129) -> 87615.2 | L23: =K23/$K$10 -> 0.025624215 | M23: =I23+K23 -> 346646.63 | N23: =M23/$M$10 -> 0.014063167 | O23: =M23-G23 -> -20710.12 | P23: =SUMIF('MVTO E'!$C$3:$C$240,"Outras",'MVTO E'!$I$3:$I$240)+SUMIF('DESP E'!$D$3:$D$146,"Outras",'DESP E'!$I$3:$I$146) -> 258353.59 | Q23: =P23/$P$10 -> 0.010851855 | R23: =SUMIF('MVTO A'!$C$3:$C$184,"Outras",'MVTO A'!$I$3:$I$184)+SUMIF('DESP A'!$D$3:$D$129,"Outras",'DESP A'!$I$3:$I$129) -> 100073.98 | S23: =R23/$R$10 -> 0.027413139 | T23: =P23+R23 -> 358427.57 | U23: =T23/$T$10 -> 0.013053712 | V23: =T23-M23 -> 11780.94 | W23: =SUMIF('MVTO E'!$C$3:$C$240,"Outras",'MVTO E'!$J$3:$J$240)+SUMIF('DESP E'!$D$3:$D$146,"Outras",'DESP E'!$J$3:$J$146) -> 390780.4 | X23: =W23/$W$10 -> 0.017603517 | Y23: =SUMIF('MVTO A'!$C$3:$C$184,"Outras",'MVTO A'!$J$3:$J$184)+SUMIF('DESP A'!$D$3:$D$129,"Outras",'DESP A'!$J$3:$J$129) -> 120705.18 | Z23: =Y23/$Y$10 -> 0.038236636 | AA23: =W23+Y23 -> 511485.58 | AB23: =AA23/$AA$10 -> 0.020172339 | AC23: =AA23-T23 -> 153058.01 | AD23: =SUMIF('MVTO E'!$C$3:$C$240,"Outras",'MVTO E'!$K$3:$K$240)+SUMIF('DESP E'!$D$3:$D$146,"Outras",'DESP E'!$K$3:$K$146) -> 0 | AE23: =AD23/$AD$10 -> #DIV/0! | AF23: =SUMIF('MVTO A'!$C$3:$C$184,"Outras",'MVTO A'!$K$3:$K$184)+SUMIF('DESP A'!$D$3:$D$129,"Outras",'DESP A'!$K$3:$K$129) -> 0 | AG23: =AF23/$AF$10 -> #DIV/0! | AH23: =AD23+AF23 -> 0 | AI23: =AH23/$AH$10 -> #DIV/0! | AJ23: =AH23-AA23 -> -511485.58 | AK23: =SUMIF('MVTO E'!$C$3:$C$240,"Outras",'MVTO E'!$L$3:$L$240)+SUMIF('DESP E'!$D$3:$D$146,"Outras",'DESP E'!$L$3:$L$146) -> 0 | AL23: =AK23/$AK$10 -> #DIV/0! | AM23: =SUMIF('MVTO A'!$C$3:$C$184,"Outras",'MVTO A'!$L$3:$L$184)+SUMIF('DESP A'!$D$3:$D$129,"Outras",'DESP A'!$L$3:$L$129) -> 0 | AN23: =AM23/$AM$10 -> #DIV/0! | AO23: =AK23+AM23 -> 0 | AP23: =AO23/$AO$10 -> #DIV/0! | AQ23: =AO23-AH23 -> 0 | AR23: =SUMIF('MVTO E'!$C$3:$C$240,"Outras",'MVTO E'!$M$3:$M$240)+SUMIF('DESP E'!$D$3:$D$146,"Outras",'DESP E'!$M$3:$M$146) -> 0 | AS23: =AR23/$AR$10 -> #DIV/0! | AT23: =SUMIF('MVTO A'!$C$3:$C$184,"Outras",'MVTO A'!$M$3:$M$189)+SUMIF('DESP A'!$D$3:$D$129,"Outras",'DESP A'!$M$3:$M$129) -> 0 | AU23: =AT23/$AT$10 -> #DIV/0! | AV23: =AR23+AT23 -> 0 | AW23: =AV23/$AV$10 -> #DIV/0! | AX23: =AV23-AO23 -> 0 | AY23: =SUMIF('MVTO E'!$C$3:$C$240,"Outras",'MVTO E'!$N$3:$N$240)+SUMIF('DESP E'!$D$3:$D$146,"Outras",'DESP E'!$N$3:$N$146) -> 0 | AZ23: =AY23/$AY$10 -> #DIV/0! | BA23: =SUMIF('MVTO A'!$C$3:$C$184,"Outras",'MVTO A'!$N$3:$N$189)+SUMIF('DESP A'!$D$3:$D$129,"Outras",'DESP A'!$N$3:$N$129) -> 0 | BB23: =BA23/$BA$10 -> #DIV/0! | BC23: =AY23+BA23 -> 0 | BD23: =BC23/$BC$10 -> #DIV/0! | BE23: =BC23-AV23 -> 0 | BF23: =SUMIF('MVTO E'!$C$3:$C$240,"Outras",'MVTO E'!$O$3:$O$240)+SUMIF('DESP E'!$D$3:$D$146,"Outras",'DESP E'!$O$3:$O$146) -> 0 | BG23: =BF23/$BF$10 -> #DIV/0! | BH23: =SUMIF('MVTO A'!$C$3:$C$195,"Outras",'MVTO A'!$O$3:$O$195)+SUMIF('DESP A'!$D$3:$D$144,"Outras",'DESP A'!$O$3:$O$144) -> 0 | BI23: =BH23/$BH$10 -> #DIV/0! | BJ23: =BF23+BH23 -> 0 | BK23: =BJ23/$BJ$10 -> #DIV/0! | BL23: =BJ23-BC23 -> 0 | BM23: =SUMIF('MVTO E'!$C$3:$C$240,"Outras",'MVTO E'!$P$3:$P$240)+SUMIF('DESP E'!$D$3:$D$146,"Outras",'DESP E'!$P$3:$P$146) -> 0 | BN23: =BM23/$BF$10 -> #DIV/0! | BO23: =SUMIF('MVTO A'!$C$3:$C$184,"Outras",'MVTO A'!$P$3:$P$189)+SUMIF('DESP A'!$D$3:$D$129,"Outras",'DESP A'!$P$3:$P$129) -> 0 | BP23: =BO23/$BH$10 -> #DIV/0! | BQ23: =BM23+BO23 -> 0 | BR23: =BQ23/$BJ$10 -> #DIV/0! | BS23: =BQ23-BJ23 -> 0 | BT23: =SUMIF('MVTO E'!$C$3:$C$240,"Outras",'MVTO E'!$Q$3:$Q$240)+SUMIF('DESP E'!$D$3:$D$146,"Outras",'DESP E'!$Q$3:$Q$146) -> 0 | BU23: =BT23/$BF$10 -> #DIV/0! | BV23: =SUMIF('MVTO A'!$C$3:$C$184,"Outras",'MVTO A'!$Q$3:$Q$189)+SUMIF('DESP A'!$D$3:$D$129,"Outras",'DESP A'!$Q$3:$Q$129) -> 0 | BW23: =BV23/$BH$10 -> #DIV/0! | BX23: =BT23+BV23 -> 0 | BY23: =BX23/$BJ$10 -> #DIV/0! | BZ23: =BX23-BQ23 -> 0 | CA23: =SUMIF('MVTO E'!$C$3:$C$240,"Outras",'MVTO E'!$R$3:$R$240)+SUMIF('DESP E'!$D$3:$D$146,"Outras",'DESP E'!$R$3:$R$146) -> 0 | CB23: =CA23/$BF$10 -> #DIV/0! | CC23: =SUMIF('MVTO A'!$C$3:$C$184,"Outras",'MVTO A'!$R$3:$R$189)+SUMIF('DESP A'!$D$3:$D$129,"Outras",'DESP A'!$R$3:$R$129) -> 0 | CD23: =CC23/$BH$10 -> #DIV/0! | CE23: =CA23+CC23 -> 0 | CF23: =CE23/$BJ$10 -> #DIV/0! | CG23: =CE23-BX23 -> 0 | CH23: =SUM(C23,I23,P23,W23,AD23,AK23,AR23,AY23,BF23,BM23,BT23,CA23) -> 1210430.4 | CI23: =CH23/$CH$10 -> 0.012087702 | CJ23: =SUM(E23,K23,R23,Y23,AF23,AM23,AT23,BA23,BH23,BO23,BV23,CC23) -> 373486.11 | CK23: =CJ23/$CJ$10 -> 0.026342018 | CL23: =SUM(G23,M23,T23,AA23,AH23,AO23,AV23,BC23,BJ23,BQ23,BX23,CE23) -> 1583916.5 | CM23: =CL23/$CL$10 -> 0.013855636
B24: Pessoal | C24: =SUMIF('MVTO E'!$C$3:$C$240,"Pessoal",'MVTO E'!$G$3:$G$240)-SUMIF('MVTO E'!$C$3:$C$240,"Pessoal_E",'MVTO E'!$G$3:$G$240)+SUMIF('DESP E'!$D$3:$D$146,"Pessoal",'DESP E'!$G$3:$G$146) -> 2271896.1 | D24: =C24/$C$10 -> 0.069052479 | E24: =SUMIF('MVTO A'!$C$3:$C$184,"Pessoal",'MVTO A'!$G$3:$G$184)-SUMIF('MVTO A'!$C$3:$C$184,"Pessoal_e",'MVTO A'!$G$3:$G$184)+SUMIF('DESP A'!$D$3:$D$129,"Pessoal",'DESP A'!$G$3:$G$129) -> 944623.16 | F24: =E24/$E$10 -> 0.23904055 | G24: =C24+E24 -> 3216519.3 | H24: =G24/$G$10 -> 0.08728034 | I24: =SUMIF('MVTO E'!$C$3:$C$240,"Pessoal",'MVTO E'!$H$3:$H$240)-SUMIF('MVTO E'!$C$3:$C$240,"Pessoal_E",'MVTO E'!$H$3:$H$240)+SUMIF('DESP E'!$D$3:$D$146,"Pessoal",'DESP E'!$H$3:$H$146) -> 2155740.1 | J24: =I24/$I$10 -> 0.10154205 | K24: =SUMIF('MVTO A'!$C$3:$C$184,"Pessoal",'MVTO A'!$H$3:$H$184)-SUMIF('MVTO A'!$C$3:$C$184,"Pessoal_E",'MVTO A'!$H$3:$H$184)+SUMIF('DESP A'!$D$3:$D$129,"Pessoal",'DESP A'!$H$3:$H$129) -> 937575.5 | L24: =K24/$K$10 -> 0.27420626 | M24: =I24+K24 -> 3093315.6 | N24: =M24/$M$10 -> 0.12549326 | O24: =M24-G24 -> -123203.69 | P24: =SUMIF('MVTO E'!$C$3:$C$240,"Pessoal",'MVTO E'!$I$3:$I$240)-SUMIF('MVTO E'!$C$3:$C$240,"Pessoal_E",'MVTO E'!$I$3:$I$240)+SUMIF('DESP E'!$D$3:$D$146,"Pessoal",'DESP E'!$I$3:$I$146) -> 1832505.3 | Q24: =P24/$P$10 -> 0.076972349 | R24: =SUMIF('MVTO A'!$C$3:$C$184,"Pessoal",'MVTO A'!$I$3:$I$184)-SUMIF('MVTO A'!$C$3:$C$184,"Pessoal_E",'MVTO A'!$I$3:$I$184)+SUMIF('DESP A'!$D$3:$D$129,"Pessoal",'DESP A'!$I$3:$I$129) -> 875086.23 | S24: =R24/$R$10 -> 0.23971126 | T24: =P24+R24 -> 2707591.6 | U24: =T24/$T$10 -> 0.098608821 | V24: =T24-M24 -> -385724.04 | W24: =SUMIF('MVTO E'!$C$3:$C$240,"Pessoal",'MVTO E'!$J$3:$J$240)-SUMIF('MVTO E'!$C$3:$C$240,"Pessoal_E",'MVTO E'!$J$3:$J$240)+SUMIF('DESP E'!$D$3:$D$146,"Pessoal",'DESP E'!$J$3:$J$146) -> 2059975.3 | X24: =W24/$W$10 -> 0.09279588 | Y24: =SUMIF('MVTO A'!$C$3:$C$184,"Pessoal",'MVTO A'!$J$3:$J$184)-SUMIF('MVTO A'!$C$3:$C$184,"Pessoal_e",'MVTO A'!$J$3:$J$184)+SUMIF('DESP A'!$D$3:$D$129,"Pessoal",'DESP A'!$J$3:$J$129) -> 696399.59 | Z24: =Y24/$Y$10 -> 0.22060344 | AA24: =W24+Y24 -> 2756374.9 | AB24: =AA24/$AA$10 -> 0.10870791 | AC24: =AA24-T24 -> 48783.34 | AD24: =SUMIF('MVTO E'!$C$3:$C$240,"Pessoal",'MVTO E'!$K$3:$K$240)-SUMIF('MVTO E'!$C$3:$C$240,"Pessoal_E",'MVTO E'!$K$3:$K$240)+SUMIF('DESP E'!$D$3:$D$146,"Pessoal",'DESP E'!$K$3:$K$146) -> 0 | AE24: =AD24/$AD$10 -> #DIV/0! | AF24: =SUMIF('MVTO A'!$C$3:$C$184,"Pessoal",'MVTO A'!$K$3:$K$184)-SUMIF('MVTO A'!$C$3:$C$184,"Pessoal_E",'MVTO A'!$K$3:$K$184)+SUMIF('DESP A'!$D$3:$D$129,"Pessoal",'DESP A'!$K$3:$K$129) -> 0 | AG24: =AF24/$AF$10 -> #DIV/0! | AH24: =AD24+AF24 -> 0 | AI24: =AH24/$AH$10 -> #DIV/0! | AJ24: =AH24-AA24 -> -2756374.9 | AK24: =SUMIF('MVTO E'!$C$3:$C$240,"Pessoal",'MVTO E'!$L$3:$L$240)-SUMIF('MVTO E'!$C$3:$C$240,"Pessoal_E",'MVTO E'!$L$3:$L$240)+SUMIF('DESP E'!$D$3:$D$146,"Pessoal",'DESP E'!$L$3:$L$146) -> 0 | AL24: =AK24/$AK$10 -> #DIV/0! | AM24: =SUMIF('MVTO A'!$C$3:$C$184,"Pessoal",'MVTO A'!$L$3:$L$184)-SUMIF('MVTO A'!$C$3:$C$184,"Pessoal_E",'MVTO A'!$L$3:$L$184)+SUMIF('DESP A'!$D$3:$D$129,"Pessoal",'DESP A'!$L$3:$L$129) -> 0 | AN24: =AM24/$AM$10 -> #DIV/0! | AO24: =AK24+AM24 -> 0 | AP24: =AO24/$AO$10 -> #DIV/0! | AQ24: =AO24-AH24 -> 0 | AR24: =SUMIF('MVTO E'!$C$3:$C$240,"Pessoal",'MVTO E'!$M$3:$M$240)-SUMIF('MVTO E'!$C$3:$C$240,"Pessoal_E",'MVTO E'!$M$3:$M$240)+SUMIF('DESP E'!$D$3:$D$146,"Pessoal",'DESP E'!$M$3:$M$146) -> 0 | AS24: =AR24/$AR$10 -> #DIV/0! | AT24: =SUMIF('MVTO A'!$C$3:$C$184,"Pessoal",'MVTO A'!$M$3:$M$189)-SUMIF('MVTO A'!$C$3:$C$184,"Pessoal_e",'MVTO A'!$M$3:$M$189)+SUMIF('DESP A'!$D$3:$D$129,"Pessoal",'DESP A'!$M$3:$M$129) -> 0 | AU24: =AT24/$AT$10 -> #DIV/0! | AV24: =AR24+AT24 -> 0 | AW24: =AV24/$AV$10 -> #DIV/0! | AX24: =AV24-AO24 -> 0 | AY24: =SUMIF('MVTO E'!$C$3:$C$240,"Pessoal",'MVTO E'!$N$3:$N$240)-SUMIF('MVTO E'!$C$3:$C$240,"Pessoal_E",'MVTO E'!$N$3:$N$240)+SUMIF('DESP E'!$D$3:$D$146,"Pessoal",'DESP E'!$N$3:$N$146) -> 0 | AZ24: =AY24/$AY$10 -> #DIV/0! | BA24: =SUMIF('MVTO A'!$C$3:$C$184,"Pessoal",'MVTO A'!$N$3:$N$189)-SUMIF('MVTO A'!$C$3:$C$184,"Pessoal_E",'MVTO A'!$N$3:$N$189)+SUMIF('DESP A'!$D$3:$D$129,"Pessoal",'DESP A'!$N$3:$N$129) -> 0 | BB24: =BA24/$BA$10 -> #DIV/0! | BC24: =AY24+BA24 -> 0 | BD24: =BC24/$BC$10 -> #DIV/0! | BE24: =BC24-AV24 -> 0 | BF24: =SUMIF('MVTO E'!$C$3:$C$240,"Pessoal",'MVTO E'!$O$3:$O$240)-SUMIF('MVTO E'!$C$3:$C$240,"Pessoal_E",'MVTO E'!$O$3:$O$240)+SUMIF('DESP E'!$D$3:$D$146,"Pessoal",'DESP E'!$O$3:$O$146) -> 0 | BG24: =BF24/$BF$10 -> #DIV/0! | BH24: =SUMIF('MVTO A'!$C$3:$C$195,"Pessoal",'MVTO A'!$O$3:$O$195)-SUMIF('MVTO A'!$C$3:$C$195,"Pessoal_E",'MVTO A'!$O$3:$O$195)+SUMIF('DESP A'!$D$3:$D$144,"Pessoal",'DESP A'!$O$3:$O$144) -> 0 | BI24: =BH24/$BH$10 -> #DIV/0! | BJ24: =BF24+BH24 -> 0 | BK24: =BJ24/$BJ$10 -> #DIV/0! | BL24: =BJ24-BC24 -> 0 | BM24: =SUMIF('MVTO E'!$C$3:$C$240,"Pessoal",'MVTO E'!$P$3:$P$240)-SUMIF('MVTO E'!$C$3:$C$240,"Pessoal_E",'MVTO E'!$P$3:$P$240)+SUMIF('DESP E'!$D$3:$D$146,"Pessoal",'DESP E'!$P$3:$P$146) -> 0 | BN24: =BM24/$BF$10 -> #DIV/0! | BO24: =SUMIF('MVTO A'!$C$3:$C$184,"Pessoal",'MVTO A'!$P$3:$P$189)-SUMIF('MVTO A'!$C$3:$C$184,"Pessoal_E",'MVTO A'!$P$3:$P$189)+SUMIF('DESP A'!$D$3:$D$129,"Pessoal",'DESP A'!$P$3:$P$129) -> 0 | BP24: =BO24/$BH$10 -> #DIV/0! | BQ24: =BM24+BO24 -> 0 | BR24: =BQ24/$BJ$10 -> #DIV/0! | BS24: =BQ24-BJ24 -> 0 | BT24: =SUMIF('MVTO E'!$C$3:$C$240,"Pessoal",'MVTO E'!$Q$3:$Q$240)-SUMIF('MVTO E'!$C$3:$C$240,"Pessoal_E",'MVTO E'!$Q$3:$Q$240)+SUMIF('DESP E'!$D$3:$D$146,"Pessoal",'DESP E'!$Q$3:$Q$146) -> 0 | BU24: =BT24/$BF$10 -> #DIV/0! | BV24: =SUMIF('MVTO A'!$C$3:$C$184,"Pessoal",'MVTO A'!$Q$3:$Q$189)-SUMIF('MVTO A'!$C$3:$C$184,"Pessoal_E",'MVTO A'!$Q$3:$Q$189)+SUMIF('DESP A'!$D$3:$D$129,"Pessoal",'DESP A'!$Q$3:$Q$129) -> 0 | BW24: =BV24/$BH$10 -> #DIV/0! | BX24: =BT24+BV24 -> 0 | BY24: =BX24/$BJ$10 -> #DIV/0! | BZ24: =BX24-BQ24 -> 0 | CA24: =SUMIF('MVTO E'!$C$3:$C$240,"Pessoal",'MVTO E'!$R$3:$R$240)-SUMIF('MVTO E'!$C$3:$C$240,"Pessoal_E",'MVTO E'!$R$3:$R$240)+SUMIF('DESP E'!$D$3:$D$146,"Pessoal",'DESP E'!$R$3:$R$146) -> 0 | CB24: =CA24/$BF$10 -> #DIV/0! | CC24: =SUMIF('MVTO A'!$C$3:$C$184,"Pessoal",'MVTO A'!$R$3:$R$189)-SUMIF('MVTO A'!$C$3:$C$184,"Pessoal_E",'MVTO A'!$R$3:$R$189)+SUMIF('DESP A'!$D$3:$D$129,"Pessoal",'DESP A'!$R$3:$R$129) -> 0 | CD24: =CC24/$BH$10 -> #DIV/0! | CE24: =CA24+CC24 -> 0 | CF24: =CE24/$BJ$10 -> #DIV/0! | CG24: =CE24-BX24 -> 0 | CH24: =SUM(C24,I24,P24,W24,AD24,AK24,AR24,AY24,BF24,BM24,BT24,CA24) -> 8320116.9 | CI24: =CH24/$CH$10 -> 0.083087052 | CJ24: =SUM(E24,K24,R24,Y24,AF24,AM24,AT24,BA24,BH24,BO24,BV24,CC24) -> 3453684.5 | CK24: =CJ24/$CJ$10 -> 0.24358876 | CL24: =SUM(G24,M24,T24,AA24,AH24,AO24,AV24,BC24,BJ24,BQ24,BX24,CE24) -> 11773801 | CM24: =CL24/$CL$10 -> 0.10299375
B25: Energia Elétrica | C25: =SUMIF('DESP E'!$D$3:$D$146,"Energia Elétrica",'DESP E'!$G$3:$G$146) -> 523866.45 | D25: =C25/$C$10 -> 0.015922505 | E25: =SUMIF('DESP A'!$D$3:$D$129,"Energia Elétrica",'DESP A'!$G$3:$G$129) -> 0 | F25: =E25/$E$10 -> 0 | G25: =C25+E25 -> 523866.45 | H25: =G25/$G$10 -> 0.014215131 | I25: =SUMIF('DESP E'!$D$3:$D$146,"Energia Elétrica",'DESP E'!$H$3:$H$146) -> 514813.91 | J25: =I25/$I$10 -> 0.024249334 | K25: =SUMIF('DESP A'!$D$3:$D$129,"Energia Elétrica",'DESP A'!$H$3:$H$129) -> 0 | L25: =K25/$K$10 -> 0 | M25: =I25+K25 -> 514813.91 | N25: =M25/$M$10 -> 0.020885575 | O25: =M25-G25 -> -9052.54 | P25: =SUMIF('DESP E'!$D$3:$D$146,"Energia Elétrica",'DESP E'!$I$3:$I$146) -> 454624.44 | Q25: =P25/$P$10 -> 0.019095994 | R25: =SUMIF('DESP A'!$D$3:$D$129,"Energia Elétrica",'DESP A'!$I$3:$I$129) -> 0 | S25: =R25/$R$10 -> 0 | T25: =P25+R25 -> 454624.44 | U25: =T25/$T$10 -> 0.016557143 | V25: =T25-M25 -> -60189.47 | W25: =SUMIF('DESP E'!$D$3:$D$146,"Energia Elétrica",'DESP E'!$J$3:$J$146) -> 551490.38 | X25: =W25/$W$10 -> 0.024843033 | Y25: =SUMIF('DESP A'!$D$3:$D$129,"Energia Elétrica",'DESP A'!$J$3:$J$129) -> 0 | Z25: =Y25/$Y$10 -> 0 | AA25: =W25+Y25 -> 551490.38 | AB25: =AA25/$AA$10 -> 0.021750077 | AC25: =AA25-T25 -> 96865.94 | AD25: =SUMIF('DESP E'!$D$3:$D$146,"Energia Elétrica",'DESP E'!$K$3:$K$146) -> 0 | AE25: =AD25/$AD$10 -> #DIV/0! | AF25: =SUMIF('DESP A'!$D$3:$D$129,"Energia Elétrica",'DESP A'!$K$3:$K$129) -> 0 | AG25: =AF25/$AF$10 -> #DIV/0! | AH25: =AD25+AF25 -> 0 | AI25: =AH25/$AH$10 -> #DIV/0! | AJ25: =AH25-AA25 -> -551490.38 | AK25: =SUMIF('DESP E'!$D$3:$D$146,"Energia Elétrica",'DESP E'!$L$3:$L$146) -> 0 | AL25: =AK25/$AK$10 -> #DIV/0! | AM25: =SUMIF('DESP A'!$D$3:$D$129,"Energia Elétrica",'DESP A'!$L$3:$L$129) -> 0 | AN25: =AM25/$AM$10 -> #DIV/0! | AO25: =AK25+AM25 -> 0 | AP25: =AO25/$AO$10 -> #DIV/0! | AQ25: =AO25-AH25 -> 0 | AR25: =SUMIF('DESP E'!$D$3:$D$146,"Energia Elétrica",'DESP E'!$M$3:$M$146) -> 0 | AS25: =AR25/$AR$10 -> #DIV/0! | AT25: =SUMIF('DESP A'!$D$3:$D$129,"Energia Elétrica",'DESP A'!$M$3:$M$129) -> 0 | AU25: =AT25/$AT$10 -> #DIV/0! | AV25: =AR25+AT25 -> 0 | AW25: =AV25/$AV$10 -> #DIV/0! | AX25: =AV25-AO25 -> 0 | AY25: =SUMIF('DESP E'!$D$3:$D$146,"Energia Elétrica",'DESP E'!$N$3:$N$146) -> 0 | AZ25: =AY25/$AY$10 -> #DIV/0! | BA25: =SUMIF('DESP A'!$D$3:$D$129,"Energia Elétrica",'DESP A'!$N$3:$N$129) -> 0 | BB25: =BA25/$BA$10 -> #DIV/0! | BC25: =AY25+BA25 -> 0 | BD25: =BC25/$BC$10 -> #DIV/0! | BE25: =BC25-AV25 -> 0 | BF25: =SUMIF('DESP E'!$D$3:$D$146,"Energia Elétrica",'DESP E'!$O$3:$O$146) -> 0 | BG25: =BF25/$BF$10 -> #DIV/0! | BH25: =SUMIF('DESP A'!$D$3:$D$129,"Energia Elétrica",'DESP A'!$O$3:$O$129) -> 0 | BI25: =BH25/$BH$10 -> #DIV/0! | BJ25: =BF25+BH25 -> 0 | BK25: =BJ25/$BJ$10 -> #DIV/0! | BL25: =BJ25-BC25 -> 0 | BM25: =SUMIF('DESP E'!$D$3:$D$146,"Energia Elétrica",'DESP E'!$P$3:$P$146) -> 0 | BN25: =BM25/$BF$10 -> #DIV/0! | BO25: =SUMIF('DESP A'!$D$3:$D$129,"Energia Elétrica",'DESP A'!$P$3:$P$129) -> 0 | BP25: =BO25/$BH$10 -> #DIV/0! | BQ25: =BM25+BO25 -> 0 | BR25: =BQ25/$BJ$10 -> #DIV/0! | BS25: =BQ25-BJ25 -> 0 | BT25: =SUMIF('DESP E'!$D$3:$D$146,"Energia Elétrica",'DESP E'!$Q$3:$Q$146) -> 0 | BU25: =BT25/$BF$10 -> #DIV/0! | BV25: =SUMIF('DESP A'!$D$3:$D$129,"Energia Elétrica",'DESP A'!$Q$3:$Q$129) -> 0 | BW25: =BV25/$BH$10 -> #DIV/0! | BX25: =BT25+BV25 -> 0 | BY25: =BX25/$BJ$10 -> #DIV/0! | BZ25: =BX25-BQ25 -> 0 | CA25: =SUMIF('DESP E'!$D$3:$D$146,"Energia Elétrica",'DESP E'!$R$3:$R$146) -> 0 | CB25: =CA25/$BF$10 -> #DIV/0! | CC25: =SUMIF('DESP A'!$D$3:$D$129,"Energia Elétrica",'DESP A'!$R$3:$R$129) -> 0 | CD25: =CC25/$BH$10 -> #DIV/0! | CE25: =CA25+CC25 -> 0 | CF25: =CE25/$BJ$10 -> #DIV/0! | CG25: =CE25-BX25 -> 0 | CH25: =SUM(C25,I25,P25,W25,AD25,AK25,AR25,AY25,BF25,BM25,BT25,CA25) -> 2044795.2 | CI25: =CH25/$CH$10 -> 0.020419906 | CJ25: =SUM(E25,K25,R25,Y25,AF25,AM25,AT25,BA25,BH25,BO25,BV25,CC25) -> 0 | CK25: =CJ25/$CJ$10 -> 0 | CL25: =SUM(G25,M25,T25,AA25,AH25,AO25,AV25,BC25,BJ25,BQ25,BX25,CE25) -> 2044795.2 | CM25: =CL25/$CL$10 -> 0.017887267
B26: Utilidades e Serviços | C26: =SUMIF('DESP E'!$D$3:$D$146,"Utilidades",'DESP E'!$G$3:$G$146) -> 296970.5 | D26: =C26/$C$10 -> 0.0090261825 | E26: =SUMIF('DESP A'!$D$3:$D$129,"Utilidades",'DESP A'!$G$3:$G$129) -> 2684.07 | F26: =E26/$E$10 -> 0.0006792143 | G26: =C26+E26 -> 299654.57 | H26: =G26/$G$10 -> 0.0081311351 | I26: =SUMIF('DESP E'!$D$3:$D$146,"Utilidades",'DESP E'!$H$3:$H$146) -> 171246.62 | J26: =I26/$I$10 -> 0.0080662475 | K26: =SUMIF('DESP A'!$D$3:$D$129,"Utilidades",'DESP A'!$H$3:$H$129) -> 1076.4 | L26: =K26/$K$10 -> 0.00031480731 | M26: =I26+K26 -> 172323.02 | N26: =M26/$M$10 -> 0.0069910025 | O26: =M26-G26 -> -127331.55 | P26: =SUMIF('DESP E'!$D$3:$D$146,"Utilidades",'DESP E'!$I$3:$I$146) -> 415071.37 | Q26: =P26/$P$10 -> 0.017434612 | R26: =SUMIF('DESP A'!$D$3:$D$129,"Utilidades",'DESP A'!$I$3:$I$129) -> 1076.4 | S26: =R26/$R$10 -> 0.00029485689 | T26: =P26+R26 -> 416147.77 | U26: =T26/$T$10 -> 0.015155846 | V26: =T26-M26 -> 243824.75 | W26: =SUMIF('DESP E'!$D$3:$D$146,"Utilidades",'DESP E'!$J$3:$J$146) -> 276058.51 | X26: =W26/$W$10 -> 0.012435631 | Y26: =SUMIF('DESP A'!$D$3:$D$129,"Utilidades",'DESP A'!$J$3:$J$129) -> 1076.4 | Z26: =Y26/$Y$10 -> 0.00034097887 | AA26: =W26+Y26 -> 277134.91 | AB26: =AA26/$AA$10 -> 0.010929847 | AC26: =AA26-T26 -> -139012.86 | AD26: =SUMIF('DESP E'!$D$3:$D$146,"Utilidades",'DESP E'!$K$3:$K$146) -> 0 | AE26: =AD26/$AD$10 -> #DIV/0! | AF26: =SUMIF('DESP A'!$D$3:$D$129,"Utilidades",'DESP A'!$K$3:$K$129) -> 0 | AG26: =AF26/$AF$10 -> #DIV/0! | AH26: =AD26+AF26 -> 0 | AI26: =AH26/$AH$10 -> #DIV/0! | AJ26: =AH26-AA26 -> -277134.91 | AK26: =SUMIF('DESP E'!$D$3:$D$146,"Utilidades",'DESP E'!$L$3:$L$146) -> 0 | AL26: =AK26/$AK$10 -> #DIV/0! | AM26: =SUMIF('DESP A'!$D$3:$D$129,"Utilidades",'DESP A'!$L$3:$L$129) -> 0 | AN26: =AM26/$AM$10 -> #DIV/0! | AO26: =AK26+AM26 -> 0 | AP26: =AO26/$AO$10 -> #DIV/0! | AQ26: =AO26-AH26 -> 0 | AR26: =SUMIF('DESP E'!$D$3:$D$146,"Utilidades",'DESP E'!$M$3:$M$146) -> 0 | AS26: =AR26/$AR$10 -> #DIV/0! | AT26: =SUMIF('DESP A'!$D$3:$D$129,"Utilidades",'DESP A'!$M$3:$M$129) -> 0 | AU26: =AT26/$AT$10 -> #DIV/0! | AV26: =AR26+AT26 -> 0 | AW26: =AV26/$AV$10 -> #DIV/0! | AX26: =AV26-AO26 -> 0 | AY26: =SUMIF('DESP E'!$D$3:$D$146,"Utilidades",'DESP E'!$N$3:$N$146) -> 0 | AZ26: =AY26/$AY$10 -> #DIV/0! | BA26: =SUMIF('DESP A'!$D$3:$D$129,"Utilidades",'DESP A'!$N$3:$N$129) -> 0 | BB26: =BA26/$BA$10 -> #DIV/0! | BC26: =AY26+BA26 -> 0 | BD26: =BC26/$BC$10 -> #DIV/0! | BE26: =BC26-AV26 -> 0 | BF26: =SUMIF('DESP E'!$D$3:$D$146,"Utilidades",'DESP E'!$O$3:$O$146) -> 0 | BG26: =BF26/$BF$10 -> #DIV/0! | BH26: =SUMIF('DESP A'!$D$3:$D$129,"Utilidades",'DESP A'!$O$3:$O$129) -> 0 | BI26: =BH26/$BH$10 -> #DIV/0! | BJ26: =BF26+BH26 -> 0 | BK26: =BJ26/$BJ$10 -> #DIV/0! | BL26: =BJ26-BC26 -> 0 | BM26: =SUMIF('DESP E'!$D$3:$D$146,"Utilidades",'DESP E'!$P$3:$P$146) -> 0 | BN26: =BM26/$BF$10 -> #DIV/0! | BO26: =SUMIF('DESP A'!$D$3:$D$129,"Utilidades",'DESP A'!$P$3:$P$129) -> 0 | BP26: =BO26/$BH$10 -> #DIV/0! | BQ26: =BM26+BO26 -> 0 | BR26: =BQ26/$BJ$10 -> #DIV/0! | BS26: =BQ26-BJ26 -> 0 | BT26: =SUMIF('DESP E'!$D$3:$D$146,"Utilidades",'DESP E'!$Q$3:$Q$146) -> 0 | BU26: =BT26/$BF$10 -> #DIV/0! | BV26: =SUMIF('DESP A'!$D$3:$D$129,"Utilidades",'DESP A'!$Q$3:$Q$129) -> 0 | BW26: =BV26/$BH$10 -> #DIV/0! | BX26: =BT26+BV26 -> 0 | BY26: =BX26/$BJ$10 -> #DIV/0! | BZ26: =BX26-BQ26 -> 0 | CA26: =SUMIF('DESP E'!$D$3:$D$146,"Utilidades",'DESP E'!$R$3:$R$146) -> 0 | CB26: =CA26/$BF$10 -> #DIV/0! | CC26: =SUMIF('DESP A'!$D$3:$D$129,"Utilidades",'DESP A'!$R$3:$R$129) -> 0 | CD26: =CC26/$BH$10 -> #DIV/0! | CE26: =CA26+CC26 -> 0 | CF26: =CE26/$BJ$10 -> #DIV/0! | CG26: =CE26-BX26 -> 0 | CH26: =SUM(C26,I26,P26,W26,AD26,AK26,AR26,AY26,BF26,BM26,BT26,CA26) -> 1159347 | CI26: =CH26/$CH$10 -> 0.011577569 | CJ26: =SUM(E26,K26,R26,Y26,AF26,AM26,AT26,BA26,BH26,BO26,BV26,CC26) -> 5913.27 | CK26: =CJ26/$CJ$10 -> 0.00041706361 | CL26: =SUM(G26,M26,T26,AA26,AH26,AO26,AV26,BC26,BJ26,BQ26,BX26,CE26) -> 1165260.3 | CM26: =CL26/$CL$10 -> 0.010193354
B27: Manutenção | C27: =SUMIF('DESP E'!$D$3:$D$146,"Manutenção",'DESP E'!$G$3:$G$146) -> 75584.77 | D27: =C27/$C$10 -> 0.0022973391 | E27: =SUMIF('DESP A'!$D$3:$D$129,"Manutenção",'DESP A'!$G$3:$G$129) -> 251.28 | F27: =E27/$E$10 -> 6.3587377e-05 | G27: =C27+E27 -> 75836.05 | H27: =G27/$G$10 -> 0.0020578133 | I27: =SUMIF('DESP E'!$D$3:$D$146,"Manutenção",'DESP E'!$H$3:$H$146) -> 87860 | J27: =I27/$I$10 -> 0.0041384788 | K27: =SUMIF('DESP A'!$D$3:$D$129,"Manutenção",'DESP A'!$H$3:$H$129) -> 0 | L27: =K27/$K$10 -> 0 | M27: =I27+K27 -> 87860 | N27: =M27/$M$10 -> 0.0035644076 | O27: =M27-G27 -> 12023.95 | P27: =SUMIF('DESP E'!$D$3:$D$146,"Manutenção",'DESP E'!$I$3:$I$146) -> 79616.11 | Q27: =P27/$P$10 -> 0.0033441862 | R27: =SUMIF('DESP A'!$D$3:$D$129,"Manutenção",'DESP A'!$I$3:$I$129) -> 0 | S27: =R27/$R$10 -> 0 | T27: =P27+R27 -> 79616.11 | U27: =T27/$T$10 -> 0.0028995698 | V27: =T27-M27 -> -8243.89 | W27: =SUMIF('DESP E'!$D$3:$D$146,"Manutenção",'DESP E'!$J$3:$J$146) -> 68367.86 | X27: =W27/$W$10 -> 0.0030797727 | Y27: =SUMIF('DESP A'!$D$3:$D$129,"Manutenção",'DESP A'!$J$3:$J$129) -> 0 | Z27: =Y27/$Y$10 -> 0 | AA27: =W27+Y27 -> 68367.86 | AB27: =AA27/$AA$10 -> 0.0026963412 | AC27: =AA27-T27 -> -11248.25 | AD27: =SUMIF('DESP E'!$D$3:$D$146,"Manutenção",'DESP E'!$K$3:$K$146) -> 0 | AE27: =AD27/$AD$10 -> #DIV/0! | AF27: =SUMIF('DESP A'!$D$3:$D$129,"Manutenção",'DESP A'!$K$3:$K$129) -> 0 | AG27: =AF27/$AF$10 -> #DIV/0! | AH27: =AD27+AF27 -> 0 | AI27: =AH27/$AH$10 -> #DIV/0! | AJ27: =AH27-AA27 -> -68367.86 | AK27: =SUMIF('DESP E'!$D$3:$D$146,"Manutenção",'DESP E'!$L$3:$L$146) -> 0 | AL27: =AK27/$AK$10 -> #DIV/0! | AM27: =SUMIF('DESP A'!$D$3:$D$129,"Manutenção",'DESP A'!$L$3:$L$129) -> 0 | AN27: =AM27/$AM$10 -> #DIV/0! | AO27: =AK27+AM27 -> 0 | AP27: =AO27/$AO$10 -> #DIV/0! | AQ27: =AO27-AH27 -> 0 | AR27: =SUMIF('DESP E'!$D$3:$D$146,"Manutenção",'DESP E'!$M$3:$M$146) -> 0 | AS27: =AR27/$AR$10 -> #DIV/0! | AT27: =SUMIF('DESP A'!$D$3:$D$129,"Manutenção",'DESP A'!$M$3:$M$129) -> 0 | AU27: =AT27/$AT$10 -> #DIV/0! | AV27: =AR27+AT27 -> 0 | AW27: =AV27/$AV$10 -> #DIV/0! | AX27: =AV27-AO27 -> 0 | AY27: =SUMIF('DESP E'!$D$3:$D$146,"Manutenção",'DESP E'!$N$3:$N$146) -> 0 | AZ27: =AY27/$AY$10 -> #DIV/0! | BA27: =SUMIF('DESP A'!$D$3:$D$129,"Manutenção",'DESP A'!$N$3:$N$129) -> 0 | BB27: =BA27/$BA$10 -> #DIV/0! | BC27: =AY27+BA27 -> 0 | BD27: =BC27/$BC$10 -> #DIV/0! | BE27: =BC27-AV27 -> 0 | BF27: =SUMIF('DESP E'!$D$3:$D$146,"Manutenção",'DESP E'!$O$3:$O$146) -> 0 | BG27: =BF27/$BF$10 -> #DIV/0! | BH27: =SUMIF('DESP A'!$D$3:$D$129,"Manutenção",'DESP A'!$O$3:$O$129) -> 0 | BI27: =BH27/$BH$10 -> #DIV/0! | BJ27: =BF27+BH27 -> 0 | BK27: =BJ27/$BJ$10 -> #DIV/0! | BL27: =BJ27-BC27 -> 0 | BM27: =SUMIF('DESP E'!$D$3:$D$146,"Manutenção",'DESP E'!$P$3:$P$146) -> 0 | BN27: =BM27/$BF$10 -> #DIV/0! | BO27: =SUMIF('DESP A'!$D$3:$D$129,"Manutenção",'DESP A'!$P$3:$P$129) -> 0 | BP27: =BO27/$BH$10 -> #DIV/0! | BQ27: =BM27+BO27 -> 0 | BR27: =BQ27/$BJ$10 -> #DIV/0! | BS27: =BQ27-BJ27 -> 0 | BT27: =SUMIF('DESP E'!$D$3:$D$146,"Manutenção",'DESP E'!$Q$3:$Q$146) -> 0 | BU27: =BT27/$BF$10 -> #DIV/0! | BV27: =SUMIF('DESP A'!$D$3:$D$129,"Manutenção",'DESP A'!$Q$3:$Q$129) -> 0 | BW27: =BV27/$BH$10 -> #DIV/0! | BX27: =BT27+BV27 -> 0 | BY27: =BX27/$BJ$10 -> #DIV/0! | BZ27: =BX27-BQ27 -> 0 | CA27: =SUMIF('DESP E'!$D$3:$D$146,"Manutenção",'DESP E'!$R$3:$R$146) -> 0 | CB27: =CA27/$BF$10 -> #DIV/0! | CC27: =SUMIF('DESP A'!$D$3:$D$129,"Manutenção",'DESP A'!$R$3:$R$129) -> 0 | CD27: =CC27/$BH$10 -> #DIV/0! | CE27: =CA27+CC27 -> 0 | CF27: =CE27/$BJ$10 -> #DIV/0! | CG27: =CE27-BX27 -> 0 | CH27: =SUM(C27,I27,P27,W27,AD27,AK27,AR27,AY27,BF27,BM27,BT27,CA27) -> 311428.74 | CI27: =CH27/$CH$10 -> 0.0031100159 | CJ27: =SUM(E27,K27,R27,Y27,AF27,AM27,AT27,BA27,BH27,BO27,BV27,CC27) -> 251.28 | CK27: =CJ27/$CJ$10 -> 1.7722807e-05 | CL27: =SUM(G27,M27,T27,AA27,AH27,AO27,AV27,BC27,BJ27,BQ27,BX27,CE27) -> 311680.02 | CM27: =CL27/$CL$10 -> 0.0027264851
B28: Uso e Consumo | C28: =SUMIF('DESP E'!$D$3:$D$146,"Uso e Consumo",'DESP E'!$G$3:$G$146) -> 6736.13 | D28: =C28/$C$10 -> 0.00020473932 | E28: =SUMIF('DESP A'!$D$3:$D$129,"Uso e Consumo",'DESP A'!$G$3:$G$129) -> 7860 | F28: =E28/$E$10 -> 0.0019890034 | G28: =C28+E28 -> 14596.13 | H28: =G28/$G$10 -> 0.00039606639 | I28: =SUMIF('DESP E'!$D$3:$D$146,"Uso e Consumo",'DESP E'!$H$3:$H$146) -> 2842.13 | J28: =I28/$I$10 -> 0.00013387315 | K28: =SUMIF('DESP A'!$D$3:$D$129,"Uso e Consumo",'DESP A'!$H$3:$H$129) -> 7084.5 | L28: =K28/$K$10 -> 0.002071955 | M28: =I28+K28 -> 9926.63 | N28: =M28/$M$10 -> 0.00040271517 | O28: =M28-G28 -> -4669.5 | P28: =SUMIF('DESP E'!$D$3:$D$146,"Uso e Consumo",'DESP E'!$I$3:$I$146) -> 4014.74 | Q28: =P28/$P$10 -> 0.00016863469 | R28: =SUMIF('DESP A'!$D$3:$D$129,"Uso e Consumo",'DESP A'!$I$3:$I$129) -> 6053.6 | S28: =R28/$R$10 -> 0.001658255 | T28: =P28+R28 -> 10068.34 | U28: =T28/$T$10 -> 0.00036668276 | V28: =T28-M28 -> 141.71 | W28: =SUMIF('DESP E'!$D$3:$D$146,"Uso e Consumo",'DESP E'!$J$3:$J$146) -> 8589.28 | X28: =W28/$W$10 -> 0.00038692201 | Y28: =SUMIF('DESP A'!$D$3:$D$129,"Uso e Consumo",'DESP A'!$J$3:$J$129) -> 7434.3 | Z28: =Y28/$Y$10 -> 0.002355016 | AA28: =W28+Y28 -> 16023.58 | AB28: =AA28/$AA$10 -> 0.00063194956 | AC28: =AA28-T28 -> 5955.24 | AD28: =SUMIF('DESP E'!$D$3:$D$146,"Uso e Consumo",'DESP E'!$K$3:$K$146) -> 0 | AE28: =AD28/$AD$10 -> #DIV/0! | AF28: =SUMIF('DESP A'!$D$3:$D$129,"Uso e Consumo",'DESP A'!$K$3:$K$129) -> 0 | AG28: =AF28/$AF$10 -> #DIV/0! | AH28: =AD28+AF28 -> 0 | AI28: =AH28/$AH$10 -> #DIV/0! | AJ28: =AH28-AA28 -> -16023.58 | AK28: =SUMIF('DESP E'!$D$3:$D$146,"Uso e Consumo",'DESP E'!$L$3:$L$146) -> 0 | AL28: =AK28/$AK$10 -> #DIV/0! | AM28: =SUMIF('DESP A'!$D$3:$D$129,"Uso e Consumo",'DESP A'!$L$3:$L$129) -> 0 | AN28: =AM28/$AM$10 -> #DIV/0! | AO28: =AK28+AM28 -> 0 | AP28: =AO28/$AO$10 -> #DIV/0! | AQ28: =AO28-AH28 -> 0 | AR28: =SUMIF('DESP E'!$D$3:$D$146,"Uso e Consumo",'DESP E'!$M$3:$M$146) -> 0 | AS28: =AR28/$AR$10 -> #DIV/0! | AT28: =SUMIF('DESP A'!$D$3:$D$129,"Uso e Consumo",'DESP A'!$M$3:$M$129) -> 0 | AU28: =AT28/$AT$10 -> #DIV/0! | AV28: =AR28+AT28 -> 0 | AW28: =AV28/$AV$10 -> #DIV/0! | AX28: =AV28-AO28 -> 0 | AY28: =SUMIF('DESP E'!$D$3:$D$146,"Uso e Consumo",'DESP E'!$N$3:$N$146) -> 0 | AZ28: =AY28/$AY$10 -> #DIV/0! | BA28: =SUMIF('DESP A'!$D$3:$D$129,"Uso e Consumo",'DESP A'!$N$3:$N$129) -> 0 | BB28: =BA28/$BA$10 -> #DIV/0! | BC28: =AY28+BA28 -> 0 | BD28: =BC28/$BC$10 -> #DIV/0! | BE28: =BC28-AV28 -> 0 | BF28: =SUMIF('DESP E'!$D$3:$D$146,"Uso e Consumo",'DESP E'!$O$3:$O$146) -> 0 | BG28: =BF28/$BF$10 -> #DIV/0! | BH28: =SUMIF('DESP A'!$D$3:$D$129,"Uso e Consumo",'DESP A'!$O$3:$O$129) -> 0 | BI28: =BH28/$BH$10 -> #DIV/0! | BJ28: =BF28+BH28 -> 0 | BK28: =BJ28/$BJ$10 -> #DIV/0! | BL28: =BJ28-BC28 -> 0 | BM28: =SUMIF('DESP E'!$D$3:$D$146,"Uso e Consumo",'DESP E'!$P$3:$P$146) -> 0 | BN28: =BM28/$BF$10 -> #DIV/0! | BO28: =SUMIF('DESP A'!$D$3:$D$129,"Uso e Consumo",'DESP A'!$P$3:$P$129) -> 0 | BP28: =BO28/$BH$10 -> #DIV/0! | BQ28: =BM28+BO28 -> 0 | BR28: =BQ28/$BJ$10 -> #DIV/0! | BS28: =BQ28-BJ28 -> 0 | BT28: =SUMIF('DESP E'!$D$3:$D$146,"Uso e Consumo",'DESP E'!$Q$3:$Q$146) -> 0 | BU28: =BT28/$BF$10 -> #DIV/0! | BV28: =SUMIF('DESP A'!$D$3:$D$129,"Uso e Consumo",'DESP A'!$Q$3:$Q$129) -> 0 | BW28: =BV28/$BH$10 -> #DIV/0! | BX28: =BT28+BV28 -> 0 | BY28: =BX28/$BJ$10 -> #DIV/0! | BZ28: =BX28-BQ28 -> 0 | CA28: =SUMIF('DESP E'!$D$3:$D$146,"Uso e Consumo",'DESP E'!$R$3:$R$146) -> 0 | CB28: =CA28/$BF$10 -> #DIV/0! | CC28: =SUMIF('DESP A'!$D$3:$D$129,"Uso e Consumo",'DESP A'!$R$3:$R$129) -> 0 | CD28: =CC28/$BH$10 -> #DIV/0! | CE28: =CA28+CC28 -> 0 | CF28: =CE28/$BJ$10 -> #DIV/0! | CG28: =CE28-BX28 -> 0 | CH28: =SUM(C28,I28,P28,W28,AD28,AK28,AR28,AY28,BF28,BM28,BT28,CA28) -> 22182.28 | CI28: =CH28/$CH$10 -> 0.00022151855 | CJ28: =SUM(E28,K28,R28,Y28,AF28,AM28,AT28,BA28,BH28,BO28,BV28,CC28) -> 28432.4 | CK28: =CJ28/$CJ$10 -> 0.0020053404 | CL28: =SUM(G28,M28,T28,AA28,AH28,AO28,AV28,BC28,BJ28,BQ28,BX28,CE28) -> 50614.68 | CM28: =CL28/$CL$10 -> 0.00044276233
B29: Informática | C29: =SUMIF('DESP E'!$D$3:$D$146,"Informática",'DESP E'!$G$3:$G$146) -> 118369.4 | D29: =C29/$C$10 -> 0.0035977439 | E29: =SUMIF('DESP A'!$D$3:$D$129,"Informática",'DESP A'!$G$3:$G$129) -> 7400.84 | F29: =E29/$E$10 -> 0.0018728112 | G29: =C29+E29 -> 125770.24 | H29: =G29/$G$10 -> 0.003412779 | I29: =SUMIF('DESP E'!$D$3:$D$146,"Informática",'DESP E'!$H$3:$H$146) -> 119742 | J29: =I29/$I$10 -> 0.00564022 | K29: =SUMIF('DESP A'!$D$3:$D$129,"Informática",'DESP A'!$H$3:$H$129) -> 7716.1 | L29: =K29/$K$10 -> 0.0022566747 | M29: =I29+K29 -> 127458.1 | N29: =M29/$M$10 -> 0.0051708698 | O29: =M29-G29 -> 1687.86 | P29: =SUMIF('DESP E'!$D$3:$D$146,"Informática",'DESP E'!$I$3:$I$146) -> 113101.91 | Q29: =P29/$P$10 -> 0.00475072 | R29: =SUMIF('DESP A'!$D$3:$D$129,"Informática",'DESP A'!$I$3:$I$129) -> 7716.1 | S29: =R29/$R$10 -> 0.0021136615 | T29: =P29+R29 -> 120818.01 | U29: =T29/$T$10 -> 0.0044001177 | V29: =T29-M29 -> -6640.09 | W29: =SUMIF('DESP E'!$D$3:$D$146,"Informática",'DESP E'!$J$3:$J$146) -> 109747.1 | X29: =W29/$W$10 -> 0.0049437868 | Y29: =SUMIF('DESP A'!$D$3:$D$129,"Informática",'DESP A'!$J$3:$J$129) -> 7716.1 | Z29: =Y29/$Y$10 -> 0.0024442837 | AA29: =W29+Y29 -> 117463.2 | AB29: =AA29/$AA$10 -> 0.0046325988 | AC29: =AA29-T29 -> -3354.81 | AD29: =SUMIF('DESP E'!$D$3:$D$146,"Informática",'DESP E'!$K$3:$K$146) -> 0 | AE29: =AD29/$AD$10 -> #DIV/0! | AF29: =SUMIF('DESP A'!$D$3:$D$129,"Informática",'DESP A'!$K$3:$K$129) -> 0 | AG29: =AF29/$AF$10 -> #DIV/0! | AH29: =AD29+AF29 -> 0 | AI29: =AH29/$AH$10 -> #DIV/0! | AJ29: =AH29-AA29 -> -117463.2 | AK29: =SUMIF('DESP E'!$D$3:$D$146,"Informática",'DESP E'!$L$3:$L$146) -> 0 | AL29: =AK29/$AK$10 -> #DIV/0! | AM29: =SUMIF('DESP A'!$D$3:$D$129,"Informática",'DESP A'!$L$3:$L$129) -> 0 | AN29: =AM29/$AM$10 -> #DIV/0! | AO29: =AK29+AM29 -> 0 | AP29: =AO29/$AO$10 -> #DIV/0! | AQ29: =AO29-AH29 -> 0 | AR29: =SUMIF('DESP E'!$D$3:$D$146,"Informática",'DESP E'!$M$3:$M$146) -> 0 | AS29: =AR29/$AR$10 -> #DIV/0! | AT29: =SUMIF('DESP A'!$D$3:$D$129,"Informática",'DESP A'!$M$3:$M$129) -> 0 | AU29: =AT29/$AT$10 -> #DIV/0! | AV29: =AR29+AT29 -> 0 | AW29: =AV29/$AV$10 -> #DIV/0! | AX29: =AV29-AO29 -> 0 | AY29: =SUMIF('DESP E'!$D$3:$D$146,"Informática",'DESP E'!$N$3:$N$146) -> 0 | AZ29: =AY29/$AY$10 -> #DIV/0! | BA29: =SUMIF('DESP A'!$D$3:$D$129,"Informática",'DESP A'!$N$3:$N$129) -> 0 | BB29: =BA29/$BA$10 -> #DIV/0! | BC29: =AY29+BA29 -> 0 | BD29: =BC29/$BC$10 -> #DIV/0! | BE29: =BC29-AV29 -> 0 | BF29: =SUMIF('DESP E'!$D$3:$D$146,"Informática",'DESP E'!$O$3:$O$146) -> 0 | BG29: =BF29/$BF$10 -> #DIV/0! | BH29: =SUMIF('DESP A'!$D$3:$D$129,"Informática",'DESP A'!$O$3:$O$129) -> 0 | BI29: =BH29/$BH$10 -> #DIV/0! | BJ29: =BF29+BH29 -> 0 | BK29: =BJ29/$BJ$10 -> #DIV/0! | BL29: =BJ29-BC29 -> 0 | BM29: =SUMIF('DESP E'!$D$3:$D$146,"Informática",'DESP E'!$P$3:$P$146) -> 0 | BN29: =BM29/$BF$10 -> #DIV/0! | BO29: =SUMIF('DESP A'!$D$3:$D$129,"Informática",'DESP A'!$P$3:$P$129) -> 0 | BP29: =BO29/$BH$10 -> #DIV/0! | BQ29: =BM29+BO29 -> 0 | BR29: =BQ29/$BJ$10 -> #DIV/0! | BS29: =BQ29-BJ29 -> 0 | BT29: =SUMIF('DESP E'!$D$3:$D$146,"Informática",'DESP E'!$Q$3:$Q$146) -> 0 | BU29: =BT29/$BF$10 -> #DIV/0! | BV29: =SUMIF('DESP A'!$D$3:$D$129,"Informática",'DESP A'!$Q$3:$Q$129) -> 0 | BW29: =BV29/$BH$10 -> #DIV/0! | BX29: =BT29+BV29 -> 0 | BY29: =BX29/$BJ$10 -> #DIV/0! | BZ29: =BX29-BQ29 -> 0 | CA29: =SUMIF('DESP E'!$D$3:$D$146,"Informática",'DESP E'!$R$3:$R$146) -> 0 | CB29: =CA29/$BF$10 -> #DIV/0! | CC29: =SUMIF('DESP A'!$D$3:$D$129,"Informática",'DESP A'!$R$3:$R$129) -> 0 | CD29: =CC29/$BH$10 -> #DIV/0! | CE29: =CA29+CC29 -> 0 | CF29: =CE29/$BJ$10 -> #DIV/0! | CG29: =CE29-BX29 -> 0 | CH29: =SUM(C29,I29,P29,W29,AD29,AK29,AR29,AY29,BF29,BM29,BT29,CA29) -> 460960.41 | CI29: =CH29/$CH$10 -> 0.0046032817 | CJ29: =SUM(E29,K29,R29,Y29,AF29,AM29,AT29,BA29,BH29,BO29,BV29,CC29) -> 30549.14 | CK29: =CJ29/$CJ$10 -> 0.0021546344 | CL29: =SUM(G29,M29,T29,AA29,AH29,AO29,AV29,BC29,BJ29,BQ29,BX29,CE29) -> 491509.55 | CM29: =CL29/$CL$10 -> 0.004299581
B30: Gerais | C30: =SUMIF('DESP E'!$D$3:$D$146,"Gerais",'DESP E'!$G$3:$G$146) -> 31496.09 | D30: =C30/$C$10 -> 0.00095729864 | E30: =SUMIF('DESP A'!$D$3:$D$129,"Gerais",'DESP A'!$G$3:$G$129) -> 0 | F30: =E30/$E$10 -> 0 | G30: =C30+E30 -> 31496.09 | H30: =G30/$G$10 -> 0.00085464728 | I30: =SUMIF('DESP E'!$D$3:$D$146,"Gerais",'DESP E'!$H$3:$H$146) -> 25162.32 | J30: =I30/$I$10 -> 0.0011852234 | K30: =SUMIF('DESP A'!$D$3:$D$129,"Gerais",'DESP A'!$H$3:$H$129) -> 0 | L30: =K30/$K$10 -> 0 | M30: =I30+K30 -> 25162.32 | N30: =M30/$M$10 -> 0.0010208145 | O30: =M30-G30 -> -6333.77 | P30: =SUMIF('DESP E'!$D$3:$D$146,"Gerais",'DESP E'!$I$3:$I$146) -> 33309.45 | Q30: =P30/$P$10 -> 0.0013991264 | R30: =SUMIF('DESP A'!$D$3:$D$129,"Gerais",'DESP A'!$I$3:$I$129) -> 0 | S30: =R30/$R$10 -> 0 | T30: =P30+R30 -> 33309.45 | U30: =T30/$T$10 -> 0.0012131097 | V30: =T30-M30 -> 8147.13 | W30: =SUMIF('DESP E'!$D$3:$D$146,"Gerais",'DESP E'!$J$3:$J$146) -> 22362.32 | X30: =W30/$W$10 -> 0.0010073573 | Y30: =SUMIF('DESP A'!$D$3:$D$129,"Gerais",'DESP A'!$J$3:$J$129) -> 0 | Z30: =Y30/$Y$10 -> 0 | AA30: =W30+Y30 -> 22362.32 | AB30: =AA30/$AA$10 -> 0.00088194139 | AC30: =AA30-T30 -> -10947.13 | AD30: =SUMIF('DESP E'!$D$3:$D$146,"Gerais",'DESP E'!$K$3:$K$146) -> 0 | AE30: =AD30/$AD$10 -> #DIV/0! | AF30: =SUMIF('DESP A'!$D$3:$D$129,"Gerais",'DESP A'!$K$3:$K$129) -> 0 | AG30: =AF30/$AF$10 -> #DIV/0! | AH30: =AD30+AF30 -> 0 | AI30: =AH30/$AH$10 -> #DIV/0! | AJ30: =AH30-AA30 -> -22362.32 | AK30: =SUMIF('DESP E'!$D$3:$D$146,"Gerais",'DESP E'!$L$3:$L$146) -> 0 | AL30: =AK30/$AK$10 -> #DIV/0! | AM30: =SUMIF('DESP A'!$D$3:$D$129,"Gerais",'DESP A'!$L$3:$L$129) -> 0 | AN30: =AM30/$AM$10 -> #DIV/0! | AO30: =AK30+AM30 -> 0 | AP30: =AO30/$AO$10 -> #DIV/0! | AQ30: =AO30-AH30 -> 0 | AR30: =SUMIF('DESP E'!$D$3:$D$146,"Gerais",'DESP E'!$M$3:$M$146) -> 0 | AS30: =AR30/$AR$10 -> #DIV/0! | AT30: =SUMIF('DESP A'!$D$3:$D$129,"Gerais",'DESP A'!$M$3:$M$129) -> 0 | AU30: =AT30/$AT$10 -> #DIV/0! | AV30: =AR30+AT30 -> 0 | AW30: =AV30/$AV$10 -> #DIV/0! | AX30: =AV30-AO30 -> 0 | AY30: =SUMIF('DESP E'!$D$3:$D$146,"Gerais",'DESP E'!$N$3:$N$146) -> 0 | AZ30: =AY30/$AY$10 -> #DIV/0! | BA30: =SUMIF('DESP A'!$D$3:$D$129,"Gerais",'DESP A'!$N$3:$N$129) -> 0 | BB30: =BA30/$BA$10 -> #DIV/0! | BC30: =AY30+BA30 -> 0 | BD30: =BC30/$BC$10 -> #DIV/0! | BE30: =BC30-AV30 -> 0 | BF30: =SUMIF('DESP E'!$D$3:$D$146,"Gerais",'DESP E'!$O$3:$O$146) -> 0 | BG30: =BF30/$BF$10 -> #DIV/0! | BH30: =SUMIF('DESP A'!$D$3:$D$129,"Gerais",'DESP A'!$O$3:$O$129) -> 0 | BI30: =BH30/$BH$10 -> #DIV/0! | BJ30: =BF30+BH30 -> 0 | BK30: =BJ30/$BJ$10 -> #DIV/0! | BL30: =BJ30-BC30 -> 0 | BM30: =SUMIF('DESP E'!$D$3:$D$146,"Gerais",'DESP E'!$P$3:$P$146) -> 0 | BN30: =BM30/$BF$10 -> #DIV/0! | BO30: =SUMIF('DESP A'!$D$3:$D$129,"Gerais",'DESP A'!$P$3:$P$129) -> 0 | BP30: =BO30/$BH$10 -> #DIV/0! | BQ30: =BM30+BO30 -> 0 | BR30: =BQ30/$BJ$10 -> #DIV/0! | BS30: =BQ30-BJ30 -> 0 | BT30: =SUMIF('DESP E'!$D$3:$D$146,"Gerais",'DESP E'!$Q$3:$Q$146) -> 0 | BU30: =BT30/$BF$10 -> #DIV/0! | BV30: =SUMIF('DESP A'!$D$3:$D$129,"Gerais",'DESP A'!$Q$3:$Q$129) -> 0 | BW30: =BV30/$BH$10 -> #DIV/0! | BX30: =BT30+BV30 -> 0 | BY30: =BX30/$BJ$10 -> #DIV/0! | BZ30: =BX30-BQ30 -> 0 | CA30: =SUMIF('DESP E'!$D$3:$D$146,"Gerais",'DESP E'!$R$3:$R$146) -> 0 | CB30: =CA30/$BF$10 -> #DIV/0! | CC30: =SUMIF('DESP A'!$D$3:$D$129,"Gerais",'DESP A'!$R$3:$R$129) -> 0 | CD30: =CC30/$BH$10 -> #DIV/0! | CE30: =CA30+CC30 -> 0 | CF30: =CE30/$BJ$10 -> #DIV/0! | CG30: =CE30-BX30 -> 0 | CH30: =SUM(C30,I30,P30,W30,AD30,AK30,AR30,AY30,BF30,BM30,BT30,CA30) -> 112330.18 | CI30: =CH30/$CH$10 -> 0.0011217611 | CJ30: =SUM(E30,K30,R30,Y30,AF30,AM30,AT30,BA30,BH30,BO30,BV30,CC30) -> 0 | CK30: =CJ30/$CJ$10 -> 0 | CL30: =SUM(G30,M30,T30,AA30,AH30,AO30,AV30,BC30,BJ30,BQ30,BX30,CE30) -> 112330.18 | CM30: =CL30/$CL$10 -> 0.00098263137
B31: Despesa Com Vendas | C31: =SUMIF('DESP E'!$D$3:$D$146,"Vendas",'DESP E'!$G$3:$G$146) -> 86972.37 | D31: =C31/$C$10 -> 0.0026434561 | E31: =SUMIF('DESP A'!$D$3:$D$129,"Vendas",'DESP A'!$G$3:$G$129) -> 0 | F31: =E31/$E$10 -> 0 | G31: =C31+E31 -> 86972.37 | H31: =G31/$G$10 -> 0.0023599977 | I31: =SUMIF('DESP E'!$D$3:$D$146,"Vendas",'DESP E'!$H$3:$H$146) -> 52192.03 | J31: =I31/$I$10 -> 0.0024584067 | K31: =SUMIF('DESP A'!$D$3:$D$129,"Vendas",'DESP A'!$H$3:$H$129) -> 1300 | L31: =K31/$K$10 -> 0.00038020206 | M31: =I31+K31 -> 53492.03 | N31: =M31/$M$10 -> 0.0021701274 | O31: =M31-G31 -> -33480.34 | P31: =SUMIF('DESP E'!$D$3:$D$146,"Vendas",'DESP E'!$I$3:$I$146) -> 37850.97 | Q31: =P31/$P$10 -> 0.0015898879 | R31: =SUMIF('DESP A'!$D$3:$D$129,"Vendas",'DESP A'!$I$3:$I$129) -> 2989 | S31: =R31/$R$10 -> 0.00081877298 | T31: =P31+R31 -> 40839.97 | U31: =T31/$T$10 -> 0.0014873666 | V31: =T31-M31 -> -12652.06 | W31: =SUMIF('DESP E'!$D$3:$D$146,"Vendas",'DESP E'!$J$3:$J$146) -> 42986.81 | X31: =W31/$W$10 -> 0.0019364304 | Y31: =SUMIF('DESP A'!$D$3:$D$129,"Vendas",'DESP A'!$J$3:$J$129) -> 0 | Z31: =Y31/$Y$10 -> 0 | AA31: =W31+Y31 -> 42986.81 | AB31: =AA31/$AA$10 -> 0.001695345 | AC31: =AA31-T31 -> 2146.84 | AD31: =SUMIF('DESP E'!$D$3:$D$146,"Vendas",'DESP E'!$K$3:$K$146) -> 0 | AE31: =AD31/$AD$10 -> #DIV/0! | AF31: =SUMIF('DESP A'!$D$3:$D$129,"Vendas",'DESP A'!$K$3:$K$129) -> 0 | AG31: =AF31/$AF$10 -> #DIV/0! | AH31: =AD31+AF31 -> 0 | AI31: =AH31/$AH$10 -> #DIV/0! | AJ31: =AH31-AA31 -> -42986.81 | AK31: =SUMIF('DESP E'!$D$3:$D$146,"Vendas",'DESP E'!$L$3:$L$146) -> 0 | AL31: =AK31/$AK$10 -> #DIV/0! | AM31: =SUMIF('DESP A'!$D$3:$D$129,"Vendas",'DESP A'!$L$3:$L$129) -> 0 | AN31: =AM31/$AM$10 -> #DIV/0! | AO31: =AK31+AM31 -> 0 | AP31: =AO31/$AO$10 -> #DIV/0! | AQ31: =AO31-AH31 -> 0 | AR31: =SUMIF('DESP E'!$D$3:$D$146,"Vendas",'DESP E'!$M$3:$M$146) -> 0 | AS31: =AR31/$AR$10 -> #DIV/0! | AT31: =SUMIF('DESP A'!$D$3:$D$129,"Vendas",'DESP A'!$M$3:$M$129) -> 0 | AU31: =AT31/$AT$10 -> #DIV/0! | AV31: =AR31+AT31 -> 0 | AW31: =AV31/$AV$10 -> #DIV/0! | AX31: =AV31-AO31 -> 0 | AY31: =SUMIF('DESP E'!$D$3:$D$146,"Vendas",'DESP E'!$N$3:$N$146) -> 0 | AZ31: =AY31/$AY$10 -> #DIV/0! | BA31: =SUMIF('DESP A'!$D$3:$D$129,"Vendas",'DESP A'!$N$3:$N$129) -> 0 | BB31: =BA31/$BA$10 -> #DIV/0! | BC31: =AY31+BA31 -> 0 | BD31: =BC31/$BC$10 -> #DIV/0! | BE31: =BC31-AV31 -> 0 | BF31: =SUMIF('DESP E'!$D$3:$D$146,"Vendas",'DESP E'!$O$3:$O$146) -> 0 | BG31: =BF31/$BF$10 -> #DIV/0! | BH31: =SUMIF('DESP A'!$D$3:$D$129,"Vendas",'DESP A'!$O$3:$O$129) -> 0 | BI31: =BH31/$BH$10 -> #DIV/0! | BJ31: =BF31+BH31 -> 0 | BK31: =BJ31/$BJ$10 -> #DIV/0! | BL31: =BJ31-BC31 -> 0 | BM31: =SUMIF('DESP E'!$D$3:$D$146,"Vendas",'DESP E'!$P$3:$P$146) -> 0 | BN31: =BM31/$BF$10 -> #DIV/0! | BO31: =SUMIF('DESP A'!$D$3:$D$129,"Vendas",'DESP A'!$P$3:$P$129) -> 0 | BP31: =BO31/$BH$10 -> #DIV/0! | BQ31: =BM31+BO31 -> 0 | BR31: =BQ31/$BJ$10 -> #DIV/0! | BS31: =BQ31-BJ31 -> 0 | BT31: =SUMIF('DESP E'!$D$3:$D$146,"Vendas",'DESP E'!$Q$3:$Q$146) -> 0 | BU31: =BT31/$BF$10 -> #DIV/0! | BV31: =SUMIF('DESP A'!$D$3:$D$129,"Vendas",'DESP A'!$Q$3:$Q$129) -> 0 | BW31: =BV31/$BH$10 -> #DIV/0! | BX31: =BT31+BV31 -> 0 | BY31: =BX31/$BJ$10 -> #DIV/0! | BZ31: =BX31-BQ31 -> 0 | CA31: =SUMIF('DESP E'!$D$3:$D$146,"Vendas",'DESP E'!$R$3:$R$146) -> 0 | CB31: =CA31/$BF$10 -> #DIV/0! | CC31: =SUMIF('DESP A'!$D$3:$D$129,"Vendas",'DESP A'!$R$3:$R$129) -> 0 | CD31: =CC31/$BH$10 -> #DIV/0! | CE31: =CA31+CC31 -> 0 | CF31: =CE31/$BJ$10 -> #DIV/0! | CG31: =CE31-BX31 -> 0 | CH31: =SUM(C31,I31,P31,W31,AD31,AK31,AR31,AY31,BF31,BM31,BT31,CA31) -> 220002.18 | CI31: =CH31/$CH$10 -> 0.0021970043 | CJ31: =SUM(E31,K31,R31,Y31,AF31,AM31,AT31,BA31,BH31,BO31,BV31,CC31) -> 4289 | CK31: =CJ31/$CJ$10 -> 0.00030250366 | CL31: =SUM(G31,M31,T31,AA31,AH31,AO31,AV31,BC31,BJ31,BQ31,BX31,CE31) -> 224291.18 | CM31: =CL31/$CL$10 -> 0.0019620333
B32: Propaganda e Publicidade | C32: =SUMIF('MVTO E'!$C$3:$C$240,"Propaganda",'MVTO E'!$G$3:$G$240)+SUMIF('DESP E'!$D$3:$D$146,"Propaganda",'DESP E'!$G$3:$G$146) -> 135091.57 | D32: =C32/$C$10 -> 0.004106001 | E32: =SUMIF('MVTO A'!$C$3:$C$184,"Propaganda",'MVTO A'!$G$3:$G$184)+SUMIF('DESP A'!$D$3:$D$129,"Propaganda",'DESP A'!$G$3:$G$129) -> 300 | F32: =E32/$E$10 -> 7.5916161e-05 | G32: =C32+E32 -> 135391.57 | H32: =G32/$G$10 -> 0.003673854 | I32: =SUMIF('MVTO E'!$C$3:$C$240,"Propaganda",'MVTO E'!$H$3:$H$240)+SUMIF('DESP E'!$D$3:$D$146,"Propaganda",'DESP E'!$H$3:$H$146) -> 60316.48 | J32: =I32/$I$10 -> 0.0028410935 | K32: =SUMIF('MVTO A'!$C$3:$C$184,"Propaganda",'MVTO A'!$H$3:$H$184)+SUMIF('DESP A'!$D$3:$D$129,"Propaganda",'DESP A'!$H$3:$H$129) -> 0 | L32: =K32/$K$10 -> 0 | M32: =I32+K32 -> 60316.48 | N32: =M32/$M$10 -> 0.0024469897 | O32: =M32-G32 -> -75075.09 | P32: =SUMIF('MVTO E'!$C$3:$C$240,"Propaganda",'MVTO E'!$I$3:$I$240)+SUMIF('DESP E'!$D$3:$D$146,"Propaganda",'DESP E'!$I$3:$I$146) -> 187763.17 | Q32: =P32/$P$10 -> 0.0078867832 | R32: =SUMIF('MVTO A'!$C$3:$C$184,"Propaganda",'MVTO A'!$I$3:$I$184)+SUMIF('DESP A'!$D$3:$D$129,"Propaganda",'DESP A'!$I$3:$I$129) -> 825 | S32: =R32/$R$10 -> 0.00022599121 | T32: =P32+R32 -> 188588.17 | U32: =T32/$T$10 -> 0.0068682653 | V32: =T32-M32 -> 128271.69 | W32: =SUMIF('MVTO E'!$C$3:$C$240,"Propaganda",'MVTO E'!$J$3:$J$240)+SUMIF('DESP E'!$D$3:$D$146,"Propaganda",'DESP E'!$J$3:$J$146) -> 89648.6 | X32: =W32/$W$10 -> 0.004038408 | Y32: =SUMIF('MVTO A'!$C$3:$C$184,"Propaganda",'MVTO A'!$J$3:$J$184)+SUMIF('DESP A'!$D$3:$D$129,"Propaganda",'DESP A'!$J$3:$J$129) -> 0 | Z32: =Y32/$Y$10 -> 0 | AA32: =W32+Y32 -> 89648.6 | AB32: =AA32/$AA$10 -> 0.0035356265 | AC32: =AA32-T32 -> -98939.57 | AD32: =SUMIF('MVTO E'!$C$3:$C$240,"Propaganda",'MVTO E'!$K$3:$K$240)+SUMIF('DESP E'!$D$3:$D$146,"Propaganda",'DESP E'!$K$3:$K$146) -> 0 | AE32: =AD32/$AD$10 -> #DIV/0! | AF32: =SUMIF('MVTO A'!$C$3:$C$184,"Propaganda",'MVTO A'!$K$3:$K$184)+SUMIF('DESP A'!$D$3:$D$129,"Propaganda",'DESP A'!$K$3:$K$129) -> 0 | AG32: =AF32/$AF$10 -> #DIV/0! | AH32: =AD32+AF32 -> 0 | AI32: =AH32/$AH$10 -> #DIV/0! | AJ32: =AH32-AA32 -> -89648.6 | AK32: =SUMIF('MVTO E'!$C$3:$C$240,"Propaganda",'MVTO E'!$L$3:$L$240)+SUMIF('DESP E'!$D$3:$D$146,"Propaganda",'DESP E'!$L$3:$L$146) -> 0 | AL32: =AK32/$AK$10 -> #DIV/0! | AM32: =SUMIF('MVTO A'!$C$3:$C$184,"Propaganda",'MVTO A'!$L$3:$L$184)+SUMIF('DESP A'!$D$3:$D$129,"Propaganda",'DESP A'!$L$3:$L$129) -> 0 | AN32: =AM32/$AM$10 -> #DIV/0! | AO32: =AK32+AM32 -> 0 | AP32: =AO32/$AO$10 -> #DIV/0! | AQ32: =AO32-AH32 -> 0 | AR32: =SUMIF('MVTO E'!$C$3:$C$240,"Propaganda",'MVTO E'!$M$3:$M$240)+SUMIF('DESP E'!$D$3:$D$146,"Propaganda",'DESP E'!$M$3:$M$146) -> 0 | AS32: =AR32/$AR$10 -> #DIV/0! | AT32: =SUMIF('MVTO A'!$C$3:$C$184,"Propaganda",'MVTO A'!$M$3:$M$189)+SUMIF('DESP A'!$D$3:$D$129,"Propaganda",'DESP A'!$M$3:$M$129) -> 0 | AU32: =AT32/$AT$10 -> #DIV/0! | AV32: =AR32+AT32 -> 0 | AW32: =AV32/$AV$10 -> #DIV/0! | AX32: =AV32-AO32 -> 0 | AY32: =SUMIF('MVTO E'!$C$3:$C$240,"Propaganda",'MVTO E'!$N$3:$N$240)+SUMIF('DESP E'!$D$3:$D$146,"Propaganda",'DESP E'!$N$3:$N$146) -> 0 | AZ32: =AY32/$AY$10 -> #DIV/0! | BA32: =SUMIF('MVTO A'!$C$3:$C$184,"Propaganda",'MVTO A'!$N$3:$N$189)+SUMIF('DESP A'!$D$3:$D$129,"Propaganda",'DESP A'!$N$3:$N$129) -> 0 | BB32: =BA32/$BA$10 -> #DIV/0! | BC32: =AY32+BA32 -> 0 | BD32: =BC32/$BC$10 -> #DIV/0! | BE32: =BC32-AV32 -> 0 | BF32: =SUMIF('MVTO E'!$C$3:$C$240,"Propaganda",'MVTO E'!$O$3:$O$240)+SUMIF('DESP E'!$D$3:$D$146,"Propaganda",'DESP E'!$O$3:$O$146) -> 0 | BG32: =BF32/$BF$10 -> #DIV/0! | BH32: =SUMIF('MVTO A'!$C$3:$C$184,"Propaganda",'MVTO A'!$O$3:$O$189)+SUMIF('DESP A'!$D$3:$D$129,"Propaganda",'DESP A'!$O$3:$O$129) -> 0 | BI32: =BH32/$BH$10 -> #DIV/0! | BJ32: =BF32+BH32 -> 0 | BK32: =BJ32/$BJ$10 -> #DIV/0! | BL32: =BJ32-BC32 -> 0 | BM32: =SUMIF('MVTO E'!$C$3:$C$240,"Propaganda",'MVTO E'!$P$3:$P$240)+SUMIF('DESP E'!$D$3:$D$146,"Propaganda",'DESP E'!$P$3:$P$146) -> 0 | BN32: =BM32/$BF$10 -> #DIV/0! | BO32: =SUMIF('MVTO A'!$C$3:$C$184,"Propaganda",'MVTO A'!$P$3:$P$189)+SUMIF('DESP A'!$D$3:$D$129,"Propaganda",'DESP A'!$P$3:$P$129) -> 0 | BP32: =BO32/$BH$10 -> #DIV/0! | BQ32: =BM32+BO32 -> 0 | BR32: =BQ32/$BJ$10 -> #DIV/0! | BS32: =BQ32-BJ32 -> 0 | BT32: =SUMIF('MVTO E'!$C$3:$C$240,"Propaganda",'MVTO E'!$Q$3:$Q$240)+SUMIF('DESP E'!$D$3:$D$146,"Propaganda",'DESP E'!$Q$3:$Q$146) -> 0 | BU32: =BT32/$BF$10 -> #DIV/0! | BV32: =SUMIF('MVTO A'!$C$3:$C$184,"Propaganda",'MVTO A'!$Q$3:$Q$189)+SUMIF('DESP A'!$D$3:$D$129,"Propaganda",'DESP A'!$Q$3:$Q$129) -> 0 | BW32: =BV32/$BH$10 -> #DIV/0! | BX32: =BT32+BV32 -> 0 | BY32: =BX32/$BJ$10 -> #DIV/0! | BZ32: =BX32-BQ32 -> 0 | CA32: =SUMIF('MVTO E'!$C$3:$C$240,"Propaganda",'MVTO E'!$R$3:$R$240)+SUMIF('DESP E'!$D$3:$D$146,"Propaganda",'DESP E'!$R$3:$R$146) -> 0 | CB32: =CA32/$BF$10 -> #DIV/0! | CC32: =SUMIF('MVTO A'!$C$3:$C$184,"Propaganda",'MVTO A'!$R$3:$R$189)+SUMIF('DESP A'!$D$3:$D$129,"Propaganda",'DESP A'!$R$3:$R$129) -> 0 | CD32: =CC32/$BH$10 -> #DIV/0! | CE32: =CA32+CC32 -> 0 | CF32: =CE32/$BJ$10 -> #DIV/0! | CG32: =CE32-BX32 -> 0 | CH32: =SUM(C32,I32,P32,W32,AD32,AK32,AR32,AY32,BF32,BM32,BT32,CA32) -> 472819.82 | CI32: =CH32/$CH$10 -> 0.0047217131 | CJ32: =SUM(E32,K32,R32,Y32,AF32,AM32,AT32,BA32,BH32,BO32,BV32,CC32) -> 1125 | CK32: =CJ32/$CJ$10 -> 7.934638e-05 | CL32: =SUM(G32,M32,T32,AA32,AH32,AO32,AV32,BC32,BJ32,BQ32,BX32,CE32) -> 473944.82 | CM32: =CL32/$CL$10 -> 0.0041459299
B33: Logística | C33: =SUMIF('DESP E'!$D$3:$D$146,"Logística",'DESP E'!$G$3:$G$146) -> 93430.43 | D33: =C33/$C$10 -> 0.0028397437 | E33: =SUMIF('DESP A'!$D$3:$D$129,"Logística",'DESP A'!$G$3:$G$129) -> 0 | F33: =E33/$E$10 -> 0 | G33: =C33+E33 -> 93430.43 | H33: =G33/$G$10 -> 0.0025352373 | I33: =SUMIF('DESP E'!$D$3:$D$146,"Logística",'DESP E'!$H$3:$H$146) -> 45835.32 | J33: =I33/$I$10 -> 0.0021589859 | K33: =SUMIF('DESP A'!$D$3:$D$129,"Logística",'DESP A'!$H$3:$H$129) -> 0 | L33: =K33/$K$10 -> 0 | M33: =I33+K33 -> 45835.32 | N33: =M33/$M$10 -> 0.001859501 | O33: =M33-G33 -> -47595.11 | P33: =SUMIF('DESP E'!$D$3:$D$146,"Logística",'DESP E'!$I$3:$I$146) -> 78304.06 | Q33: =P33/$P$10 -> 0.003289075 | R33: =SUMIF('DESP A'!$D$3:$D$129,"Logística",'DESP A'!$I$3:$I$129) -> 0 | S33: =R33/$R$10 -> 0 | T33: =P33+R33 -> 78304.06 | U33: =T33/$T$10 -> 0.0028517857 | V33: =T33-M33 -> 32468.74 | W33: =SUMIF('DESP E'!$D$3:$D$146,"Logística",'DESP E'!$J$3:$J$146) -> 72558.07 | X33: =W33/$W$10 -> 0.0032685294 | Y33: =SUMIF('DESP A'!$D$3:$D$129,"Logística",'DESP A'!$J$3:$J$129) -> 0 | Z33: =Y33/$Y$10 -> 0 | AA33: =W33+Y33 -> 72558.07 | AB33: =AA33/$AA$10 -> 0.0028615978 | AC33: =AA33-T33 -> -5745.99 | AD33: =SUMIF('DESP E'!$D$3:$D$146,"Logística",'DESP E'!$K$3:$K$146) -> 0 | AE33: =AD33/$AD$10 -> #DIV/0! | AF33: =SUMIF('DESP A'!$D$3:$D$129,"Logística",'DESP A'!$K$3:$K$129) -> 0 | AG33: =AF33/$AF$10 -> #DIV/0! | AH33: =AD33+AF33 -> 0 | AI33: =AH33/$AH$10 -> #DIV/0! | AJ33: =AH33-AA33 -> -72558.07 | AK33: =SUMIF('DESP E'!$D$3:$D$146,"Logística",'DESP E'!$L$3:$L$146) -> 0 | AL33: =AK33/$AK$10 -> #DIV/0! | AM33: =SUMIF('DESP A'!$D$3:$D$129,"Logística",'DESP A'!$L$3:$L$129) -> 0 | AN33: =AM33/$AM$10 -> #DIV/0! | AO33: =AK33+AM33 -> 0 | AP33: =AO33/$AO$10 -> #DIV/0! | AQ33: =AO33-AH33 -> 0 | AR33: =SUMIF('DESP E'!$D$3:$D$146,"Logística",'DESP E'!$M$3:$M$146) -> 0 | AS33: =AR33/$AR$10 -> #DIV/0! | AT33: =SUMIF('DESP A'!$D$3:$D$129,"Logística",'DESP A'!$M$3:$M$129) -> 0 | AU33: =AT33/$AT$10 -> #DIV/0! | AV33: =AR33+AT33 -> 0 | AW33: =AV33/$AV$10 -> #DIV/0! | AX33: =AV33-AO33 -> 0 | AY33: =SUMIF('DESP E'!$D$3:$D$146,"Logística",'DESP E'!$N$3:$N$146) -> 0 | AZ33: =AY33/$AY$10 -> #DIV/0! | BA33: =SUMIF('DESP A'!$D$3:$D$129,"Logística",'DESP A'!$N$3:$N$129) -> 0 | BB33: =BA33/$BA$10 -> #DIV/0! | BC33: =AY33+BA33 -> 0 | BD33: =BC33/$BC$10 -> #DIV/0! | BE33: =BC33-AV33 -> 0 | BF33: =SUMIF('DESP E'!$D$3:$D$146,"Logística",'DESP E'!$O$3:$O$146) -> 0 | BG33: =BF33/$BF$10 -> #DIV/0! | BH33: =SUMIF('DESP A'!$D$3:$D$129,"Logística",'DESP A'!$O$3:$O$129) -> 0 | BI33: =BH33/$BH$10 -> #DIV/0! | BJ33: =BF33+BH33 -> 0 | BK33: =BJ33/$BJ$10 -> #DIV/0! | BL33: =BJ33-BC33 -> 0 | BM33: =SUMIF('DESP E'!$D$3:$D$146,"Logística",'DESP E'!$P$3:$P$146) -> 0 | BN33: =BM33/$BF$10 -> #DIV/0! | BO33: =SUMIF('DESP A'!$D$3:$D$129,"Logística",'DESP A'!$P$3:$P$129) -> 0 | BP33: =BO33/$BH$10 -> #DIV/0! | BQ33: =BM33+BO33 -> 0 | BR33: =BQ33/$BJ$10 -> #DIV/0! | BS33: =BQ33-BJ33 -> 0 | BT33: =SUMIF('DESP E'!$D$3:$D$146,"Logística",'DESP E'!$Q$3:$Q$146) -> 0 | BU33: =BT33/$BF$10 -> #DIV/0! | BV33: =SUMIF('DESP A'!$D$3:$D$129,"Logística",'DESP A'!$Q$3:$Q$129) -> 0 | BW33: =BV33/$BH$10 -> #DIV/0! | BX33: =BT33+BV33 -> 0 | BY33: =BX33/$BJ$10 -> #DIV/0! | BZ33: =BX33-BQ33 -> 0 | CA33: =SUMIF('DESP E'!$D$3:$D$146,"Logística",'DESP E'!$R$3:$R$146) -> 0 | CB33: =CA33/$BF$10 -> #DIV/0! | CC33: =SUMIF('DESP A'!$D$3:$D$129,"Logística",'DESP A'!$R$3:$R$129) -> 0 | CD33: =CC33/$BH$10 -> #DIV/0! | CE33: =CA33+CC33 -> 0 | CF33: =CE33/$BJ$10 -> #DIV/0! | CG33: =CE33-BX33 -> 0 | CH33: =SUM(C33,I33,P33,W33,AD33,AK33,AR33,AY33,BF33,BM33,BT33,CA33) -> 290127.88 | CI33: =CH33/$CH$10 -> 0.0028972995 | CJ33: =SUM(E33,K33,R33,Y33,AF33,AM33,AT33,BA33,BH33,BO33,BV33,CC33) -> 0 | CK33: =CJ33/$CJ$10 -> 0 | CL33: =SUM(G33,M33,T33,AA33,AH33,AO33,AV33,BC33,BJ33,BQ33,BX33,CE33) -> 290127.88 | CM33: =CL33/$CL$10 -> 0.0025379534
B34: Viagens | C34: =SUMIF('DESP E'!$D$3:$D$146,"Viagens",'DESP E'!$G$3:$G$146) -> 340 | D34: =C34/$C$10 -> 1.033403e-05 | E34: =SUMIF('DESP A'!$D$3:$D$129,"Viagens",'DESP A'!$G$3:$G$129) -> 0 | F34: =E34/$E$10 -> 0 | G34: =C34+E34 -> 340 | H34: =G34/$G$10 -> 9.2259095e-06 | I34: =SUMIF('DESP E'!$D$3:$D$146,"Viagens",'DESP E'!$H$3:$H$146) -> 1729.6 | J34: =I34/$I$10 -> 8.1469531e-05 | K34: =SUMIF('DESP A'!$D$3:$D$129,"Viagens",'DESP A'!$H$3:$H$129) -> 0 | L34: =K34/$K$10 -> 0 | M34: =I34+K34 -> 1729.6 | N34: =M34/$M$10 -> 7.0168442e-05 | O34: =M34-G34 -> 1389.6 | P34: =SUMIF('DESP E'!$D$3:$D$146,"Viagens",'DESP E'!$I$3:$I$146) -> 11158.62 | Q34: =P34/$P$10 -> 0.00046870543 | R34: =SUMIF('DESP A'!$D$3:$D$129,"Viagens",'DESP A'!$I$3:$I$129) -> 0 | S34: =R34/$R$10 -> 0 | T34: =P34+R34 -> 11158.62 | U34: =T34/$T$10 -> 0.00040639008 | V34: =T34-M34 -> 9429.02 | W34: =SUMIF('DESP E'!$D$3:$D$146,"Viagens",'DESP E'!$J$3:$J$146) -> 5932.07 | X34: =W34/$W$10 -> 0.00026722245 | Y34: =SUMIF('DESP A'!$D$3:$D$129,"Viagens",'DESP A'!$J$3:$J$129) -> 0 | Z34: =Y34/$Y$10 -> 0 | AA34: =W34+Y34 -> 5932.07 | AB34: =AA34/$AA$10 -> 0.00023395328 | AC34: =AA34-T34 -> -5226.55 | AD34: =SUMIF('DESP E'!$D$3:$D$146,"Viagens",'DESP E'!$K$3:$K$146) -> 0 | AE34: =AD34/$AD$10 -> #DIV/0! | AF34: =SUMIF('DESP A'!$D$3:$D$129,"Viagens",'DESP A'!$K$3:$K$129) -> 0 | AG34: =AF34/$AF$10 -> #DIV/0! | AH34: =AD34+AF34 -> 0 | AI34: =AH34/$AH$10 -> #DIV/0! | AJ34: =AH34-AA34 -> -5932.07 | AK34: =SUMIF('DESP E'!$D$3:$D$146,"Viagens",'DESP E'!$L$3:$L$146) -> 0 | AL34: =AK34/$AK$10 -> #DIV/0! | AM34: =SUMIF('DESP A'!$D$3:$D$129,"Viagens",'DESP A'!$L$3:$L$129) -> 0 | AN34: =AM34/$AM$10 -> #DIV/0! | AO34: =AK34+AM34 -> 0 | AP34: =AO34/$AO$10 -> #DIV/0! | AQ34: =AO34-AH34 -> 0 | AR34: =SUMIF('DESP E'!$D$3:$D$146,"Viagens",'DESP E'!$M$3:$M$146) -> 0 | AS34: =AR34/$AR$10 -> #DIV/0! | AT34: =SUMIF('DESP A'!$D$3:$D$129,"Viagens",'DESP A'!$M$3:$M$129) -> 0 | AU34: =AT34/$AT$10 -> #DIV/0! | AV34: =AR34+AT34 -> 0 | AW34: =AV34/$AV$10 -> #DIV/0! | AX34: =AV34-AO34 -> 0 | AY34: =SUMIF('DESP E'!$D$3:$D$146,"Viagens",'DESP E'!$N$3:$N$146) -> 0 | AZ34: =AY34/$AY$10 -> #DIV/0! | BA34: =SUMIF('DESP A'!$D$3:$D$129,"Viagens",'DESP A'!$N$3:$N$129) -> 0 | BB34: =BA34/$BA$10 -> #DIV/0! | BC34: =AY34+BA34 -> 0 | BD34: =BC34/$BC$10 -> #DIV/0! | BE34: =BC34-AV34 -> 0 | BF34: =SUMIF('DESP E'!$D$3:$D$146,"Viagens",'DESP E'!$O$3:$O$146) -> 0 | BG34: =BF34/$BF$10 -> #DIV/0! | BH34: =SUMIF('DESP A'!$D$3:$D$129,"Viagens",'DESP A'!$O$3:$O$129) -> 0 | BI34: =BH34/$BH$10 -> #DIV/0! | BJ34: =BF34+BH34 -> 0 | BK34: =BJ34/$BJ$10 -> #DIV/0! | BL34: =BJ34-BC34 -> 0 | BM34: =SUMIF('DESP E'!$D$3:$D$146,"Viagens",'DESP E'!$P$3:$P$146) -> 0 | BN34: =BM34/$BF$10 -> #DIV/0! | BO34: =SUMIF('DESP A'!$D$3:$D$129,"Viagens",'DESP A'!$P$3:$P$129) -> 0 | BP34: =BO34/$BH$10 -> #DIV/0! | BQ34: =BM34+BO34 -> 0 | BR34: =BQ34/$BJ$10 -> #DIV/0! | BS34: =BQ34-BJ34 -> 0 | BT34: =SUMIF('DESP E'!$D$3:$D$146,"Viagens",'DESP E'!$Q$3:$Q$146) -> 0 | BU34: =BT34/$BF$10 -> #DIV/0! | BV34: =SUMIF('DESP A'!$D$3:$D$129,"Viagens",'DESP A'!$Q$3:$Q$129) -> 0 | BW34: =BV34/$BH$10 -> #DIV/0! | BX34: =BT34+BV34 -> 0 | BY34: =BX34/$BJ$10 -> #DIV/0! | BZ34: =BX34-BQ34 -> 0 | CA34: =SUMIF('DESP E'!$D$3:$D$146,"Viagens",'DESP E'!$R$3:$R$146) -> 0 | CB34: =CA34/$BF$10 -> #DIV/0! | CC34: =SUMIF('DESP A'!$D$3:$D$129,"Viagens",'DESP A'!$R$3:$R$129) -> 0 | CD34: =CC34/$BH$10 -> #DIV/0! | CE34: =CA34+CC34 -> 0 | CF34: =CE34/$BJ$10 -> #DIV/0! | CG34: =CE34-BX34 -> 0 | CH34: =SUM(C34,I34,P34,W34,AD34,AK34,AR34,AY34,BF34,BM34,BT34,CA34) -> 19160.29 | CI34: =CH34/$CH$10 -> 0.0001913401 | CJ34: =SUM(E34,K34,R34,Y34,AF34,AM34,AT34,BA34,BH34,BO34,BV34,CC34) -> 0 | CK34: =CJ34/$CJ$10 -> 0 | CL34: =SUM(G34,M34,T34,AA34,AH34,AO34,AV34,BC34,BJ34,BQ34,BX34,CE34) -> 19160.29 | CM34: =CL34/$CL$10 -> 0.00016760858
B35: Comerciais | C35: =SUMIF('DESP E'!$D$3:$D$146,"Comerciais",'DESP E'!$G$3:$G$146) -> 28582.04 | D35: =C35/$C$10 -> 0.00086872841 | E35: =SUMIF('DESP A'!$D$3:$D$129,"Comerciais",'DESP A'!$G$3:$G$129) -> 0 | F35: =E35/$E$10 -> 0 | G35: =C35+E35 -> 28582.04 | H35: =G35/$G$10 -> 0.00077557445 | I35: =SUMIF('DESP E'!$D$3:$D$146,"Comerciais",'DESP E'!$H$3:$H$146) -> 3259.57 | J35: =I35/$I$10 -> 0.00015353587 | K35: =SUMIF('DESP A'!$D$3:$D$129,"Comerciais",'DESP A'!$H$3:$H$129) -> 0 | L35: =K35/$K$10 -> 0 | M35: =I35+K35 -> 3259.57 | N35: =M35/$M$10 -> 0.00013223806 | O35: =M35-G35 -> -25322.47 | P35: =SUMIF('DESP E'!$D$3:$D$146,"Comerciais",'DESP E'!$I$3:$I$146) -> 26042.79 | Q35: =P35/$P$10 -> 0.0010938984 | R35: =SUMIF('DESP A'!$D$3:$D$129,"Comerciais",'DESP A'!$I$3:$I$129) -> 0 | S35: =R35/$R$10 -> 0 | T35: =P35+R35 -> 26042.79 | U35: =T35/$T$10 -> 0.00094846241 | V35: =T35-M35 -> 22783.22 | W35: =SUMIF('DESP E'!$D$3:$D$146,"Comerciais",'DESP E'!$J$3:$J$146) -> 16319.84 | X35: =W35/$W$10 -> 0.00073516119 | Y35: =SUMIF('DESP A'!$D$3:$D$129,"Comerciais",'DESP A'!$J$3:$J$129) -> 0 | Z35: =Y35/$Y$10 -> 0 | AA35: =W35+Y35 -> 16319.84 | AB35: =AA35/$AA$10 -> 0.00064363368 | AC35: =AA35-T35 -> -9722.95 | AD35: =SUMIF('DESP E'!$D$3:$D$146,"Comerciais",'DESP E'!$K$3:$K$146) -> 0 | AE35: =AD35/$AD$10 -> #DIV/0! | AF35: =SUMIF('DESP A'!$D$3:$D$129,"Comerciais",'DESP A'!$K$3:$K$129) -> 0 | AG35: =AF35/$AF$10 -> #DIV/0! | AH35: =AD35+AF35 -> 0 | AI35: =AH35/$AH$10 -> #DIV/0! | AJ35: =AH35-AA35 -> -16319.84 | AK35: =SUMIF('DESP E'!$D$3:$D$146,"Comerciais",'DESP E'!$L$3:$L$146) -> 0 | AL35: =AK35/$AK$10 -> #DIV/0! | AM35: =SUMIF('DESP A'!$D$3:$D$129,"Comerciais",'DESP A'!$L$3:$L$129) -> 0 | AN35: =AM35/$AM$10 -> #DIV/0! | AO35: =AK35+AM35 -> 0 | AP35: =AO35/$AO$10 -> #DIV/0! | AQ35: =AO35-AH35 -> 0 | AR35: =SUMIF('DESP E'!$D$3:$D$146,"Comerciais",'DESP E'!$M$3:$M$146) -> 0 | AS35: =AR35/$AR$10 -> #DIV/0! | AT35: =SUMIF('DESP A'!$D$3:$D$129,"Comerciais",'DESP A'!$M$3:$M$129) -> 0 | AU35: =AT35/$AT$10 -> #DIV/0! | AV35: =AR35+AT35 -> 0 | AW35: =AV35/$AV$10 -> #DIV/0! | AX35: =AV35-AO35 -> 0 | AY35: =SUMIF('DESP E'!$D$3:$D$146,"Comerciais",'DESP E'!$N$3:$N$146) -> 0 | AZ35: =AY35/$AY$10 -> #DIV/0! | BA35: =SUMIF('DESP A'!$D$3:$D$129,"Comerciais",'DESP A'!$N$3:$N$129) -> 0 | BB35: =BA35/$BA$10 -> #DIV/0! | BC35: =AY35+BA35 -> 0 | BD35: =BC35/$BC$10 -> #DIV/0! | BE35: =BC35-AV35 -> 0 | BF35: =SUMIF('DESP E'!$D$3:$D$146,"Comerciais",'DESP E'!$O$3:$O$146) -> 0 | BG35: =BF35/$BF$10 -> #DIV/0! | BH35: =SUMIF('DESP A'!$D$3:$D$129,"Comerciais",'DESP A'!$O$3:$O$129) -> 0 | BI35: =BH35/$BH$10 -> #DIV/0! | BJ35: =BF35+BH35 -> 0 | BK35: =BJ35/$BJ$10 -> #DIV/0! | BL35: =BJ35-BC35 -> 0 | BM35: =SUMIF('DESP E'!$D$3:$D$146,"Comerciais",'DESP E'!$P$3:$P$146) -> 0 | BN35: =BM35/$BF$10 -> #DIV/0! | BO35: =SUMIF('DESP A'!$D$3:$D$129,"Comerciais",'DESP A'!$P$3:$P$129) -> 0 | BP35: =BO35/$BH$10 -> #DIV/0! | BQ35: =BM35+BO35 -> 0 | BR35: =BQ35/$BJ$10 -> #DIV/0! | BS35: =BQ35-BJ35 -> 0 | BT35: =SUMIF('DESP E'!$D$3:$D$146,"Comerciais",'DESP E'!$Q$3:$Q$146) -> 0 | BU35: =BT35/$BF$10 -> #DIV/0! | BV35: =SUMIF('DESP A'!$D$3:$D$129,"Comerciais",'DESP A'!$Q$3:$Q$129) -> 0 | BW35: =BV35/$BH$10 -> #DIV/0! | BX35: =BT35+BV35 -> 0 | BY35: =BX35/$BJ$10 -> #DIV/0! | BZ35: =BX35-BQ35 -> 0 | CA35: =SUMIF('DESP E'!$D$3:$D$146,"Comerciais",'DESP E'!$R$3:$R$146) -> 0 | CB35: =CA35/$BF$10 -> #DIV/0! | CC35: =SUMIF('DESP A'!$D$3:$D$129,"Comerciais",'DESP A'!$R$3:$R$129) -> 0 | CD35: =CC35/$BH$10 -> #DIV/0! | CE35: =CA35+CC35 -> 0 | CF35: =CE35/$BJ$10 -> #DIV/0! | CG35: =CE35-BX35 -> 0 | CH35: =SUM(C35,I35,P35,W35,AD35,AK35,AR35,AY35,BF35,BM35,BT35,CA35) -> 74204.24 | CI35: =CH35/$CH$10 -> 0.00074102463 | CJ35: =SUM(E35,K35,R35,Y35,AF35,AM35,AT35,BA35,BH35,BO35,BV35,CC35) -> 0 | CK35: =CJ35/$CJ$10 -> 0 | CL35: =SUM(G35,M35,T35,AA35,AH35,AO35,AV35,BC35,BJ35,BQ35,BX35,CE35) -> 74204.24 | CM35: =CL35/$CL$10 -> 0.00064911687
B36: Administrativas | C36: =SUMIF('DESP E'!$D$3:$D$146,"Administrativas",'DESP E'!$G$3:$G$146) -> 0 | D36: =C36/$C$10 -> 0 | E36: =SUMIF('DESP A'!$D$3:$D$129,"Administrativas",'DESP A'!$G$3:$G$129) -> 0 | F36: =E36/$E$10 -> 0 | G36: =C36+E36 -> 0 | H36: =G36/$G$10 -> 0 | I36: =SUMIF('DESP E'!$D$3:$D$146,"Administrativas",'DESP E'!$H$3:$H$146) -> 0 | J36: =I36/$I$10 -> 0 | K36: =SUMIF('DESP A'!$D$3:$D$129,"Administrativas",'DESP A'!$H$3:$H$129) -> 0 | L36: =K36/$K$10 -> 0 | M36: =I36+K36 -> 0 | N36: =M36/$M$10 -> 0 | O36: =M36-G36 -> 0 | P36: =SUMIF('DESP E'!$D$3:$D$146,"Administrativas",'DESP E'!$I$3:$I$146) -> 0 | Q36: =P36/$P$10 -> 0 | R36: =SUMIF('DESP A'!$D$3:$D$129,"Administrativas",'DESP A'!$I$3:$I$129) -> 0 | S36: =R36/$R$10 -> 0 | T36: =P36+R36 -> 0 | U36: =T36/$T$10 -> 0 | V36: =T36-M36 -> 0 | W36: =SUMIF('DESP E'!$D$3:$D$146,"Administrativas",'DESP E'!$J$3:$J$146) -> 0 | X36: =W36/$W$10 -> 0 | Y36: =SUMIF('DESP A'!$D$3:$D$129,"Administrativas",'DESP A'!$J$3:$J$129) -> 0 | Z36: =Y36/$Y$10 -> 0 | AA36: =W36+Y36 -> 0 | AB36: =AA36/$AA$10 -> 0 | AC36: =AA36-T36 -> 0 | AD36: =SUMIF('DESP E'!$D$3:$D$146,"Administrativas",'DESP E'!$K$3:$K$146) -> 0 | AE36: =AD36/$AD$10 -> #DIV/0! | AF36: =SUMIF('DESP A'!$D$3:$D$129,"Administrativas",'DESP A'!$K$3:$K$129) -> 0 | AG36: =AF36/$AF$10 -> #DIV/0! | AH36: =AD36+AF36 -> 0 | AI36: =AH36/$AH$10 -> #DIV/0! | AJ36: =AH36-AA36 -> 0 | AK36: =SUMIF('DESP E'!$D$3:$D$146,"Administrativas",'DESP E'!$L$3:$L$146) -> 0 | AL36: =AK36/$AK$10 -> #DIV/0! | AM36: =SUMIF('DESP A'!$D$3:$D$129,"Administrativas",'DESP A'!$L$3:$L$129) -> 0 | AN36: =AM36/$AM$10 -> #DIV/0! | AO36: =AK36+AM36 -> 0 | AP36: =AO36/$AO$10 -> #DIV/0! | AQ36: =AO36-AH36 -> 0 | AR36: =SUMIF('DESP E'!$D$3:$D$146,"Administrativas",'DESP E'!$M$3:$M$146) -> 0 | AS36: =AR36/$AR$10 -> #DIV/0! | AT36: =SUMIF('DESP A'!$D$3:$D$129,"Administrativas",'DESP A'!$M$3:$M$129) -> 0 | AU36: =AT36/$AT$10 -> #DIV/0! | AV36: =AR36+AT36 -> 0 | AW36: =AV36/$AV$10 -> #DIV/0! | AX36: =AV36-AO36 -> 0 | AY36: =SUMIF('DESP E'!$D$3:$D$146,"Administrativas",'DESP E'!$N$3:$N$146) -> 0 | AZ36: =AY36/$AY$10 -> #DIV/0! | BA36: =SUMIF('DESP A'!$D$3:$D$129,"Administrativas",'DESP A'!$N$3:$N$129) -> 0 | BB36: =BA36/$BA$10 -> #DIV/0! | BC36: =AY36+BA36 -> 0 | BD36: =BC36/$BC$10 -> #DIV/0! | BE36: =BC36-AV36 -> 0 | BF36: =SUMIF('DESP E'!$D$3:$D$146,"Administrativas",'DESP E'!$O$3:$O$146) -> 0 | BG36: =BF36/$BF$10 -> #DIV/0! | BH36: =SUMIF('DESP A'!$D$3:$D$129,"Administrativas",'DESP A'!$O$3:$O$129) -> 0 | BI36: =BH36/$BH$10 -> #DIV/0! | BJ36: =BF36+BH36 -> 0 | BK36: =BJ36/$BJ$10 -> #DIV/0! | BL36: =BJ36-BC36 -> 0 | BM36: =SUMIF('DESP E'!$D$3:$D$146,"Administrativas",'DESP E'!$P$3:$P$146) -> 0 | BN36: =BM36/$BF$10 -> #DIV/0! | BO36: =SUMIF('DESP A'!$D$3:$D$129,"Administrativas",'DESP A'!$P$3:$P$129) -> 0 | BP36: =BO36/$BH$10 -> #DIV/0! | BQ36: =BM36+BO36 -> 0 | BR36: =BQ36/$BJ$10 -> #DIV/0! | BS36: =BQ36-BJ36 -> 0 | BT36: =SUMIF('DESP E'!$D$3:$D$146,"Administrativas",'DESP E'!$Q$3:$Q$146) -> 0 | BU36: =BT36/$BF$10 -> #DIV/0! | BV36: =SUMIF('DESP A'!$D$3:$D$129,"Administrativas",'DESP A'!$Q$3:$Q$129) -> 0 | BW36: =BV36/$BH$10 -> #DIV/0! | BX36: =BT36+BV36 -> 0 | BY36: =BX36/$BJ$10 -> #DIV/0! | BZ36: =BX36-BQ36 -> 0 | CA36: =SUMIF('DESP E'!$D$3:$D$146,"Administrativas",'DESP E'!$R$3:$R$146) -> 0 | CB36: =CA36/$BF$10 -> #DIV/0! | CC36: =SUMIF('DESP A'!$D$3:$D$129,"Administrativas",'DESP A'!$R$3:$R$129) -> 0 | CD36: =CC36/$BH$10 -> #DIV/0! | CE36: =CA36+CC36 -> 0 | CF36: =CE36/$BJ$10 -> #DIV/0! | CG36: =CE36-BX36 -> 0 | CH36: =SUM(C36,I36,P36,W36,AD36,AK36,AR36,AY36,BF36,BM36,BT36,CA36) -> 0 | CI36: =CH36/$CH$10 -> 0 | CJ36: =SUM(E36,K36,R36,Y36,AF36,AM36,AT36,BA36,BH36,BO36,BV36,CC36) -> 0 | CK36: =CJ36/$CJ$10 -> 0 | CL36: =SUM(G36,M36,T36,AA36,AH36,AO36,AV36,BC36,BJ36,BQ36,BX36,CE36) -> 0 | CM36: =CL36/$CL$10 -> 0
B37: Indedutíveis | C37: =SUMIF('DESP E'!$D$3:$D$146,"Indedutíveis",'DESP E'!$G$3:$G$146) -> 0 | D37: =C37/$C$10 -> 0 | E37: =SUMIF('DESP A'!$D$3:$D$129,"Indedutíveis",'DESP A'!$G$3:$G$129) -> 0 | F37: =E37/$E$10 -> 0 | G37: =C37+E37 -> 0 | H37: =G37/$G$10 -> 0 | I37: =SUMIF('DESP E'!$D$3:$D$146,"Indedutíveis",'DESP E'!$H$3:$H$146) -> 157.39 | J37: =I37/$I$10 -> 7.4135577e-06 | K37: =SUMIF('DESP A'!$D$3:$D$129,"Indedutíveis",'DESP A'!$H$3:$H$129) -> 0 | L37: =K37/$K$10 -> 0 | M37: =I37+K37 -> 157.39 | N37: =M37/$M$10 -> 6.3851822e-06 | O37: =M37-G37 -> 157.39 | P37: =SUMIF('DESP E'!$D$3:$D$146,"Indedutíveis",'DESP E'!$I$3:$I$146) -> 0 | Q37: =P37/$P$10 -> 0 | R37: =SUMIF('DESP A'!$D$3:$D$129,"Indedutíveis",'DESP A'!$I$3:$I$129) -> 0 | S37: =R37/$R$10 -> 0 | T37: =P37+R37 -> 0 | U37: =T37/$T$10 -> 0 | V37: =T37-M37 -> -157.39 | W37: =SUMIF('DESP E'!$D$3:$D$146,"Indedutíveis",'DESP E'!$J$3:$J$146) -> 0 | X37: =W37/$W$10 -> 0 | Y37: =SUMIF('DESP A'!$D$3:$D$129,"Indedutíveis",'DESP A'!$J$3:$J$129) -> 0 | Z37: =Y37/$Y$10 -> 0 | AA37: =W37+Y37 -> 0 | AB37: =AA37/$AA$10 -> 0 | AC37: =AA37-T37 -> 0 | AD37: =SUMIF('DESP E'!$D$3:$D$146,"Indedutíveis",'DESP E'!$K$3:$K$146) -> 0 | AE37: =AD37/$AD$10 -> #DIV/0! | AF37: =SUMIF('DESP A'!$D$3:$D$129,"Indedutíveis",'DESP A'!$K$3:$K$129) -> 0 | AG37: =AF37/$AF$10 -> #DIV/0! | AH37: =AD37+AF37 -> 0 | AI37: =AH37/$AH$10 -> #DIV/0! | AJ37: =AH37-AA37 -> 0 | AK37: =SUMIF('DESP E'!$D$3:$D$146,"Indedutíveis",'DESP E'!$L$3:$L$146) -> 0 | AL37: =AK37/$AK$10 -> #DIV/0! | AM37: =SUMIF('DESP A'!$D$3:$D$129,"Indedutíveis",'DESP A'!$L$3:$L$129) -> 0 | AN37: =AM37/$AM$10 -> #DIV/0! | AO37: =AK37+AM37 -> 0 | AP37: =AO37/$AO$10 -> #DIV/0! | AQ37: =AO37-AH37 -> 0 | AR37: =SUMIF('DESP E'!$D$3:$D$146,"Indedutíveis",'DESP E'!$M$3:$M$146) -> 0 | AS37: =AR37/$AR$10 -> #DIV/0! | AT37: =SUMIF('DESP A'!$D$3:$D$129,"Indedutíveis",'DESP A'!$M$3:$M$129) -> 0 | AU37: =AT37/$AT$10 -> #DIV/0! | AV37: =AR37+AT37 -> 0 | AW37: =AV37/$AV$10 -> #DIV/0! | AX37: =AV37-AO37 -> 0 | AY37: =SUMIF('DESP E'!$D$3:$D$146,"Indedutíveis",'DESP E'!$N$3:$N$146) -> 0 | AZ37: =AY37/$AY$10 -> #DIV/0! | BA37: =SUMIF('DESP A'!$D$3:$D$129,"Indedutíveis",'DESP A'!$N$3:$N$129) -> 0 | BB37: =BA37/$BA$10 -> #DIV/0! | BC37: =AY37+BA37 -> 0 | BD37: =BC37/$BC$10 -> #DIV/0! | BE37: =BC37-AV37 -> 0 | BF37: =SUMIF('DESP E'!$D$3:$D$146,"Indedutíveis",'DESP E'!$O$3:$O$146) -> 0 | BG37: =BF37/$BF$10 -> #DIV/0! | BH37: =SUMIF('DESP A'!$D$3:$D$129,"Indedutíveis",'DESP A'!$O$3:$O$129) -> 0 | BI37: =BH37/$BH$10 -> #DIV/0! | BJ37: =BF37+BH37 -> 0 | BK37: =BJ37/$BJ$10 -> #DIV/0! | BL37: =BJ37-BC37 -> 0 | BM37: =SUMIF('DESP E'!$D$3:$D$146,"Indedutíveis",'DESP E'!$P$3:$P$146) -> 0 | BN37: =BM37/$BF$10 -> #DIV/0! | BO37: =SUMIF('DESP A'!$D$3:$D$129,"Indedutíveis",'DESP A'!$P$3:$P$129) -> 0 | BP37: =BO37/$BH$10 -> #DIV/0! | BQ37: =BM37+BO37 -> 0 | BR37: =BQ37/$BJ$10 -> #DIV/0! | BS37: =BQ37-BJ37 -> 0 | BT37: =SUMIF('DESP E'!$D$3:$D$146,"Indedutíveis",'DESP E'!$Q$3:$Q$146) -> 0 | BU37: =BT37/$BF$10 -> #DIV/0! | BV37: =SUMIF('DESP A'!$D$3:$D$129,"Indedutíveis",'DESP A'!$Q$3:$Q$129) -> 0 | BW37: =BV37/$BH$10 -> #DIV/0! | BX37: =BT37+BV37 -> 0 | BY37: =BX37/$BJ$10 -> #DIV/0! | BZ37: =BX37-BQ37 -> 0 | CA37: =SUMIF('DESP E'!$D$3:$D$146,"Indedutíveis",'DESP E'!$R$3:$R$146) -> 0 | CB37: =CA37/$BF$10 -> #DIV/0! | CC37: =SUMIF('DESP A'!$D$3:$D$129,"Indedutíveis",'DESP A'!$R$3:$R$129) -> 0 | CD37: =CC37/$BH$10 -> #DIV/0! | CE37: =CA37+CC37 -> 0 | CF37: =CE37/$BJ$10 -> #DIV/0! | CG37: =CE37-BX37 -> 0 | CH37: =SUM(C37,I37,P37,W37,AD37,AK37,AR37,AY37,BF37,BM37,BT37,CA37) -> 157.39 | CI37: =CH37/$CH$10 -> 1.5717413e-06 | CJ37: =SUM(E37,K37,R37,Y37,AF37,AM37,AT37,BA37,BH37,BO37,BV37,CC37) -> 0 | CK37: =CJ37/$CJ$10 -> 0 | CL37: =SUM(G37,M37,T37,AA37,AH37,AO37,AV37,BC37,BJ37,BQ37,BX37,CE37) -> 157.39 | CM37: =CL37/$CL$10 -> 1.3768014e-06
B38: Aluguel | C38: =SUMIF('MVTO E'!$C$3:$C$240,"Desp_Aluguel",'MVTO E'!$G$3:$G$240) -> 529678.4 | D38: =C38/$C$10 -> 0.016099154 | E38: =SUMIF('MVTO A'!$C$3:$C$184,"Desp_Aluguel",'MVTO A'!$G$3:$G$184) -> 0 | F38: =E38/$E$10 -> 0 | G38: =C38+E38 -> 529678.4 | H38: =G38/$G$10 -> 0.014372838 | I38: =SUMIF('MVTO E'!$C$3:$C$240,"Desp_Aluguel",'MVTO E'!$H$3:$H$240) -> 565211.64 | J38: =I38/$I$10 -> 0.026623223 | K38: =SUMIF('MVTO A'!$C$3:$C$184,"Desp_Aluguel",'MVTO A'!$H$3:$H$184) -> 0 | L38: =K38/$K$10 -> 0 | M38: =I38+K38 -> 565211.64 | N38: =M38/$M$10 -> 0.022930169 | O38: =M38-G38 -> 35533.24 | P38: =SUMIF('MVTO E'!$C$3:$C$240,"Desp_Aluguel",'MVTO E'!$I$3:$I$240) -> 520594.89 | Q38: =P38/$P$10 -> 0.02186701 | R38: =SUMIF('MVTO A'!$C$3:$C$184,"Desp_Aluguel",'MVTO A'!$I$3:$I$184) -> 0 | S38: =R38/$R$10 -> 0 | T38: =P38+R38 -> 520594.89 | U38: =T38/$T$10 -> 0.018959746 | V38: =T38-M38 -> -44616.75 | W38: =SUMIF('MVTO E'!$C$3:$C$240,"Desp_Aluguel",'MVTO E'!$J$3:$J$240) -> 542205.63 | X38: =W38/$W$10 -> 0.024424782 | Y38: =SUMIF('MVTO A'!$C$3:$C$184,"Desp_Aluguel",'MVTO A'!$J$3:$J$184) -> 0 | Z38: =Y38/$Y$10 -> 0 | AA38: =W38+Y38 -> 542205.63 | AB38: =AA38/$AA$10 -> 0.021383899 | AC38: =AA38-T38 -> 21610.74 | AD38: =SUMIF('MVTO E'!$C$3:$C$240,"Desp_Aluguel",'MVTO E'!$K$3:$K$240) -> 0 | AE38: =AD38/$AD$10 -> #DIV/0! | AF38: =SUMIF('MVTO A'!$C$3:$C$184,"Desp_Aluguel",'MVTO A'!$K$3:$K$184) -> 0 | AG38: =AF38/$AF$10 -> #DIV/0! | AH38: =AD38+AF38 -> 0 | AI38: =AH38/$AH$10 -> #DIV/0! | AJ38: =AH38-AA38 -> -542205.63 | AK38: =SUMIF('MVTO E'!$C$3:$C$240,"Desp_Aluguel",'MVTO E'!$L$3:$L$240) -> 0 | AL38: =AK38/$AK$10 -> #DIV/0! | AM38: =SUMIF('MVTO A'!$C$3:$C$184,"Desp_Aluguel",'MVTO A'!$L$3:$L$184) -> 0 | AN38: =AM38/$AM$10 -> #DIV/0! | AO38: =AK38+AM38 -> 0 | AP38: =AO38/$AO$10 -> #DIV/0! | AQ38: =AO38-AH38 -> 0 | AR38: =SUMIF('MVTO E'!$C$3:$C$240,"Desp_Aluguel",'MVTO E'!$M$3:$M$240) -> 0 | AS38: =AR38/$AR$10 -> #DIV/0! | AT38: =SUMIF('MVTO A'!$C$3:$C$184,"Desp_Aluguel",'MVTO A'!$M$3:$M$189) -> 0 | AU38: =AT38/$AT$10 -> #DIV/0! | AV38: =AR38+AT38 -> 0 | AW38: =AV38/$AV$10 -> #DIV/0! | AX38: =AV38-AO38 -> 0 | AY38: =SUMIF('MVTO E'!$C$3:$C$240,"Desp_Aluguel",'MVTO E'!$N$3:$N$240) -> 0 | AZ38: =AY38/$AY$10 -> #DIV/0! | BA38: =SUMIF('MVTO A'!$C$3:$C$184,"Desp_Aluguel",'MVTO A'!$N$3:$N$189) -> 0 | BB38: =BA38/$BA$10 -> #DIV/0! | BC38: =AY38+BA38 -> 0 | BD38: =BC38/$BC$10 -> #DIV/0! | BE38: =BC38-AV38 -> 0 | BF38: =SUMIF('MVTO E'!$C$3:$C$240,"Desp_Aluguel",'MVTO E'!$O$3:$O$240) -> 0 | BG38: =BF38/$BF$10 -> #DIV/0! | BH38: =SUMIF('MVTO A'!$C$3:$C$184,"Desp_Aluguel",'MVTO A'!$O$3:$O$189) -> 0 | BI38: =BH38/$BH$10 -> #DIV/0! | BJ38: =BF38+BH38 -> 0 | BK38: =BJ38/$BJ$10 -> #DIV/0! | BL38: =BJ38-BC38 -> 0 | BM38: =SUMIF('MVTO E'!$C$3:$C$240,"Desp_Aluguel",'MVTO E'!$P$3:$P$240) -> 0 | BN38: =BM38/$BF$10 -> #DIV/0! | BO38: =SUMIF('MVTO A'!$C$3:$C$184,"Desp_Aluguel",'MVTO A'!$P$3:$P$189) -> 0 | BP38: =BO38/$BH$10 -> #DIV/0! | BQ38: =BM38+BO38 -> 0 | BR38: =BQ38/$BJ$10 -> #DIV/0! | BS38: =BQ38-BJ38 -> 0 | BT38: =SUMIF('MVTO E'!$C$3:$C$240,"Desp_Aluguel",'MVTO E'!$Q$3:$Q$240) -> 0 | BU38: =BT38/$BF$10 -> #DIV/0! | BV38: =SUMIF('MVTO A'!$C$3:$C$184,"Desp_Aluguel",'MVTO A'!$Q$3:$Q$189) -> 0 | BW38: =BV38/$BH$10 -> #DIV/0! | BX38: =BT38+BV38 -> 0 | BY38: =BX38/$BJ$10 -> #DIV/0! | BZ38: =BX38-BQ38 -> 0 | CA38: =SUMIF('MVTO E'!$C$3:$C$240,"Desp_Aluguel",'MVTO E'!$R$3:$R$240) -> 0 | CB38: =CA38/$BF$10 -> #DIV/0! | CC38: =SUMIF('MVTO A'!$C$3:$C$184,"Desp_Aluguel",'MVTO A'!$R$3:$R$189) -> 0 | CD38: =CC38/$BH$10 -> #DIV/0! | CE38: =CA38+CC38 -> 0 | CF38: =CE38/$BJ$10 -> #DIV/0! | CG38: =CE38-BX38 -> 0 | CH38: =SUM(C38,I38,P38,W38,AD38,AK38,AR38,AY38,BF38,BM38,BT38,CA38) -> 2157690.6 | CI38: =CH38/$CH$10 -> 0.021547311 | CJ38: =SUM(E38,K38,R38,Y38,AF38,AM38,AT38,BA38,BH38,BO38,BV38,CC38) -> 0 | CK38: =CJ38/$CJ$10 -> 0 | CL38: =SUM(G38,M38,T38,AA38,AH38,AO38,AV38,BC38,BJ38,BQ38,BX38,CE38) -> 2157690.6 | CM38: =CL38/$CL$10 -> 0.018874842
B39: Seguros | C39: =SUMIF('MVTO E'!$C$3:$C$240,"Desp_Seguros",'MVTO E'!$G$3:$G$240) -> 43169.59 | D39: =C39/$C$10 -> 0.0013121054 | E39: =SUMIF('MVTO A'!$C$3:$C$184,"Desp_Seguros",'MVTO A'!$G$3:$G$184) -> 0 | F39: =E39/$E$10 -> 0 | G39: =C39+E39 -> 43169.59 | H39: =G39/$G$10 -> 0.001171408 | I39: =SUMIF('MVTO E'!$C$3:$C$240,"Desp_Seguros",'MVTO E'!$H$3:$H$240) -> 9843.09 | J39: =I39/$I$10 -> 0.0004636401 | K39: =SUMIF('MVTO A'!$C$3:$C$184,"Desp_Seguros",'MVTO A'!$H$3:$H$184) -> 0 | L39: =K39/$K$10 -> 0 | M39: =I39+K39 -> 9843.09 | N39: =M39/$M$10 -> 0.00039932603 | O39: =M39-G39 -> -33326.5 | P39: =SUMIF('MVTO E'!$C$3:$C$240,"Desp_Seguros",'MVTO E'!$I$3:$I$240) -> 10158.49 | Q39: =P39/$P$10 -> 0.00042669608 | R39: =SUMIF('MVTO A'!$C$3:$C$184,"Desp_Seguros",'MVTO A'!$I$3:$I$184) -> 0 | S39: =R39/$R$10 -> 0 | T39: =P39+R39 -> 10158.49 | U39: =T39/$T$10 -> 0.00036996596 | V39: =T39-M39 -> 315.4 | W39: =SUMIF('MVTO E'!$C$3:$C$240,"Desp_Seguros",'MVTO E'!$J$3:$J$240) -> 10036.08 | X39: =W39/$W$10 -> 0.00045209613 | Y39: =SUMIF('MVTO A'!$C$3:$C$184,"Desp_Seguros",'MVTO A'!$J$3:$J$184) -> 0 | Z39: =Y39/$Y$10 -> 0 | AA39: =W39+Y39 -> 10036.08 | AB39: =AA39/$AA$10 -> 0.0003958102 | AC39: =AA39-T39 -> -122.41 | AD39: =SUMIF('MVTO E'!$C$3:$C$240,"Desp_Seguros",'MVTO E'!$K$3:$K$240) -> 0 | AE39: =AD39/$AD$10 -> #DIV/0! | AF39: =SUMIF('MVTO A'!$C$3:$C$184,"Desp_Seguros",'MVTO A'!$K$3:$K$184) -> 0 | AG39: =AF39/$AF$10 -> #DIV/0! | AH39: =AD39+AF39 -> 0 | AI39: =AH39/$AH$10 -> #DIV/0! | AJ39: =AH39-AA39 -> -10036.08 | AK39: =SUMIF('MVTO E'!$C$3:$C$240,"Desp_Seguros",'MVTO E'!$L$3:$L$240) -> 0 | AL39: =AK39/$AK$10 -> #DIV/0! | AM39: =SUMIF('MVTO A'!$C$3:$C$184,"Desp_Seguros",'MVTO A'!$L$3:$L$184) -> 0 | AN39: =AM39/$AM$10 -> #DIV/0! | AO39: =AK39+AM39 -> 0 | AP39: =AO39/$AO$10 -> #DIV/0! | AQ39: =AO39-AH39 -> 0 | AR39: =SUMIF('MVTO E'!$C$3:$C$240,"Desp_Seguros",'MVTO E'!$M$3:$M$240) -> 0 | AS39: =AR39/$AR$10 -> #DIV/0! | AT39: =SUMIF('MVTO A'!$C$3:$C$184,"Desp_Seguros",'MVTO A'!$M$3:$M$189) -> 0 | AU39: =AT39/$AT$10 -> #DIV/0! | AV39: =AR39+AT39 -> 0 | AW39: =AV39/$AV$10 -> #DIV/0! | AX39: =AV39-AO39 -> 0 | AY39: =SUMIF('MVTO E'!$C$3:$C$240,"Desp_Seguros",'MVTO E'!$N$3:$N$240) -> 0 | AZ39: =AY39/$AY$10 -> #DIV/0! | BA39: =SUMIF('MVTO A'!$C$3:$C$184,"Desp_Seguros",'MVTO A'!$N$3:$N$189) -> 0 | BB39: =BA39/$BA$10 -> #DIV/0! | BC39: =AY39+BA39 -> 0 | BD39: =BC39/$BC$10 -> #DIV/0! | BE39: =BC39-AV39 -> 0 | BF39: =SUMIF('MVTO E'!$C$3:$C$240,"Desp_Seguros",'MVTO E'!$O$3:$O$240) -> 0 | BG39: =BF39/$BF$10 -> #DIV/0! | BH39: =SUMIF('MVTO A'!$C$3:$C$184,"Desp_Seguros",'MVTO A'!$O$3:$O$189) -> 0 | BI39: =BH39/$BH$10 -> #DIV/0! | BJ39: =BF39+BH39 -> 0 | BK39: =BJ39/$BJ$10 -> #DIV/0! | BL39: =BJ39-BC39 -> 0 | BM39: =SUMIF('MVTO E'!$C$3:$C$240,"Desp_Seguros",'MVTO E'!$P$3:$P$240) -> 0 | BN39: =BM39/$BF$10 -> #DIV/0! | BO39: =SUMIF('MVTO A'!$C$3:$C$184,"Desp_Seguros",'MVTO A'!$P$3:$P$189) -> 0 | BP39: =BO39/$BH$10 -> #DIV/0! | BQ39: =BM39+BO39 -> 0 | BR39: =BQ39/$BJ$10 -> #DIV/0! | BS39: =BQ39-BJ39 -> 0 | BT39: =SUMIF('MVTO E'!$C$3:$C$240,"Desp_Seguros",'MVTO E'!$Q$3:$Q$240) -> 0 | BU39: =BT39/$BF$10 -> #DIV/0! | BV39: =SUMIF('MVTO A'!$C$3:$C$184,"Desp_Seguros",'MVTO A'!$Q$3:$Q$189) -> 0 | BW39: =BV39/$BH$10 -> #DIV/0! | BX39: =BT39+BV39 -> 0 | BY39: =BX39/$BJ$10 -> #DIV/0! | BZ39: =BX39-BQ39 -> 0 | CA39: =SUMIF('MVTO E'!$C$3:$C$240,"Desp_Seguros",'MVTO E'!$R$3:$R$240) -> 0 | CB39: =CA39/$BF$10 -> #DIV/0! | CC39: =SUMIF('MVTO A'!$C$3:$C$184,"Desp_Seguros",'MVTO A'!$R$3:$R$189) -> 0 | CD39: =CC39/$BH$10 -> #DIV/0! | CE39: =CA39+CC39 -> 0 | CF39: =CE39/$BJ$10 -> #DIV/0! | CG39: =CE39-BX39 -> 0 | CH39: =SUM(C39,I39,P39,W39,AD39,AK39,AR39,AY39,BF39,BM39,BT39,CA39) -> 73207.25 | CI39: =CH39/$CH$10 -> 0.00073106841 | CJ39: =SUM(E39,K39,R39,Y39,AF39,AM39,AT39,BA39,BH39,BO39,BV39,CC39) -> 0 | CK39: =CJ39/$CJ$10 -> 0 | CL39: =SUM(G39,M39,T39,AA39,AH39,AO39,AV39,BC39,BJ39,BQ39,BX39,CE39) -> 73207.25 | CM39: =CL39/$CL$10 -> 0.00064039549
B40: Taxas DE Cartões de Crédito | C40: =SUMIF('MVTO E'!$C$3:$C$240,"Desp_TAXA",'MVTO E'!$G$3:$G$240) -> 376072.94 | D40: =C40/$C$10 -> 0.011430438 | E40: =SUMIF('MVTO A'!$C$3:$C$184,"Desp_TAXA",'MVTO A'!$G$3:$G$184) -> 38904.17 | F40: =E40/$E$10 -> 0.0098448508 | G40: =C40+E40 -> 414977.11 | H40: =G40/$G$10 -> 0.011260415 | I40: =SUMIF('MVTO E'!$C$3:$C$240,"Desp_TAXA",'MVTO E'!$H$3:$H$240) -> 221272.42 | J40: =I40/$I$10 -> 0.010422618 | K40: =SUMIF('MVTO A'!$C$3:$C$184,"Desp_TAXA",'MVTO A'!$H$3:$H$184) -> 33807.7 | L40: =K40/$K$10 -> 0.0098875055 | M40: =I40+K40 -> 255080.12 | N40: =M40/$M$10 -> 0.01034839 | O40: =M40-G40 -> -159896.99 | P40: =SUMIF('MVTO E'!$C$3:$C$240,"Desp_TAXA",'MVTO E'!$I$3:$I$240) -> 270488.1 | Q40: =P40/$P$10 -> 0.011361552 | R40: =SUMIF('MVTO A'!$C$3:$C$184,"Desp_TAXA",'MVTO A'!$I$3:$I$184) -> 35244.94 | S40: =R40/$R$10 -> 0.0096546018 | T40: =P40+R40 -> 305733.04 | U40: =T40/$T$10 -> 0.011134609 | V40: =T40-M40 -> 50652.92 | W40: =SUMIF('MVTO E'!$C$3:$C$240,"Desp_TAXA",'MVTO E'!$J$3:$J$240) -> 220776.2 | X40: =W40/$W$10 -> 0.0099453239 | Y40: =SUMIF('MVTO A'!$C$3:$C$184,"Desp_TAXA",'MVTO A'!$J$3:$J$184) -> 32385.26 | Z40: =Y40/$Y$10 -> 0.010258909 | AA40: =W40+Y40 -> 253161.46 | AB40: =AA40/$AA$10 -> 0.0099843652 | AC40: =AA40-T40 -> -52571.58 | AD40: =SUMIF('MVTO E'!$C$3:$C$240,"Desp_TAXA",'MVTO E'!$K$3:$K$240) -> 0 | AE40: =AD40/$AD$10 -> #DIV/0! | AF40: =SUMIF('MVTO A'!$C$3:$C$184,"Desp_TAXA",'MVTO A'!$K$3:$K$184) -> 0 | AG40: =AF40/$AF$10 -> #DIV/0! | AH40: =AD40+AF40 -> 0 | AI40: =AH40/$AH$10 -> #DIV/0! | AJ40: =AH40-AA40 -> -253161.46 | AK40: =SUMIF('MVTO E'!$C$3:$C$240,"Desp_TAXA",'MVTO E'!$L$3:$L$240) -> 0 | AL40: =AK40/$AK$10 -> #DIV/0! | AM40: =SUMIF('MVTO A'!$C$3:$C$184,"Desp_TAXA",'MVTO A'!$L$3:$L$184) -> 0 | AN40: =AM40/$AM$10 -> #DIV/0! | AO40: =AK40+AM40 -> 0 | AP40: =AO40/$AO$10 -> #DIV/0! | AQ40: =AO40-AH40 -> 0 | AR40: =SUMIF('MVTO E'!$C$3:$C$240,"Desp_TAXA",'MVTO E'!$M$3:$M$240) -> 0 | AS40: =AR40/$AR$10 -> #DIV/0! | AT40: =SUMIF('MVTO A'!$C$3:$C$184,"Desp_TAXA",'MVTO A'!$M$3:$M$189) -> 0 | AU40: =AT40/$AT$10 -> #DIV/0! | AV40: =AR40+AT40 -> 0 | AW40: =AV40/$AV$10 -> #DIV/0! | AX40: =AV40-AO40 -> 0 | AY40: =SUMIF('MVTO E'!$C$3:$C$240,"Desp_TAXA",'MVTO E'!$N$3:$N$240) -> 0 | AZ40: =AY40/$AY$10 -> #DIV/0! | BA40: =SUMIF('MVTO A'!$C$3:$C$184,"Desp_TAXA",'MVTO A'!$N$3:$N$189) -> 0 | BB40: =BA40/$BA$10 -> #DIV/0! | BC40: =AY40+BA40 -> 0 | BD40: =BC40/$BC$10 -> #DIV/0! | BE40: =BC40-AV40 -> 0 | BF40: =SUMIF('MVTO E'!$C$3:$C$240,"Desp_TAXA",'MVTO E'!$O$3:$O$240) -> 0 | BG40: =BF40/$BF$10 -> #DIV/0! | BH40: =SUMIF('MVTO A'!$C$3:$C$184,"Desp_TAXA",'MVTO A'!$O$3:$O$189) -> 0 | BI40: =BH40/$BH$10 -> #DIV/0! | BJ40: =BF40+BH40 -> 0 | BK40: =BJ40/$BJ$10 -> #DIV/0! | BL40: =BJ40-BC40 -> 0 | BM40: =SUMIF('MVTO E'!$C$3:$C$240,"Desp_TAXA",'MVTO E'!$P$3:$P$240) -> 0 | BN40: =BM40/$BF$10 -> #DIV/0! | BO40: =SUMIF('MVTO A'!$C$3:$C$184,"Desp_TAXA",'MVTO A'!$P$3:$P$189) -> 0 | BP40: =BO40/$BH$10 -> #DIV/0! | BQ40: =BM40+BO40 -> 0 | BR40: =BQ40/$BJ$10 -> #DIV/0! | BS40: =BQ40-BJ40 -> 0 | BT40: =SUMIF('MVTO E'!$C$3:$C$240,"Desp_TAXA",'MVTO E'!$Q$3:$Q$240) -> 0 | BU40: =BT40/$BF$10 -> #DIV/0! | BV40: =SUMIF('MVTO A'!$C$3:$C$184,"Desp_TAXA",'MVTO A'!$Q$3:$Q$189) -> 0 | BW40: =BV40/$BH$10 -> #DIV/0! | BX40: =BT40+BV40 -> 0 | BY40: =BX40/$BJ$10 -> #DIV/0! | BZ40: =BX40-BQ40 -> 0 | CA40: =SUMIF('MVTO E'!$C$3:$C$240,"Desp_TAXA",'MVTO E'!$R$3:$R$240) -> 0 | CB40: =CA40/$BF$10 -> #DIV/0! | CC40: =SUMIF('MVTO A'!$C$3:$C$184,"Desp_TAXA",'MVTO A'!$R$3:$R$189) -> 0 | CD40: =CC40/$BH$10 -> #DIV/0! | CE40: =CA40+CC40 -> 0 | CF40: =CE40/$BJ$10 -> #DIV/0! | CG40: =CE40-BX40 -> 0 | CH40: =SUM(C40,I40,P40,W40,AD40,AK40,AR40,AY40,BF40,BM40,BT40,CA40) -> 1088609.7 | CI40: =CH40/$CH$10 -> 0.010871166 | CJ40: =SUM(E40,K40,R40,Y40,AF40,AM40,AT40,BA40,BH40,BO40,BV40,CC40) -> 140342.07 | CK40: =CJ40/$CJ$10 -> 0.0098983424 | CL40: =SUM(G40,M40,T40,AA40,AH40,AO40,AV40,BC40,BJ40,BQ40,BX40,CE40) -> 1228951.7 | CM40: =CL40/$CL$10 -> 0.010750508
B41: ( - ) Recuperação de Despesas | C41: =SUMIF('MVTO E'!$C$3:$C$240,"Rec_Desp",'MVTO E'!$G$3:$G$240)*-1 -> -21680.8 | D41: =C41/$C$10 -> -0.0006589707 | E41: =SUMIF('MVTO A'!$C$3:$C$184,"Rec_Desp",'MVTO A'!$G$3:$G$184)*-1 -> -75 | F41: =E41/$E$10 -> -1.897904e-05 | G41: =C41+E41 -> -21755.8 | H41: =G41/$G$10 -> -0.00059034424 | I41: =SUMIF('MVTO E'!$C$3:$C$240,"Rec_Desp",'MVTO E'!$H$3:$H$240)*-1 -> -326.07 | J41: =I41/$I$10 -> -1.5358909e-05 | K41: =SUMIF('MVTO A'!$C$3:$C$184,"Rec_Desp",'MVTO A'!$H$3:$H$184)*-1 -> 0 | L41: =K41/$K$10 -> 0 | M41: =I41+K41 -> -326.07 | N41: =M41/$M$10 -> -1.322839e-05 | O41: =M41-G41 -> 21429.73 | P41: =SUMIF('MVTO E'!$C$3:$C$240,"Rec_Desp",'MVTO E'!$I$3:$I$240)*-1 -> -3662.74 | Q41: =P41/$P$10 -> -0.00015384932 | R41: =SUMIF('MVTO A'!$C$3:$C$184,"Rec_Desp",'MVTO A'!$I$3:$I$184)*-1 -> 0 | S41: =R41/$R$10 -> 0 | T41: =P41+R41 -> -3662.74 | U41: =T41/$T$10 -> -0.00013339474 | V41: =T41-M41 -> -3336.67 | W41: =SUMIF('MVTO E'!$C$3:$C$240,"Rec_Desp",'MVTO E'!$J$3:$J$240)*-1 -> -1147.84 | X41: =W41/$W$10 -> -5.1706844e-05 | Y41: =SUMIF('MVTO A'!$C$3:$C$184,"Rec_Desp",'MVTO A'!$J$3:$J$184)*-1 -> -468.02 | Z41: =Y41/$Y$10 -> -0.00014825802 | AA41: =W41+Y41 -> -1615.86 | AB41: =AA41/$AA$10 -> -6.3727458e-05 | AC41: =AA41-T41 -> 2046.88 | AD41: =SUMIF('MVTO E'!$C$3:$C$240,"Rec_Desp",'MVTO E'!$K$3:$K$240)*-1 -> 0 | AE41: =AD41/$AD$10 -> #DIV/0! | AF41: =SUMIF('MVTO A'!$C$3:$C$184,"Rec_Desp",'MVTO A'!$K$3:$K$184)*-1 -> 0 | AG41: =AF41/$AF$10 -> #DIV/0! | AH41: =AD41+AF41 -> 0 | AI41: =AH41/$AH$10 -> #DIV/0! | AJ41: =AH41-AA41 -> 1615.86 | AK41: =SUMIF('MVTO E'!$C$3:$C$240,"Rec_Desp",'MVTO E'!$L$3:$L$240)*-1 -> 0 | AL41: =AK41/$AK$10 -> #DIV/0! | AM41: =SUMIF('MVTO A'!$C$3:$C$184,"Rec_Desp",'MVTO A'!$L$3:$L$184)*-1 -> 0 | AN41: =AM41/$AM$10 -> #DIV/0! | AO41: =AK41+AM41 -> 0 | AP41: =AO41/$AO$10 -> #DIV/0! | AQ41: =AO41-AH41 -> 0 | AR41: =SUMIF('MVTO E'!$C$3:$C$240,"Rec_Desp",'MVTO E'!$M$3:$M$240)*-1 -> 0 | AS41: =AR41/$AR$10 -> #DIV/0! | AT41: =SUMIF('MVTO A'!$C$3:$C$184,"Rec_Desp",'MVTO A'!$M$3:$M$189)*-1 -> 0 | AU41: =AT41/$AT$10 -> #DIV/0! | AV41: =AR41+AT41 -> 0 | AW41: =AV41/$AV$10 -> #DIV/0! | AX41: =AV41-AO41 -> 0 | AY41: =SUMIF('MVTO E'!$C$3:$C$240,"Rec_Desp",'MVTO E'!$N$3:$N$240)*-1 -> 0 | AZ41: =AY41/$AY$10 -> #DIV/0! | BA41: =SUMIF('MVTO A'!$C$3:$C$184,"Rec_Desp",'MVTO A'!$N$3:$N$189)*-1 -> 0 | BB41: =BA41/$BA$10 -> #DIV/0! | BC41: =AY41+BA41 -> 0 | BD41: =BC41/$BC$10 -> #DIV/0! | BE41: =BC41-AV41 -> 0 | BF41: =SUMIF('MVTO E'!$C$3:$C$240,"Rec_Desp",'MVTO E'!$O$3:$O$240)*-1 -> 0 | BG41: =BF41/$BF$10 -> #DIV/0! | BH41: =SUMIF('MVTO A'!$C$3:$C$184,"Rec_Desp",'MVTO A'!$O$3:$O$189)*-1 -> 0 | BI41: =BH41/$BH$10 -> #DIV/0! | BJ41: =BF41+BH41 -> 0 | BK41: =BJ41/$BJ$10 -> #DIV/0! | BL41: =BJ41-BC41 -> 0 | BM41: =SUMIF('MVTO E'!$C$3:$C$240,"Rec_Desp",'MVTO E'!$P$3:$P$240)*-1 -> 0 | BN41: =BM41/$BF$10 -> #DIV/0! | BO41: =SUMIF('MVTO A'!$C$3:$C$184,"Rec_Desp",'MVTO A'!$P$3:$P$189)*-1 -> 0 | BP41: =BO41/$BH$10 -> #DIV/0! | BQ41: =BM41+BO41 -> 0 | BR41: =BQ41/$BJ$10 -> #DIV/0! | BS41: =BQ41-BJ41 -> 0 | BT41: =SUMIF('MVTO E'!$C$3:$C$240,"Rec_Desp",'MVTO E'!$Q$3:$Q$240)*-1 -> 0 | BU41: =BT41/$BF$10 -> #DIV/0! | BV41: =SUMIF('MVTO A'!$C$3:$C$184,"Rec_Desp",'MVTO A'!$Q$3:$Q$189)*-1 -> 0 | BW41: =BV41/$BH$10 -> #DIV/0! | BX41: =BT41+BV41 -> 0 | BY41: =BX41/$BJ$10 -> #DIV/0! | BZ41: =BX41-BQ41 -> 0 | CA41: =SUMIF('MVTO E'!$C$3:$C$240,"Rec_Desp",'MVTO E'!$R$3:$R$240)*-1 -> 0 | CB41: =CA41/$BF$10 -> #DIV/0! | CC41: =SUMIF('MVTO A'!$C$3:$C$184,"Rec_Desp",'MVTO A'!$R$3:$R$189)*-1 -> 0 | CD41: =CC41/$BH$10 -> #DIV/0! | CE41: =CA41+CC41 -> 0 | CF41: =CE41/$BJ$10 -> #DIV/0! | CG41: =CE41-BX41 -> 0 | CH41: =SUM(C41,I41,P41,W41,AD41,AK41,AR41,AY41,BF41,BM41,BT41,CA41) -> -26817.45 | CI41: =CH41/$CH$10 -> -0.00026780668 | CJ41: =SUM(E41,K41,R41,Y41,AF41,AM41,AT41,BA41,BH41,BO41,BV41,CC41) -> -543.02 | CK41: =CJ41/$CJ$10 -> -3.8299263e-05 | CL41: =SUM(G41,M41,T41,AA41,AH41,AO41,AV41,BC41,BJ41,BQ41,BX41,CE41) -> -27360.47 | CM41: =CL41/$CL$10 -> -0.00023934134
B42: Lucro das operações | C42: =IFERROR(C19-C20,"") -> 1039053.6 | D42: =D19-D20 -> 0.031581209 | E42: =IFERROR(E19-E20,"") -> 2283069.4 | F42: =F19-F20 -> -0.19675736 | G42: =C42+E42 -> 3322123 | H42: =H19-H20 -> 0.12310862 | I42: =IFERROR(I19-I20,"") -> 2814936.5 | J42: =J19-J20 -> 0.13259225 | K42: =IFERROR(K19-K20,"") -> 1820238 | L42: =L19-L20 -> 0.5323525 | M42: =I42+K42 -> 4635174.6 | N42: =N19-N20 -> 0.1880452 | O42: =M42-G42 -> 1313051.6 | P42: =IFERROR(P19-P20,"") -> 1850730.2 | Q42: =Q19-Q20 -> 0.077737863 | R42: =IFERROR(R19-R20,"") -> 2242779.6 | S42: =S19-S20 -> -0.21019266 | T42: =P42+R42 -> 4093509.8 | U42: =U19-U20 -> 0.088929161 | V42: =T42-M42 -> -541664.75 | W42: =IFERROR(W19-W20,"") -> 988657.57 | X42: =X19-X20 -> 0.04453614 | Y42: =IFERROR(Y19-Y20,"") -> 1830523.5 | Z42: =Z19-Z20 -> -0.22536491 | AA42: =W42+Y42 -> 2819181.1 | AB42: =AB19-AB20 -> 0.033694408 | AC42: =AA42-T42 -> -1274328.7 | AD42: =IFERROR(AD19-AD20,"") -> 0 | AE42: =AE19-AE20 -> #DIV/0! | AF42: =IFERROR(AF19-AF20,"") -> 0 | AG42: =AG19-AG20 -> #DIV/0! | AH42: =AD42+AF42 -> 0 | AI42: =AI19-AI20 -> #DIV/0! | AJ42: =AH42-AA42 -> -2819181.1 | AK42: =IFERROR(AK19-AK20,"") -> 0 | AL42: =AL19-AL20 -> #DIV/0! | AM42: =IFERROR(AM19-AM20,"") -> 0 | AN42: =AN19-AN20 -> #DIV/0! | AO42: =AK42+AM42 -> 0 | AP42: =AP19-AP20 -> #DIV/0! | AQ42: =AO42-AH42 -> 0 | AR42: =IFERROR(AR19-AR20,"") -> 0 | AS42: =AS19-AS20 -> #DIV/0! | AT42: =IFERROR(AT19-AT20,"") -> 0 | AU42: =AU19-AU20 -> #DIV/0! | AV42: =AR42+AT42 -> 0 | AW42: =AW19-AW20 -> #DIV/0! | AX42: =AV42-AO42 -> 0 | AY42: =IFERROR(AY19-AY20,"") -> 0 | AZ42: =AZ19-AZ20 -> #DIV/0! | BA42: =IFERROR(BA19-BA20,"") -> 0 | BB42: =BB19-BB20 -> #DIV/0! | BC42: =AY42+BA42 -> 0 | BD42: =BD19-BD20 -> #DIV/0! | BE42: =BC42-AV42 -> 0 | BF42: =IFERROR(BF19-BF20,"") -> 0 | BG42: =BG19-BG20 -> #DIV/0! | BH42: =IFERROR(BH19-BH20,"") -> 0 | BI42: =BI19-BI20 -> #DIV/0! | BJ42: =BF42+BH42 -> 0 | BK42: =BK19-BK20 -> #DIV/0! | BL42: =BJ42-BC42 -> 0 | BM42: =IFERROR(BM19-BM20,"") -> 0 | BN42: =BN19-BN20 -> #DIV/0! | BO42: =IFERROR(BO19-BO20,"") -> 0 | BP42: =BP19-BP20 -> #DIV/0! | BQ42: =BM42+BO42 -> 0 | BR42: =BR19-BR20 -> #DIV/0! | BS42: =BQ42-BJ42 -> 0 | BT42: =IFERROR(BT19-BT20,"") -> 0 | BU42: =BU19-BU20 -> #DIV/0! | BV42: =IFERROR(BV19-BV20,"") -> 0 | BW42: =BW19-BW20 -> #DIV/0! | BX42: =BT42+BV42 -> 0 | BY42: =BY19-BY20 -> #DIV/0! | BZ42: =BX42-BQ42 -> 0 | CA42: =IFERROR(CA19-CA20,"") -> 0 | CB42: =CB19-CB20 -> #DIV/0! | CC42: =IFERROR(CC19-CC20,"") -> 0 | CD42: =CD19-CD20 -> #DIV/0! | CE42: =CA42+CC42 -> 0 | CF42: =CF19-CF20 -> #DIV/0! | CG42: =CE42-BX42 -> 0 | CH42: =IFERROR(CH19-CH20,"") -> 6693377.9 | CI42: =CH42/$CH$10 -> 0.066841974 | CJ42: =IFERROR(CJ19-CJ20,"") -> 8176610.6 | CK42: =CJ42/$CJ$10 -> 0.57669728 | CL42: =IFERROR(CL19-CL20,"") -> 14869988 | CM42: =CL42/$CL$10 -> 0.13007828
B43: Resultado Financeiro | C43: =IFERROR(C45-C44,"") -> -103329.57 | D43: =C43/$C$10 -> -0.0031406202 | E43: =IFERROR(E45-E44,"") -> -335.62 | F43: =E43/$E$10 -> -8.492994e-05 | G43: =C43+E43 -> -103665.19 | H43: =G43/$G$10 -> -0.0028129578 | I43: =IFERROR(I45-I44,"") -> -13822.53 | J43: =I43/$I$10 -> -0.00065108408 | K43: =IFERROR(K45-K44,"") -> -398.85 | L43: =K43/$K$10 -> -0.00011664892 | M43: =I43+K43 -> -14221.38 | N43: =M43/$M$10 -> -0.00057694963 | O43: =M43-G43 -> 89443.81 | P43: =IFERROR(P45-P44,"") -> -332694.98 | Q43: =P43/$P$10 -> -0.013974483 | R43: =IFERROR(R45-R44,"") -> -381.98 | S43: =R43/$R$10 -> -0.0001046353 | T43: =P43+R43 -> -333076.96 | U43: =T43/$T$10 -> -0.012130458 | V43: =T43-M43 -> -318855.58 | W43: =IFERROR(W45-W44,"") -> -1801685.7 | X43: =W43/$W$10 -> -0.081160687 | Y43: =IFERROR(Y45-Y44,"") -> -162973.84 | Z43: =Y43/$Y$10 -> -0.05162638 | AA43: =W43+Y43 -> -1964659.6 | AB43: =AA43/$AA$10 -> -0.077483668 | AC43: =AA43-T43 -> -1631582.6 | AD43: =IFERROR(AD45-AD44,"") -> 0 | AE43: =AD43/$AD$10 -> #DIV/0! | AF43: =IFERROR(AF45-AF44,"") -> 0 | AG43: =AF43/$AF$10 -> #DIV/0! | AH43: =AD43+AF43 -> 0 | AI43: =AH43/$AH$10 -> #DIV/0! | AJ43: =AH43-AA43 -> 1964659.6 | AK43: =IFERROR(AK45-AK44,"") -> 0 | AL43: =AK43/$AK$10 -> #DIV/0! | AM43: =IFERROR(AM45-AM44,"") -> 0 | AN43: =AM43/$AM$10 -> #DIV/0! | AO43: =AK43+AM43 -> 0 | AP43: =AO43/$AO$10 -> #DIV/0! | AQ43: =AO43-AH43 -> 0 | AR43: =IFERROR(AR45-AR44,"") -> 0 | AS43: =AR43/$AR$10 -> #DIV/0! | AT43: =IFERROR(AT45-AT44,"") -> 0 | AU43: =AT43/$AT$10 -> #DIV/0! | AV43: =AR43+AT43 -> 0 | AW43: =AV43/$AV$10 -> #DIV/0! | AX43: =AV43-AO43 -> 0 | AY43: =IFERROR(AY45-AY44,"") -> 0 | AZ43: =AY43/$AY$10 -> #DIV/0! | BA43: =IFERROR(BA45-BA44,"") -> 0 | BB43: =BA43/$BA$10 -> #DIV/0! | BC43: =AY43+BA43 -> 0 | BD43: =BC43/$BC$10 -> #DIV/0! | BE43: =BC43-AV43 -> 0 | BF43: =IFERROR(BF45-BF44,"") -> 0 | BG43: =BF43/$BF$10 -> #DIV/0! | BH43: =IFERROR(BH45-BH44,"") -> 0 | BI43: =BH43/$BH$10 -> #DIV/0! | BJ43: =BF43+BH43 -> 0 | BK43: =BJ43/$BJ$10 -> #DIV/0! | BL43: =BJ43-BC43 -> 0 | BM43: =IFERROR(BM45-BM44,"") -> 0 | BN43: =BM43/$BF$10 -> #DIV/0! | BO43: =IFERROR(BO45-BO44,"") -> 0 | BP43: =BO43/$BH$10 -> #DIV/0! | BQ43: =BM43+BO43 -> 0 | BR43: =BQ43/$BJ$10 -> #DIV/0! | BS43: =BQ43-BJ43 -> 0 | BT43: =IFERROR(BT45-BT44,"") -> 0 | BU43: =BT43/$BF$10 -> #DIV/0! | BV43: =IFERROR(BV45-BV44,"") -> 0 | BW43: =BV43/$BH$10 -> #DIV/0! | BX43: =BT43+BV43 -> 0 | BY43: =BX43/$BJ$10 -> #DIV/0! | BZ43: =BX43-BQ43 -> 0 | CA43: =IFERROR(CA45-CA44,"") -> 0 | CB43: =CA43/$BF$10 -> #DIV/0! | CC43: =IFERROR(CC45-CC44,"") -> 0 | CD43: =CC43/$BH$10 -> #DIV/0! | CE43: =CA43+CC43 -> 0 | CF43: =CE43/$BJ$10 -> #DIV/0! | CG43: =CE43-BX43 -> 0 | CH43: =IFERROR(CH44-CH45,"") -> 2251532.8 | CI43: =CH43/$CH$4 -> 0.37480958 | CJ43: =IFERROR(CJ44-CJ45,"") -> 164090.29 | CK43: =CJ43/$CJ$4 -> #DIV/0! | CL43: =IFERROR(CL44-CL45,"") -> 2415623.1 | CM43: =CL43/$CL$4 -> 0.40212547
B44: Receita Financeira | C44: =SUMIF('MVTO E'!$C$3:$C$240,"EFIN",'MVTO E'!$G$3:$G$240) -> 115863.02 | D44: =C44/$C$10 -> 0.0035215645 | E44: =SUMIF('MVTO A'!$C$3:$C$184,"EFIN",'MVTO A'!$G$3:$G$184) -> 1321.59 | F44: =E44/$E$10 -> 0.00033443346 | G44: =C44+E44 -> 117184.61 | H44: =G44/$G$10 -> 0.0031798077 | I44: =SUMIF('MVTO E'!$C$3:$C$240,"EFIN",'MVTO E'!$H$3:$H$240) -> 27467.08 | J44: =I44/$I$10 -> 0.0012937848 | K44: =SUMIF('MVTO A'!$C$3:$C$184,"EFIN",'MVTO A'!$H$3:$H$184) -> 1322.8 | L44: =K44/$K$10 -> 0.00038687022 | M44: =I44+K44 -> 28789.88 | N44: =M44/$M$10 -> 0.0011679816 | O44: =M44-G44 -> -88394.73 | P44: =SUMIF('MVTO E'!$C$3:$C$240,"EFIN",'MVTO E'!$I$3:$I$240) -> 344331.37 | Q44: =P44/$P$10 -> 0.014463256 | R44: =SUMIF('MVTO A'!$C$3:$C$184,"EFIN",'MVTO A'!$I$3:$I$184) -> 1436.84 | S44: =R44/$R$10 -> 0.00039359176 | T44: =P44+R44 -> 345768.21 | U44: =T44/$T$10 -> 0.012592666 | V44: =T44-M44 -> 316978.33 | W44: =SUMIF('MVTO E'!$C$3:$C$240,"EFIN",'MVTO E'!$J$3:$J$240) -> 1810170.1 | X44: =W44/$W$10 -> 0.081542885 | Y44: =SUMIF('MVTO A'!$C$3:$C$184,"EFIN",'MVTO A'!$J$3:$J$184) -> 164002.78 | Z44: =Y44/$Y$10 -> 0.051952324 | AA44: =W44+Y44 -> 1974172.9 | AB44: =AA44/$AA$10 -> 0.077858862 | AC44: =AA44-T44 -> 1628404.7 | AD44: =SUMIF('MVTO E'!$C$3:$C$240,"EFIN",'MVTO E'!$K$3:$K$240) -> 0 | AE44: =AD44/$AD$10 -> #DIV/0! | AF44: =SUMIF('MVTO A'!$C$3:$C$184,"EFIN",'MVTO A'!$K$3:$K$184) -> 0 | AG44: =AF44/$AF$10 -> #DIV/0! | AH44: =AD44+AF44 -> 0 | AI44: =AH44/$AH$10 -> #DIV/0! | AJ44: =AH44-AA44 -> -1974172.9 | AK44: =SUMIF('MVTO E'!$C$3:$C$240,"EFIN",'MVTO E'!$L$3:$L$240) -> 0 | AL44: =AK44/$AK$10 -> #DIV/0! | AM44: =SUMIF('MVTO A'!$C$3:$C$184,"EFIN",'MVTO A'!$L$3:$L$184) -> 0 | AN44: =AM44/$AM$10 -> #DIV/0! | AO44: =AK44+AM44 -> 0 | AP44: =AO44/$AO$10 -> #DIV/0! | AQ44: =AO44-AH44 -> 0 | AR44: =SUMIF('MVTO E'!$C$3:$C$240,"EFIN",'MVTO E'!$M$3:$M$240) -> 0 | AS44: =AR44/$AR$10 -> #DIV/0! | AT44: =SUMIF('MVTO A'!$C$3:$C$184,"EFIN",'MVTO A'!$M$3:$M$189) -> 0 | AU44: =AT44/$AT$10 -> #DIV/0! | AV44: =AR44+AT44 -> 0 | AW44: =AV44/$AV$10 -> #DIV/0! | AX44: =AV44-AO44 -> 0 | AY44: =SUMIF('MVTO E'!$C$3:$C$240,"EFIN",'MVTO E'!$N$3:$N$240) -> 0 | AZ44: =AY44/$AY$10 -> #DIV/0! | BA44: =SUMIF('MVTO A'!$C$3:$C$184,"EFIN",'MVTO A'!$N$3:$N$189) -> 0 | BB44: =BA44/$BA$10 -> #DIV/0! | BC44: =AY44+BA44 -> 0 | BD44: =BC44/$BC$10 -> #DIV/0! | BE44: =BC44-AV44 -> 0 | BF44: =SUMIF('MVTO E'!$C$3:$C$240,"EFIN",'MVTO E'!$O$3:$O$240) -> 0 | BG44: =BF44/$BF$10 -> #DIV/0! | BH44: =SUMIF('MVTO A'!$C$3:$C$184,"EFIN",'MVTO A'!$O$3:$O$189) -> 0 | BI44: =BH44/$BH$10 -> #DIV/0! | BJ44: =BF44+BH44 -> 0 | BK44: =BJ44/$BJ$10 -> #DIV/0! | BL44: =BJ44-BC44 -> 0 | BM44: =SUMIF('MVTO E'!$C$3:$C$240,"EFIN",'MVTO E'!$P$3:$P$240) -> 0 | BN44: =BM44/$BF$10 -> #DIV/0! | BO44: =SUMIF('MVTO A'!$C$3:$C$184,"EFIN",'MVTO A'!$P$3:$P$189) -> 0 | BP44: =BO44/$BH$10 -> #DIV/0! | BQ44: =BM44+BO44 -> 0 | BR44: =BQ44/$BJ$10 -> #DIV/0! | BS44: =BQ44-BJ44 -> 0 | BT44: =SUMIF('MVTO E'!$C$3:$C$240,"EFIN",'MVTO E'!$Q$3:$Q$240) -> 0 | BU44: =BT44/$BF$10 -> #DIV/0! | BV44: =SUMIF('MVTO A'!$C$3:$C$184,"EFIN",'MVTO A'!$Q$3:$Q$189) -> 0 | BW44: =BV44/$BH$10 -> #DIV/0! | BX44: =BT44+BV44 -> 0 | BY44: =BX44/$BJ$10 -> #DIV/0! | BZ44: =BX44-BQ44 -> 0 | CA44: =SUMIF('MVTO E'!$C$3:$C$240,"EFIN",'MVTO E'!$R$3:$R$240) -> 0 | CB44: =CA44/$BF$10 -> #DIV/0! | CC44: =SUMIF('MVTO A'!$C$3:$C$184,"EFIN",'MVTO A'!$R$3:$R$189) -> 0 | CD44: =CC44/$BH$10 -> #DIV/0! | CE44: =CA44+CC44 -> 0 | CF44: =CE44/$BJ$10 -> #DIV/0! | CG44: =CE44-BX44 -> 0 | CH44: =SUM(C44,I44,P44,W44,AD44,AK44,AR44,AY44,BF44,BM44,BT44,CA44) -> 2297831.6 | CI44: =CH44/$CH$4 -> 0.38251688 | CJ44: =SUM(E44,K44,R44,Y44,AF44,AM44,AT44,BA44,BH44,BO44,BV44,CC44) -> 168084.01 | CK44: =CJ44/$CJ$4 -> #DIV/0! | CL44: =SUM(G44,M44,T44,AA44,AH44,AO44,AV44,BC44,BJ44,BQ44,BX44,CE44) -> 2465915.6 | CM44: =CL44/$CL$4 -> 0.41049759
B45: Despesas Financeiras | C45: =SUMIF('MVTO E'!$C$3:$C$240,"SFIN",'MVTO E'!$G$3:$G$240)+SUMIF('DESP E'!$D$3:$D$146,"SFIN",'DESP E'!$G$3:$G$146) -> 12533.45 | D45: =C45/$C$10 -> 0.00038094426 | E45: =SUMIF('MVTO A'!$C$3:$C$184,"SFIN",'MVTO A'!$G$3:$G$184)+SUMIF('DESP A'!$D$3:$D$129,"SFIN",'DESP A'!$G$3:$G$129) -> 985.97 | F45: =E45/$E$10 -> 0.00024950352 | G45: =C45+E45 -> 13519.42 | H45: =G45/$G$10 -> 0.00036684984 | I45: =SUMIF('MVTO E'!$C$3:$C$240,"SFIN",'MVTO E'!$H$3:$H$240)+SUMIF('DESP E'!$D$3:$D$146,"SFIN",'DESP E'!$H$3:$H$146) -> 13644.55 | J45: =I45/$I$10 -> 0.00064270067 | K45: =SUMIF('MVTO A'!$C$3:$C$184,"SFIN",'MVTO A'!$H$3:$H$184)+SUMIF('DESP A'!$D$3:$D$129,"SFIN",'DESP A'!$H$3:$H$129) -> 923.95 | L45: =K45/$K$10 -> 0.0002702213 | M45: =I45+K45 -> 14568.5 | N45: =M45/$M$10 -> 0.000591032 | O45: =M45-G45 -> 1049.08 | P45: =SUMIF('MVTO E'!$C$3:$C$240,"SFIN",'MVTO E'!$I$3:$I$240)+SUMIF('DESP E'!$D$3:$D$146,"SFIN",'DESP E'!$I$3:$I$146) -> 11636.39 | Q45: =P45/$P$10 -> 0.00048877363 | R45: =SUMIF('MVTO A'!$C$3:$C$184,"SFIN",'MVTO A'!$I$3:$I$184)+SUMIF('DESP A'!$D$3:$D$129,"SFIN",'DESP A'!$I$3:$I$129) -> 1054.86 | S45: =R45/$R$10 -> 0.00028895646 | T45: =P45+R45 -> 12691.25 | U45: =T45/$T$10 -> 0.00046220753 | V45: =T45-M45 -> -1877.25 | W45: =SUMIF('MVTO E'!$C$3:$C$240,"SFIN",'MVTO E'!$J$3:$J$240)+SUMIF('DESP E'!$D$3:$D$146,"SFIN",'DESP E'!$J$3:$J$146) -> 8484.4 | X45: =W45/$W$10 -> 0.00038219747 | Y45: =SUMIF('MVTO A'!$C$3:$C$184,"SFIN",'MVTO A'!$J$3:$J$184)+SUMIF('DESP A'!$D$3:$D$129,"SFIN",'DESP A'!$J$3:$J$129) -> 1028.94 | Z45: =Y45/$Y$10 -> 0.00032594462 | AA45: =W45+Y45 -> 9513.34 | AB45: =AA45/$AA$10 -> 0.000375194 | AC45: =AA45-T45 -> -3177.91 | AD45: =SUMIF('MVTO E'!$C$3:$C$240,"SFIN",'MVTO E'!$K$3:$K$240)+SUMIF('DESP E'!$D$3:$D$146,"SFIN",'DESP E'!$K$3:$K$146) -> 0 | AE45: =AD45/$AD$10 -> #DIV/0! | AF45: =SUMIF('MVTO A'!$C$3:$C$184,"SFIN",'MVTO A'!$K$3:$K$184)+SUMIF('DESP A'!$D$3:$D$129,"SFIN",'DESP A'!$K$3:$K$129) -> 0 | AG45: =AF45/$AF$10 -> #DIV/0! | AH45: =AD45+AF45 -> 0 | AI45: =AH45/$AH$10 -> #DIV/0! | AJ45: =AH45-AA45 -> -9513.34 | AK45: =SUMIF('MVTO E'!$C$3:$C$240,"SFIN",'MVTO E'!$L$3:$L$240)+SUMIF('DESP E'!$D$3:$D$146,"SFIN",'DESP E'!$L$3:$L$146) -> 0 | AL45: =AK45/$AK$10 -> #DIV/0! | AM45: =SUMIF('MVTO A'!$C$3:$C$184,"SFIN",'MVTO A'!$L$3:$L$184)+SUMIF('DESP A'!$D$3:$D$129,"SFIN",'DESP A'!$L$3:$L$129) -> 0 | AN45: =AM45/$AM$10 -> #DIV/0! | AO45: =AK45+AM45 -> 0 | AP45: =AO45/$AO$10 -> #DIV/0! | AQ45: =AO45-AH45 -> 0 | AR45: =SUMIF('MVTO E'!$C$3:$C$240,"SFIN",'MVTO E'!$M$3:$M$240)+SUMIF('DESP E'!$D$3:$D$146,"SFIN",'DESP E'!$M$3:$M$146) -> 0 | AS45: =AR45/$AR$10 -> #DIV/0! | AT45: =SUMIF('MVTO A'!$C$3:$C$184,"SFIN",'MVTO A'!$M$3:$M$189)+SUMIF('DESP A'!$D$3:$D$129,"SFIN",'DESP A'!$M$3:$M$129) -> 0 | AU45: =AT45/$AT$10 -> #DIV/0! | AV45: =AR45+AT45 -> 0 | AW45: =AV45/$AV$10 -> #DIV/0! | AX45: =AV45-AO45 -> 0 | AY45: =SUMIF('MVTO E'!$C$3:$C$240,"SFIN",'MVTO E'!$N$3:$N$240)+SUMIF('DESP E'!$D$3:$D$146,"SFIN",'DESP E'!$N$3:$N$146) -> 0 | AZ45: =AY45/$AY$10 -> #DIV/0! | BA45: =SUMIF('MVTO A'!$C$3:$C$184,"SFIN",'MVTO A'!$N$3:$N$189)+SUMIF('DESP A'!$D$3:$D$129,"SFIN",'DESP A'!$N$3:$N$129) -> 0 | BB45: =BA45/$BA$10 -> #DIV/0! | BC45: =AY45+BA45 -> 0 | BD45: =BC45/$BC$10 -> #DIV/0! | BE45: =BC45-AV45 -> 0 | BF45: =SUMIF('MVTO E'!$C$3:$C$240,"SFIN",'MVTO E'!$O$3:$O$240)+SUMIF('DESP E'!$D$3:$D$146,"SFIN",'DESP E'!$O$3:$O$146) -> 0 | BG45: =BF45/$BF$10 -> #DIV/0! | BH45: =SUMIF('MVTO A'!$C$3:$C$184,"SFIN",'MVTO A'!$O$3:$O$189)+SUMIF('DESP A'!$D$3:$D$129,"SFIN",'DESP A'!$O$3:$O$129) -> 0 | BI45: =BH45/$BH$10 -> #DIV/0! | BJ45: =BF45+BH45 -> 0 | BK45: =BJ45/$BJ$10 -> #DIV/0! | BL45: =BJ45-BC45 -> 0 | BM45: =SUMIF('MVTO E'!$C$3:$C$240,"SFIN",'MVTO E'!$P$3:$P$240)+SUMIF('DESP E'!$D$3:$D$146,"SFIN",'DESP E'!$P$3:$P$146) -> 0 | BN45: =BM45/$BF$10 -> #DIV/0! | BO45: =SUMIF('MVTO A'!$C$3:$C$184,"SFIN",'MVTO A'!$P$3:$P$189)+SUMIF('DESP A'!$D$3:$D$129,"SFIN",'DESP A'!$P$3:$P$129) -> 0 | BP45: =BO45/$BH$10 -> #DIV/0! | BQ45: =BM45+BO45 -> 0 | BR45: =BQ45/$BJ$10 -> #DIV/0! | BS45: =BQ45-BJ45 -> 0 | BT45: =SUMIF('MVTO E'!$C$3:$C$240,"SFIN",'MVTO E'!$Q$3:$Q$240)+SUMIF('DESP E'!$D$3:$D$146,"SFIN",'DESP E'!$Q$3:$Q$146) -> 0 | BU45: =BT45/$BF$10 -> #DIV/0! | BV45: =SUMIF('MVTO A'!$C$3:$C$184,"SFIN",'MVTO A'!$Q$3:$Q$189)+SUMIF('DESP A'!$D$3:$D$129,"SFIN",'DESP A'!$Q$3:$Q$129) -> 0 | BW45: =BV45/$BH$10 -> #DIV/0! | BX45: =BT45+BV45 -> 0 | BY45: =BX45/$BJ$10 -> #DIV/0! | BZ45: =BX45-BQ45 -> 0 | CA45: =SUMIF('MVTO E'!$C$3:$C$240,"SFIN",'MVTO E'!$R$3:$R$240)+SUMIF('DESP E'!$D$3:$D$146,"SFIN",'DESP E'!$R$3:$R$146) -> 0 | CB45: =CA45/$BF$10 -> #DIV/0! | CC45: =SUMIF('MVTO A'!$C$3:$C$184,"SFIN",'MVTO A'!$R$3:$R$189)+SUMIF('DESP A'!$D$3:$D$129,"SFIN",'DESP A'!$R$3:$R$129) -> 0 | CD45: =CC45/$BH$10 -> #DIV/0! | CE45: =CA45+CC45 -> 0 | CF45: =CE45/$BJ$10 -> #DIV/0! | CG45: =CE45-BX45 -> 0 | CH45: =SUM(C45,I45,P45,W45,AD45,AK45,AR45,AY45,BF45,BM45,BT45,CA45) -> 46298.79 | CI45: =CH45/$CH$4 -> 0.0077072961 | CJ45: =SUM(E45,K45,R45,Y45,AF45,AM45,AT45,BA45,BH45,BO45,BV45,CC45) -> 3993.72 | CK45: =CJ45/$CJ$4 -> #DIV/0! | CL45: =SUM(G45,M45,T45,AA45,AH45,AO45,AV45,BC45,BJ45,BQ45,BX45,CE45) -> 50292.51 | CM45: =CL45/$CL$4 -> 0.0083721252
B46: Lucro antes do Imposto de Renda | C46: =C42+C44-C45 -> 1142383.2 | D46: =C46/$C$10 -> 0.034721829 | E46: =E42+E44-E45 -> 2283405 | F46: =E46/$E$10 -> 0.57782447 | G46: =C46+E46 -> 3425788.2 | H46: =G46/$G$10 -> 0.092958857 | I46: =I42+I44-I45 -> 2828759.1 | J46: =I46/$I$10 -> 0.13324334 | K46: =K42+K44-K45 -> 1820636.9 | L46: =K46/$K$10 -> 0.53246914 | M46: =I46+K46 -> 4649395.9 | N46: =M46/$M$10 -> 0.18862215 | O46: =M46-G46 -> 1223607.8 | P46: =P42+P44-P45 -> 2183425.1 | Q46: =P46/$P$10 -> 0.091712346 | R46: =R42+R44-R45 -> 2243161.6 | S46: =R46/$R$10 -> 0.61446642 | T46: =P46+R46 -> 4426586.8 | U46: =T46/$T$10 -> 0.16121357 | V46: =T46-M46 -> -222809.17 | W46: =W42+W44-W45 -> 2790343.3 | X46: =W46/$W$10 -> 0.12569683 | Y46: =Y42+Y44-Y45 -> 1993497.3 | Z46: =Y46/$Y$10 -> 0.6314943 | AA46: =W46+Y46 -> 4783840.6 | AB46: =AA46/$AA$10 -> 0.18866858 | AC46: =AA46-T46 -> 357253.88 | AD46: =AD42+AD44-AD45 -> 0 | AE46: =AD46/$AD$10 -> #DIV/0! | AF46: =AF42+AF44-AF45 -> 0 | AG46: =AF46/$AF$10 -> #DIV/0! | AH46: =AD46+AF46 -> 0 | AI46: =AH46/$AH$10 -> #DIV/0! | AJ46: =AH46-AA46 -> -4783840.6 | AK46: =AK42+AK44-AK45 -> 0 | AL46: =AK46/$AK$10 -> #DIV/0! | AM46: =AM42+AM44-AM45 -> 0 | AN46: =AM46/$AM$10 -> #DIV/0! | AO46: =AK46+AM46 -> 0 | AP46: =AO46/$AO$10 -> #DIV/0! | AQ46: =AO46-AH46 -> 0 | AR46: =AR42+AR44-AR45 -> 0 | AS46: =AR46/$AR$10 -> #DIV/0! | AT46: =AT42+AT44-AT45 -> 0 | AU46: =AT46/$AT$10 -> #DIV/0! | AV46: =AR46+AT46 -> 0 | AW46: =AV46/$AV$10 -> #DIV/0! | AX46: =AV46-AO46 -> 0 | AY46: =AY42+AY44-AY45 -> 0 | AZ46: =AY46/$AY$10 -> #DIV/0! | BA46: =BA42+BA44-BA45 -> 0 | BB46: =BA46/$BA$10 -> #DIV/0! | BC46: =AY46+BA46 -> 0 | BD46: =BC46/$BC$10 -> #DIV/0! | BE46: =BC46-AV46 -> 0 | BF46: =BF42+BF44-BF45 -> 0 | BG46: =BF46/$BF$10 -> #DIV/0! | BH46: =BH42+BH44-BH45 -> 0 | BI46: =BH46/$BH$10 -> #DIV/0! | BJ46: =BF46+BH46 -> 0 | BK46: =BJ46/$BJ$10 -> #DIV/0! | BL46: =BJ46-BC46 -> 0 | BM46: =BM42+BM44-BM45 -> 0 | BN46: =BM46/$BF$10 -> #DIV/0! | BO46: =BO42+BO44-BO45 -> 0 | BP46: =BO46/$BH$10 -> #DIV/0! | BQ46: =BM46+BO46 -> 0 | BR46: =BQ46/$BJ$10 -> #DIV/0! | BS46: =BQ46-BJ46 -> 0 | BT46: =BT42+BT44-BT45 -> 0 | BU46: =BT46/$BF$10 -> #DIV/0! | BV46: =BV42+BV44-BV45 -> 0 | BW46: =BV46/$BH$10 -> #DIV/0! | BX46: =BT46+BV46 -> 0 | BY46: =BX46/$BJ$10 -> #DIV/0! | BZ46: =BX46-BQ46 -> 0 | CA46: =CA42+CA44-CA45 -> 0 | CB46: =CA46/$BF$10 -> #DIV/0! | CC46: =CC42+CC44-CC45 -> 0 | CD46: =CC46/$BH$10 -> #DIV/0! | CE46: =CA46+CC46 -> 0 | CF46: =CE46/$BJ$10 -> #DIV/0! | CG46: =CE46-BX46 -> 0 | CH46: =IFERROR(CH42+CH43,"") -> 8944910.7 | CI46: =CH46/$CH$4 -> 1.489047 | CJ46: =IFERROR(CJ42+CJ43,"") -> 8340700.8 | CK46: =CJ46/$CJ$4 -> #DIV/0! | CL46: =IFERROR(CL42+CL43,"") -> 17285612 | CM46: =CL46/$CL$4 -> 2.8775121
B47: Despesa de Imposto de Renda | D47: =C47/$C$10 -> 0 | F47: =E47/$E$10 -> 0 | H47: =G47/$G$10 -> 0 | J47: =I47/$I$10 -> 0 | L47: =K47/$K$10 -> 0 | N47: =M47/$M$10 -> 0 | O47: =M47-G47 -> 0 | Q47: =P47/$P$10 -> 0 | S47: =R47/$R$10 -> 0 | U47: =T47/$T$10 -> 0 | V47: =T47-M47 -> 0 | X47: =W47/$W$10 -> 0 | Z47: =Y47/$Y$10 -> 0 | AB47: =AA47/$AA$10 -> 0 | AC47: =AA47-T47 -> 0 | AE47: =AD47/$AD$10 -> #DIV/0! | AG47: =AF47/$AF$10 -> #DIV/0! | AI47: =AH47/$AH$10 -> #DIV/0! | AJ47: =AH47-AA47 -> 0 | AL47: =AK47/$AK$10 -> #DIV/0! | AN47: =AM47/$AM$10 -> #DIV/0! | AP47: =AO47/$AO$10 -> #DIV/0! | AQ47: =AO47-AH47 -> 0 | AS47: =AR47/$AR$10 -> #DIV/0! | AU47: =AT47/$AT$10 -> #DIV/0! | AW47: =AV47/$AV$10 -> #DIV/0! | AX47: =AV47-AO47 -> 0 | AZ47: =AY47/$AY$10 -> #DIV/0! | BB47: =BA47/$BA$10 -> #DIV/0! | BD47: =BC47/$BC$10 -> #DIV/0! | BE47: =BC47-AV47 -> 0 | BG47: =BF47/$BF$10 -> #DIV/0! | BI47: =BH47/$BH$10 -> #DIV/0! | BK47: =BJ47/$BJ$10 -> #DIV/0! | BL47: =BJ47-BC47 -> 0 | BN47: =BM47/$BF$10 -> #DIV/0! | BP47: =BO47/$BH$10 -> #DIV/0! | BR47: =BQ47/$BJ$10 -> #DIV/0! | BS47: =BQ47-BJ47 -> 0 | BU47: =BT47/$BF$10 -> #DIV/0! | BW47: =BV47/$BH$10 -> #DIV/0! | BY47: =BX47/$BJ$10 -> #DIV/0! | BZ47: =BX47-BQ47 -> 0 | CB47: =CA47/$BF$10 -> #DIV/0! | CD47: =CC47/$BH$10 -> #DIV/0! | CF47: =CE47/$BJ$10 -> #DIV/0! | CG47: =CE47-BX47 -> 0 | CH47: =SUM(C47,I47,P47,W47,AD47,AK47,AR47,AY47,BF47,BM47,BT47,CA47) -> 0 | CI47: =CH47/$CH$4 -> 0 | CJ47: =SUM(E47,K47,R47,Y47,AF47,AM47,AT47,BA47,BH47,BO47,BV47,CC47) -> 0 | CK47: =CJ47/$CJ$4 -> #DIV/0! | CL47: =SUM(G47,M47,T47,AA47,AH47,AO47,AV47,BC47,BJ47,BQ47,BX47,CE47) -> 0 | CM47: =CL47/$CL$4 -> 0
B48: Lucro líquido | C48: =C42+C44-C45 -> 1142383.2 | D48: =C48/$C$10 -> 0.034721829 | E48: =E42+E44-E45 -> 2283405 | F48: =E48/$E$10 -> 0.57782447 | G48: =C48+E48 -> 3425788.2 | H48: =G48/$G$10 -> 0.092958857 | I48: =I42+I44-I45 -> 2828759.1 | J48: =I48/$I$10 -> 0.13324334 | K48: =K42+K44-K45 -> 1820636.9 | L48: =K48/$K$10 -> 0.53246914 | M48: =I48+K48 -> 4649395.9 | N48: =M48/$M$10 -> 0.18862215 | O48: =M48-G48 -> 1223607.8 | P48: =P42+P44-P45 -> 2183425.1 | Q48: =P48/$P$10 -> 0.091712346 | R48: =R42+R44-R45 -> 2243161.6 | S48: =R48/$R$10 -> 0.61446642 | T48: =P48+R48 -> 4426586.8 | U48: =T48/$T$10 -> 0.16121357 | V48: =T48-M48 -> -222809.17 | W48: =W42+W44-W45 -> 2790343.3 | X48: =W48/$W$10 -> 0.12569683 | Y48: =Y42+Y44-Y45 -> 1993497.3 | Z48: =Y48/$Y$10 -> 0.6314943 | AA48: =W48+Y48 -> 4783840.6 | AB48: =AA48/$AA$10 -> 0.18866858 | AC48: =AA48-T48 -> 357253.88 | AD48: =AD42+AD44-AD45 -> 0 | AE48: =AD48/$AD$10 -> #DIV/0! | AF48: =AF42+AF44-AF45 -> 0 | AG48: =AF48/$AF$10 -> #DIV/0! | AH48: =AD48+AF48 -> 0 | AI48: =AH48/$AH$10 -> #DIV/0! | AJ48: =AH48-AA48 -> -4783840.6 | AK48: =AK42+AK44-AK45 -> 0 | AL48: =AK48/$AK$10 -> #DIV/0! | AM48: =AM42+AM44-AM45 -> 0 | AN48: =AM48/$AM$10 -> #DIV/0! | AO48: =AK48+AM48 -> 0 | AP48: =AO48/$AO$10 -> #DIV/0! | AQ48: =AO48-AH48 -> 0 | AR48: =AR42+AR44-AR45 -> 0 | AS48: =AR48/$AR$10 -> #DIV/0! | AT48: =AT42+AT44-AT45 -> 0 | AU48: =AT48/$AT$10 -> #DIV/0! | AV48: =AR48+AT48 -> 0 | AW48: =AV48/$AV$10 -> #DIV/0! | AX48: =AV48-AO48 -> 0 | AY48: =AY42+AY44-AY45 -> 0 | AZ48: =AY48/$AY$10 -> #DIV/0! | BA48: =BA42+BA44-BA45 -> 0 | BB48: =BA48/$BA$10 -> #DIV/0! | BC48: =AY48+BA48 -> 0 | BD48: =BC48/$BC$10 -> #DIV/0! | BE48: =BC48-AV48 -> 0 | BF48: =BF42+BF44-BF45 -> 0 | BG48: =BF48/$BF$10 -> #DIV/0! | BH48: =BH42+BH44-BH45 -> 0 | BI48: =BH48/$BH$10 -> #DIV/0! | BJ48: =BF48+BH48 -> 0 | BK48: =BJ48/$BJ$10 -> #DIV/0! | BL48: =BJ48-BC48 -> 0 | BM48: =BM42+BM44-BM45 -> 0 | BN48: =BM48/$BF$10 -> #DIV/0! | BO48: =BO42+BO44-BO45 -> 0 | BP48: =BO48/$BH$10 -> #DIV/0! | BQ48: =BM48+BO48 -> 0 | BR48: =BQ48/$BJ$10 -> #DIV/0! | BS48: =BQ48-BJ48 -> 0 | BT48: =BT42+BT44-BT45 -> 0 | BU48: =BT48/$BF$10 -> #DIV/0! | BV48: =BV42+BV44-BV45 -> 0 | BW48: =BV48/$BH$10 -> #DIV/0! | BX48: =BT48+BV48 -> 0 | BY48: =BX48/$BJ$10 -> #DIV/0! | BZ48: =BX48-BQ48 -> 0 | CA48: =CA42+CA44-CA45 -> 0 | CB48: =CA48/$BF$10 -> #DIV/0! | CC48: =CC42+CC44-CC45 -> 0 | CD48: =CC48/$BH$10 -> #DIV/0! | CE48: =CA48+CC48 -> 0 | CF48: =CE48/$BJ$10 -> #DIV/0! | CG48: =CE48-BX48 -> 0 | CH48: =CH42+CH44-CH45 -> 8944910.7 | CI48: =CH48/$CH$10 -> 0.089326421 | CJ48: =CJ42+CJ44-CJ45 -> 8340700.8 | CK48: =CJ48/$CJ$10 -> 0.58827059 | CL48: =CL42+CL44-CL45 -> 17285612 | CM48: =CL48/$CL$10 -> 0.15120945
B49: Investimentos e Financiamentos | C49: =IFERROR(C50-C57,"") -> 7647475.5 | D49: =C49/$C$10 -> 0.23243894 | E49: =IFERROR(E50-E57,"") -> 220345.98 | F49: =E49/$E$10 -> 0.055759403 | G49: =C49+E49 -> 7867821.5 | H49: =G49/$G$10 -> 0.21349355 | I49: =IFERROR(I50-I57,"") -> 2674807.6 | J49: =I49/$I$10 -> 0.12599174 | K49: =IFERROR(K50-K57,"") -> 220769 | L49: =K49/$K$10 -> 0.064566791 | M49: =I49+K49 -> 2895576.6 | N49: =M49/$M$10 -> 0.11747115 | O49: =M49-G49 -> -4972244.9 | P49: =IFERROR(P50-P57,"") -> 6846239 | Q49: =P49/$P$10 -> 0.28756866 | R49: =IFERROR(R50-R57,"") -> 220258.18 | S49: =R49/$R$10 -> 0.060335044 | T49: =P49+R49 -> 7066497.2 | U49: =T49/$T$10 -> 0.25735749 | V49: =T49-M49 -> 4170920.6 | W49: =IFERROR(W50-W57,"") -> 5549732.1 | X49: =W49/$W$10 -> 0.24999925 | Y49: =IFERROR(Y50-Y57,"") -> 221889.58 | Z49: =Y49/$Y$10 -> 0.070289537 | AA49: =W49+Y49 -> 5771621.7 | AB49: =AA49/$AA$10 -> 0.2276254 | AC49: =AA49-T49 -> -1294875.5 | AD49: =IFERROR(AD50-AD57,"") -> 0 | AE49: =AD49/$AD$10 -> #DIV/0! | AF49: =IFERROR(AF50-AF57,"") -> 0 | AG49: =AF49/$AF$10 -> #DIV/0! | AH49: =AD49+AF49 -> 0 | AI49: =AH49/$AH$10 -> #DIV/0! | AJ49: =AH49-AA49 -> -5771621.7 | AK49: =IFERROR(AK50-AK57,"") -> 0 | AL49: =AK49/$AK$10 -> #DIV/0! | AM49: =IFERROR(AM50-AM57,"") -> 0 | AN49: =AM49/$AM$10 -> #DIV/0! | AO49: =AK49+AM49 -> 0 | AP49: =AO49/$AO$10 -> #DIV/0! | AQ49: =AO49-AH49 -> 0 | AR49: =IFERROR(AR50-AR57,"") -> 0 | AS49: =AR49/$AR$10 -> #DIV/0! | AT49: =IFERROR(AT50-AT57,"") -> 0 | AU49: =AT49/$AT$10 -> #DIV/0! | AV49: =AR49+AT49 -> 0 | AW49: =AV49/$AV$10 -> #DIV/0! | AX49: =AV49-AO49 -> 0 | AY49: =IFERROR(AY50-AY57,"") -> 0 | AZ49: =AY49/$AY$10 -> #DIV/0! | BA49: =IFERROR(BA50-BA57,"") -> 0 | BB49: =BA49/$BA$10 -> #DIV/0! | BC49: =AY49+BA49 -> 0 | BD49: =BC49/$BC$10 -> #DIV/0! | BE49: =BC49-AV49 -> 0 | BF49: =IFERROR(BF50-BF57,"") -> 0 | BG49: =BF49/$BF$10 -> #DIV/0! | BH49: =IFERROR(BH50-BH57,"") -> 0 | BI49: =BH49/$BH$10 -> #DIV/0! | BJ49: =BF49+BH49 -> 0 | BK49: =BJ49/$BJ$10 -> #DIV/0! | BL49: =BJ49-BC49 -> 0 | BM49: =IFERROR(BM50-BM57,"") -> 0 | BN49: =BM49/$BF$10 -> #DIV/0! | BO49: =IFERROR(BO50-BO57,"") -> 0 | BP49: =BO49/$BH$10 -> #DIV/0! | BQ49: =BM49+BO49 -> 0 | BR49: =BQ49/$BJ$10 -> #DIV/0! | BS49: =BQ49-BJ49 -> 0 | BT49: =IFERROR(BT50-BT57,"") -> 0 | BU49: =BT49/$BF$10 -> #DIV/0! | BV49: =IFERROR(BV50-BV57,"") -> 0 | BW49: =BV49/$BH$10 -> #DIV/0! | BX49: =BT49+BV49 -> 0 | BY49: =BX49/$BJ$10 -> #DIV/0! | BZ49: =BX49-BQ49 -> 0 | CA49: =IFERROR(CA50-CA57,"") -> 0 | CB49: =CA49/$BF$10 -> #DIV/0! | CC49: =IFERROR(CC50-CC57,"") -> 0 | CD49: =CC49/$BH$10 -> #DIV/0! | CE49: =CA49+CC49 -> 0 | CF49: =CE49/$BJ$10 -> #DIV/0! | CG49: =CE49-BX49 -> 0 | CH49: =IFERROR(CH50-CH57,"") -> 16320910 | CI49: =CH49/$CH$10 -> 0.16298525 | CJ49: =IFERROR(CJ50-CJ57,"") -> 658732.38 | CK49: =CJ49/$CJ$10 -> 0.046460471 | CL49: =IFERROR(CL50-CL57,"") -> 16979643 | CM49: =CL49/$CL$10 -> 0.14853292
B50: Saídas | C50: =SUM(C51:C56) -> 8586436.2 | D50: =C50/$C$10 -> 0.26097791 | E50: =SUM(E51:E56) -> 228282.94 | F50: =E50/$E$10 -> 0.057767882 | G50: =C50+E50 -> 8814719.2 | H50: =G50/$G$10 -> 0.23918765 | I50: =SUM(I51:I56) -> 4902049.8 | J50: =I50/$I$10 -> 0.23090177 | K50: =SUM(K51:K56) -> 228145.88 | L50: =K50/$K$10 -> 0.066724257 | M50: =I50+K50 -> 5130195.7 | N50: =M50/$M$10 -> 0.2081278 | O50: =M50-G50 -> -3684523.4 | P50: =SUM(P51:P56) -> 8810884.2 | Q50: =P50/$P$10 -> 0.3700914 | R50: =SUM(R51:R56) -> 225716.18 | S50: =R50/$R$10 -> 0.061830147 | T50: =P50+R50 -> 9036600.4 | U50: =T50/$T$10 -> 0.32910743 | V50: =T50-M50 -> 3906404.7 | W50: =SUM(W51:W56) -> 6282130.2 | X50: =W50/$W$10 -> 0.28299164 | Y50: =SUM(Y51:Y56) -> 227587.18 | Z50: =Y50/$Y$10 -> 0.072094406 | AA50: =W50+Y50 -> 6509717.4 | AB50: =AA50/$AA$10 -> 0.25673495 | AC50: =AA50-T50 -> -2526883 | AD50: =SUM(AD51:AD56) -> 0 | AE50: =AD50/$AD$10 -> #DIV/0! | AF50: =SUM(AF51:AF56) -> 0 | AG50: =AF50/$AF$10 -> #DIV/0! | AH50: =AD50+AF50 -> 0 | AI50: =AH50/$AH$10 -> #DIV/0! | AJ50: =AH50-AA50 -> -6509717.4 | AK50: =SUM(AK51:AK56) -> 0 | AL50: =AK50/$AK$10 -> #DIV/0! | AM50: =SUM(AM51:AM56) -> 0 | AN50: =AM50/$AM$10 -> #DIV/0! | AO50: =AK50+AM50 -> 0 | AP50: =AO50/$AO$10 -> #DIV/0! | AQ50: =AO50-AH50 -> 0 | AR50: =SUM(AR51:AR56) -> 0 | AS50: =AR50/$AR$10 -> #DIV/0! | AT50: =SUM(AT51:AT56) -> 0 | AU50: =AT50/$AT$10 -> #DIV/0! | AV50: =AR50+AT50 -> 0 | AW50: =AV50/$AV$10 -> #DIV/0! | AX50: =AV50-AO50 -> 0 | AY50: =SUM(AY51:AY56) -> 0 | AZ50: =AY50/$AY$10 -> #DIV/0! | BA50: =SUM(BA51:BA56) -> 0 | BB50: =BA50/$BA$10 -> #DIV/0! | BC50: =AY50+BA50 -> 0 | BD50: =BC50/$BC$10 -> #DIV/0! | BE50: =BC50-AV50 -> 0 | BF50: =SUM(BF51:BF56) -> 0 | BG50: =BF50/$BF$10 -> #DIV/0! | BH50: =SUM(BH51:BH56) -> 0 | BI50: =BH50/$BH$10 -> #DIV/0! | BJ50: =BF50+BH50 -> 0 | BK50: =BJ50/$BJ$10 -> #DIV/0! | BL50: =BJ50-BC50 -> 0 | BM50: =SUM(BM51:BM56) -> 0 | BN50: =BM50/$BF$10 -> #DIV/0! | BO50: =SUM(BO51:BO56) -> 0 | BP50: =BO50/$BH$10 -> #DIV/0! | BQ50: =BM50+BO50 -> 0 | BR50: =BQ50/$BJ$10 -> #DIV/0! | BS50: =BQ50-BJ50 -> 0 | BT50: =SUM(BT51:BT56) -> 0 | BU50: =BT50/$BF$10 -> #DIV/0! | BV50: =SUM(BV51:BV56) -> 0 | BW50: =BV50/$BH$10 -> #DIV/0! | BX50: =BT50+BV50 -> 0 | BY50: =BX50/$BJ$10 -> #DIV/0! | BZ50: =BX50-BQ50 -> 0 | CA50: =SUM(CA51:CA56) -> 0 | CB50: =CA50/$BF$10 -> #DIV/0! | CC50: =SUM(CC51:CC56) -> 0 | CD50: =CC50/$BH$10 -> #DIV/0! | CE50: =CA50+CC50 -> 0 | CF50: =CE50/$BJ$10 -> #DIV/0! | CG50: =CE50-BX50 -> 0 | CH50: =IF(SUM(CH51:CH54)=0,"",SUM(CH51:CH54)) -> 22184156 | CI50: =CH50/$CH$10 -> 0.22153729 | CJ50: =IF(SUM(CJ51:CJ54)=0,"",SUM(CJ51:CJ54)) -> 685201.82 | CK50: =CJ50/$CJ$10 -> 0.048327363 | CL50: =IF(SUM(CL51:CL54)=0,"",SUM(CL51:CL54)) -> 22869358 | CM50: =CL50/$CL$10 -> 0.20005442
B51: Empréstimos & Financ Bancários | C51: =SUMIF('MVTO E'!$C$3:$C$240,"Empres_S",'MVTO E'!$G$3:$G$240) -> 5825866.4 | D51: =C51/$C$10 -> 0.17707258 | E51: =SUMIF('MVTO A'!$C$3:$C$184,"Empres_S",'MVTO A'!$G$3:$G$184) -> 87936.96 | F51: =E51/$E$10 -> 0.022252788 | G51: =C51+E51 -> 5913803.4 | H51: =G51/$G$10 -> 0.16047122 | I51: =SUMIF('MVTO E'!$C$3:$C$240,"Empres_S",'MVTO E'!$H$3:$H$240) -> 2365724.2 | J51: =I51/$I$10 -> 0.11143295 | K51: =SUMIF('MVTO A'!$C$3:$C$184,"Empres_S",'MVTO A'!$H$3:$H$184) -> 87376.87 | L51: =K51/$K$10 -> 0.025554512 | M51: =I51+K51 -> 2453101 | N51: =M51/$M$10 -> 0.099520281 | O51: =M51-G51 -> -3460702.3 | P51: =SUMIF('MVTO E'!$C$3:$C$240,"Empres_S",'MVTO E'!$I$3:$I$240) -> 5328894.2 | Q51: =P51/$P$10 -> 0.22383428 | R51: =SUMIF('MVTO A'!$C$3:$C$184,"Empres_S",'MVTO A'!$I$3:$I$184) -> 85458 | S51: =R51/$R$10 -> 0.023409402 | T51: =P51+R51 -> 5414352.2 | U51: =T51/$T$10 -> 0.19718738 | V51: =T51-M51 -> 2961251.2 | W51: =SUMIF('MVTO E'!$C$3:$C$240,"Empres_S",'MVTO E'!$J$3:$J$240) -> 3080492.8 | X51: =W51/$W$10 -> 0.13876722 | Y51: =SUMIF('MVTO A'!$C$3:$C$184,"Empres_S",'MVTO A'!$J$3:$J$184) -> 85697.59 | Z51: =Y51/$Y$10 -> 0.027147034 | AA51: =W51+Y51 -> 3166190.4 | AB51: =AA51/$AA$10 -> 0.12487051 | AC51: =AA51-T51 -> -2248161.8 | AD51: =SUMIF('MVTO E'!$C$3:$C$240,"Empres_S",'MVTO E'!$K$3:$K$240) -> 0 | AE51: =AD51/$AD$10 -> #DIV/0! | AF51: =SUMIF('MVTO A'!$C$3:$C$184,"Empres_S",'MVTO A'!$K$3:$K$184) -> 0 | AG51: =AF51/$AF$10 -> #DIV/0! | AH51: =AD51+AF51 -> 0 | AI51: =AH51/$AH$10 -> #DIV/0! | AJ51: =AH51-AA51 -> -3166190.4 | AK51: =SUMIF('MVTO E'!$C$3:$C$240,"Empres_S",'MVTO E'!$L$3:$L$240) -> 0 | AL51: =AK51/$AK$10 -> #DIV/0! | AM51: =SUMIF('MVTO A'!$C$3:$C$184,"Empres_S",'MVTO A'!$L$3:$L$184) -> 0 | AN51: =AM51/$AM$10 -> #DIV/0! | AO51: =AK51+AM51 -> 0 | AP51: =AO51/$AO$10 -> #DIV/0! | AQ51: =AO51-AH51 -> 0 | AR51: =SUMIF('MVTO E'!$C$3:$C$240,"Empres_S",'MVTO E'!$M$3:$M$240) -> 0 | AS51: =AR51/$AR$10 -> #DIV/0! | AT51: =SUMIF('MVTO A'!$C$3:$C$184,"Empres_S",'MVTO A'!$M$3:$M$189) -> 0 | AU51: =AT51/$AT$10 -> #DIV/0! | AV51: =AR51+AT51 -> 0 | AW51: =AV51/$AV$10 -> #DIV/0! | AX51: =AV51-AO51 -> 0 | AY51: =SUMIF('MVTO E'!$C$3:$C$240,"Empres_S",'MVTO E'!$N$3:$N$240) -> 0 | AZ51: =AY51/$AY$10 -> #DIV/0! | BA51: =SUMIF('MVTO A'!$C$3:$C$184,"Empres_S",'MVTO A'!$N$3:$N$189) -> 0 | BB51: =BA51/$BA$10 -> #DIV/0! | BC51: =AY51+BA51 -> 0 | BD51: =BC51/$BC$10 -> #DIV/0! | BE51: =BC51-AV51 -> 0 | BF51: =SUMIF('MVTO E'!$C$3:$C$240,"Empres_S",'MVTO E'!$O$3:$O$240) -> 0 | BG51: =BF51/$BF$10 -> #DIV/0! | BH51: =SUMIF('MVTO A'!$C$3:$C$184,"Empres_S",'MVTO A'!$O$3:$O$189) -> 0 | BI51: =BH51/$BH$10 -> #DIV/0! | BJ51: =BF51+BH51 -> 0 | BK51: =BJ51/$BJ$10 -> #DIV/0! | BL51: =BJ51-BC51 -> 0 | BM51: =SUMIF('MVTO E'!$C$3:$C$240,"Empres_S",'MVTO E'!$P$3:$P$240) -> 0 | BN51: =BM51/$BF$10 -> #DIV/0! | BO51: =SUMIF('MVTO A'!$C$3:$C$184,"Empres_S",'MVTO A'!$P$3:$P$189) -> 0 | BP51: =BO51/$BH$10 -> #DIV/0! | BQ51: =BM51+BO51 -> 0 | BR51: =BQ51/$BJ$10 -> #DIV/0! | BS51: =BQ51-BJ51 -> 0 | BT51: =SUMIF('MVTO E'!$C$3:$C$240,"Empres_S",'MVTO E'!$Q$3:$Q$240) -> 0 | BU51: =BT51/$BF$10 -> #DIV/0! | BV51: =SUMIF('MVTO A'!$C$3:$C$184,"Empres_S",'MVTO A'!$Q$3:$Q$189) -> 0 | BW51: =BV51/$BH$10 -> #DIV/0! | BX51: =BT51+BV51 -> 0 | BY51: =BX51/$BJ$10 -> #DIV/0! | BZ51: =BX51-BQ51 -> 0 | CA51: =SUMIF('MVTO E'!$C$3:$C$240,"Empres_S",'MVTO E'!$R$3:$R$240) -> 0 | CB51: =CA51/$BF$10 -> #DIV/0! | CC51: =SUMIF('MVTO A'!$C$3:$C$184,"Empres_S",'MVTO A'!$R$3:$R$189) -> 0 | CD51: =CC51/$BH$10 -> #DIV/0! | CE51: =CA51+CC51 -> 0 | CF51: =CE51/$BJ$10 -> #DIV/0! | CG51: =CE51-BX51 -> 0 | CH51: =SUM(C51,I51,P51,W51,AD51,AK51,AR51,AY51,BF51,BM51,BT51,CA51) -> 16600978 | CI51: =CH51/$CH$10 -> 0.16578208 | CJ51: =SUM(E51,K51,R51,Y51,AF51,AM51,AT51,BA51,BH51,BO51,BV51,CC51) -> 346469.42 | CK51: =CJ51/$CJ$10 -> 0.024436528 | CL51: =SUM(G51,M51,T51,AA51,AH51,AO51,AV51,BC51,BJ51,BQ51,BX51,CE51) -> 16947447 | CM51: =CL51/$CL$10 -> 0.14825128
B52: Investimentos | C52: =SUMIF('MVTO E'!$C$3:$C$240,"Investimentos",'MVTO E'!$G$3:$G$240) -> 600 | D52: =C52/$C$10 -> 1.8236524e-05 | E52: =SUMIF('MVTO A'!$C$3:$C$177,"Investimentos",'MVTO A'!$G$3:$G$177) -> 0 | F52: =E52/$E$10 -> 0 | G52: =C52+E52 -> 600 | H52: =G52/$G$10 -> 1.6281017e-05 | I52: =SUMIF('MVTO E'!$C$3:$C$240,"Investimentos",'MVTO E'!$H$3:$H$240) -> 200 | J52: =I52/$I$10 -> 9.420621e-06 | K52: =SUMIF('MVTO A'!$C$3:$C$177,"Investimentos",'MVTO A'!$H$3:$H$177) -> 0 | L52: =K52/$K$10 -> 0 | M52: =I52+K52 -> 200 | N52: =M52/$M$10 -> 8.1138347e-06 | O52: =M52-G52 -> -400 | P52: =SUMIF('MVTO E'!$C$3:$C$240,"Investimentos",'MVTO E'!$I$3:$I$240) -> 200 | Q52: =P52/$P$10 -> 8.4007777e-06 | R52: =SUMIF('MVTO A'!$C$3:$C$177,"Investimentos",'MVTO A'!$I$3:$I$177) -> 0 | S52: =R52/$R$10 -> 0 | T52: =P52+R52 -> 200 | U52: =T52/$T$10 -> 7.2838771e-06 | V52: =T52-M52 -> 0 | W52: =SUMIF('MVTO E'!$C$3:$C$240,"Investimentos",'MVTO E'!$J$3:$J$240) -> 200 | X52: =W52/$W$10 -> 9.0094167e-06 | Y52: =SUMIF('MVTO A'!$C$3:$C$177,"Investimentos",'MVTO A'!$J$3:$J$184) -> 0 | Z52: =Y52/$Y$10 -> 0 | AA52: =W52+Y52 -> 200 | AB52: =AA52/$AA$10 -> 7.887745e-06 | AC52: =AA52-T52 -> 0 | AD52: =SUMIF('MVTO E'!$C$3:$C$240,"Investimentos",'MVTO E'!$K$3:$K$240) -> 0 | AE52: =AD52/$AD$10 -> #DIV/0! | AF52: =SUMIF('MVTO A'!$C$3:$C$177,"Investimentos",'MVTO A'!$K$3:$K$177) -> 0 | AG52: =AF52/$AF$10 -> #DIV/0! | AH52: =AD52+AF52 -> 0 | AI52: =AH52/$AH$10 -> #DIV/0! | AJ52: =AH52-AA52 -> -200 | AK52: =SUMIF('MVTO E'!$C$3:$C$240,"Investimentos",'MVTO E'!$L$3:$L$240) -> 0 | AL52: =AK52/$AK$10 -> #DIV/0! | AM52: =SUMIF('MVTO A'!$C$3:$C$177,"Investimentos",'MVTO A'!$I$3:$I$177) -> 0 | AN52: =AM52/$AM$10 -> #DIV/0! | AO52: =AK52+AM52 -> 0 | AP52: =AO52/$AO$10 -> #DIV/0! | AQ52: =AO52-AH52 -> 0 | AR52: =SUMIF('MVTO E'!$C$3:$C$240,"Investimentos",'MVTO E'!$M$3:$M$240) -> 0 | AS52: =AR52/$AR$10 -> #DIV/0! | AT52: =SUMIF('MVTO A'!$C$3:$C$177,"Investimentos",'MVTO A'!$M$3:$M$189) -> 0 | AU52: =AT52/$AT$10 -> #DIV/0! | AV52: =AR52+AT52 -> 0 | AW52: =AV52/$AV$10 -> #DIV/0! | AX52: =AV52-AO52 -> 0 | AY52: =SUMIF('MVTO E'!$C$3:$C$240,"Investimentos",'MVTO E'!$N$3:$N$240) -> 0 | AZ52: =AY52/$AY$10 -> #DIV/0! | BA52: =SUMIF('MVTO A'!$C$3:$C$177,"Investimentos",'MVTO A'!$I$3:$I$177) -> 0 | BB52: =BA52/$BA$10 -> #DIV/0! | BC52: =AY52+BA52 -> 0 | BD52: =BC52/$BC$10 -> #DIV/0! | BE52: =BC52-AV52 -> 0 | BF52: =SUMIF('MVTO E'!$C$3:$C$240,"Investimentos",'MVTO E'!$O$3:$O$240) -> 0 | BG52: =BF52/$BF$10 -> #DIV/0! | BH52: =SUMIF('MVTO A'!$C$3:$C$177,"Investimentos",'MVTO A'!$I$3:$I$177) -> 0 | BI52: =BH52/$BH$10 -> #DIV/0! | BJ52: =BF52+BH52 -> 0 | BK52: =BJ52/$BJ$10 -> #DIV/0! | BL52: =BJ52-BC52 -> 0 | BM52: =SUMIF('MVTO E'!$C$3:$C$240,"Investimentos",'MVTO E'!$P$3:$P$240) -> 0 | BN52: =BM52/$BF$10 -> #DIV/0! | BO52: =SUMIF('MVTO A'!$C$3:$C$177,"Investimentos",'MVTO A'!$I$3:$I$177) -> 0 | BP52: =BO52/$BH$10 -> #DIV/0! | BQ52: =BM52+BO52 -> 0 | BR52: =BQ52/$BJ$10 -> #DIV/0! | BS52: =BQ52-BJ52 -> 0 | BT52: =SUMIF('MVTO E'!$C$3:$C$240,"Investimentos",'MVTO E'!$Q$3:$Q$240) -> 0 | BU52: =BT52/$BF$10 -> #DIV/0! | BV52: =SUMIF('MVTO A'!$C$3:$C$177,"Investimentos",'MVTO A'!$I$3:$I$177) -> 0 | BW52: =BV52/$BH$10 -> #DIV/0! | BX52: =BT52+BV52 -> 0 | BY52: =BX52/$BJ$10 -> #DIV/0! | BZ52: =BX52-BQ52 -> 0 | CA52: =SUMIF('MVTO E'!$C$3:$C$240,"Investimentos",'MVTO E'!$R$3:$R$240) -> 0 | CB52: =CA52/$BF$10 -> #DIV/0! | CC52: =SUMIF('MVTO A'!$C$3:$C$177,"Investimentos",'MVTO A'!$R$3:$R$189) -> 0 | CD52: =CC52/$BH$10 -> #DIV/0! | CE52: =CA52+CC52 -> 0 | CF52: =CE52/$BJ$10 -> #DIV/0! | CG52: =CE52-BX52 -> 0 | CH52: =SUM(C52,I52,P52,W52,AD52,AK52,AR52,AY52,BF52,BM52,BT52,CA52) -> 1200 | CI52: =CH52/$CH$10 -> 1.1983541e-05 | CJ52: =SUM(E52,K52,R52,Y52,AF52,AM52,AT52,BA52,BH52,BO52,BV52,CC52) -> 0 | CK52: =CJ52/$CJ$10 -> 0 | CL52: =SUM(G52,M52,T52,AA52,AH52,AO52,AV52,BC52,BJ52,BQ52,BX52,CE52) -> 1200 | CM52: =CL52/$CL$10 -> 1.0497247e-05
