Workbook
Name ABR: #REF!
Name ABR: #REF!
Name ABR: #REF!
Name ABR: #REF!
Name ANO: #REF!
Name CONTA: #REF!
Name CONTA: #REF!
Name CONTA: #REF!
Name CONTA: #REF!
Name DESCRIÇÃO: #REF!
Name DESCRIÇÃO: #REF!
Name DESCRIÇÃO: #REF!
Name DESCRIÇÃO: #REF!
Name FEV: #REF!
Name FEV: #REF!
Name FEV: #REF!
Name FEV: #REF!
Name JAN: #REF!
Name JAN: #REF!
Name JAN: #REF!
Name JAN: #REF!
Name LEGENDA: #REF!
Name LEGENDA: #REF!
Name LEGENDA: #REF!
Name LEGENDA: #REF!
Name LucroLiquido: '2025'!#REF!
Name LucroLiquido: '2026'!#REF!
Name LucroLiquido: CLAUDE!#REF!
Name LucroLiquido: #REF!
Name MAI: #REF!
Name MAI: #REF!
Name MAI: #REF!
Name MAI: #REF!
Name MAR: #REF!
Name MAR: #REF!
Name MAR: #REF!
Name MAR: #REF!
Name Rub: #REF!
Name Rub: #REF!
Name Rub: #REF!
Name Rub: #REF!
Name Rubrica: #REF!
Name Rubrica: #REF!
Name Rubrica: #REF!
Name Rubrica: #REF!

Sheet 2026
C2: CONTA | D2: Janeiro | I2: Fevereiro | N2: Março | S2: Abril | X2: Maio | AC2: Junho | AH2: Julho | AM2: Agosto | AR2: Setembro | AW2: Outubro | BB2: Novembro | BG2: Dezembro | BL2: GERAL
C3: Receita | D3: ✅REALIZADO | E3: 📐%REA | F3: 🎯ORÇADO | G3: 📊%ORC | H3: ↔️DIF | I3: ✅REALIZADO | J3: 📐%REA | K3: 🎯ORÇADO | L3: 📊%ORC | M3: ↔️DIF | N3: ✅REALIZADO | O3: 📐%REA | P3: 🎯ORÇADO | Q3: 📊%ORC | R3: ↔️DIF | S3: ✅REALIZADO | T3: 📐%REA | U3: 🎯ORÇADO | V3: 📊%ORC | W3: ↔️DIF | X3: ✅REALIZADO | Y3: 📐%REA | Z3: 🎯ORÇADO | AA3: 📊%ORC | AB3: ↔️DIF | AC3: ✅REALIZADO | AD3: 📐%REA | AE3: 🎯ORÇADO | AF3: 📊%ORC | AG3: ↔️DIF | AH3: ✅REALIZADO | AI3: 📐%REA | AJ3: 🎯ORÇADO | AK3: 📊%ORC | AL3: ↔️DIF | AM3: ✅REALIZADO | AN3: 📐%REA | AO3: 🎯ORÇADO | AP3: 📊%ORC | AQ3: ↔️DIF | AR3: ✅REALIZADO | AS3: 📐%REA | AT3: 🎯ORÇADO | AU3: 📊%ORC | AV3: ↔️DIF | AW3: ✅REALIZADO | AX3: 📐%REA | AY3: 🎯ORÇADO | AZ3: 📊%ORC | BA3: ↔️DIF | BB3: ✅REALIZADO | BC3: 📐%REA | BD3: 🎯ORÇADO | BE3: 📊%ORC | BF3: ↔️DIF | BG3: ✅REALIZADO | BH3: 📐%REA | BI3: 🎯ORÇADO | BJ3: 📊%ORC | BK3: ↔️DIF | BL3: ✅REALIZADO | BM3: 📐%REA | BN3: 🎯ORÇADO | BO3: 📊%ORC | BP3: ↔️DIF | BQ3: ✅BASE - 2025 | BR3: 📐%REA
A4: Vda_Din | C4: Vendas - Dinheiro | D4: =SUMIF(EXTRATO!$F$14:$F$194,"Vda_Din",EXTRATO!$I$14:$I$194) -> 4546012.6 | E4: =D4/$D$12 -> 0.1816145 | F4: =$F$12*BR4 -> 4300373.9 | G4: =IF(F4="","",F4/$F$12) -> 0.19138347 | H4: =IF(G4="","",E4-G4) -> -0.0097689711 | I4: =SUMIF(EXTRATO!$F$14:$F$194,"Vda_Din",EXTRATO!$J$14:$J$194) -> 4418376 | J4: =I4/$I$12 -> 0.1955827 | K4: =$K$12*BR4 -> 4535788.3 | L4: =IF(K4="","",K4/$K$12) -> 0.19138347 | M4: =IF(L4="","",J4-L4) -> 0.0041992292 | O4: =IFERROR(N4/$N$16,"") | P4: =$P$12*BR4 -> 4784586.8 | Q4: =IF(P4="","",P4/$P$12) -> 0.19138347 | R4: =N4-P4 -> -4784586.8 | T4: =S4/$D$16 -> 0 | U4: =$U$12*BR4 -> 4975970.3 | V4: =IF(U4="","",U4/$U$12) -> 0.19138347 | W4: =IF(V4="","",T4-V4) -> -0.19138347 | Y4: =X4/$D$16 -> 0 | Z4: =$Z$12*BR4 -> 5167353.7 | AA4: =IF(Z4="","",Z4/$Z$12) -> 0.19138347 | AB4: =IF(AA4="","",Y4-AA4) -> -0.19138347 | AD4: =AC4/$D$16 -> 0 | AE4: =$AE$12*BR4 -> 4975970.3 | AF4: =IF(AE4="","",AE4/$AE$12) -> 0.19138347 | AG4: =IF(AF4="","",AD4-AF4) -> -0.19138347 | AI4: =AH4/$D$16 -> 0 | AJ4: =$AJ$12*BR4 -> 5320460.5 | AK4: =IF(AJ4="","",AJ4/$AJ$12) -> 0.19138347 | AL4: =IF(AK4="","",AI4-AK4) -> -0.19138347 | AN4: =AM4/$D$16 -> 0 | AO4: =$AO$12*BR4 -> 4995108.6 | AP4: =IF(AO4="","",AO4/$AO$12) -> 0.19138347 | AQ4: =IF(AP4="","",AN4-AP4) -> -0.19138347 | AS4: =AR4/$D$16 -> 0 | AT4: =$AT$12*BR4 -> 4956831.9 | AU4: =IF(AT4="","",AT4/$AT$12) -> 0.19138347 | AV4: =IF(AU4="","",AS4-AU4) -> -0.19138347 | AX4: =AW4/$D$16 -> 0 | AY4: =$AY$12*BR4 -> 5263045.5 | AZ4: =IF(AY4="","",AY4/$AY$12) -> 0.19138347 | BA4: =IF(AZ4="","",AX4-AZ4) -> -0.19138347 | BC4: =BB4/$D$16 -> 0 | BD4: =$BD$12*BR4 -> 5129077.1 | BE4: =IF(BD4="","",BD4/$BD$12) -> 0.19138347 | BF4: =IF(BE4="","",BC4-BE4) -> -0.19138347 | BH4: =BG4/$D$16 -> 0 | BI4: =$BI$12*BR4 -> 5760642.5 | BJ4: =IF(BI4="","",BI4/$BI$12) -> 0.19138347 | BK4: =IF(BJ4="","",BH4-BJ4) -> -0.19138347 | BL4: =SUM(D4,I4,N4,S4,X4,AC4,AH4,AM4,AR4,AW4,BB4,BG4) -> 8964388.6 | BM4: =BL4/$BL$16 -> 0.20152969 | BN4: =F4+K4+P4+U4+Z4+AE4+AJ4+AO4+AT4+AY4+BD4+BI4 -> 60165209 | BO4: =IF(BN4="","",BN4/$BN$16) -> 0.20349736 | BP4: =IF(BO4="","",BM4-BO4) -> -0.0019676709 | BQ4: 55862595 | BR4: =BQ4/$BQ$12 -> 0.19138347
A5: Vda_Cre | C5: Vendas - Crédito | D5: =SUMIF(EXTRATO!$F$14:$F$194,"Vda_CRE",EXTRATO!$I$14:$I$194) -> 8387984.4 | E5: =D5/$D$12 -> 0.33510237 | F5: =$F$12*BR5 -> 6786491.1 | G5: =IF(F5="","",F5/$F$12) -> 0.30202542 | H5: =IF(G5="","",E5-G5) -> 0.033076953 | I5: =SUMIF(EXTRATO!$F$14:$F$194,"Vda_CRE",EXTRATO!$J$14:$J$194) -> 6111541.4 | J5: =I5/$I$12 -> 0.27053193 | K5: =$K$12*BR5 -> 7158002.4 | L5: =IF(K5="","",K5/$K$12) -> 0.30202542 | M5: =IF(L5="","",J5-L5) -> -0.031493489 | O5: =IFERROR(N5/$N$16,"") | P5: =$P$12*BR5 -> 7550635.4 | Q5: =IF(P5="","",P5/$P$12) -> 0.30202542 | R5: =N5-P5 -> -7550635.4 | T5: =S5/$D$16 -> 0 | U5: =$U$12*BR5 -> 7852660.8 | V5: =IF(U5="","",U5/$U$12) -> 0.30202542 | W5: =IF(V5="","",T5-V5) -> -0.30202542 | Y5: =X5/$D$16 -> 0 | Z5: =$Z$12*BR5 -> 8154686.2 | AA5: =IF(Z5="","",Z5/$Z$12) -> 0.30202542 | AB5: =IF(AA5="","",Y5-AA5) -> -0.30202542 | AD5: =AC5/$D$16 -> 0 | AE5: =$AE$12*BR5 -> 7852660.8 | AF5: =IF(AE5="","",AE5/$AE$12) -> 0.30202542 | AG5: =IF(AF5="","",AD5-AF5) -> -0.30202542 | AI5: =AH5/$D$16 -> 0 | AJ5: =$AJ$12*BR5 -> 8396306.6 | AK5: =IF(AJ5="","",AJ5/$AJ$12) -> 0.30202542 | AL5: =IF(AK5="","",AI5-AK5) -> -0.30202542 | AN5: =AM5/$D$16 -> 0 | AO5: =$AO$12*BR5 -> 7882863.4 | AP5: =IF(AO5="","",AO5/$AO$12) -> 0.30202542 | AQ5: =IF(AP5="","",AN5-AP5) -> -0.30202542 | AS5: =AR5/$D$16 -> 0 | AT5: =$AT$12*BR5 -> 7822458.3 | AU5: =IF(AT5="","",AT5/$AT$12) -> 0.30202542 | AV5: =IF(AU5="","",AS5-AU5) -> -0.30202542 | AX5: =AW5/$D$16 -> 0 | AY5: =$AY$12*BR5 -> 8305699 | AZ5: =IF(AY5="","",AY5/$AY$12) -> 0.30202542 | BA5: =IF(AZ5="","",AX5-AZ5) -> -0.30202542 | BC5: =BB5/$D$16 -> 0 | BD5: =$BD$12*BR5 -> 8094281.2 | BE5: =IF(BD5="","",BD5/$BD$12) -> 0.30202542 | BF5: =IF(BE5="","",BC5-BE5) -> -0.30202542 | BH5: =BG5/$D$16 -> 0 | BI5: =$BI$12*BR5 -> 9090965 | BJ5: =IF(BI5="","",BI5/$BI$12) -> 0.30202542 | BK5: =IF(BJ5="","",BH5-BJ5) -> -0.30202542 | BL5: =SUM(D5,I5,N5,S5,X5,AC5,AH5,AM5,AR5,AW5,BB5,BG5) -> 14499526 | BM5: =BL5/$BL$16 -> 0.32596589 | BN5: =F5+K5+P5+U5+Z5+AE5+AJ5+AO5+AT5+AY5+BD5+BI5 -> 94947710 | BO5: =IF(BN5="","",BN5/$BN$16) -> 0.32114254 | BP5: =IF(BO5="","",BM5-BO5) -> 0.004823348 | BQ5: 88157684 | BR5: =BQ5/$BQ$12 -> 0.30202542
A6: Vda_Deb | C6: Vendas - Débito | D6: =SUMIF(EXTRATO!$F$14:$F$194,"Vda_DEB",EXTRATO!$I$14:$I$194) -> 5430450.8 | E6: =D6/$D$12 -> 0.21694806 | F6: =$F$12*BR6 -> 5323308.9 | G6: =IF(F6="","",F6/$F$12) -> 0.23690808 | H6: =IF(G6="","",E6-G6) -> -0.01996002 | I6: =SUMIF(EXTRATO!$F$14:$F$194,"Vda_DEB",EXTRATO!$J$14:$J$194) -> 5267023.6 | J6: =I6/$I$12 -> 0.23314872 | K6: =$K$12*BR6 -> 5614721.5 | L6: =IF(K6="","",K6/$K$12) -> 0.23690808 | M6: =IF(L6="","",J6-L6) -> -0.0037593616 | O6: =IFERROR(N6/$N$16,"") | P6: =$P$12*BR6 -> 5922702 | Q6: =IF(P6="","",P6/$P$12) -> 0.23690808 | R6: =N6-P6 -> -5922702 | T6: =S6/$D$16 -> 0 | U6: =$U$12*BR6 -> 6159610.1 | V6: =IF(U6="","",U6/$U$12) -> 0.23690808 | W6: =IF(V6="","",T6-V6) -> -0.23690808 | Y6: =X6/$D$16 -> 0 | Z6: =$Z$12*BR6 -> 6396518.2 | AA6: =IF(Z6="","",Z6/$Z$12) -> 0.23690808 | AB6: =IF(AA6="","",Y6-AA6) -> -0.23690808 | AD6: =AC6/$D$16 -> 0 | AE6: =$AE$12*BR6 -> 6159610.1 | AF6: =IF(AE6="","",AE6/$AE$12) -> 0.23690808 | AG6: =IF(AF6="","",AD6-AF6) -> -0.23690808 | AI6: =AH6/$D$16 -> 0 | AJ6: =$AJ$12*BR6 -> 6586044.6 | AK6: =IF(AJ6="","",AJ6/$AJ$12) -> 0.23690808 | AL6: =IF(AK6="","",AI6-AK6) -> -0.23690808 | AN6: =AM6/$D$16 -> 0 | AO6: =$AO$12*BR6 -> 6183300.9 | AP6: =IF(AO6="","",AO6/$AO$12) -> 0.23690808 | AQ6: =IF(AP6="","",AN6-AP6) -> -0.23690808 | AS6: =AR6/$D$16 -> 0 | AT6: =$AT$12*BR6 -> 6135919.3 | AU6: =IF(AT6="","",AT6/$AT$12) -> 0.23690808 | AV6: =IF(AU6="","",AS6-AU6) -> -0.23690808 | AX6: =AW6/$D$16 -> 0 | AY6: =$AY$12*BR6 -> 6514972.2 | AZ6: =IF(AY6="","",AY6/$AY$12) -> 0.23690808 | BA6: =IF(AZ6="","",AX6-AZ6) -> -0.23690808 | BC6: =BB6/$D$16 -> 0 | BD6: =$BD$12*BR6 -> 6349136.6 | BE6: =IF(BD6="","",BD6/$BD$12) -> 0.23690808 | BF6: =IF(BE6="","",BC6-BE6) -> -0.23690808 | BH6: =BG6/$D$16 -> 0 | BI6: =$BI$12*BR6 -> 7130933.2 | BJ6: =IF(BI6="","",BI6/$BI$12) -> 0.23690808 | BK6: =IF(BJ6="","",BH6-BJ6) -> -0.23690808 | BL6: =SUM(D6,I6,N6,S6,X6,AC6,AH6,AM6,AR6,AW6,BB6,BG6) -> 10697474 | BM6: =BL6/$BL$16 -> 0.24049144 | BN6: =F6+K6+P6+U6+Z6+AE6+AJ6+AO6+AT6+AY6+BD6+BI6 -> 74476778 | BO6: =IF(BN6="","",BN6/$BN$16) -> 0.25190351 | BP6: =IF(BO6="","",BM6-BO6) -> -0.011412076 | BQ6: 69150696 | BR6: =BQ6/$BQ$12 -> 0.23690808
A7: Vda_Cli | C7: Vendas - Clientes | D7: =SUMIF(EXTRATO!$F$14:$F$194,"Vda_CLI",EXTRATO!$I$14:$I$194) -> 311912.58 | E7: =D7/$D$12 -> 0.012460997 | F7: =$F$12*BR7 -> 271263.62 | G7: =IF(F7="","",F7/$F$12) -> 0.012072293 | H7: =IF(G7="","",E7-G7) -> 0.00038870402 | I7: =SUMIF(EXTRATO!$F$14:$F$194,"Vda_CLI",EXTRATO!$J$14:$J$194) -> 276494.3 | J7: =I7/$I$12 -> 0.012239226 | K7: =$K$12*BR7 -> 286113.33 | L7: =IF(K7="","",K7/$K$12) -> 0.012072293 | M7: =IF(L7="","",J7-L7) -> 0.0001669334 | O7: =IFERROR(N7/$N$16,"") | P7: =$P$12*BR7 -> 301807.31 | Q7: =IF(P7="","",P7/$P$12) -> 0.012072293 | R7: =N7-P7 -> -301807.31 | T7: =S7/$D$16 -> 0 | U7: =$U$12*BR7 -> 313879.61 | V7: =IF(U7="","",U7/$U$12) -> 0.012072293 | W7: =IF(V7="","",T7-V7) -> -0.012072293 | Y7: =X7/$D$16 -> 0 | Z7: =$Z$12*BR7 -> 325951.9 | AA7: =IF(Z7="","",Z7/$Z$12) -> 0.012072293 | AB7: =IF(AA7="","",Y7-AA7) -> -0.012072293 | AD7: =AC7/$D$16 -> 0 | AE7: =$AE$12*BR7 -> 313879.61 | AF7: =IF(AE7="","",AE7/$AE$12) -> 0.012072293 | AG7: =IF(AF7="","",AD7-AF7) -> -0.012072293 | AI7: =AH7/$D$16 -> 0 | AJ7: =$AJ$12*BR7 -> 335609.73 | AK7: =IF(AJ7="","",AJ7/$AJ$12) -> 0.012072293 | AL7: =IF(AK7="","",AI7-AK7) -> -0.012072293 | AN7: =AM7/$D$16 -> 0 | AO7: =$AO$12*BR7 -> 315086.84 | AP7: =IF(AO7="","",AO7/$AO$12) -> 0.012072293 | AQ7: =IF(AP7="","",AN7-AP7) -> -0.012072293 | AS7: =AR7/$D$16 -> 0 | AT7: =$AT$12*BR7 -> 312672.38 | AU7: =IF(AT7="","",AT7/$AT$12) -> 0.012072293 | AV7: =IF(AU7="","",AS7-AU7) -> -0.012072293 | AX7: =AW7/$D$16 -> 0 | AY7: =$AY$12*BR7 -> 331988.05 | AZ7: =IF(AY7="","",AY7/$AY$12) -> 0.012072293 | BA7: =IF(AZ7="","",AX7-AZ7) -> -0.012072293 | BC7: =BB7/$D$16 -> 0 | BD7: =$BD$12*BR7 -> 323537.44 | BE7: =IF(BD7="","",BD7/$BD$12) -> 0.012072293 | BF7: =IF(BE7="","",BC7-BE7) -> -0.012072293 | BH7: =BG7/$D$16 -> 0 | BI7: =$BI$12*BR7 -> 363376.01 | BJ7: =IF(BI7="","",BI7/$BI$12) -> 0.012072293 | BK7: =IF(BJ7="","",BH7-BJ7) -> -0.012072293 | BL7: =SUM(D7,I7,N7,S7,X7,AC7,AH7,AM7,AR7,AW7,BB7,BG7) -> 588406.88 | BM7: =BL7/$BL$16 -> 0.013228058 | BN7: =F7+K7+P7+U7+Z7+AE7+AJ7+AO7+AT7+AY7+BD7+BI7 -> 3795165.8 | BO7: =IF(BN7="","",BN7/$BN$16) -> 0.012836425 | BP7: =IF(BO7="","",BM7-BO7) -> 0.00039163295 | BQ7: 3523760.9 | BR7: =BQ7/$BQ$12 -> 0.012072293
A8: Vda_Pri | C8: Vendas - Private | D8: =SUMIF(EXTRATO!$F$14:$F$194,"Vda_pri",EXTRATO!$I$14:$I$194) -> 1877803.6 | E8: =D8/$D$12 -> 0.07501879 | F8: =$F$12*BR8 -> 1487355.7 | G8: =IF(F8="","",F8/$F$12) -> 0.06619315 | H8: =IF(G8="","",E8-G8) -> 0.0088256403 | I8: =SUMIF(EXTRATO!$F$14:$F$194,"Vda_pri",EXTRATO!$J$14:$J$194) -> 1773360.1 | J8: =I8/$I$12 -> 0.078499103 | K8: =$K$12*BR8 -> 1568777.6 | L8: =IF(K8="","",K8/$K$12) -> 0.06619315 | M8: =IF(L8="","",J8-L8) -> 0.012305953 | O8: =IFERROR(N8/$N$16,"") | P8: =$P$12*BR8 -> 1654828.7 | Q8: =IF(P8="","",P8/$P$12) -> 0.06619315 | R8: =N8-P8 -> -1654828.7 | T8: =S8/$D$16 -> 0 | U8: =$U$12*BR8 -> 1721021.9 | V8: =IF(U8="","",U8/$U$12) -> 0.06619315 | W8: =IF(V8="","",T8-V8) -> -0.06619315 | Y8: =X8/$D$16 -> 0 | Z8: =$Z$12*BR8 -> 1787215 | AA8: =IF(Z8="","",Z8/$Z$12) -> 0.06619315 | AB8: =IF(AA8="","",Y8-AA8) -> -0.06619315 | AD8: =AC8/$D$16 -> 0 | AE8: =$AE$12*BR8 -> 1721021.9 | AF8: =IF(AE8="","",AE8/$AE$12) -> 0.06619315 | AG8: =IF(AF8="","",AD8-AF8) -> -0.06619315 | AI8: =AH8/$D$16 -> 0 | AJ8: =$AJ$12*BR8 -> 1840169.6 | AK8: =IF(AJ8="","",AJ8/$AJ$12) -> 0.06619315 | AL8: =IF(AK8="","",AI8-AK8) -> -0.06619315 | AN8: =AM8/$D$16 -> 0 | AO8: =$AO$12*BR8 -> 1727641.2 | AP8: =IF(AO8="","",AO8/$AO$12) -> 0.06619315 | AQ8: =IF(AP8="","",AN8-AP8) -> -0.06619315 | AS8: =AR8/$D$16 -> 0 | AT8: =$AT$12*BR8 -> 1714402.6 | AU8: =IF(AT8="","",AT8/$AT$12) -> 0.06619315 | AV8: =IF(AU8="","",AS8-AU8) -> -0.06619315 | AX8: =AW8/$D$16 -> 0 | AY8: =$AY$12*BR8 -> 1820311.6 | AZ8: =IF(AY8="","",AY8/$AY$12) -> 0.06619315 | BA8: =IF(AZ8="","",AX8-AZ8) -> -0.06619315 | BC8: =BB8/$D$16 -> 0 | BD8: =$BD$12*BR8 -> 1773976.4 | BE8: =IF(BD8="","",BD8/$BD$12) -> 0.06619315 | BF8: =IF(BE8="","",BC8-BE8) -> -0.06619315 | BH8: =BG8/$D$16 -> 0 | BI8: =$BI$12*BR8 -> 1992413.8 | BJ8: =IF(BI8="","",BI8/$BI$12) -> 0.06619315 | BK8: =IF(BJ8="","",BH8-BJ8) -> -0.06619315 | BL8: =SUM(D8,I8,N8,S8,X8,AC8,AH8,AM8,AR8,AW8,BB8,BG8) -> 3651163.7 | BM8: =BL8/$BL$16 -> 0.082082327 | BN8: =F8+K8+P8+U8+Z8+AE8+AJ8+AO8+AT8+AY8+BD8+BI8 -> 20809136 | BO8: =IF(BN8="","",BN8/$BN$16) -> 0.070382939 | BP8: =IF(BO8="","",BM8-BO8) -> 0.011699389 | BQ8: 19321006 | BR8: =BQ8/$BQ$12 -> 0.06619315
A9: Vda_Pix | C9: Vendas - Pix | D9: =SUMIF(EXTRATO!$F$14:$F$194,"Vda_PIX",EXTRATO!$I$14:$I$194) -> 4357122.2 | E9: =D9/$D$12 -> 0.17406827 | F9: =$F$12*BR9 -> 4160152.3 | G9: =IF(F9="","",F9/$F$12) -> 0.18514306 | H9: =IF(G9="","",E9-G9) -> -0.011074787 | I9: =SUMIF(EXTRATO!$F$14:$F$194,"Vda_PIX",EXTRATO!$J$14:$J$194) -> 4610181.1 | J9: =I9/$I$12 -> 0.2040731 | K9: =$K$12*BR9 -> 4387890.6 | L9: =IF(K9="","",K9/$K$12) -> 0.18514306 | M9: =IF(L9="","",J9-L9) -> 0.018930037 | O9: =IFERROR(N9/$N$16,"") | P9: =$P$12*BR9 -> 4628576.5 | Q9: =IF(P9="","",P9/$P$12) -> 0.18514306 | R9: =N9-P9 -> -4628576.5 | T9: =S9/$D$16 -> 0 | U9: =$U$12*BR9 -> 4813719.6 | V9: =IF(U9="","",U9/$U$12) -> 0.18514306 | W9: =IF(V9="","",T9-V9) -> -0.18514306 | Y9: =X9/$D$16 -> 0 | Z9: =$Z$12*BR9 -> 4998862.7 | AA9: =IF(Z9="","",Z9/$Z$12) -> 0.18514306 | AB9: =IF(AA9="","",Y9-AA9) -> -0.18514306 | AD9: =AC9/$D$16 -> 0 | AE9: =$AE$12*BR9 -> 4813719.6 | AF9: =IF(AE9="","",AE9/$AE$12) -> 0.18514306 | AG9: =IF(AF9="","",AD9-AF9) -> -0.18514306 | AI9: =AH9/$D$16 -> 0 | AJ9: =$AJ$12*BR9 -> 5146977.1 | AK9: =IF(AJ9="","",AJ9/$AJ$12) -> 0.18514306 | AL9: =IF(AK9="","",AI9-AK9) -> -0.18514306 | AN9: =AM9/$D$16 -> 0 | AO9: =$AO$12*BR9 -> 4832233.9 | AP9: =IF(AO9="","",AO9/$AO$12) -> 0.18514306 | AQ9: =IF(AP9="","",AN9-AP9) -> -0.18514306 | AS9: =AR9/$D$16 -> 0 | AT9: =$AT$12*BR9 -> 4795205.3 | AU9: =IF(AT9="","",AT9/$AT$12) -> 0.18514306 | AV9: =IF(AU9="","",AS9-AU9) -> -0.18514306 | AX9: =AW9/$D$16 -> 0 | AY9: =$AY$12*BR9 -> 5091434.2 | AZ9: =IF(AY9="","",AY9/$AY$12) -> 0.18514306 | BA9: =IF(AZ9="","",AX9-AZ9) -> -0.18514306 | BC9: =BB9/$D$16 -> 0 | BD9: =$BD$12*BR9 -> 4961834 | BE9: =IF(BD9="","",BD9/$BD$12) -> 0.18514306 | BF9: =IF(BE9="","",BC9-BE9) -> -0.18514306 | BH9: =BG9/$D$16 -> 0 | BI9: =$BI$12*BR9 -> 5572806.1 | BJ9: =IF(BI9="","",BI9/$BI$12) -> 0.18514306 | BK9: =IF(BJ9="","",BH9-BJ9) -> -0.18514306 | BL9: =SUM(D9,I9,N9,S9,X9,AC9,AH9,AM9,AR9,AW9,BB9,BG9) -> 8967303.3 | BM9: =BL9/$BL$16 -> 0.20159521 | BN9: =F9+K9+P9+U9+Z9+AE9+AJ9+AO9+AT9+AY9+BD9+BI9 -> 58203412 | BO9: =IF(BN9="","",BN9/$BN$16) -> 0.19686195 | BP9: =IF(BO9="","",BM9-BO9) -> 0.004733261 | BQ9: 54041092 | BR9: =BQ9/$BQ$12 -> 0.18514306
A10: Vda_Che | B10: Vda_Che_S | C10: Vendas - Cheques | D10: =SUMIF(EXTRATO!$F$14:$F$194,"Vda_Che",EXTRATO!$I$14:$I$194)-SUMIF(EXTRATO!$F$14:$F$194,"Vda_Che_S",EXTRATO!$I$14:$I$194) -> 110104.36 | E10: =D10/$D$12 -> 0.0043987006 | F10: =$F$12*BR10 -> 136244.35 | G10: =IF(F10="","",F10/$F$12) -> 0.0060634067 | H10: =IF(G10="","",E10-G10) -> -0.0016647061 | I10: =SUMIF(EXTRATO!$F$14:$F$194,"Vda_Che",EXTRATO!$J$14:$J$194)-SUMIF(EXTRATO!$F$14:$F$194,"Vda_Che_S",EXTRATO!$J$14:$J$194) -> 123887.88 | J10: =I10/$I$12 -> 0.0054839892 | K10: =$K$12*BR10 -> 143702.74 | L10: =IF(K10="","",K10/$K$12) -> 0.0060634067 | M10: =IF(L10="","",J10-L10) -> -0.00057941752 | O10: =IFERROR(N10/$N$16,"") | P10: =$P$12*BR10 -> 151585.17 | Q10: =IF(P10="","",P10/$P$12) -> 0.0060634067 | R10: =N10-P10 -> -151585.17 | T10: =S10/$D$16 -> 0 | U10: =$U$12*BR10 -> 157648.58 | V10: =IF(U10="","",U10/$U$12) -> 0.0060634067 | W10: =IF(V10="","",T10-V10) -> -0.0060634067 | Y10: =X10/$D$16 -> 0 | Z10: =$Z$12*BR10 -> 163711.98 | AA10: =IF(Z10="","",Z10/$Z$12) -> 0.0060634067 | AB10: =IF(AA10="","",Y10-AA10) -> -0.0060634067 | AD10: =AC10/$D$16 -> 0 | AE10: =$AE$12*BR10 -> 157648.58 | AF10: =IF(AE10="","",AE10/$AE$12) -> 0.0060634067 | AG10: =IF(AF10="","",AD10-AF10) -> -0.0060634067 | AI10: =AH10/$D$16 -> 0 | AJ10: =$AJ$12*BR10 -> 168562.71 | AK10: =IF(AJ10="","",AJ10/$AJ$12) -> 0.0060634067 | AL10: =IF(AK10="","",AI10-AK10) -> -0.0060634067 | AN10: =AM10/$D$16 -> 0 | AO10: =$AO$12*BR10 -> 158254.92 | AP10: =IF(AO10="","",AO10/$AO$12) -> 0.0060634067 | AQ10: =IF(AP10="","",AN10-AP10) -> -0.0060634067 | AS10: =AR10/$D$16 -> 0 | AT10: =$AT$12*BR10 -> 157042.23 | AU10: =IF(AT10="","",AT10/$AT$12) -> 0.0060634067 | AV10: =IF(AU10="","",AS10-AU10) -> -0.0060634067 | AX10: =AW10/$D$16 -> 0 | AY10: =$AY$12*BR10 -> 166743.69 | AZ10: =IF(AY10="","",AY10/$AY$12) -> 0.0060634067 | BA10: =IF(AZ10="","",AX10-AZ10) -> -0.0060634067 | BC10: =BB10/$D$16 -> 0 | BD10: =$BD$12*BR10 -> 162499.3 | BE10: =IF(BD10="","",BD10/$BD$12) -> 0.0060634067 | BF10: =IF(BE10="","",BC10-BE10) -> -0.0060634067 | BH10: =BG10/$D$16 -> 0 | BI10: =$BI$12*BR10 -> 182508.54 | BJ10: =IF(BI10="","",BI10/$BI$12) -> 0.0060634067 | BK10: =IF(BJ10="","",BH10-BJ10) -> -0.0060634067 | BL10: =SUM(D10,I10,N10,S10,X10,AC10,AH10,AM10,AR10,AW10,BB10,BG10) -> 233992.24 | BM10: =BL10/$BL$16 -> 0.0052604127 | BN10: =F10+K10+P10+U10+Z10+AE10+AJ10+AO10+AT10+AY10+BD10+BI10 -> 1906152.8 | BO10: =IF(BN10="","",BN10/$BN$16) -> 0.0064471987 | BP10: =IF(BO10="","",BM10-BO10) -> -0.001186786 | BQ10: 1769837.4 | BR10: =BQ10/$BQ$12 -> 0.0060634067
A11: Vda_Dly | C11: Vendas - Delivery | D11: =SUMIF(EXTRATO!$F$14:$F$194,"Vda_DLY",EXTRATO!$I$14:$I$194) -> 9719.78 | E11: =D11/$D$12 -> 0.00038830799 | F11: =$F$12*BR11 -> 4743.8681 | G11: =IF(F11="","",F11/$F$12) -> 0.0002111207 | H11: =IF(G11="","",E11-G11) -> 0.00017718729 | I11: =SUMIF(EXTRATO!$F$14:$F$194,"Vda_DLY",EXTRATO!$J$14:$J$194) -> 9967.89 | J11: =I11/$I$12 -> 0.00044123607 | K11: =$K$12*BR11 -> 5003.5605 | L11: =IF(K11="","",K11/$K$12) -> 0.0002111207 | M11: =IF(L11="","",J11-L11) -> 0.00023011537 | O11: =IFERROR(N11/$N$16,"") | P11: =$P$12*BR11 -> 5278.0174 | Q11: =IF(P11="","",P11/$P$12) -> 0.0002111207 | R11: =N11-P11 -> -5278.0174 | T11: =S11/$D$16 -> 0 | U11: =$U$12*BR11 -> 5489.1381 | V11: =IF(U11="","",U11/$U$12) -> 0.0002111207 | W11: =IF(V11="","",T11-V11) -> -0.0002111207 | Y11: =X11/$D$16 -> 0 | Z11: =$Z$12*BR11 -> 5700.2588 | AA11: =IF(Z11="","",Z11/$Z$12) -> 0.0002111207 | AB11: =IF(AA11="","",Y11-AA11) -> -0.0002111207 | AD11: =AC11/$D$16 -> 0 | AE11: =$AE$12*BR11 -> 5489.1381 | AF11: =IF(AE11="","",AE11/$AE$12) -> 0.0002111207 | AG11: =IF(AF11="","",AD11-AF11) -> -0.0002111207 | AI11: =AH11/$D$16 -> 0 | AJ11: =$AJ$12*BR11 -> 5869.1554 | AK11: =IF(AJ11="","",AJ11/$AJ$12) -> 0.0002111207 | AL11: =IF(AK11="","",AI11-AK11) -> -0.0002111207 | AN11: =AM11/$D$16 -> 0 | AO11: =$AO$12*BR11 -> 5510.2502 | AP11: =IF(AO11="","",AO11/$AO$12) -> 0.0002111207 | AQ11: =IF(AP11="","",AN11-AP11) -> -0.0002111207 | AS11: =AR11/$D$16 -> 0 | AT11: =$AT$12*BR11 -> 5468.026 | AU11: =IF(AT11="","",AT11/$AT$12) -> 0.0002111207 | AV11: =IF(AU11="","",AS11-AU11) -> -0.0002111207 | AX11: =AW11/$D$16 -> 0 | AY11: =$AY$12*BR11 -> 5805.8192 | AZ11: =IF(AY11="","",AY11/$AY$12) -> 0.0002111207 | BA11: =IF(AZ11="","",AX11-AZ11) -> -0.0002111207 | BC11: =BB11/$D$16 -> 0 | BD11: =$BD$12*BR11 -> 5658.0347 | BE11: =IF(BD11="","",BD11/$BD$12) -> 0.0002111207 | BF11: =IF(BE11="","",BC11-BE11) -> -0.0002111207 | BH11: =BG11/$D$16 -> 0 | BI11: =$BI$12*BR11 -> 6354.733 | BJ11: =IF(BI11="","",BI11/$BI$12) -> 0.0002111207 | BK11: =IF(BJ11="","",BH11-BJ11) -> -0.0002111207 | BL11: =SUM(D11,I11,N11,S11,X11,AC11,AH11,AM11,AR11,AW11,BB11,BG11) -> 19687.67 | BM11: =BL11/$BL$16 -> 0.0004426013 | BN11: =F11+K11+P11+U11+Z11+AE11+AJ11+AO11+AT11+AY11+BD11+BI11 -> 66369.999 | BO11: =IF(BN11="","",BN11/$BN$16) -> 0.00022448388 | BP11: =IF(BO11="","",BM11-BO11) -> 0.00021811742 | BQ11: 61623.66 | BR11: =BQ11/$BQ$12 -> 0.0002111207
C12: Vendas - Totais | D12: =SUM(D4:D11) -> 25031110 | E12: =SUM(E4:E11) -> 1 | F12: 22469934 | G12: =SUM(G4:G11) -> 1 | H12: =IF(G12="","",E12-G12) -> 2.220446e-16 | I12: =SUM(I4:I11) -> 22590832 | J12: =SUM(J4:J11) -> 1 | K12: 23700000 | L12: =SUM(L4:L11) -> 1 | M12: =IF(L12="","",J12-L12) -> -1.110223e-16 | N12: =SUM(N4:N11) -> 0 | O12: =IFERROR(SUM(O4:O11),"") -> 0 | P12: 25000000 | Q12: =SUM(Q4:Q11) -> 1 | R12: =N12-P12 -> -25000000 | S12: =SUM(S4:S11) -> 0 | T12: =SUM(T4:T11) -> 0 | U12: 26000000 | V12: =SUM(V4:V11) -> 1 | W12: =IF(V12="","",T12-V12) -> -1 | X12: =SUM(X4:X11) -> 0 | Y12: =SUM(Y4:Y11) -> 0 | Z12: 27000000 | AA12: =SUM(AA4:AA11) -> 1 | AB12: =IF(AA12="","",Y12-AA12) -> -1 | AC12: =SUM(AC4:AC11) -> 0 | AD12: =SUM(AD4:AD11) -> 0 | AE12: 26000000 | AF12: =SUM(AF4:AF11) -> 1 | AG12: =IF(AF12="","",AD12-AF12) -> -1 | AH12: =SUM(AH4:AH11) -> 0 | AI12: =SUM(AI4:AI11) -> 0 | AJ12: 27800000 | AK12: =SUM(AK4:AK11) -> 1 | AL12: =IF(AK12="","",AI12-AK12) -> -1 | AM12: =SUM(AM4:AM11) -> 0 | AN12: =SUM(AN4:AN11) -> 0 | AO12: 26100000 | AP12: =SUM(AP4:AP11) -> 1 | AQ12: =IF(AP12="","",AN12-AP12) -> -1 | AR12: =SUM(AR4:AR11) -> 0 | AS12: =SUM(AS4:AS11) -> 0 | AT12: 25900000 | AU12: =SUM(AU4:AU11) -> 1 | AV12: =IF(AU12="","",AS12-AU12) -> -1 | AW12: =SUM(AW4:AW11) -> 0 | AX12: =SUM(AX4:AX11) -> 0 | AY12: 27500000 | AZ12: =SUM(AZ4:AZ11) -> 1 | BA12: =IF(AZ12="","",AX12-AZ12) -> -1 | BB12: =SUM(BB4:BB11) -> 0 | BC12: =SUM(BC4:BC11) -> 0 | BD12: 26800000 | BE12: =SUM(BE4:BE11) -> 1 | BF12: =IF(BE12="","",BC12-BE12) -> -1 | BG12: =SUM(BG4:BG11) -> 0 | BH12: =SUM(BH4:BH11) -> 0 | BI12: 30100000 | BJ12: =SUM(BJ4:BJ11) -> 1 | BK12: =IF(BJ12="","",BH12-BJ12) -> -1 | BL12: =SUM(BL4:BL11) -> 47621942 | BM12: =SUM(BM4:BM11) -> 1.0705956 | BN12: =F12+K12+P12+U12+Z12+AE12+AJ12+AO12+AT12+AY12+BD12+BI12 -> 3.1436993e+08 | BO12: =IF(BN12="","",SUM(BO4:BO11)) -> 1.0632964 | BP12: =IF(BO12="","",BM12-BO12) -> 0.007299215 | BQ12: =SUM(BQ4:BQ11) -> 2.9188829e+08 | BR12: =SUM(BR4:BR11) -> 1
A13: Trocas | C13: ( - ) Devolução de Vendas | D13: =SUMIF(EXTRATO!$F$14:$F$194,"Trocas",EXTRATO!$I$14:$I$194) -> 8489.33 | E13: =D13/$D$12 -> 0.00033915116 | F13: =$F$12*BR13 -> 18161.648 | G13: =IF(F13="","",F13/$F$12) -> 0.00080826441 | H13: =IF(G13="","",E13-G13) -> -0.00046911325 | I13: =SUMIF(EXTRATO!$F$14:$F$194,"Trocas",EXTRATO!$J$14:$J$194) -> 6435.62 | J13: =I13/$I$12 -> 0.00028487751 | K13: =$K$12*BR13 -> 19155.867 | L13: =IF(K13="","",K13/$K$12) -> 0.00080826441 | M13: =IF(L13="","",J13-L13) -> -0.0005233869 | O13: =IFERROR(N13/$N$16,"") | P13: =$P$12*BR13 -> 20206.61 | Q13: =IF(P13="","",P13/$P$12) -> 0.00080826441 | R13: =N13-P13 -> -20206.61 | T13: =S13/$D$16 -> 0 | U13: =$U$12*BR13 -> 21014.875 | V13: =IF(U13="","",U13/$U$12) -> 0.00080826441 | W13: =IF(V13="","",T13-V13) -> -0.00080826441 | Y13: =X13/$D$16 -> 0 | Z13: =$Z$12*BR13 -> 21823.139 | AA13: =IF(Z13="","",Z13/$Z$12) -> 0.00080826441 | AB13: =IF(AA13="","",Y13-AA13) -> -0.00080826441 | AD13: =AC13/$D$16 -> 0 | AE13: =$AE$12*BR13 -> 21014.875 | AF13: =IF(AE13="","",AE13/$AE$12) -> 0.00080826441 | AG13: =IF(AF13="","",AD13-AF13) -> -0.00080826441 | AI13: =AH13/$D$16 -> 0 | AJ13: =$AJ$12*BR13 -> 22469.751 | AK13: =IF(AJ13="","",AJ13/$AJ$12) -> 0.00080826441 | AL13: =IF(AK13="","",AI13-AK13) -> -0.00080826441 | AN13: =AM13/$D$16 -> 0 | AO13: =$AO$12*BR13 -> 21095.701 | AP13: =IF(AO13="","",AO13/$AO$12) -> 0.00080826441 | AQ13: =IF(AP13="","",AN13-AP13) -> -0.00080826441 | AS13: =AR13/$D$16 -> 0 | AT13: =$AT$12*BR13 -> 20934.048 | AU13: =IF(AT13="","",AT13/$AT$12) -> 0.00080826441 | AV13: =IF(AU13="","",AS13-AU13) -> -0.00080826441 | AX13: =AW13/$D$16 -> 0 | AY13: =$AY$12*BR13 -> 22227.271 | AZ13: =IF(AY13="","",AY13/$AY$12) -> 0.00080826441 | BA13: =IF(AZ13="","",AX13-AZ13) -> -0.00080826441 | BC13: =BB13/$D$16 -> 0 | BD13: =$BD$12*BR13 -> 21661.486 | BE13: =IF(BD13="","",BD13/$BD$12) -> 0.00080826441 | BF13: =IF(BE13="","",BC13-BE13) -> -0.00080826441 | BH13: =BG13/$D$16 -> 0 | BI13: =$BI$12*BR13 -> 24328.759 | BJ13: =IF(BI13="","",BI13/$BI$12) -> 0.00080826441 | BK13: =IF(BJ13="","",BH13-BJ13) -> -0.00080826441 | BL13: =SUM(D13,I13,N13,S13,X13,AC13,AH13,AM13,AR13,AW13,BB13,BG13) -> 14924.95 | BM13: =BL13/$BL$16 -> 0.00033552991 | BN13: =F13+K13+P13+U13+Z13+AE13+AJ13+AO13+AT13+AY13+BD13+BI13 -> 254094.03 | BO13: =IF(BN13="","",BN13/$BN$16) -> 0.00085942465 | BP13: =IF(BO13="","",BM13-BO13) -> -0.00052389474 | BQ13: 235922.92 | BR13: =BQ13/$BQ$12 -> 0.00080826441
A14: Vda_S | C14: ( - ) Extra - Caixa | D14: =SUMIF(EXTRATO!$F$14:$F$194,"Vda_s",EXTRATO!$I$14:$I$194) -> 103291.45 | E14: =D14/$D$12 -> 0.0041265229 | F14: =$F$12*BR14 -> 103928.51 | G14: =IF(F14="","",F14/$F$12) -> 0.0046252257 | H14: =IF(G14="","",E14-G14) -> -0.00049870275 | I14: =SUMIF(EXTRATO!$F$14:$F$194,"Vda_s",EXTRATO!$J$14:$J$194) -> 50270.76 | J14: =I14/$I$12 -> 0.0022252726 | K14: =$K$12*BR14 -> 109617.85 | L14: =IF(K14="","",K14/$K$12) -> 0.0046252257 | M14: =IF(L14="","",J14-L14) -> -0.0023999531 | O14: =IFERROR(N14/$N$16,"") | P14: =$P$12*BR14 -> 115630.64 | Q14: =IF(P14="","",P14/$P$12) -> 0.0046252257 | R14: =N14-P14 -> -115630.64 | T14: =S14/$D$16 -> 0 | U14: =$U$12*BR14 -> 120255.87 | V14: =IF(U14="","",U14/$U$12) -> 0.0046252257 | W14: =IF(V14="","",T14-V14) -> -0.0046252257 | Y14: =X14/$D$16 -> 0 | Z14: =$Z$12*BR14 -> 124881.09 | AA14: =IF(Z14="","",Z14/$Z$12) -> 0.0046252257 | AB14: =IF(AA14="","",Y14-AA14) -> -0.0046252257 | AD14: =AC14/$D$16 -> 0 | AE14: =$AE$12*BR14 -> 120255.87 | AF14: =IF(AE14="","",AE14/$AE$12) -> 0.0046252257 | AG14: =IF(AF14="","",AD14-AF14) -> -0.0046252257 | AI14: =AH14/$D$16 -> 0 | AJ14: =$AJ$12*BR14 -> 128581.27 | AK14: =IF(AJ14="","",AJ14/$AJ$12) -> 0.0046252257 | AL14: =IF(AK14="","",AI14-AK14) -> -0.0046252257 | AN14: =AM14/$D$16 -> 0 | AO14: =$AO$12*BR14 -> 120718.39 | AP14: =IF(AO14="","",AO14/$AO$12) -> 0.0046252257 | AQ14: =IF(AP14="","",AN14-AP14) -> -0.0046252257 | AS14: =AR14/$D$16 -> 0 | AT14: =$AT$12*BR14 -> 119793.34 | AU14: =IF(AT14="","",AT14/$AT$12) -> 0.0046252257 | AV14: =IF(AU14="","",AS14-AU14) -> -0.0046252257 | AX14: =AW14/$D$16 -> 0 | AY14: =$AY$12*BR14 -> 127193.71 | AZ14: =IF(AY14="","",AY14/$AY$12) -> 0.0046252257 | BA14: =IF(AZ14="","",AX14-AZ14) -> -0.0046252257 | BC14: =BB14/$D$16 -> 0 | BD14: =$BD$12*BR14 -> 123956.05 | BE14: =IF(BD14="","",BD14/$BD$12) -> 0.0046252257 | BF14: =IF(BE14="","",BC14-BE14) -> -0.0046252257 | BH14: =BG14/$D$16 -> 0 | BI14: =$BI$12*BR14 -> 139219.29 | BJ14: =IF(BI14="","",BI14/$BI$12) -> 0.0046252257 | BK14: =IF(BJ14="","",BH14-BJ14) -> -0.0046252257 | BL14: =SUM(D14,I14,N14,S14,X14,AC14,AH14,AM14,AR14,AW14,BB14,BG14) -> 153562.21 | BM14: =BL14/$BL$16 -> 0.0034522538 | BN14: =F14+K14+P14+U14+Z14+AE14+AJ14+AO14+AT14+AY14+BD14+BI14 -> 1454031.9 | BO14: =IF(BN14="","",BN14/$BN$16) -> 0.0049179859 | BP14: =IF(BO14="","",BM14-BO14) -> -0.0014657321 | BQ14: 1350049.2 | BR14: =BQ14/$BQ$12 -> 0.0046252257
A15: Vda_Pri_S | C15: ( - ) Repasse Private | D15: =SUMIF(EXTRATO!$F$14:$F$194,"Vda_pri_S",EXTRATO!$I$14:$I$194) -> 1532944 | E15: =D15/$D$12 -> 0.06124155 | F15: =$F$12*BR15 -> 1215510.8 | G15: =IF(F15="","",F15/$F$12) -> 0.054094987 | H15: =IF(G15="","",E15-G15) -> 0.0071465628 | I15: =SUMIF(EXTRATO!$F$14:$F$194,"Vda_pri_S",EXTRATO!$J$14:$J$194) -> 1438784.4 | J15: =I15/$I$12 -> 0.063688865 | K15: =$K$12*BR15 -> 1282051.2 | L15: =IF(K15="","",K15/$K$12) -> 0.054094987 | M15: =IF(L15="","",J15-L15) -> 0.0095938774 | O15: =IFERROR(N15/$N$16,"") | P15: =$P$12*BR15 -> 1352374.7 | Q15: =IF(P15="","",P15/$P$12) -> 0.054094987 | R15: =N15-P15 -> -1352374.7 | T15: =S15/$D$16 -> 0 | U15: =$U$12*BR15 -> 1406469.7 | V15: =IF(U15="","",U15/$U$12) -> 0.054094987 | W15: =IF(V15="","",T15-V15) -> -0.054094987 | Y15: =X15/$D$16 -> 0 | Z15: =$Z$12*BR15 -> 1460564.7 | AA15: =IF(Z15="","",Z15/$Z$12) -> 0.054094987 | AB15: =IF(AA15="","",Y15-AA15) -> -0.054094987 | AD15: =AC15/$D$16 -> 0 | AE15: =$AE$12*BR15 -> 1406469.7 | AF15: =IF(AE15="","",AE15/$AE$12) -> 0.054094987 | AG15: =IF(AF15="","",AD15-AF15) -> -0.054094987 | AI15: =AH15/$D$16 -> 0 | AJ15: =$AJ$12*BR15 -> 1503840.6 | AK15: =IF(AJ15="","",AJ15/$AJ$12) -> 0.054094987 | AL15: =IF(AK15="","",AI15-AK15) -> -0.054094987 | AN15: =AM15/$D$16 -> 0 | AO15: =$AO$12*BR15 -> 1411879.2 | AP15: =IF(AO15="","",AO15/$AO$12) -> 0.054094987 | AQ15: =IF(AP15="","",AN15-AP15) -> -0.054094987 | AS15: =AR15/$D$16 -> 0 | AT15: =$AT$12*BR15 -> 1401060.2 | AU15: =IF(AT15="","",AT15/$AT$12) -> 0.054094987 | AV15: =IF(AU15="","",AS15-AU15) -> -0.054094987 | AX15: =AW15/$D$16 -> 0 | AY15: =$AY$12*BR15 -> 1487612.1 | AZ15: =IF(AY15="","",AY15/$AY$12) -> 0.054094987 | BA15: =IF(AZ15="","",AX15-AZ15) -> -0.054094987 | BC15: =BB15/$D$16 -> 0 | BD15: =$BD$12*BR15 -> 1449745.7 | BE15: =IF(BD15="","",BD15/$BD$12) -> 0.054094987 | BF15: =IF(BE15="","",BC15-BE15) -> -0.054094987 | BH15: =BG15/$D$16 -> 0 | BI15: =$BI$12*BR15 -> 1628259.1 | BJ15: =IF(BI15="","",BI15/$BI$12) -> 0.054094987 | BK15: =IF(BJ15="","",BH15-BJ15) -> -0.054094987 | BL15: =SUM(D15,I15,N15,S15,X15,AC15,AH15,AM15,AR15,AW15,BB15,BG15) -> 2971728.4 | BM15: =BL15/$BL$16 -> 0.066807848 | BN15: =F15+K15+P15+U15+Z15+AE15+AJ15+AO15+AT15+AY15+BD15+BI15 -> 17005838 | BO15: =IF(BN15="","",BN15/$BN$16) -> 0.057519006 | BP15: =IF(BO15="","",BM15-BO15) -> 0.0092888419 | BQ15: 15789694 | BR15: =BQ15/$BQ$12 -> 0.054094987
C16: ( = ) Vendas Líquidas Recebidas | D16: =D12-D13-D14-D15 -> 23386386 | E16: 1 | F16: =F12-F13-F14-F15 -> 21132333 | G16: 1 | H16: =IF(G16="","",E16-G16) -> 0 | I16: =I12-I13-I14-I15 -> 21095341 | J16: 1 | K16: =K12-K13-K14-K15 -> 22289175 | L16: =IF(K16="","",K16/$K$16) -> 1 | M16: =IF(L16="","",J16-L16) -> 0 | N16: =N12-N13-N14-N15 -> 0 | O16: =IFERROR(SUM(O4:O11)-O14-O15,"") | P16: =P12-P13-P14-P15 -> 23511788 | Q16: =IF(P16="","",P16/$P$16) -> 1 | R16: =N16-P16 -> -23511788 | S16: =S12-S13-S14-S15 -> 0 | T16: =SUM(T4:T11)-T14-T15 -> 0 | U16: =U12-U13-U14-U15 -> 24452260 | V16: =IF(U16="","",U16/$U$16) -> 1 | W16: =IF(V16="","",T16-V16) -> -1 | X16: =X12-X13-X14-X15 -> 0 | Y16: =SUM(Y4:Y11)-Y14-Y15 -> 0 | Z16: =Z12-Z13-Z14-Z15 -> 25392731 | AA16: =IF(Z16="","",Z16/$Z$16) -> 1 | AB16: =IF(AA16="","",Y16-AA16) -> -1 | AC16: =AC12-AC13-AC14-AC15 -> 0 | AD16: =SUM(AD4:AD11)-AD14-AD15 -> 0 | AE16: =AE12-AE13-AE14-AE15 -> 24452260 | AF16: =IF(AE16="","",AE16/$AE$16) -> 1 | AG16: =IF(AF16="","",AD16-AF16) -> -1 | AH16: =AH12-AH13-AH14-AH15 -> 0 | AI16: =SUM(AI4:AI11)-AI14-AI15 -> 0 | AJ16: =AJ12-AJ13-AJ14-AJ15 -> 26145108 | AK16: =IF(AJ16="","",AJ16/$AJ$16) -> 1 | AL16: =IF(AK16="","",AI16-AK16) -> -1 | AM16: =AM12-AM13-AM14-AM15 -> 0 | AN16: =SUM(AN4:AN11)-AN14-AN15 -> 0 | AO16: =AO12-AO13-AO14-AO15 -> 24546307 | AP16: =IF(AO16="","",AO16/$AO$16) -> 1 | AQ16: =IF(AP16="","",AN16-AP16) -> -1 | AR16: =AR12-AR13-AR14-AR15 -> 0 | AS16: =SUM(AS4:AS11)-AS14-AS15 -> 0 | AT16: =AT12-AT13-AT14-AT15 -> 24358212 | AU16: =IF(AT16="","",AT16/$AT$16) -> 1 | AV16: =IF(AU16="","",AS16-AU16) -> -1 | AW16: =AW12-AW13-AW14-AW15 -> 0 | AX16: =SUM(AX4:AX11)-AX14-AX15 -> 0 | AY16: =AY12-AY13-AY14-AY15 -> 25862967 | AZ16: =IF(AY16="","",AY16/$AY$16) -> 1 | BA16: =IF(AZ16="","",AX16-AZ16) -> -1 | BB16: =BB12-BB13-BB14-BB15 -> 0 | BC16: =SUM(BC4:BC11)-BC14-BC15 -> 0 | BD16: =BD12-BD13-BD14-BD15 -> 25204637 | BE16: =IF(BD16="","",BD16/$BD$16) -> 1 | BF16: =IF(BE16="","",BC16-BE16) -> -1 | BG16: =BG12-BG13-BG14-BG15 -> 0 | BH16: =SUM(BH4:BH11)-BH14-BH15 -> 0 | BI16: =BI12-BI13-BI14-BI15 -> 28308193 | BJ16: =IF(BI16="","",BI16/$BI$16) -> 1 | BK16: =IF(BJ16="","",BH16-BJ16) -> -1 | BL16: =BL12-BL13-BL14-BL15 -> 44481727 | BM16: =SUM(BM4:BM11)-BM14-BM15 -> 1.0003355 | BN16: =F16+K16+P16+U16+Z16+AE16+AJ16+AO16+AT16+AY16+BD16+BI16 -> 2.9565597e+08 | BO16: =IF(BN16="","",BN16/$BN$16) -> 1 | BP16: =IF(BO16="","",BM16-BO16) -> 0.00033552991 | BQ16: =BQ12-BQ13-BQ14-BQ15 -> 2.7451263e+08 | BR16: 1
A17: Compras | C17: ( - ) Compras | D17: =SUMIF(EXTRATO!$F$14:$F$194,"COMPRAS",EXTRATO!$I$14:$I$194)+SUMIF(DESPESA!$E$4:$E$140,"Compras",DESPESA!$I$4:$I$140) -> 18525796 | E17: =D17/$D$16 -> 0.79216158 | F17: =F16*75% -> 15849250 | G17: =IF(F17="","",F17/$F$16) -> 0.75 | H17: =IF(G17="","",E17-G17) -> 0.042161582 | I17: =SUMIF(EXTRATO!$F$14:$F$194,"COMPRAS",EXTRATO!$J$14:$J$194)+SUMIF(DESPESA!$E$4:$E$140,"Compras",DESPESA!$J$4:$J$140) -> 16679785 | J17: =I17/$I$16 -> 0.79068569 | K17: =K16*75% -> 16716881 | L17: =IF(K17="","",K17/$K$16) -> 0.75 | M17: =IF(L17="","",J17-L17) -> 0.040685695 | O17: =IFERROR(N17/$N$16,"") | P17: =P16*75% -> 17633841 | Q17: =IF(P17="","",P17/$P$16) -> 0.75 | R17: =N17-P17 -> -17633841 | T17: =S17/$D$16 -> 0 | U17: =U16*75% -> 18339195 | V17: =IF(U17="","",U17/$U$16) -> 0.75 | W17: =IF(V17="","",T17-V17) -> -0.75 | Y17: =X17/$D$16 -> 0 | Z17: =Z16*75% -> 19044548 | AA17: =IF(Z17="","",Z17/$Z$16) -> 0.75 | AB17: =IF(AA17="","",Y17-AA17) -> -0.75 | AD17: =AC17/$D$16 -> 0 | AE17: =AE16*75% -> 18339195 | AF17: =IF(AE17="","",AE17/$AE$16) -> 0.75 | AG17: =IF(AF17="","",AD17-AF17) -> -0.75 | AI17: =AH17/$D$16 -> 0 | AJ17: =AJ16*75% -> 19608831 | AK17: =IF(AJ17="","",AJ17/$AJ$16) -> 0.75 | AL17: =IF(AK17="","",AI17-AK17) -> -0.75 | AN17: =AM17/$D$16 -> 0 | AO17: =AO16*75% -> 18409730 | AP17: =IF(AO17="","",AO17/$AO$16) -> 0.75 | AQ17: =IF(AP17="","",AN17-AP17) -> -0.75 | AS17: =AR17/$D$16 -> 0 | AT17: =AT16*75% -> 18268659 | AU17: =IF(AT17="","",AT17/$AT$16) -> 0.75 | AV17: =IF(AU17="","",AS17-AU17) -> -0.75 | AX17: =AW17/$D$16 -> 0 | AY17: =AY16*75% -> 19397225 | AZ17: =IF(AY17="","",AY17/$AY$16) -> 0.75 | BA17: =IF(AZ17="","",AX17-AZ17) -> -0.75 | BC17: =BB17/$D$16 -> 0 | BD17: =BD16*75% -> 18903478 | BE17: =IF(BD17="","",BD17/$BD$16) -> 0.75 | BF17: =IF(BE17="","",BC17-BE17) -> -0.75 | BH17: =BG17/$D$16 -> 0 | BI17: =BI16*75% -> 21231145 | BJ17: =IF(BI17="","",BI17/$BI$16) -> 0.75 | BK17: =IF(BJ17="","",BH17-BJ17) -> -0.75 | BL17: =SUM(D17,I17,N17,S17,X17,AC17,AH17,AM17,AR17,AW17,BB17,BG17) -> 35205581 | BM17: =BL17/$BL$16 -> 0.79146165 | BN17: =F17+K17+P17+U17+Z17+AE17+AJ17+AO17+AT17+AY17+BD17+BI17 -> 2.2174198e+08 | BO17: =IF(BN17="","",BN17/$BN$16) -> 0.75 | BP17: =IF(BO17="","",BM17-BO17) -> 0.041461646 | BQ17: 2.1858673e+08 | BR17: =BQ17/$BQ$16 -> 0.79627205
C18: ( = ) Margem de Venda 1 | D18: =D16-D17 -> 4860589.4 | E18: =E16-E17 -> 0.20783842 | F18: =F16-F17 -> 5283083.2 | G18: =IF(F18="","",G16-G17) -> 0.25 | H18: =IF(G18="","",E18-G18) -> -0.042161582 | I18: =I16-I17 -> 4415556.7 | J18: =J16-J17 -> 0.20931431 | K18: =K16-K17 -> 5572293.8 | L18: =IF(K18="","",L16-L17) -> 0.25 | M18: =IF(L18="","",J18-L18) -> -0.040685695 | N18: =N16-N17 -> 0 | O18: =IFERROR(O16-O17,"") | P18: =P16-P17 -> 5877947 | Q18: =IF(P18="","",Q16-Q17) -> 0.25 | R18: =N18-P18 -> -5877947 | S18: =S16-S17 -> 0 | T18: =T16-T17 -> 0 | U18: =U16-U17 -> 6113064.9 | V18: =IF(U18="","",V16-V17) -> 0.25 | W18: =IF(V18="","",T18-V18) -> -0.25 | X18: =X16-X17 -> 0 | Y18: =Y16-Y17 -> 0 | Z18: =Z16-Z17 -> 6348182.8 | AA18: =IF(Z18="","",AA16-AA17) -> 0.25 | AB18: =IF(AA18="","",Y18-AA18) -> -0.25 | AC18: =AC16-AC17 -> 0 | AD18: =AD16-AD17 -> 0 | AE18: =AE16-AE17 -> 6113064.9 | AF18: =IF(AE18="","",AF16-AF17) -> 0.25 | AG18: =IF(AF18="","",AD18-AF18) -> -0.25 | AH18: =AH16-AH17 -> 0 | AI18: =AI16-AI17 -> 0 | AJ18: =AJ16-AJ17 -> 6536277.1 | AK18: =IF(AJ18="","",AK16-AK17) -> 0.25 | AL18: =IF(AK18="","",AI18-AK18) -> -0.25 | AM18: =AM16-AM17 -> 0 | AN18: =AN16-AN17 -> 0 | AO18: =AO16-AO17 -> 6136576.7 | AP18: =IF(AO18="","",AP16-AP17) -> 0.25 | AQ18: =IF(AP18="","",AN18-AP18) -> -0.25 | AR18: =AR16-AR17 -> 0 | AS18: =AS16-AS17 -> 0 | AT18: =AT16-AT17 -> 6089553.1 | AU18: =IF(AT18="","",AU16-AU17) -> 0.25 | AV18: =IF(AU18="","",AS18-AU18) -> -0.25 | AW18: =AW16-AW17 -> 0 | AX18: =AX16-AX17 -> 0 | AY18: =AY16-AY17 -> 6465741.7 | AZ18: =IF(AY18="","",AZ16-AZ17) -> 0.25 | BA18: =IF(AZ18="","",AX18-AZ18) -> -0.25 | BB18: =BB16-BB17 -> 0 | BC18: =BC16-BC17 -> 0 | BD18: =BD16-BD17 -> 6301159.2 | BE18: =IF(BD18="","",BE16-BE17) -> 0.25 | BF18: =IF(BE18="","",BC18-BE18) -> -0.25 | BG18: =BG16-BG17 -> 0 | BH18: =BH16-BH17 -> 0 | BI18: =BI16-BI17 -> 7077048.2 | BJ18: =IF(BI18="","",BJ16-BJ17) -> 0.25 | BK18: =IF(BJ18="","",BH18-BJ18) -> -0.25 | BL18: =BL16-BL17 -> 9276146.1 | BM18: =BM16-BM17 -> 0.20887388 | BN18: =F18+K18+P18+U18+Z18+AE18+AJ18+AO18+AT18+AY18+BD18+BI18 -> 73913993 | BO18: =IF(BN18="","",BO16-BO17) -> 0.25 | BP18: =IF(BO18="","",BM18-BO18) -> -0.041126116 | BQ18: =BQ16-BQ17 -> 55925894 | BR18: =BR16-BR17 -> 0.20372795
A19: Tributario | C19: ( - ) Impostos Sobre Vendas | D19: =SUMIF(EXTRATO!$F$14:$F$194,"I_Vda",EXTRATO!$I$14:$I$194) -> 1511235.3 | E19: =D19/$D$16 -> 0.064620303 | F19: =$F$16*6.5% -> 1373601.6 | G19: =IF(F19="","",F19/$F$16) -> 0.065 | H19: =IF(G19="","",E19-G19) -> -0.00037969688 | I19: =SUMIF(EXTRATO!$F$14:$F$194,"I_Vda",EXTRATO!$J$14:$J$194) -> 1215043.8 | J19: =I19/$I$16 -> 0.057597729 | K19: =$K$16*6.5% -> 1448796.4 | L19: =IF(K19="","",K19/$K$16) -> 0.065 | M19: =IF(L19="","",J19-L19) -> -0.0074022707 | O19: =IFERROR(N19/$N$16,"") | P19: =$P$16*6.5% -> 1528266.2 | Q19: =IF(P19="","",P19/$P$16) -> 0.065 | R19: =N19-P19 -> -1528266.2 | T19: =S19/$D$16 -> 0 | U19: =$U$16*6.5% -> 1589396.9 | V19: =IF(U19="","",U19/$U$16) -> 0.065 | W19: =IF(V19="","",T19-V19) -> -0.065 | Y19: =X19/$D$16 -> 0 | Z19: =$Z$16*6.5% -> 1650527.5 | AA19: =IF(Z19="","",Z19/$Z$16) -> 0.065 | AB19: =IF(AA19="","",Y19-AA19) -> -0.065 | AD19: =AC19/$D$16 -> 0 | AE19: =$AE$16*6.5% -> 1589396.9 | AF19: =IF(AE19="","",AE19/$AE$16) -> 0.065 | AG19: =IF(AF19="","",AD19-AF19) -> -0.065 | AI19: =AH19/$D$16 -> 0 | AJ19: =$AJ$16*6.5% -> 1699432 | AK19: =IF(AJ19="","",AJ19/$AJ$16) -> 0.065 | AL19: =IF(AK19="","",AI19-AK19) -> -0.065 | AN19: =AM19/$D$16 -> 0 | AO19: =$AO$16*6.5% -> 1595509.9 | AP19: =IF(AO19="","",AO19/$AO$16) -> 0.065 | AQ19: =IF(AP19="","",AN19-AP19) -> -0.065 | AS19: =AR19/$D$16 -> 0 | AT19: =$AT$16*6.5% -> 1583283.8 | AU19: =IF(AT19="","",AT19/$AT$16) -> 0.065 | AV19: =IF(AU19="","",AS19-AU19) -> -0.065 | AX19: =AW19/$D$16 -> 0 | AY19: =$AY$16*6.5% -> 1681092.8 | AZ19: =IF(AY19="","",AY19/$AY$16) -> 0.065 | BA19: =IF(AZ19="","",AX19-AZ19) -> -0.065 | BC19: =BB19/$D$16 -> 0 | BD19: =$BD$16*6.5% -> 1638301.4 | BE19: =IF(BD19="","",BD19/$BD$16) -> 0.065 | BF19: =IF(BE19="","",BC19-BE19) -> -0.065 | BH19: =BG19/$D$16 -> 0 | BI19: =$BI$16*6.5% -> 1840032.5 | BJ19: =IF(BI19="","",BI19/$BI$16) -> 0.065 | BK19: =IF(BJ19="","",BH19-BJ19) -> -0.065 | BL19: =SUM(D19,I19,N19,S19,X19,AC19,AH19,AM19,AR19,AW19,BB19,BG19) -> 2726279.1 | BM19: =BL19/$BL$16 -> 0.061289866 | BN19: =F19+K19+P19+U19+Z19+AE19+AJ19+AO19+AT19+AY19+BD19+BI19 -> 19217638 | BO19: =IF(BN19="","",BN19/$BN$16) -> 0.065 | BP19: =IF(BO19="","",BM19-BO19) -> -0.0037101339 | BQ19: 12680836 | BR19: =BQ19/$BQ$16 -> 0.046193998
C20: ( = ) Margem de Venda 2 | D20: =D18-D19 -> 3349354.1 | E20: =E18-E19 -> 0.14321812 | F20: =F18-F19 -> 3909481.6 | G20: =IF(F20="","",G18-G19) -> 0.185 | H20: =IF(G20="","",E20-G20) -> -0.041781885 | I20: =I18-I19 -> 3200513 | J20: =J18-J19 -> 0.15171658 | K20: =K18-K19 -> 4123497.4 | L20: =IF(K20="","",L18-L19) -> 0.185 | M20: =IF(L20="","",J20-L20) -> -0.033283424 | N20: =N18-N19 -> 0 | O20: =IFERROR(O18-O19,"") | P20: =P18-P19 -> 4349680.8 | Q20: =IF(P20="","",Q18-Q19) -> 0.185 | R20: =N20-P20 -> -4349680.8 | S20: =S18-S19 -> 0 | T20: =T18-T19 -> 0 | U20: =U18-U19 -> 4523668 | V20: =IF(U20="","",V18-V19) -> 0.185 | W20: =IF(V20="","",T20-V20) -> -0.185 | X20: =X18-X19 -> 0 | Y20: =Y18-Y19 -> 0 | Z20: =Z18-Z19 -> 4697655.3 | AA20: =IF(Z20="","",AA18-AA19) -> 0.185 | AB20: =IF(AA20="","",Y20-AA20) -> -0.185 | AC20: =AC18-AC19 -> 0 | AD20: =AD18-AD19 -> 0 | AE20: =AE18-AE19 -> 4523668 | AF20: =IF(AE20="","",AF18-AF19) -> 0.185 | AG20: =IF(AF20="","",AD20-AF20) -> -0.185 | AH20: =AH18-AH19 -> 0 | AI20: =AI18-AI19 -> 0 | AJ20: =AJ18-AJ19 -> 4836845 | AK20: =IF(AJ20="","",AK18-AK19) -> 0.185 | AL20: =IF(AK20="","",AI20-AK20) -> -0.185 | AM20: =AM18-AM19 -> 0 | AN20: =AN18-AN19 -> 0 | AO20: =AO18-AO19 -> 4541066.7 | AP20: =IF(AO20="","",AP18-AP19) -> 0.185 | AQ20: =IF(AP20="","",AN20-AP20) -> -0.185 | AR20: =AR18-AR19 -> 0 | AS20: =AS18-AS19 -> 0 | AT20: =AT18-AT19 -> 4506269.3 | AU20: =IF(AT20="","",AU18-AU19) -> 0.185 | AV20: =IF(AU20="","",AS20-AU20) -> -0.185 | AW20: =AW18-AW19 -> 0 | AX20: =AX18-AX19 -> 0 | AY20: =AY18-AY19 -> 4784648.9 | AZ20: =IF(AY20="","",AZ18-AZ19) -> 0.185 | BA20: =IF(AZ20="","",AX20-AZ20) -> -0.185 | BB20: =BB18-BB19 -> 0 | BC20: =BC18-BC19 -> 0 | BD20: =BD18-BD19 -> 4662857.8 | BE20: =IF(BD20="","",BE18-BE19) -> 0.185 | BF20: =IF(BE20="","",BC20-BE20) -> -0.185 | BG20: =BG18-BG19 -> 0 | BH20: =BH18-BH19 -> 0 | BI20: =BI18-BI19 -> 5237015.7 | BJ20: =IF(BI20="","",BJ18-BJ19) -> 0.185 | BK20: =IF(BJ20="","",BH20-BJ20) -> -0.185 | BL20: =BL18-BL19 -> 6549867 | BM20: =BM18-BM19 -> 0.14758402 | BN20: =F20+K20+P20+U20+Z20+AE20+AJ20+AO20+AT20+AY20+BD20+BI20 -> 54696355 | BO20: =IF(BN20="","",BO18-BO19) -> 0.185 | BP20: =IF(BO20="","",BM20-BO20) -> -0.037415982 | BQ20: =BQ18-BQ19 -> 43245058 | BR20: =BR18-BR19 -> 0.15753395
A21: ENOP | B21: ENOP_S | C21: ( + ) Crédito Operacionais | D21: =SUMIF(EXTRATO!$F$14:$F$194,"ENOP",EXTRATO!$I$14:$I$194)-SUMIF(EXTRATO!$F$14:$F$194,"ENOP_S",EXTRATO!$I$14:$I$194) -> 192682.46 | E21: =D21/$D$16 -> 0.0082390868 | F21: =$F$16*BR21 -> 23661.492 | G21: =IF(F21="","",F21/$F$16) -> 0.001119682 | H21: =IF(G21="","",E21-G21) -> 0.0071194048 | I21: =SUMIF(EXTRATO!$F$14:$F$194,"ENOP",EXTRATO!$J$14:$J$194)-SUMIF(EXTRATO!$F$14:$F$194,"ENOP_S",EXTRATO!$J$14:$J$194) -> 2549.12 | J21: =I21/$I$16 -> 0.00012083805 | K21: =$K$16*BR21 -> 24956.787 | L21: =IF(K21="","",K21/$K$16) -> 0.001119682 | M21: =IF(L21="","",J21-L21) -> -0.00099884391 | O21: =IFERROR(N21/$N$16,"") | P21: =$P$16*BR21 -> 26325.725 | Q21: =IF(P21="","",P21/$P$16) -> 0.001119682 | R21: =N21-P21 -> -26325.725 | T21: =S21/$D$16 -> 0 | U21: =$U$16*BR21 -> 27378.754 | V21: =IF(U21="","",U21/$U$16) -> 0.001119682 | W21: =IF(V21="","",T21-V21) -> -0.001119682 | Y21: =X21/$D$16 -> 0 | Z21: =$Z$16*BR21 -> 28431.783 | AA21: =IF(Z21="","",Z21/$Z$16) -> 0.001119682 | AB21: =IF(AA21="","",Y21-AA21) -> -0.001119682 | AD21: =AC21/$D$16 -> 0 | AE21: =$AE$16*BR21 -> 27378.754 | AF21: =IF(AE21="","",AE21/$AE$16) -> 0.001119682 | AG21: =IF(AF21="","",AD21-AF21) -> -0.001119682 | AI21: =AH21/$D$16 -> 0 | AJ21: =$AJ$16*BR21 -> 29274.206 | AK21: =IF(AJ21="","",AJ21/$AJ$16) -> 0.001119682 | AL21: =IF(AK21="","",AI21-AK21) -> -0.001119682 | AN21: =AM21/$D$16 -> 0 | AO21: =$AO$16*BR21 -> 27484.057 | AP21: =IF(AO21="","",AO21/$AO$16) -> 0.001119682 | AQ21: =IF(AP21="","",AN21-AP21) -> -0.001119682 | AS21: =AR21/$D$16 -> 0 | AT21: =$AT$16*BR21 -> 27273.451 | AU21: =IF(AT21="","",AT21/$AT$16) -> 0.001119682 | AV21: =IF(AU21="","",AS21-AU21) -> -0.001119682 | AX21: =AW21/$D$16 -> 0 | AY21: =$AY$16*BR21 -> 28958.298 | AZ21: =IF(AY21="","",AY21/$AY$16) -> 0.001119682 | BA21: =IF(AZ21="","",AX21-AZ21) -> -0.001119682 | BC21: =BB21/$D$16 -> 0 | BD21: =$BD$16*BR21 -> 28221.177 | BE21: =IF(BD21="","",BD21/$BD$16) -> 0.001119682 | BF21: =IF(BE21="","",BC21-BE21) -> -0.001119682 | BH21: =BG21/$D$16 -> 0 | BI21: =$BI$16*BR21 -> 31696.173 | BJ21: =IF(BI21="","",BI21/$BI$16) -> 0.001119682 | BK21: =IF(BJ21="","",BH21-BJ21) -> -0.001119682 | BL21: =SUM(D21,I21,N21,S21,X21,AC21,AH21,AM21,AR21,AW21,BB21,BG21) -> 195231.58 | BM21: =BL21/$BL$16 -> 0.0043890288 | BN21: =F21+K21+P21+U21+Z21+AE21+AJ21+AO21+AT21+AY21+BD21+BI21 -> 331040.66 | BO21: =IF(BN21="","",BN21/$BN$16) -> 0.001119682 | BP21: =IF(BO21="","",BM21-BO21) -> 0.0032693468 | BQ21: 307366.84 | BR21: =BQ21/$BQ$16 -> 0.001119682
A22: Acordo_E | B22: Acordo_S | C22: ( + ) Acordos Comerciais | D22: =SUMIF(EXTRATO!$F$14:$F$194,"Acordo_E",EXTRATO!$I$14:$I$194)-SUMIF(EXTRATO!$F$14:$F$194,"Acordo_S",EXTRATO!$I$14:$I$194) -> 287208.95 | E22: =D22/$D$16 -> 0.012281032 | F22: =$F$16*BR22 -> 228654.98 | G22: =IF(F22="","",F22/$F$16) -> 0.010820148 | H22: =IF(G22="","",E22-G22) -> 0.0014608838 | I22: =SUMIF(EXTRATO!$F$14:$F$194,"Acordo_E",EXTRATO!$J$14:$J$194)-SUMIF(EXTRATO!$F$14:$F$194,"Acordo_S",EXTRATO!$J$14:$J$194) -> 195834.05 | J22: =I22/$I$16 -> 0.0092832842 | K22: =$K$16*BR22 -> 241172.18 | L22: =IF(K22="","",K22/$K$16) -> 0.010820148 | M22: =IF(L22="","",J22-L22) -> -0.001536864 | O22: =IFERROR(N22/$N$16,"") | P22: =$P$16*BR22 -> 254401.03 | Q22: =IF(P22="","",P22/$P$16) -> 0.010820148 | R22: =N22-P22 -> -254401.03 | T22: =S22/$D$16 -> 0 | U22: =$U$16*BR22 -> 264577.07 | V22: =IF(U22="","",U22/$U$16) -> 0.010820148 | W22: =IF(V22="","",T22-V22) -> -0.010820148 | Y22: =X22/$D$16 -> 0 | Z22: =$Z$16*BR22 -> 274753.12 | AA22: =IF(Z22="","",Z22/$Z$16) -> 0.010820148 | AB22: =IF(AA22="","",Y22-AA22) -> -0.010820148 | AD22: =AC22/$D$16 -> 0 | AE22: =$AE$16*BR22 -> 264577.07 | AF22: =IF(AE22="","",AE22/$AE$16) -> 0.010820148 | AG22: =IF(AF22="","",AD22-AF22) -> -0.010820148 | AI22: =AH22/$D$16 -> 0 | AJ22: =$AJ$16*BR22 -> 282893.95 | AK22: =IF(AJ22="","",AJ22/$AJ$16) -> 0.010820148 | AL22: =IF(AK22="","",AI22-AK22) -> -0.010820148 | AN22: =AM22/$D$16 -> 0 | AO22: =$AO$16*BR22 -> 265594.68 | AP22: =IF(AO22="","",AO22/$AO$16) -> 0.010820148 | AQ22: =IF(AP22="","",AN22-AP22) -> -0.010820148 | AS22: =AR22/$D$16 -> 0 | AT22: =$AT$16*BR22 -> 263559.47 | AU22: =IF(AT22="","",AT22/$AT$16) -> 0.010820148 | AV22: =IF(AU22="","",AS22-AU22) -> -0.010820148 | AX22: =AW22/$D$16 -> 0 | AY22: =$AY$16*BR22 -> 279841.14 | AZ22: =IF(AY22="","",AY22/$AY$16) -> 0.010820148 | BA22: =IF(AZ22="","",AX22-AZ22) -> -0.010820148 | BC22: =BB22/$D$16 -> 0 | BD22: =$BD$16*BR22 -> 272717.91 | BE22: =IF(BD22="","",BD22/$BD$16) -> 0.010820148 | BF22: =IF(BE22="","",BC22-BE22) -> -0.010820148 | BH22: =BG22/$D$16 -> 0 | BI22: =$BI$16*BR22 -> 306298.84 | BJ22: =IF(BI22="","",BI22/$BI$16) -> 0.010820148 | BK22: =IF(BJ22="","",BH22-BJ22) -> -0.010820148 | BL22: =SUM(D22,I22,N22,S22,X22,AC22,AH22,AM22,AR22,AW22,BB22,BG22) -> 483043 | BM22: =BL22/$BL$16 -> 0.010859358 | BN22: =F22+K22+P22+U22+Z22+AE22+AJ22+AO22+AT22+AY22+BD22+BI22 -> 3199041.4 | BO22: =IF(BN22="","",BN22/$BN$16) -> 0.010820148 | BP22: =IF(BO22="","",BM22-BO22) -> 3.9209794e-05 | BQ22: 2970267.3 | BR22: =BQ22/$BQ$16 -> 0.010820148
A23: Devf_E | C23: ( + ) Devoluções | D23: =SUMIF(EXTRATO!$F$14:$F$194,"devf_e",EXTRATO!$I$14:$I$194) -> 159091.48 | E23: =D23/$D$16 -> 0.0068027391 | F23: =$F$16*BR23 -> 123907.54 | G23: =IF(F23="","",F23/$F$16) -> 0.0058634104 | H23: =IF(G23="","",E23-G23) -> 0.00093932875 | I23: =SUMIF(EXTRATO!$F$14:$F$194,"devf_e",EXTRATO!$J$14:$J$194) -> 207041.3 | J23: =I23/$I$16 -> 0.0098145508 | K23: =$K$16*BR23 -> 130690.58 | L23: =IF(K23="","",K23/$K$16) -> 0.0058634104 | M23: =IF(L23="","",J23-L23) -> 0.0039511404 | O23: =IFERROR(N23/$N$16,"") | P23: =$P$16*BR23 -> 137859.26 | Q23: =IF(P23="","",P23/$P$16) -> 0.0058634104 | R23: =N23-P23 -> -137859.26 | T23: =S23/$D$16 -> 0 | U23: =$U$16*BR23 -> 143373.63 | V23: =IF(U23="","",U23/$U$16) -> 0.0058634104 | W23: =IF(V23="","",T23-V23) -> -0.0058634104 | Y23: =X23/$D$16 -> 0 | Z23: =$Z$16*BR23 -> 148888 | AA23: =IF(Z23="","",Z23/$Z$16) -> 0.0058634104 | AB23: =IF(AA23="","",Y23-AA23) -> -0.0058634104 | AD23: =AC23/$D$16 -> 0 | AE23: =$AE$16*BR23 -> 143373.63 | AF23: =IF(AE23="","",AE23/$AE$16) -> 0.0058634104 | AG23: =IF(AF23="","",AD23-AF23) -> -0.0058634104 | AI23: =AH23/$D$16 -> 0 | AJ23: =$AJ$16*BR23 -> 153299.5 | AK23: =IF(AJ23="","",AJ23/$AJ$16) -> 0.0058634104 | AL23: =IF(AK23="","",AI23-AK23) -> -0.0058634104 | AN23: =AM23/$D$16 -> 0 | AO23: =$AO$16*BR23 -> 143925.07 | AP23: =IF(AO23="","",AO23/$AO$16) -> 0.0058634104 | AQ23: =IF(AP23="","",AN23-AP23) -> -0.0058634104 | AS23: =AR23/$D$16 -> 0 | AT23: =$AT$16*BR23 -> 142822.2 | AU23: =IF(AT23="","",AT23/$AT$16) -> 0.0058634104 | AV23: =IF(AU23="","",AS23-AU23) -> -0.0058634104 | AX23: =AW23/$D$16 -> 0 | AY23: =$AY$16*BR23 -> 151645.19 | AZ23: =IF(AY23="","",AY23/$AY$16) -> 0.0058634104 | BA23: =IF(AZ23="","",AX23-AZ23) -> -0.0058634104 | BC23: =BB23/$D$16 -> 0 | BD23: =$BD$16*BR23 -> 147785.13 | BE23: =IF(BD23="","",BD23/$BD$16) -> 0.0058634104 | BF23: =IF(BE23="","",BC23-BE23) -> -0.0058634104 | BH23: =BG23/$D$16 -> 0 | BI23: =$BI$16*BR23 -> 165982.55 | BJ23: =IF(BI23="","",BI23/$BI$16) -> 0.0058634104 | BK23: =IF(BJ23="","",BH23-BJ23) -> -0.0058634104 | BL23: =SUM(D23,I23,N23,S23,X23,AC23,AH23,AM23,AR23,AW23,BB23,BG23) -> 366132.78 | BM23: =BL23/$BL$16 -> 0.0082310829 | BN23: =F23+K23+P23+U23+Z23+AE23+AJ23+AO23+AT23+AY23+BD23+BI23 -> 1733552.3 | BO23: =IF(BN23="","",BN23/$BN$16) -> 0.0058634104 | BP23: =IF(BO23="","",BM23-BO23) -> 0.0023676725 | BQ23: 1609580.2 | BR23: =BQ23/$BQ$16 -> 0.0058634104
C24: ( = ) Sub Total de Fornecedores | D24: =SUM(D22:D23) -> 446300.43 | E24: =SUM(E22:E23) -> 0.019083771 | F24: =SUM(F22:F23) -> 352562.52 | G24: =IF(F24="","",SUM(G22:G23)) -> 0.016683559 | H24: =IF(G24="","",E24-G24) -> 0.0024002125 | I24: =SUM(I22:I23) -> 402875.35 | J24: =SUM(J22:J23) -> 0.019097835 | K24: =SUM(K22:K23) -> 371862.76 | L24: =IF(K24="","",SUM(L22:L23)) -> 0.016683559 | M24: =IF(L24="","",J24-L24) -> 0.0024142764 | N24: =SUM(N22:N23) -> 0 | O24: =IFERROR(SUM(O22:O23),"") -> 0 | P24: =SUM(P22:P23) -> 392260.3 | Q24: =IF(P24="","",SUM(Q22:Q23)) -> 0.016683559 | R24: =N24-P24 -> -392260.3 | S24: =SUM(S22:S23) -> 0 | T24: =SUM(T22:T23) -> 0 | U24: =SUM(U22:U23) -> 407950.71 | V24: =IF(U24="","",SUM(V22:V23)) -> 0.016683559 | W24: =IF(V24="","",T24-V24) -> -0.016683559 | X24: =SUM(X22:X23) -> 0 | Y24: =SUM(Y22:Y23) -> 0 | Z24: =SUM(Z22:Z23) -> 423641.12 | AA24: =IF(Z24="","",SUM(AA22:AA23)) -> 0.016683559 | AB24: =IF(AA24="","",Y24-AA24) -> -0.016683559 | AC24: =SUM(AC22:AC23) -> 0 | AD24: =SUM(AD22:AD23) -> 0 | AE24: =SUM(AE22:AE23) -> 407950.71 | AF24: =IF(AE24="","",SUM(AF22:AF23)) -> 0.016683559 | AG24: =IF(AF24="","",AD24-AF24) -> -0.016683559 | AH24: =SUM(AH22:AH23) -> 0 | AI24: =SUM(AI22:AI23) -> 0 | AJ24: =SUM(AJ22:AJ23) -> 436193.45 | AK24: =IF(AJ24="","",SUM(AK22:AK23)) -> 0.016683559 | AL24: =IF(AK24="","",AI24-AK24) -> -0.016683559 | AM24: =SUM(AM22:AM23) -> 0 | AN24: =SUM(AN22:AN23) -> 0 | AO24: =SUM(AO22:AO23) -> 409519.75 | AP24: =IF(AO24="","",SUM(AP22:AP23)) -> 0.016683559 | AQ24: =IF(AP24="","",AN24-AP24) -> -0.016683559 | AR24: =SUM(AR22:AR23) -> 0 | AS24: =SUM(AS22:AS23) -> 0 | AT24: =SUM(AT22:AT23) -> 406381.67 | AU24: =IF(AT24="","",SUM(AU22:AU23)) -> 0.016683559 | AV24: =IF(AU24="","",AS24-AU24) -> -0.016683559 | AW24: =SUM(AW22:AW23) -> 0 | AX24: =SUM(AX22:AX23) -> 0 | AY24: =SUM(AY22:AY23) -> 431486.33 | AZ24: =IF(AY24="","",SUM(AZ22:AZ23)) -> 0.016683559 | BA24: =IF(AZ24="","",AX24-AZ24) -> -0.016683559 | BB24: =SUM(BB22:BB23) -> 0 | BC24: =SUM(BC22:BC23) -> 0 | BD24: =SUM(BD22:BD23) -> 420503.04 | BE24: =IF(BD24="","",SUM(BE22:BE23)) -> 0.016683559 | BF24: =IF(BE24="","",BC24-BE24) -> -0.016683559 | BG24: =SUM(BG22:BG23) -> 0 | BH24: =SUM(BH22:BH23) -> 0 | BI24: =SUM(BI22:BI23) -> 472281.4 | BJ24: =IF(BI24="","",SUM(BJ22:BJ23)) -> 0.016683559 | BK24: =IF(BJ24="","",BH24-BJ24) -> -0.016683559 | BL24: =SUM(BL22:BL23) -> 849175.78 | BM24: =SUM(BM22:BM23) -> 0.019090441 | BN24: =F24+K24+P24+U24+Z24+AE24+AJ24+AO24+AT24+AY24+BD24+BI24 -> 4932593.7 | BO24: =IF(BN24="","",SUM(BO22:BO23)) -> 0.016683559 | BP24: =IF(BO24="","",BM24-BO24) -> 0.0024068823 | BQ24: =SUM(BQ22:BQ23) -> 4579847.5 | BR24: =SUM(BR22:BR23) -> 0.016683559
A25: CHQ_E | B25: CHQ_S | C25: ( +/- ) Mvto Chq. Devolvidos | D25: =SUMIF(EXTRATO!$F$14:$F$194,"CHQ_E",EXTRATO!$I$14:$I$194)-SUMIF(EXTRATO!$F$14:$F$194,"CHQ_S",EXTRATO!$I$14:$I$194) -> -824.99 | E25: =D25/$D$16 -> -3.5276507e-05 | G25: 0 | H25: =IF(G25="","",E25-G25) -> -3.5276507e-05 | I25: =SUMIF(EXTRATO!$F$14:$F$194,"CHQ_E",EXTRATO!$J$14:$J$194)-SUMIF(EXTRATO!$F$14:$F$194,"CHQ_S",EXTRATO!$J$14:$J$194) -> -39.7 | J25: =I25/$I$16 -> -1.8819321e-06 | K25: =0 -> 0 | L25: =IF(K25="","",K25/$K$16) -> 0 | M25: =IF(L25="","",J25-L25) -> -1.8819321e-06 | O25: =IFERROR(N25/$N$16,"") | P25: =0 -> 0 | Q25: =IF(P25="","",P25/$P$16) -> 0 | R25: =N25-P25 -> 0 | T25: =S25/$D$16 -> 0 | U25: =0 -> 0 | V25: =IF(U25="","",U25/$U$16) -> 0 | W25: =IF(V25="","",T25-V25) -> 0 | Y25: =X25/$D$16 -> 0 | Z25: =0 -> 0 | AA25: =IF(Z25="","",Z25/$Z$16) -> 0 | AB25: =IF(AA25="","",Y25-AA25) -> 0 | AD25: =AC25/$D$16 -> 0 | AE25: =0 -> 0 | AF25: =IF(AE25="","",AE25/$AE$16) -> 0 | AG25: =IF(AF25="","",AD25-AF25) -> 0 | AI25: =AH25/$D$16 -> 0 | AJ25: =0 -> 0 | AK25: =IF(AJ25="","",AJ25/$AJ$16) -> 0 | AL25: =IF(AK25="","",AI25-AK25) -> 0 | AN25: =AM25/$D$16 -> 0 | AO25: =0 -> 0 | AP25: =IF(AO25="","",AO25/$AO$16) -> 0 | AQ25: =IF(AP25="","",AN25-AP25) -> 0 | AS25: =AR25/$D$16 -> 0 | AT25: =0 -> 0 | AU25: =IF(AT25="","",AT25/$AT$16) -> 0 | AV25: =IF(AU25="","",AS25-AU25) -> 0 | AX25: =AW25/$D$16 -> 0 | AY25: =0 -> 0 | AZ25: =IF(AY25="","",AY25/$AY$16) -> 0 | BA25: =IF(AZ25="","",AX25-AZ25) -> 0 | BC25: =BB25/$D$16 -> 0 | BD25: =0 -> 0 | BE25: =IF(BD25="","",BD25/$BD$16) -> 0 | BF25: =IF(BE25="","",BC25-BE25) -> 0 | BH25: =BG25/$D$16 -> 0 | BI25: =0 -> 0 | BJ25: =IF(BI25="","",BI25/$BI$16) -> 0 | BK25: =IF(BJ25="","",BH25-BJ25) -> 0 | BL25: =SUM(D25,I25,N25,S25,X25,AC25,AH25,AM25,AR25,AW25,BB25,BG25) -> -864.69 | BM25: =BL25/$BL$16 -> -1.9439218e-05 | BN25: =F25+K25+P25+U25+Z25+AE25+AJ25+AO25+AT25+AY25+BD25+BI25 -> 0 | BO25: =IF(BN25="","",BN25/$BN$16) -> 0 | BP25: =IF(BO25="","",BM25-BO25) -> -1.9439218e-05 | BQ25: -3832.03 | BR25: =BQ25/$BQ$16 -> -1.3959394e-05
C26: Lucro Bruto | D26: =D20+D24+D25+D21 -> 3987512 | E26: =E20+E21+E24+E25 -> 0.1705057 | F26: =F18-F19+F21+F24+F25 -> 4285705.6 | G26: =IF(F26="","",G20+G21+G24+G25) -> 0.20280324 | H26: =IF(G26="","",E26-G26) -> -0.032297544 | I26: =I20+I24+I25+I21 -> 3605897.7 | J26: =J20+J21+J24+J25 -> 0.17093337 | K26: =K18-K19+K21+K24+K25 -> 4520316.9 | L26: =IF(K26="","",L20+L21+L24+L25) -> 0.20280324 | M26: =IF(L26="","",J26-L26) -> -0.031869873 | N26: =N20+N24+N25+N21 -> 0 | O26: =IFERROR(O20+O21+O24+O25,"") | P26: =P18-P19+P21+P24+P25 -> 4768266.8 | Q26: =IF(P26="","",Q20+Q21+Q24+Q25) -> 0.20280324 | R26: =IFERROR(IF(Q26="","",O26-Q26),"") | S26: =S20+S24+S25+S21 -> 0 | T26: =T20+T21+T24+T25 -> 0 | U26: =U18-U19+U21+U24+U25 -> 4958997.5 | V26: =IF(U26="","",V20+V21+V24+V25) -> 0.20280324 | W26: =IF(V26="","",T26-V26) -> -0.20280324 | X26: =X20+X24+X25+X21 -> 0 | Y26: =Y20+Y21+Y24+Y25 -> 0 | Z26: =Z18-Z19+Z21+Z24+Z25 -> 5149728.2 | AA26: =IF(Z26="","",AA20+AA21+AA24+AA25) -> 0.20280324 | AB26: =IF(AA26="","",Y26-AA26) -> -0.20280324 | AC26: =AC20+AC24+AC25+AC21 -> 0 | AD26: =AD20+AD21+AD24+AD25 -> 0 | AE26: =AE18-AE19+AE21+AE24+AE25 -> 4958997.5 | AF26: =IF(AE26="","",AF20+AF21+AF24+AF25) -> 0.20280324 | AG26: =IF(AF26="","",AD26-AF26) -> -0.20280324 | AH26: =AH20+AH24+AH25+AH21 -> 0 | AI26: =AI20+AI21+AI24+AI25 -> 0 | AJ26: =AJ18-AJ19+AJ21+AJ24+AJ25 -> 5302312.7 | AK26: =IF(AJ26="","",AK20+AK21+AK24+AK25) -> 0.20280324 | AL26: =IF(AK26="","",AI26-AK26) -> -0.20280324 | AM26: =AM20+AM24+AM25+AM21 -> 0 | AN26: =AN20+AN21+AN24+AN25 -> 0 | AO26: =AO18-AO19+AO21+AO24+AO25 -> 4978070.6 | AP26: =IF(AO26="","",AP20+AP21+AP24+AP25) -> 0.20280324 | AQ26: =IF(AP26="","",AN26-AP26) -> -0.20280324 | AR26: =AR20+AR24+AR25+AR21 -> 0 | AS26: =AS20+AS21+AS24+AS25 -> 0 | AT26: =AT18-AT19+AT21+AT24+AT25 -> 4939924.4 | AU26: =IF(AT26="","",AU20+AU21+AU24+AU25) -> 0.20280324 | AV26: =IF(AU26="","",AS26-AU26) -> -0.20280324 | AW26: =AW20+AW24+AW25+AW21 -> 0 | AX26: =AX20+AX21+AX24+AX25 -> 0 | AY26: =AY18-AY19+AY21+AY24+AY25 -> 5245093.5 | AZ26: =IF(AY26="","",AZ20+AZ21+AZ24+AZ25) -> 0.20280324 | BA26: =IF(AZ26="","",AX26-AZ26) -> -0.20280324 | BB26: =BB20+BB24+BB25+BB21 -> 0 | BC26: =BC20+BC21+BC24+BC25 -> 0 | BD26: =BD18-BD19+BD21+BD24+BD25 -> 5111582 | BE26: =IF(BD26="","",BE20+BE21+BE24+BE25) -> 0.20280324 | BF26: =IF(BE26="","",BC26-BE26) -> -0.20280324 | BG26: =BG20+BG24+BG25+BG21 -> 0 | BH26: =BH20+BH21+BH24+BH25 -> 0 | BI26: =BI18-BI19+BI21+BI24+BI25 -> 5740993.2 | BJ26: =IF(BI26="","",BJ20+BJ21+BJ24+BJ25) -> 0.20280324 | BK26: =IF(BJ26="","",BH26-BJ26) -> -0.20280324 | BL26: =BL20+BL24+BL25+BL21 -> 7593409.7 | BM26: =BM20+BM21+BM24+BM25 -> 0.17104405 | BN26: =F26+K26+P26+U26+Z26+AE26+AJ26+AO26+AT26+AY26+BD26+BI26 -> 59959989 | BO26: =IF(BN26="","",BO20+BO21+BO24+BO25) -> 0.20280324 | BP26: =IF(BO26="","",BM26-BO26) -> -0.031759192 | BQ26: =BQ20+BQ24+BQ25+BQ21 -> 48128441 | BR26: =BR20+BR21+BR24+BR25 -> 0.17532323
C28: Custos operacionais
A29: Pessoal | B29: Pessoal_E | C29: ( - ) Pessoal/Folha | D29: =SUMIF(EXTRATO!$F$14:$F$194,"PESSOAL",EXTRATO!$I$14:$I$194)-SUMIF(EXTRATO!$F$14:$F$194,"PESSOAL_E",EXTRATO!$I$14:$I$194)+SUMIF(DESPESA!$E$4:$E$140,"PESSOAL",DESPESA!$I$4:$I$140) -> 672226.15 | E29: =D29/$D$16 -> 0.028744337 | F29: 1120013.6 | G29: =IF(OR(F29="",F$16=0),"",F29/$F$16) -> 0.053 | H29: =IF(G29="","",E29-G29) -> -0.024255663 | I29: =SUMIF(EXTRATO!$F$14:$F$194,"PESSOAL",EXTRATO!$J$14:$J$194)-SUMIF(EXTRATO!$F$14:$F$194,"PESSOAL_E",EXTRATO!$J$14:$J$194)+SUMIF(DESPESA!$E$4:$E$140,"PESSOAL",DESPESA!$J$4:$J$140) -> 670371.83 | J29: =I29/$I$16 -> 0.031778193 | K29: 1181326.3 | L29: =IF(OR(K29="",K$16=0),"",K29/$K$16) -> 0.053 | M29: =IF(L29="","",J29-L29) -> -0.021221807 | O29: =IFERROR(N29/$N$16,"") | P29: 1246124.8 | Q29: =IF(OR(P29="",P$16=0),"",P29/$P$16) -> 0.053 | R29: =N29-P29 -> -1246124.8 | T29: =S29/$D$16 -> 0 | U29: 1295969.8 | V29: =IF(OR(U29="",U$16=0),"",U29/$U$16) -> 0.053 | W29: =IF(V29="","",T29-V29) -> -0.053 | Y29: =X29/$D$16 -> 0 | Z29: 1345814.7 | AA29: =IF(OR(Z29="",Z$16=0),"",Z29/$Z$16) -> 0.053 | AB29: =IF(AA29="","",Y29-AA29) -> -0.053 | AD29: =AC29/$D$16 -> 0 | AE29: 1295969.8 | AF29: =IF(OR(AE29="",AE$16=0),"",AE29/$AE$16) -> 0.053 | AG29: =IF(AF29="","",AD29-AF29) -> -0.053 | AI29: =AH29/$D$16 -> 0 | AJ29: 1385690.7 | AK29: =IF(OR(AJ29="",AJ$16=0),"",AJ29/$AJ$16) -> 0.053 | AL29: =IF(AK29="","",AI29-AK29) -> -0.053 | AN29: =AM29/$D$16 -> 0 | AO29: 1300954.3 | AP29: =IF(OR(AO29="",AO$16=0),"",AO29/$AO$16) -> 0.053 | AQ29: =IF(AP29="","",AN29-AP29) -> -0.053 | AS29: =AR29/$D$16 -> 0 | AT29: 1290985.3 | AU29: =IF(OR(AT29="",AT$16=0),"",AT29/$AT$16) -> 0.053 | AV29: =IF(AU29="","",AS29-AU29) -> -0.053 | AX29: =AW29/$D$16 -> 0 | AY29: 1370737.2 | AZ29: =IF(OR(AY29="",AY$16=0),"",AY29/$AY$16) -> 0.053 | BA29: =IF(AZ29="","",AX29-AZ29) -> -0.053 | BC29: =BB29/$D$16 -> 0 | BD29: 1335845.8 | BE29: =IF(OR(BD29="",BD$16=0),"",BD29/$BD$16) -> 0.053 | BF29: =IF(BE29="","",BC29-BE29) -> -0.053 | BH29: =BG29/$D$16 -> 0 | BI29: 1500334.2 | BJ29: =IF(OR(BI29="",BI$16=0),"",BI29/$BI$16) -> 0.053 | BK29: =IF(BJ29="","",BH29-BJ29) -> -0.053 | BL29: =SUM(D29,I29,N29,S29,X29,AC29,AH29,AM29,AR29,AW29,BB29,BG29) -> 1342598 | BM29: =BL29/$BL$16 -> 0.030183135 | BN29: =F29+K29+P29+U29+Z29+AE29+AJ29+AO29+AT29+AY29+BD29+BI29 -> 15669766 | BO29: =IF(BN29="","",BN29/$BN$16) -> 0.053 | BP29: =IF(BO29="","",BM29-BO29) -> -0.022816865 | BQ29: 15006488 | BR29: =BQ29/$BQ$16 -> 0.054665929
A30: Tributaria | C30: ( - ) Tributária | D30: =SUMIF(EXTRATO!$F$14:$F$194,"Trib",EXTRATO!$I$14:$I$194)+SUMIF(DESPESA!$E$4:$E$140,"Trib",DESPESA!$I$4:$I$140) -> 351119.12 | E30: =D30/$D$16 -> 0.015013826 | F30: 0 | G30: =IF(OR(F30="",F$16=0),"",F30/$F$16) -> 0 | H30: =IF(G30="","",E30-G30) -> 0.015013826 | I30: =SUMIF(EXTRATO!$F$14:$F$194,"Trib",EXTRATO!$J$14:$J$194)+SUMIF(DESPESA!$E$4:$E$140,"Trib",DESPESA!$J$4:$J$140) -> 28998.06 | J30: =I30/$I$16 -> 0.0013746191 | K30: 0 | L30: =IF(OR(K30="",K$16=0),"",K30/$K$16) -> 0 | M30: =IF(L30="","",J30-L30) -> 0.0013746191 | O30: =IFERROR(N30/$N$16,"") | P30: 44672.397 | Q30: =IF(OR(P30="",P$16=0),"",P30/$P$16) -> 0.0019 | R30: =N30-P30 -> -44672.397 | T30: =S30/$D$16 -> 0 | U30: 46459.293 | V30: =IF(OR(U30="",U$16=0),"",U30/$U$16) -> 0.0019 | W30: =IF(V30="","",T30-V30) -> -0.0019 | Y30: =X30/$D$16 -> 0 | Z30: 48246.189 | AA30: =IF(OR(Z30="",Z$16=0),"",Z30/$Z$16) -> 0.0019 | AB30: =IF(AA30="","",Y30-AA30) -> -0.0019 | AD30: =AC30/$D$16 -> 0 | AE30: 46459.293 | AF30: =IF(OR(AE30="",AE$16=0),"",AE30/$AE$16) -> 0.0019 | AG30: =IF(AF30="","",AD30-AF30) -> -0.0019 | AI30: =AH30/$D$16 -> 0 | AJ30: 49675.706 | AK30: =IF(OR(AJ30="",AJ$16=0),"",AJ30/$AJ$16) -> 0.0019 | AL30: =IF(AK30="","",AI30-AK30) -> -0.0019 | AN30: =AM30/$D$16 -> 0 | AO30: 46637.983 | AP30: =IF(OR(AO30="",AO$16=0),"",AO30/$AO$16) -> 0.0019 | AQ30: =IF(AP30="","",AN30-AP30) -> -0.0019 | AS30: =AR30/$D$16 -> 0 | AT30: 46280.604 | AU30: =IF(OR(AT30="",AT$16=0),"",AT30/$AT$16) -> 0.0019 | AV30: =IF(AU30="","",AS30-AU30) -> -0.0019 | AX30: =AW30/$D$16 -> 0 | AY30: 49139.637 | AZ30: =IF(OR(AY30="",AY$16=0),"",AY30/$AY$16) -> 0.0019 | BA30: =IF(AZ30="","",AX30-AZ30) -> -0.0019 | BC30: =BB30/$D$16 -> 0 | BD30: 47888.81 | BE30: =IF(OR(BD30="",BD$16=0),"",BD30/$BD$16) -> 0.0019 | BF30: =IF(BE30="","",BC30-BE30) -> -0.0019 | BH30: =BG30/$D$16 -> 0 | BI30: 53785.566 | BJ30: =IF(OR(BI30="",BI$16=0),"",BI30/$BI$16) -> 0.0019 | BK30: =IF(BJ30="","",BH30-BJ30) -> -0.0019 | BL30: =SUM(D30,I30,N30,S30,X30,AC30,AH30,AM30,AR30,AW30,BB30,BG30) -> 380117.18 | BM30: =BL30/$BL$16 -> 0.0085454682 | BN30: =F30+K30+P30+U30+Z30+AE30+AJ30+AO30+AT30+AY30+BD30+BI30 -> 479245.48 | BO30: =IF(BN30="","",BN30/$BN$16) -> 0.0016209565 | BP30: =IF(BO30="","",BM30-BO30) -> 0.0069245116 | BQ30: 815860.6 | BR30: =BQ30/$BQ$16 -> 0.002972033
A31: Energia | C31: ( - ) Energia Elétrica | D31: =SUMIF(DESPESA!$E$4:$E$140,"Energia",DESPESA!$I$4:$I$140) -> 132780.12 | E31: =D31/$D$16 -> 0.0056776675 | F31: 101435.2 | G31: =IF(OR(F31="",F$16=0),"",F31/$F$16) -> 0.0048 | H31: =IF(G31="","",E31-G31) -> 0.00087766746 | I31: =SUMIF(DESPESA!$E$4:$E$140,"Energia",DESPESA!$J$4:$J$140) -> 136572.56 | J31: =I31/$I$16 -> 0.0064740626 | K31: 106988.04 | L31: =IF(OR(K31="",K$16=0),"",K31/$K$16) -> 0.0048 | M31: =IF(L31="","",J31-L31) -> 0.0016740626 | O31: =IFERROR(N31/$N$16,"") | P31: 112856.58 | Q31: =IF(OR(P31="",P$16=0),"",P31/$P$16) -> 0.0048 | R31: =N31-P31 -> -112856.58 | T31: =S31/$D$16 -> 0 | U31: 117370.85 | V31: =IF(OR(U31="",U$16=0),"",U31/$U$16) -> 0.0048 | W31: =IF(V31="","",T31-V31) -> -0.0048 | Y31: =X31/$D$16 -> 0 | Z31: 121885.11 | AA31: =IF(OR(Z31="",Z$16=0),"",Z31/$Z$16) -> 0.0048 | AB31: =IF(AA31="","",Y31-AA31) -> -0.0048 | AD31: =AC31/$D$16 -> 0 | AE31: 117370.85 | AF31: =IF(OR(AE31="",AE$16=0),"",AE31/$AE$16) -> 0.0048 | AG31: =IF(AF31="","",AD31-AF31) -> -0.0048 | AI31: =AH31/$D$16 -> 0 | AJ31: 125496.52 | AK31: =IF(OR(AJ31="",AJ$16=0),"",AJ31/$AJ$16) -> 0.0048 | AL31: =IF(AK31="","",AI31-AK31) -> -0.0048 | AN31: =AM31/$D$16 -> 0 | AO31: 117822.27 | AP31: =IF(OR(AO31="",AO$16=0),"",AO31/$AO$16) -> 0.0048 | AQ31: =IF(AP31="","",AN31-AP31) -> -0.0048 | AS31: =AR31/$D$16 -> 0 | AT31: 116919.42 | AU31: =IF(OR(AT31="",AT$16=0),"",AT31/$AT$16) -> 0.0048 | AV31: =IF(AU31="","",AS31-AU31) -> -0.0048 | AX31: =AW31/$D$16 -> 0 | AY31: 124142.24 | AZ31: =IF(OR(AY31="",AY$16=0),"",AY31/$AY$16) -> 0.0048 | BA31: =IF(AZ31="","",AX31-AZ31) -> -0.0048 | BC31: =BB31/$D$16 -> 0 | BD31: 120982.26 | BE31: =IF(OR(BD31="",BD$16=0),"",BD31/$BD$16) -> 0.0048 | BF31: =IF(BE31="","",BC31-BE31) -> -0.0048 | BH31: =BG31/$D$16 -> 0 | BI31: 135879.33 | BJ31: =IF(OR(BI31="",BI$16=0),"",BI31/$BI$16) -> 0.0048 | BK31: =IF(BJ31="","",BH31-BJ31) -> -0.0048 | BL31: =SUM(D31,I31,N31,S31,X31,AC31,AH31,AM31,AR31,AW31,BB31,BG31) -> 269352.68 | BM31: =BL31/$BL$16 -> 0.0060553557 | BN31: =F31+K31+P31+U31+Z31+AE31+AJ31+AO31+AT31+AY31+BD31+BI31 -> 1419148.7 | BO31: =IF(BN31="","",BN31/$BN$16) -> 0.0048 | BP31: =IF(BO31="","",BM31-BO31) -> 0.0012553557 | BQ31: 1317035.2 | BR31: =BQ31/$BQ$16 -> 0.0047977218
A32: Utilidades | C32: ( - ) Utilidades e Serviços | D32: =SUMIF(DESPESA!$E$4:$E$140,"Utilidades",DESPESA!$I$4:$I$140) -> 64318.61 | E32: =D32/$D$16 -> 0.0027502587 | F32: 61283.765 | G32: =IF(OR(F32="",F$16=0),"",F32/$F$16) -> 0.0029 | H32: =IF(G32="","",E32-G32) -> -0.00014974131 | I32: =SUMIF(DESPESA!$E$4:$E$140,"Utilidades",DESPESA!$J$4:$J$140) -> 43094.68 | J32: =I32/$I$16 -> 0.0020428529 | K32: 64638.608 | L32: =IF(OR(K32="",K$16=0),"",K32/$K$16) -> 0.0029 | M32: =IF(L32="","",J32-L32) -> -0.00085714706 | O32: =IFERROR(N32/$N$16,"") | P32: 68184.185 | Q32: =IF(OR(P32="",P$16=0),"",P32/$P$16) -> 0.0029 | R32: =N32-P32 -> -68184.185 | T32: =S32/$D$16 -> 0 | U32: 70911.553 | V32: =IF(OR(U32="",U$16=0),"",U32/$U$16) -> 0.0029 | W32: =IF(V32="","",T32-V32) -> -0.0029 | Y32: =X32/$D$16 -> 0 | Z32: 73638.92 | AA32: =IF(OR(Z32="",Z$16=0),"",Z32/$Z$16) -> 0.0029 | AB32: =IF(AA32="","",Y32-AA32) -> -0.0029 | AD32: =AC32/$D$16 -> 0 | AE32: 70911.553 | AF32: =IF(OR(AE32="",AE$16=0),"",AE32/$AE$16) -> 0.0029 | AG32: =IF(AF32="","",AD32-AF32) -> -0.0029 | AI32: =AH32/$D$16 -> 0 | AJ32: 75820.814 | AK32: =IF(OR(AJ32="",AJ$16=0),"",AJ32/$AJ$16) -> 0.0029 | AL32: =IF(AK32="","",AI32-AK32) -> -0.0029 | AN32: =AM32/$D$16 -> 0 | AO32: 71184.29 | AP32: =IF(OR(AO32="",AO$16=0),"",AO32/$AO$16) -> 0.0029 | AQ32: =IF(AP32="","",AN32-AP32) -> -0.0029 | AS32: =AR32/$D$16 -> 0 | AT32: 70638.816 | AU32: =IF(OR(AT32="",AT$16=0),"",AT32/$AT$16) -> 0.0029 | AV32: =IF(AU32="","",AS32-AU32) -> -0.0029 | AX32: =AW32/$D$16 -> 0 | AY32: 75002.604 | AZ32: =IF(OR(AY32="",AY$16=0),"",AY32/$AY$16) -> 0.0029 | BA32: =IF(AZ32="","",AX32-AZ32) -> -0.0029 | BC32: =BB32/$D$16 -> 0 | BD32: 73093.447 | BE32: =IF(OR(BD32="",BD$16=0),"",BD32/$BD$16) -> 0.0029 | BF32: =IF(BE32="","",BC32-BE32) -> -0.0029 | BH32: =BG32/$D$16 -> 0 | BI32: 82093.759 | BJ32: =IF(OR(BI32="",BI$16=0),"",BI32/$BI$16) -> 0.0029 | BK32: =IF(BJ32="","",BH32-BJ32) -> -0.0029 | BL32: =SUM(D32,I32,N32,S32,X32,AC32,AH32,AM32,AR32,AW32,BB32,BG32) -> 107413.29 | BM32: =BL32/$BL$16 -> 0.0024147734 | BN32: =F32+K32+P32+U32+Z32+AE32+AJ32+AO32+AT32+AY32+BD32+BI32 -> 857402.31 | BO32: =IF(BN32="","",BN32/$BN$16) -> 0.0029 | BP32: =IF(BO32="","",BM32-BO32) -> -0.00048522662 | BQ32: 772940.03 | BR32: =BQ32/$BQ$16 -> 0.0028156811
A33: Manut | C33: ( - ) Manutenções | D33: =SUMIF(DESPESA!$E$4:$E$140,"Manut",DESPESA!$I$4:$I$140) -> 88484.1 | E33: =D33/$D$16 -> 0.0037835731 | F33: 65510.232 | G33: =IF(OR(F33="",F$16=0),"",F33/$F$16) -> 0.0031 | H33: =IF(G33="","",E33-G33) -> 0.00068357314 | I33: =SUMIF(DESPESA!$E$4:$E$140,"Manut",DESPESA!$J$4:$J$140) -> 64908.81 | J33: =I33/$I$16 -> 0.0030769263 | K33: 69096.443 | L33: =IF(OR(K33="",K$16=0),"",K33/$K$16) -> 0.0031 | M33: =IF(L33="","",J33-L33) -> -2.3073727e-05 | O33: =IFERROR(N33/$N$16,"") | P33: 72886.543 | Q33: =IF(OR(P33="",P$16=0),"",P33/$P$16) -> 0.0031 | R33: =N33-P33 -> -72886.543 | T33: =S33/$D$16 -> 0 | U33: 75802.005 | V33: =IF(OR(U33="",U$16=0),"",U33/$U$16) -> 0.0031 | W33: =IF(V33="","",T33-V33) -> -0.0031 | Y33: =X33/$D$16 -> 0 | Z33: 78717.466 | AA33: =IF(OR(Z33="",Z$16=0),"",Z33/$Z$16) -> 0.0031 | AB33: =IF(AA33="","",Y33-AA33) -> -0.0031 | AD33: =AC33/$D$16 -> 0 | AE33: 75802.005 | AF33: =IF(OR(AE33="",AE$16=0),"",AE33/$AE$16) -> 0.0031 | AG33: =IF(AF33="","",AD33-AF33) -> -0.0031 | AI33: =AH33/$D$16 -> 0 | AJ33: 81049.836 | AK33: =IF(OR(AJ33="",AJ$16=0),"",AJ33/$AJ$16) -> 0.0031 | AL33: =IF(AK33="","",AI33-AK33) -> -0.0031 | AN33: =AM33/$D$16 -> 0 | AO33: 76093.551 | AP33: =IF(OR(AO33="",AO$16=0),"",AO33/$AO$16) -> 0.0031 | AQ33: =IF(AP33="","",AN33-AP33) -> -0.0031 | AS33: =AR33/$D$16 -> 0 | AT33: 75510.459 | AU33: =IF(OR(AT33="",AT$16=0),"",AT33/$AT$16) -> 0.0031 | AV33: =IF(AU33="","",AS33-AU33) -> -0.0031 | AX33: =AW33/$D$16 -> 0 | AY33: 80175.197 | AZ33: =IF(OR(AY33="",AY$16=0),"",AY33/$AY$16) -> 0.0031 | BA33: =IF(AZ33="","",AX33-AZ33) -> -0.0031 | BC33: =BB33/$D$16 -> 0 | BD33: 78134.374 | BE33: =IF(OR(BD33="",BD$16=0),"",BD33/$BD$16) -> 0.0031 | BF33: =IF(BE33="","",BC33-BE33) -> -0.0031 | BH33: =BG33/$D$16 -> 0 | BI33: 87755.398 | BJ33: =IF(OR(BI33="",BI$16=0),"",BI33/$BI$16) -> 0.0031 | BK33: =IF(BJ33="","",BH33-BJ33) -> -0.0031 | BL33: =SUM(D33,I33,N33,S33,X33,AC33,AH33,AM33,AR33,AW33,BB33,BG33) -> 153392.91 | BM33: =BL33/$BL$16 -> 0.0034484477 | BN33: =F33+K33+P33+U33+Z33+AE33+AJ33+AO33+AT33+AY33+BD33+BI33 -> 916533.51 | BO33: =IF(BN33="","",BN33/$BN$16) -> 0.0031 | BP33: =IF(BO33="","",BM33-BO33) -> 0.00034844773 | BQ33: 866623.75 | BR33: =BQ33/$BQ$16 -> 0.003156954
A34: Veiculos | C34: ( - ) Veículos | D34: =SUMIF(DESPESA!$E$4:$E$140,"Veiculos",DESPESA!$I$4:$I$140) -> 116819.73 | E34: =D34/$D$16 -> 0.0049952024 | F34: 95095.498 | G34: =IF(OR(F34="",F$16=0),"",F34/$F$16) -> 0.0045 | H34: =IF(G34="","",E34-G34) -> 0.00049520244 | I34: =SUMIF(DESPESA!$E$4:$E$140,"Veiculos",DESPESA!$J$4:$J$140) -> 61820.73 | J34: =I34/$I$16 -> 0.0029305394 | K34: 100301.29 | L34: =IF(OR(K34="",K$16=0),"",K34/$K$16) -> 0.0045 | M34: =IF(L34="","",J34-L34) -> -0.0015694606 | O34: =IFERROR(N34/$N$16,"") | P34: 105803.05 | Q34: =IF(OR(P34="",P$16=0),"",P34/$P$16) -> 0.0045 | R34: =N34-P34 -> -105803.05 | T34: =S34/$D$16 -> 0 | U34: 110035.17 | V34: =IF(OR(U34="",U$16=0),"",U34/$U$16) -> 0.0045 | W34: =IF(V34="","",T34-V34) -> -0.0045 | Y34: =X34/$D$16 -> 0 | Z34: 114267.29 | AA34: =IF(OR(Z34="",Z$16=0),"",Z34/$Z$16) -> 0.0045 | AB34: =IF(AA34="","",Y34-AA34) -> -0.0045 | AD34: =AC34/$D$16 -> 0 | AE34: 110035.17 | AF34: =IF(OR(AE34="",AE$16=0),"",AE34/$AE$16) -> 0.0045 | AG34: =IF(AF34="","",AD34-AF34) -> -0.0045 | AI34: =AH34/$D$16 -> 0 | AJ34: 117652.99 | AK34: =IF(OR(AJ34="",AJ$16=0),"",AJ34/$AJ$16) -> 0.0045 | AL34: =IF(AK34="","",AI34-AK34) -> -0.0045 | AN34: =AM34/$D$16 -> 0 | AO34: 110458.38 | AP34: =IF(OR(AO34="",AO$16=0),"",AO34/$AO$16) -> 0.0045 | AQ34: =IF(AP34="","",AN34-AP34) -> -0.0045 | AS34: =AR34/$D$16 -> 0 | AT34: 109611.96 | AU34: =IF(OR(AT34="",AT$16=0),"",AT34/$AT$16) -> 0.0045 | AV34: =IF(AU34="","",AS34-AU34) -> -0.0045 | AX34: =AW34/$D$16 -> 0 | AY34: 116383.35 | AZ34: =IF(OR(AY34="",AY$16=0),"",AY34/$AY$16) -> 0.0045 | BA34: =IF(AZ34="","",AX34-AZ34) -> -0.0045 | BC34: =BB34/$D$16 -> 0 | BD34: 113420.87 | BE34: =IF(OR(BD34="",BD$16=0),"",BD34/$BD$16) -> 0.0045 | BF34: =IF(BE34="","",BC34-BE34) -> -0.0045 | BH34: =BG34/$D$16 -> 0 | BI34: 127386.87 | BJ34: =IF(OR(BI34="",BI$16=0),"",BI34/$BI$16) -> 0.0045 | BK34: =IF(BJ34="","",BH34-BJ34) -> -0.0045 | BL34: =SUM(D34,I34,N34,S34,X34,AC34,AH34,AM34,AR34,AW34,BB34,BG34) -> 178640.46 | BM34: =BL34/$BL$16 -> 0.0040160415 | BN34: =F34+K34+P34+U34+Z34+AE34+AJ34+AO34+AT34+AY34+BD34+BI34 -> 1330451.9 | BO34: =IF(BN34="","",BN34/$BN$16) -> 0.0045 | BP34: =IF(BO34="","",BM34-BO34) -> -0.00048395852 | BQ34: 1264424.8 | BR34: =BQ34/$BQ$16 -> 0.0046060715
A35: M_Imovel | C35: ( - ) Manutenção Imóveis | D35: =SUMIF(DESPESA!$E$4:$E$140,"M_imovel",DESPESA!$I$4:$I$140) -> 11588.26 | E35: =D35/$D$16 -> 0.00049551308 | F35: 23245.566 | G35: =IF(OR(F35="",F$16=0),"",F35/$F$16) -> 0.0011 | H35: =IF(G35="","",E35-G35) -> -0.00060448692 | I35: =SUMIF(DESPESA!$E$4:$E$140,"M_imovel",DESPESA!$J$4:$J$140) -> 33400.69 | J35: =I35/$I$16 -> 0.0015833207 | K35: 24518.093 | L35: =IF(OR(K35="",K$16=0),"",K35/$K$16) -> 0.0011 | M35: =IF(L35="","",J35-L35) -> 0.00048332067 | O35: =IFERROR(N35/$N$16,"") | P35: 25862.967 | Q35: =IF(OR(P35="",P$16=0),"",P35/$P$16) -> 0.0011 | R35: =N35-P35 -> -25862.967 | T35: =S35/$D$16 -> 0 | U35: 26897.486 | V35: =IF(OR(U35="",U$16=0),"",U35/$U$16) -> 0.0011 | W35: =IF(V35="","",T35-V35) -> -0.0011 | Y35: =X35/$D$16 -> 0 | Z35: 27932.004 | AA35: =IF(OR(Z35="",Z$16=0),"",Z35/$Z$16) -> 0.0011 | AB35: =IF(AA35="","",Y35-AA35) -> -0.0011 | AD35: =AC35/$D$16 -> 0 | AE35: 26897.486 | AF35: =IF(OR(AE35="",AE$16=0),"",AE35/$AE$16) -> 0.0011 | AG35: =IF(AF35="","",AD35-AF35) -> -0.0011 | AI35: =AH35/$D$16 -> 0 | AJ35: 28759.619 | AK35: =IF(OR(AJ35="",AJ$16=0),"",AJ35/$AJ$16) -> 0.0011 | AL35: =IF(AK35="","",AI35-AK35) -> -0.0011 | AN35: =AM35/$D$16 -> 0 | AO35: 27000.937 | AP35: =IF(OR(AO35="",AO$16=0),"",AO35/$AO$16) -> 0.0011 | AQ35: =IF(AP35="","",AN35-AP35) -> -0.0011 | AS35: =AR35/$D$16 -> 0 | AT35: 26794.034 | AU35: =IF(OR(AT35="",AT$16=0),"",AT35/$AT$16) -> 0.0011 | AV35: =IF(AU35="","",AS35-AU35) -> -0.0011 | AX35: =AW35/$D$16 -> 0 | AY35: 28449.264 | AZ35: =IF(OR(AY35="",AY$16=0),"",AY35/$AY$16) -> 0.0011 | BA35: =IF(AZ35="","",AX35-AZ35) -> -0.0011 | BC35: =BB35/$D$16 -> 0 | BD35: 27725.1 | BE35: =IF(OR(BD35="",BD$16=0),"",BD35/$BD$16) -> 0.0011 | BF35: =IF(BE35="","",BC35-BE35) -> -0.0011 | BH35: =BG35/$D$16 -> 0 | BI35: 31139.012 | BJ35: =IF(OR(BI35="",BI$16=0),"",BI35/$BI$16) -> 0.0011 | BK35: =IF(BJ35="","",BH35-BJ35) -> -0.0011 | BL35: =SUM(D35,I35,N35,S35,X35,AC35,AH35,AM35,AR35,AW35,BB35,BG35) -> 44988.95 | BM35: =BL35/$BL$16 -> 0.001011403 | BN35: =F35+K35+P35+U35+Z35+AE35+AJ35+AO35+AT35+AY35+BD35+BI35 -> 325221.57 | BO35: =IF(BN35="","",BN35/$BN$16) -> 0.0011 | BP35: =IF(BO35="","",BM35-BO35) -> -8.8597044e-05 | BQ35: 326374.28 | BR35: =BQ35/$BQ$16 -> 0.0011889226
A36: Mkt | C36: ( - ) Propaganda/Marketing | D36: =SUMIF(DESPESA!$E$4:$E$140,"Mkt",DESPESA!$I$4:$I$140) -> 34024.39 | E36: =D36/$D$16 -> 0.0014548802 | F36: 35924.966 | G36: =IF(OR(F36="",F$16=0),"",F36/$F$16) -> 0.0017 | H36: =IF(G36="","",E36-G36) -> -0.00024511977 | I36: =SUMIF(DESPESA!$E$4:$E$140,"Mkt",DESPESA!$J$4:$J$140) -> 32165.39 | J36: =I36/$I$16 -> 0.0015247627 | K36: 37891.598 | L36: =IF(OR(K36="",K$16=0),"",K36/$K$16) -> 0.0017 | M36: =IF(L36="","",J36-L36) -> -0.00017523728 | O36: =IFERROR(N36/$N$16,"") | P36: 39970.04 | Q36: =IF(OR(P36="",P$16=0),"",P36/$P$16) -> 0.0017 | R36: =N36-P36 -> -39970.04 | T36: =S36/$D$16 -> 0 | U36: 41568.841 | V36: =IF(OR(U36="",U$16=0),"",U36/$U$16) -> 0.0017 | W36: =IF(V36="","",T36-V36) -> -0.0017 | Y36: =X36/$D$16 -> 0 | Z36: 43167.643 | AA36: =IF(OR(Z36="",Z$16=0),"",Z36/$Z$16) -> 0.0017 | AB36: =IF(AA36="","",Y36-AA36) -> -0.0017 | AD36: =AC36/$D$16 -> 0 | AE36: 41568.841 | AF36: =IF(OR(AE36="",AE$16=0),"",AE36/$AE$16) -> 0.0017 | AG36: =IF(AF36="","",AD36-AF36) -> -0.0017 | AI36: =AH36/$D$16 -> 0 | AJ36: 44446.684 | AK36: =IF(OR(AJ36="",AJ$16=0),"",AJ36/$AJ$16) -> 0.0017 | AL36: =IF(AK36="","",AI36-AK36) -> -0.0017 | AN36: =AM36/$D$16 -> 0 | AO36: 41728.721 | AP36: =IF(OR(AO36="",AO$16=0),"",AO36/$AO$16) -> 0.0017 | AQ36: =IF(AP36="","",AN36-AP36) -> -0.0017 | AS36: =AR36/$D$16 -> 0 | AT36: 41408.961 | AU36: =IF(OR(AT36="",AT$16=0),"",AT36/$AT$16) -> 0.0017 | AV36: =IF(AU36="","",AS36-AU36) -> -0.0017 | AX36: =AW36/$D$16 -> 0 | AY36: 43967.044 | AZ36: =IF(OR(AY36="",AY$16=0),"",AY36/$AY$16) -> 0.0017 | BA36: =IF(AZ36="","",AX36-AZ36) -> -0.0017 | BC36: =BB36/$D$16 -> 0 | BD36: 42847.883 | BE36: =IF(OR(BD36="",BD$16=0),"",BD36/$BD$16) -> 0.0017 | BF36: =IF(BE36="","",BC36-BE36) -> -0.0017 | BH36: =BG36/$D$16 -> 0 | BI36: 48123.928 | BJ36: =IF(OR(BI36="",BI$16=0),"",BI36/$BI$16) -> 0.0017 | BK36: =IF(BJ36="","",BH36-BJ36) -> -0.0017 | BL36: =SUM(D36,I36,N36,S36,X36,AC36,AH36,AM36,AR36,AW36,BB36,BG36) -> 66189.78 | BM36: =BL36/$BL$16 -> 0.0014880218 | BN36: =F36+K36+P36+U36+Z36+AE36+AJ36+AO36+AT36+AY36+BD36+BI36 -> 502615.15 | BO36: =IF(BN36="","",BN36/$BN$16) -> 0.0017 | BP36: =IF(BO36="","",BM36-BO36) -> -0.00021197818 | BQ36: 466819.31 | BR36: =BQ36/$BQ$16 -> 0.0017005386
A37: TI | C37: ( - ) Informática | D37: =SUMIF(DESPESA!$E$4:$E$140,"TI",DESPESA!$I$4:$I$140) -> 61500.14 | E37: =D37/$D$16 -> 0.0026297411 | F37: 46491.132 | G37: =IF(OR(F37="",F$16=0),"",F37/$F$16) -> 0.0022 | H37: =IF(G37="","",E37-G37) -> 0.00042974114 | I37: =SUMIF(DESPESA!$E$4:$E$140,"TI",DESPESA!$J$4:$J$140) -> 54331.93 | J37: =I37/$I$16 -> 0.0025755416 | K37: 49036.185 | L37: =IF(OR(K37="",K$16=0),"",K37/$K$16) -> 0.0022 | M37: =IF(L37="","",J37-L37) -> 0.00037554164 | O37: =IFERROR(N37/$N$16,"") | P37: 51725.934 | Q37: =IF(OR(P37="",P$16=0),"",P37/$P$16) -> 0.0022 | R37: =N37-P37 -> -51725.934 | T37: =S37/$D$16 -> 0 | U37: 53794.971 | V37: =IF(OR(U37="",U$16=0),"",U37/$U$16) -> 0.0022 | W37: =IF(V37="","",T37-V37) -> -0.0022 | Y37: =X37/$D$16 -> 0 | Z37: 55864.008 | AA37: =IF(OR(Z37="",Z$16=0),"",Z37/$Z$16) -> 0.0022 | AB37: =IF(AA37="","",Y37-AA37) -> -0.0022 | AD37: =AC37/$D$16 -> 0 | AE37: 53794.971 | AF37: =IF(OR(AE37="",AE$16=0),"",AE37/$AE$16) -> 0.0022 | AG37: =IF(AF37="","",AD37-AF37) -> -0.0022 | AI37: =AH37/$D$16 -> 0 | AJ37: 57519.238 | AK37: =IF(OR(AJ37="",AJ$16=0),"",AJ37/$AJ$16) -> 0.0022 | AL37: =IF(AK37="","",AI37-AK37) -> -0.0022 | AN37: =AM37/$D$16 -> 0 | AO37: 54001.875 | AP37: =IF(OR(AO37="",AO$16=0),"",AO37/$AO$16) -> 0.0022 | AQ37: =IF(AP37="","",AN37-AP37) -> -0.0022 | AS37: =AR37/$D$16 -> 0 | AT37: 53588.067 | AU37: =IF(OR(AT37="",AT$16=0),"",AT37/$AT$16) -> 0.0022 | AV37: =IF(AU37="","",AS37-AU37) -> -0.0022 | AX37: =AW37/$D$16 -> 0 | AY37: 56898.527 | AZ37: =IF(OR(AY37="",AY$16=0),"",AY37/$AY$16) -> 0.0022 | BA37: =IF(AZ37="","",AX37-AZ37) -> -0.0022 | BC37: =BB37/$D$16 -> 0 | BD37: 55450.201 | BE37: =IF(OR(BD37="",BD$16=0),"",BD37/$BD$16) -> 0.0022 | BF37: =IF(BE37="","",BC37-BE37) -> -0.0022 | BH37: =BG37/$D$16 -> 0 | BI37: 62278.024 | BJ37: =IF(OR(BI37="",BI$16=0),"",BI37/$BI$16) -> 0.0022 | BK37: =IF(BJ37="","",BH37-BJ37) -> -0.0022 | BL37: =SUM(D37,I37,N37,S37,X37,AC37,AH37,AM37,AR37,AW37,BB37,BG37) -> 115832.07 | BM37: =BL37/$BL$16 -> 0.0026040372 | BN37: =F37+K37+P37+U37+Z37+AE37+AJ37+AO37+AT37+AY37+BD37+BI37 -> 650443.13 | BO37: =IF(BN37="","",BN37/$BN$16) -> 0.0022 | BP37: =IF(BO37="","",BM37-BO37) -> 0.00040403717 | BQ37: 623702.39 | BR37: =BQ37/$BQ$16 -> 0.0022720353
A38: Coprporativo | C38: ( - ) Corporativo | D38: =SUMIF(DESPESA!$E$4:$E$140,"Corporativo",DESPESA!$I$4:$I$140) -> 243677.45 | E38: =D38/$D$16 -> 0.010419629 | F38: 230342.43 | G38: =IF(OR(F38="",F$16=0),"",F38/$F$16) -> 0.0109 | H38: =IF(G38="","",E38-G38) -> -0.00048037145 | I38: =SUMIF(DESPESA!$E$4:$E$140,"Corporativo",DESPESA!$J$4:$J$140) -> 199188.06 | J38: =I38/$I$16 -> 0.0094422772 | K38: 242952.01 | L38: =IF(OR(K38="",K$16=0),"",K38/$K$16) -> 0.0109 | M38: =IF(L38="","",J38-L38) -> -0.0014577228 | O38: =IFERROR(N38/$N$16,"") | P38: 256278.49 | Q38: =IF(OR(P38="",P$16=0),"",P38/$P$16) -> 0.0109 | R38: =N38-P38 -> -256278.49 | T38: =S38/$D$16 -> 0 | U38: 266529.63 | V38: =IF(OR(U38="",U$16=0),"",U38/$U$16) -> 0.0109 | W38: =IF(V38="","",T38-V38) -> -0.0109 | Y38: =X38/$D$16 -> 0 | Z38: 276780.77 | AA38: =IF(OR(Z38="",Z$16=0),"",Z38/$Z$16) -> 0.0109 | AB38: =IF(AA38="","",Y38-AA38) -> -0.0109 | AD38: =AC38/$D$16 -> 0 | AE38: 266529.63 | AF38: =IF(OR(AE38="",AE$16=0),"",AE38/$AE$16) -> 0.0109 | AG38: =IF(AF38="","",AD38-AF38) -> -0.0109 | AI38: =AH38/$D$16 -> 0 | AJ38: 284981.68 | AK38: =IF(OR(AJ38="",AJ$16=0),"",AJ38/$AJ$16) -> 0.0109 | AL38: =IF(AK38="","",AI38-AK38) -> -0.0109 | AN38: =AM38/$D$16 -> 0 | AO38: 267554.74 | AP38: =IF(OR(AO38="",AO$16=0),"",AO38/$AO$16) -> 0.0109 | AQ38: =IF(AP38="","",AN38-AP38) -> -0.0109 | AS38: =AR38/$D$16 -> 0 | AT38: 265504.52 | AU38: =IF(OR(AT38="",AT$16=0),"",AT38/$AT$16) -> 0.0109 | AV38: =IF(AU38="","",AS38-AU38) -> -0.0109 | AX38: =AW38/$D$16 -> 0 | AY38: 281906.34 | AZ38: =IF(OR(AY38="",AY$16=0),"",AY38/$AY$16) -> 0.0109 | BA38: =IF(AZ38="","",AX38-AZ38) -> -0.0109 | BC38: =BB38/$D$16 -> 0 | BD38: 274730.54 | BE38: =IF(OR(BD38="",BD$16=0),"",BD38/$BD$16) -> 0.0109 | BF38: =IF(BE38="","",BC38-BE38) -> -0.0109 | BH38: =BG38/$D$16 -> 0 | BI38: 308559.3 | BJ38: =IF(OR(BI38="",BI$16=0),"",BI38/$BI$16) -> 0.0109 | BK38: =IF(BJ38="","",BH38-BJ38) -> -0.0109 | BL38: =SUM(D38,I38,N38,S38,X38,AC38,AH38,AM38,AR38,AW38,BB38,BG38) -> 442865.51 | BM38: =BL38/$BL$16 -> 0.0099561222 | BN38: =F38+K38+P38+U38+Z38+AE38+AJ38+AO38+AT38+AY38+BD38+BI38 -> 3222650.1 | BO38: =IF(BN38="","",BN38/$BN$16) -> 0.0109 | BP38: =IF(BO38="","",BM38-BO38) -> -0.00094387776 | BQ38: 3446885.3 | BR38: =BQ38/$BQ$16 -> 0.012556381
A39: Ligadas | C39: ( - ) Ligadas | D39: =SUMIF(DESPESA!$E$4:$E$140,"Ligadas",DESPESA!$I$4:$I$140) -> 190000 | E39: =D39/$D$16 -> 0.008124385 | F39: 154266.03 | G39: =IF(OR(F39="",F$16=0),"",F39/$F$16) -> 0.0073 | H39: =IF(G39="","",E39-G39) -> 0.00082438502 | I39: =SUMIF(DESPESA!$E$4:$E$140,"Ligadas",DESPESA!$J$4:$J$140) -> 220000 | J39: =I39/$I$16 -> 0.010428843 | K39: 162710.98 | L39: =IF(OR(K39="",K$16=0),"",K39/$K$16) -> 0.0073 | M39: =IF(L39="","",J39-L39) -> 0.0031288429 | O39: =IFERROR(N39/$N$16,"") | P39: 171636.05 | Q39: =IF(OR(P39="",P$16=0),"",P39/$P$16) -> 0.0073 | R39: =N39-P39 -> -171636.05 | T39: =S39/$D$16 -> 0 | U39: 178501.5 | V39: =IF(OR(U39="",U$16=0),"",U39/$U$16) -> 0.0073 | W39: =IF(V39="","",T39-V39) -> -0.0073 | Y39: =X39/$D$16 -> 0 | Z39: 185366.94 | AA39: =IF(OR(Z39="",Z$16=0),"",Z39/$Z$16) -> 0.0073 | AB39: =IF(AA39="","",Y39-AA39) -> -0.0073 | AD39: =AC39/$D$16 -> 0 | AE39: 178501.5 | AF39: =IF(OR(AE39="",AE$16=0),"",AE39/$AE$16) -> 0.0073 | AG39: =IF(AF39="","",AD39-AF39) -> -0.0073 | AI39: =AH39/$D$16 -> 0 | AJ39: 190859.29 | AK39: =IF(OR(AJ39="",AJ$16=0),"",AJ39/$AJ$16) -> 0.0073 | AL39: =IF(AK39="","",AI39-AK39) -> -0.0073 | AN39: =AM39/$D$16 -> 0 | AO39: 179188.04 | AP39: =IF(OR(AO39="",AO$16=0),"",AO39/$AO$16) -> 0.0073 | AQ39: =IF(AP39="","",AN39-AP39) -> -0.0073 | AS39: =AR39/$D$16 -> 0 | AT39: 177814.95 | AU39: =IF(OR(AT39="",AT$16=0),"",AT39/$AT$16) -> 0.0073 | AV39: =IF(AU39="","",AS39-AU39) -> -0.0073 | AX39: =AW39/$D$16 -> 0 | AY39: 188799.66 | AZ39: =IF(OR(AY39="",AY$16=0),"",AY39/$AY$16) -> 0.0073 | BA39: =IF(AZ39="","",AX39-AZ39) -> -0.0073 | BC39: =BB39/$D$16 -> 0 | BD39: 183993.85 | BE39: =IF(OR(BD39="",BD$16=0),"",BD39/$BD$16) -> 0.0073 | BF39: =IF(BE39="","",BC39-BE39) -> -0.0073 | BH39: =BG39/$D$16 -> 0 | BI39: 206649.81 | BJ39: =IF(OR(BI39="",BI$16=0),"",BI39/$BI$16) -> 0.0073 | BK39: =IF(BJ39="","",BH39-BJ39) -> -0.0073 | BL39: =SUM(D39,I39,N39,S39,X39,AC39,AH39,AM39,AR39,AW39,BB39,BG39) -> 410000 | BM39: =BL39/$BL$16 -> 0.0092172681 | BN39: =F39+K39+P39+U39+Z39+AE39+AJ39+AO39+AT39+AY39+BD39+BI39 -> 2158288.6 | BO39: =IF(BN39="","",BN39/$BN$16) -> 0.0073 | BP39: =IF(BO39="","",BM39-BO39) -> 0.0019172681 | BQ39: 1928000 | BR39: =BQ39/$BQ$16 -> 0.0070233563
A40: Operacional | C40: ( - ) Prestadores de Serviços Operacionais | D40: =SUMIF(DESPESA!$E$4:$E$140,"Operacional",DESPESA!$I$4:$I$140) -> 59810.6 | E40: =D40/$D$16 -> 0.0025574965 | F40: 50717.599 | G40: =IF(OR(F40="",F$16=0),"",F40/$F$16) -> 0.0024 | H40: =IF(G40="","",E40-G40) -> 0.00015749654 | I40: =SUMIF(DESPESA!$E$4:$E$140,"Operacional",DESPESA!$J$4:$J$140) -> 41209.09 | J40: =I40/$I$16 -> 0.0019534687 | K40: 53494.02 | L40: =IF(OR(K40="",K$16=0),"",K40/$K$16) -> 0.0024 | M40: =IF(L40="","",J40-L40) -> -0.00044653125 | O40: =IFERROR(N40/$N$16,"") | P40: 56428.291 | Q40: =IF(OR(P40="",P$16=0),"",P40/$P$16) -> 0.0024 | R40: =N40-P40 -> -56428.291 | T40: =S40/$D$16 -> 0 | U40: 58685.423 | V40: =IF(OR(U40="",U$16=0),"",U40/$U$16) -> 0.0024 | W40: =IF(V40="","",T40-V40) -> -0.0024 | Y40: =X40/$D$16 -> 0 | Z40: 60942.555 | AA40: =IF(OR(Z40="",Z$16=0),"",Z40/$Z$16) -> 0.0024 | AB40: =IF(AA40="","",Y40-AA40) -> -0.0024 | AD40: =AC40/$D$16 -> 0 | AE40: 58685.423 | AF40: =IF(OR(AE40="",AE$16=0),"",AE40/$AE$16) -> 0.0024 | AG40: =IF(AF40="","",AD40-AF40) -> -0.0024 | AI40: =AH40/$D$16 -> 0 | AJ40: 62748.26 | AK40: =IF(OR(AJ40="",AJ$16=0),"",AJ40/$AJ$16) -> 0.0024 | AL40: =IF(AK40="","",AI40-AK40) -> -0.0024 | AN40: =AM40/$D$16 -> 0 | AO40: 58911.136 | AP40: =IF(OR(AO40="",AO$16=0),"",AO40/$AO$16) -> 0.0024 | AQ40: =IF(AP40="","",AN40-AP40) -> -0.0024 | AS40: =AR40/$D$16 -> 0 | AT40: 58459.71 | AU40: =IF(OR(AT40="",AT$16=0),"",AT40/$AT$16) -> 0.0024 | AV40: =IF(AU40="","",AS40-AU40) -> -0.0024 | AX40: =AW40/$D$16 -> 0 | AY40: 62071.121 | AZ40: =IF(OR(AY40="",AY$16=0),"",AY40/$AY$16) -> 0.0024 | BA40: =IF(AZ40="","",AX40-AZ40) -> -0.0024 | BC40: =BB40/$D$16 -> 0 | BD40: 60491.128 | BE40: =IF(OR(BD40="",BD$16=0),"",BD40/$BD$16) -> 0.0024 | BF40: =IF(BE40="","",BC40-BE40) -> -0.0024 | BH40: =BG40/$D$16 -> 0 | BI40: 67939.663 | BJ40: =IF(OR(BI40="",BI$16=0),"",BI40/$BI$16) -> 0.0024 | BK40: =IF(BJ40="","",BH40-BJ40) -> -0.0024 | BL40: =SUM(D40,I40,N40,S40,X40,AC40,AH40,AM40,AR40,AW40,BB40,BG40) -> 101019.69 | BM40: =BL40/$BL$16 -> 0.002271038 | BN40: =F40+K40+P40+U40+Z40+AE40+AJ40+AO40+AT40+AY40+BD40+BI40 -> 709574.33 | BO40: =IF(BN40="","",BN40/$BN$16) -> 0.0024 | BP40: =IF(BO40="","",BM40-BO40) -> -0.00012896204 | BQ40: 695551.73 | BR40: =BQ40/$BQ$16 -> 0.0025337695
A41: Viagens | C41: ( - ) Viagens | D41: =SUMIF(DESPESA!$E$4:$E$140,"Viagens",DESPESA!$I$4:$I$140) -> 260 | E41: =D41/$D$16 -> 1.1117579e-05 | F41: 0 | G41: =IF(OR(F41="",F$16=0),"",F41/$F$16) -> 0 | H41: =IF(G41="","",E41-G41) -> 1.1117579e-05 | I41: =SUMIF(DESPESA!$E$4:$E$140,"Viagens",DESPESA!$J$4:$J$140) -> 0 | J41: =I41/$I$16 -> 0 | K41: 0 | L41: =IF(OR(K41="",K$16=0),"",K41/$K$16) -> 0 | M41: =IF(L41="","",J41-L41) -> 0 | O41: =IFERROR(N41/$N$16,"") | P41: 2351.1788 | Q41: =IF(OR(P41="",P$16=0),"",P41/$P$16) -> 0.0001 | R41: =N41-P41 -> -2351.1788 | T41: =S41/$D$16 -> 0 | U41: 2445.226 | V41: =IF(OR(U41="",U$16=0),"",U41/$U$16) -> 0.0001 | W41: =IF(V41="","",T41-V41) -> -0.0001 | Y41: =X41/$D$16 -> 0 | Z41: 2539.2731 | AA41: =IF(OR(Z41="",Z$16=0),"",Z41/$Z$16) -> 0.0001 | AB41: =IF(AA41="","",Y41-AA41) -> -0.0001 | AD41: =AC41/$D$16 -> 0 | AE41: 2445.226 | AF41: =IF(OR(AE41="",AE$16=0),"",AE41/$AE$16) -> 0.0001 | AG41: =IF(AF41="","",AD41-AF41) -> -0.0001 | AI41: =AH41/$D$16 -> 0 | AJ41: 2614.5108 | AK41: =IF(OR(AJ41="",AJ$16=0),"",AJ41/$AJ$16) -> 0.0001 | AL41: =IF(AK41="","",AI41-AK41) -> -0.0001 | AN41: =AM41/$D$16 -> 0 | AO41: 2454.6307 | AP41: =IF(OR(AO41="",AO$16=0),"",AO41/$AO$16) -> 0.0001 | AQ41: =IF(AP41="","",AN41-AP41) -> -0.0001 | AS41: =AR41/$D$16 -> 0 | AT41: 2435.8212 | AU41: =IF(OR(AT41="",AT$16=0),"",AT41/$AT$16) -> 0.0001 | AV41: =IF(AU41="","",AS41-AU41) -> -0.0001 | AX41: =AW41/$D$16 -> 0 | AY41: 2586.2967 | AZ41: =IF(OR(AY41="",AY$16=0),"",AY41/$AY$16) -> 0.0001 | BA41: =IF(AZ41="","",AX41-AZ41) -> -0.0001 | BC41: =BB41/$D$16 -> 0 | BD41: 2520.4637 | BE41: =IF(OR(BD41="",BD$16=0),"",BD41/$BD$16) -> 0.0001 | BF41: =IF(BE41="","",BC41-BE41) -> -0.0001 | BH41: =BG41/$D$16 -> 0 | BI41: 2830.8193 | BJ41: =IF(OR(BI41="",BI$16=0),"",BI41/$BI$16) -> 0.0001 | BK41: =IF(BJ41="","",BH41-BJ41) -> -0.0001 | BL41: =SUM(D41,I41,N41,S41,X41,AC41,AH41,AM41,AR41,AW41,BB41,BG41) -> 260 | BM41: =BL41/$BL$16 -> 5.8450968e-06 | BN41: =F41+K41+P41+U41+Z41+AE41+AJ41+AO41+AT41+AY41+BD41+BI41 -> 25223.446 | BO41: =IF(BN41="","",BN41/$BN$16) -> 8.5313502e-05 | BP41: =IF(BO41="","",BM41-BO41) -> -7.9468405e-05 | BQ41: 21960 | BR41: =BQ41/$BQ$16 -> 7.999632e-05
A42: Expediente | C42: ( - ) Expediente | D42: =SUMIF(DESPESA!$E$4:$E$140,"Expediente",DESPESA!$I$4:$I$140) -> 4740.53 | E42: =D42/$D$16 -> 0.00020270469 | F42: 6339.6999 | G42: =IF(OR(F42="",F$16=0),"",F42/$F$16) -> 0.0003 | H42: =IF(G42="","",E42-G42) -> -9.7295311e-05 | I42: =SUMIF(DESPESA!$E$4:$E$140,"Expediente",DESPESA!$J$4:$J$140) -> 5285.51 | J42: =I42/$I$16 -> 0.00025055342 | K42: 6686.7525 | L42: =IF(OR(K42="",K$16=0),"",K42/$K$16) -> 0.0003 | M42: =IF(L42="","",J42-L42) -> -4.9446576e-05 | O42: =IFERROR(N42/$N$16,"") | P42: 7053.5364 | Q42: =IF(OR(P42="",P$16=0),"",P42/$P$16) -> 0.0003 | R42: =N42-P42 -> -7053.5364 | T42: =S42/$D$16 -> 0 | U42: 7335.6779 | V42: =IF(OR(U42="",U$16=0),"",U42/$U$16) -> 0.0003 | W42: =IF(V42="","",T42-V42) -> -0.0003 | Y42: =X42/$D$16 -> 0 | Z42: 7617.8193 | AA42: =IF(OR(Z42="",Z$16=0),"",Z42/$Z$16) -> 0.0003 | AB42: =IF(AA42="","",Y42-AA42) -> -0.0003 | AD42: =AC42/$D$16 -> 0 | AE42: 7335.6779 | AF42: =IF(OR(AE42="",AE$16=0),"",AE42/$AE$16) -> 0.0003 | AG42: =IF(AF42="","",AD42-AF42) -> -0.0003 | AI42: =AH42/$D$16 -> 0 | AJ42: 7843.5325 | AK42: =IF(OR(AJ42="",AJ$16=0),"",AJ42/$AJ$16) -> 0.0003 | AL42: =IF(AK42="","",AI42-AK42) -> -0.0003 | AN42: =AM42/$D$16 -> 0 | AO42: 7363.892 | AP42: =IF(OR(AO42="",AO$16=0),"",AO42/$AO$16) -> 0.0003 | AQ42: =IF(AP42="","",AN42-AP42) -> -0.0003 | AS42: =AR42/$D$16 -> 0 | AT42: 7307.4637 | AU42: =IF(OR(AT42="",AT$16=0),"",AT42/$AT$16) -> 0.0003 | AV42: =IF(AU42="","",AS42-AU42) -> -0.0003 | AX42: =AW42/$D$16 -> 0 | AY42: 7758.8901 | AZ42: =IF(OR(AY42="",AY$16=0),"",AY42/$AY$16) -> 0.0003 | BA42: =IF(AZ42="","",AX42-AZ42) -> -0.0003 | BC42: =BB42/$D$16 -> 0 | BD42: 7561.391 | BE42: =IF(OR(BD42="",BD$16=0),"",BD42/$BD$16) -> 0.0003 | BF42: =IF(BE42="","",BC42-BE42) -> -0.0003 | BH42: =BG42/$D$16 -> 0 | BI42: 8492.4579 | BJ42: =IF(OR(BI42="",BI$16=0),"",BI42/$BI$16) -> 0.0003 | BK42: =IF(BJ42="","",BH42-BJ42) -> -0.0003 | BL42: =SUM(D42,I42,N42,S42,X42,AC42,AH42,AM42,AR42,AW42,BB42,BG42) -> 10026.04 | BM42: =BL42/$BL$16 -> 0.00022539682 | BN42: =F42+K42+P42+U42+Z42+AE42+AJ42+AO42+AT42+AY42+BD42+BI42 -> 88696.791 | BO42: =IF(BN42="","",BN42/$BN$16) -> 0.0003 | BP42: =IF(BO42="","",BM42-BO42) -> -7.4603175e-05 | BQ42: 80894.75 | BR42: =BQ42/$BQ$16 -> 0.00029468499
A43: Embalagens | C43: ( - ) Embalagens | D43: =SUMIF(DESPESA!$E$4:$E$140,"Embalagens",DESPESA!$I$4:$I$140) -> 168 | E43: =D43/$D$16 -> 7.1836668e-06 | F43: 0 | G43: =IF(OR(F43="",F$16=0),"",F43/$F$16) -> 0 | H43: =IF(G43="","",E43-G43) -> 7.1836668e-06 | I43: =SUMIF(DESPESA!$E$4:$E$140,"Embalagens",DESPESA!$J$4:$J$140) -> 0 | J43: =I43/$I$16 -> 0 | K43: 0 | L43: =IF(OR(K43="",K$16=0),"",K43/$K$16) -> 0 | M43: =IF(L43="","",J43-L43) -> 0 | O43: =IFERROR(N43/$N$16,"") | P43: 235.11788 | Q43: =IF(OR(P43="",P$16=0),"",P43/$P$16) -> 1e-05 | R43: =N43-P43 -> -235.11788 | T43: =S43/$D$16 -> 0 | U43: 244.5226 | V43: =IF(OR(U43="",U$16=0),"",U43/$U$16) -> 1e-05 | W43: =IF(V43="","",T43-V43) -> -1e-05 | Y43: =X43/$D$16 -> 0 | Z43: 253.92731 | AA43: =IF(OR(Z43="",Z$16=0),"",Z43/$Z$16) -> 1e-05 | AB43: =IF(AA43="","",Y43-AA43) -> -1e-05 | AD43: =AC43/$D$16 -> 0 | AE43: 244.5226 | AF43: =IF(OR(AE43="",AE$16=0),"",AE43/$AE$16) -> 1e-05 | AG43: =IF(AF43="","",AD43-AF43) -> -1e-05 | AI43: =AH43/$D$16 -> 0 | AJ43: 261.45108 | AK43: =IF(OR(AJ43="",AJ$16=0),"",AJ43/$AJ$16) -> 1e-05 | AL43: =IF(AK43="","",AI43-AK43) -> -1e-05 | AN43: =AM43/$D$16 -> 0 | AO43: 245.46307 | AP43: =IF(OR(AO43="",AO$16=0),"",AO43/$AO$16) -> 1e-05 | AQ43: =IF(AP43="","",AN43-AP43) -> -1e-05 | AS43: =AR43/$D$16 -> 0 | AT43: 243.58212 | AU43: =IF(OR(AT43="",AT$16=0),"",AT43/$AT$16) -> 1e-05 | AV43: =IF(AU43="","",AS43-AU43) -> -1e-05 | AX43: =AW43/$D$16 -> 0 | AY43: 258.62967 | AZ43: =IF(OR(AY43="",AY$16=0),"",AY43/$AY$16) -> 1e-05 | BA43: =IF(AZ43="","",AX43-AZ43) -> -1e-05 | BC43: =BB43/$D$16 -> 0 | BD43: 252.04637 | BE43: =IF(OR(BD43="",BD$16=0),"",BD43/$BD$16) -> 1e-05 | BF43: =IF(BE43="","",BC43-BE43) -> -1e-05 | BH43: =BG43/$D$16 -> 0 | BI43: 283.08193 | BJ43: =IF(OR(BI43="",BI$16=0),"",BI43/$BI$16) -> 1e-05 | BK43: =IF(BJ43="","",BH43-BJ43) -> -1e-05 | BL43: =SUM(D43,I43,N43,S43,X43,AC43,AH43,AM43,AR43,AW43,BB43,BG43) -> 168 | BM43: =BL43/$BL$16 -> 3.7768318e-06 | BN43: =F43+K43+P43+U43+Z43+AE43+AJ43+AO43+AT43+AY43+BD43+BI43 -> 2522.3446 | BO43: =IF(BN43="","",BN43/$BN$16) -> 8.5313502e-06 | BP43: =IF(BO43="","",BM43-BO43) -> -4.7545184e-06 | BQ43: 1338.14 | BR43: =BQ43/$BQ$16 -> 4.8746027e-06
A44: Fretes | C44: ( - ) Fretes | D44: =SUMIF(DESPESA!$E$4:$E$140,"Fretes",DESPESA!$I$4:$I$140) -> 15660 | E44: =D44/$D$16 -> 0.00066962037 | F44: 21132.333 | G44: =IF(OR(F44="",F$16=0),"",F44/$F$16) -> 0.001 | H44: =IF(G44="","",E44-G44) -> -0.00033037963 | I44: =SUMIF(DESPESA!$E$4:$E$140,"Fretes",DESPESA!$J$4:$J$140) -> 20175 | J44: =I44/$I$16 -> 0.00095637229 | K44: 22289.175 | L44: =IF(OR(K44="",K$16=0),"",K44/$K$16) -> 0.001 | M44: =IF(L44="","",J44-L44) -> -4.3627706e-05 | O44: =IFERROR(N44/$N$16,"") | P44: 23511.788 | Q44: =IF(OR(P44="",P$16=0),"",P44/$P$16) -> 0.001 | R44: =N44-P44 -> -23511.788 | T44: =S44/$D$16 -> 0 | U44: 24452.26 | V44: =IF(OR(U44="",U$16=0),"",U44/$U$16) -> 0.001 | W44: =IF(V44="","",T44-V44) -> -0.001 | Y44: =X44/$D$16 -> 0 | Z44: 25392.731 | AA44: =IF(OR(Z44="",Z$16=0),"",Z44/$Z$16) -> 0.001 | AB44: =IF(AA44="","",Y44-AA44) -> -0.001 | AD44: =AC44/$D$16 -> 0 | AE44: 24452.26 | AF44: =IF(OR(AE44="",AE$16=0),"",AE44/$AE$16) -> 0.001 | AG44: =IF(AF44="","",AD44-AF44) -> -0.001 | AI44: =AH44/$D$16 -> 0 | AJ44: 26145.108 | AK44: =IF(OR(AJ44="",AJ$16=0),"",AJ44/$AJ$16) -> 0.001 | AL44: =IF(AK44="","",AI44-AK44) -> -0.001 | AN44: =AM44/$D$16 -> 0 | AO44: 24546.307 | AP44: =IF(OR(AO44="",AO$16=0),"",AO44/$AO$16) -> 0.001 | AQ44: =IF(AP44="","",AN44-AP44) -> -0.001 | AS44: =AR44/$D$16 -> 0 | AT44: 24358.212 | AU44: =IF(OR(AT44="",AT$16=0),"",AT44/$AT$16) -> 0.001 | AV44: =IF(AU44="","",AS44-AU44) -> -0.001 | AX44: =AW44/$D$16 -> 0 | AY44: 25862.967 | AZ44: =IF(OR(AY44="",AY$16=0),"",AY44/$AY$16) -> 0.001 | BA44: =IF(AZ44="","",AX44-AZ44) -> -0.001 | BC44: =BB44/$D$16 -> 0 | BD44: 25204.637 | BE44: =IF(OR(BD44="",BD$16=0),"",BD44/$BD$16) -> 0.001 | BF44: =IF(BE44="","",BC44-BE44) -> -0.001 | BH44: =BG44/$D$16 -> 0 | BI44: 28308.193 | BJ44: =IF(OR(BI44="",BI$16=0),"",BI44/$BI$16) -> 0.001 | BK44: =IF(BJ44="","",BH44-BJ44) -> -0.001 | BL44: =SUM(D44,I44,N44,S44,X44,AC44,AH44,AM44,AR44,AW44,BB44,BG44) -> 35835 | BM44: =BL44/$BL$16 -> 0.00080561171 | BN44: =F44+K44+P44+U44+Z44+AE44+AJ44+AO44+AT44+AY44+BD44+BI44 -> 295655.97 | BO44: =IF(BN44="","",BN44/$BN$16) -> 0.001 | BP44: =IF(BO44="","",BM44-BO44) -> -0.00019438829 | BQ44: 270473.94 | BR44: =BQ44/$BQ$16 -> 0.00098528779
A45: Indedutiveis | C45: ( - ) Indedutiveis | D45: =SUMIF(DESPESA!$E$4:$E$140,"Indedutiveis",DESPESA!$I$4:$I$140) -> 13357.08 | E45: =D45/$D$16 -> 0.00057114769 | F45: 33811.733 | G45: =IF(OR(F45="",F$16=0),"",F45/$F$16) -> 0.0016 | H45: =IF(G45="","",E45-G45) -> -0.0010288523 | I45: =SUMIF(DESPESA!$E$4:$E$140,"Indedutiveis",DESPESA!$J$4:$J$140) -> 23724.09 | J45: =I45/$I$16 -> 0.0011246128 | K45: 35662.68 | L45: =IF(OR(K45="",K$16=0),"",K45/$K$16) -> 0.0016 | M45: =IF(L45="","",J45-L45) -> -0.00047538724 | O45: =IFERROR(N45/$N$16,"") | P45: 37618.861 | Q45: =IF(OR(P45="",P$16=0),"",P45/$P$16) -> 0.0016 | R45: =N45-P45 -> -37618.861 | T45: =S45/$D$16 -> 0 | U45: 39123.615 | V45: =IF(OR(U45="",U$16=0),"",U45/$U$16) -> 0.0016 | W45: =IF(V45="","",T45-V45) -> -0.0016 | Y45: =X45/$D$16 -> 0 | Z45: 40628.37 | AA45: =IF(OR(Z45="",Z$16=0),"",Z45/$Z$16) -> 0.0016 | AB45: =IF(AA45="","",Y45-AA45) -> -0.0016 | AD45: =AC45/$D$16 -> 0 | AE45: 39123.615 | AF45: =IF(OR(AE45="",AE$16=0),"",AE45/$AE$16) -> 0.0016 | AG45: =IF(AF45="","",AD45-AF45) -> -0.0016 | AI45: =AH45/$D$16 -> 0 | AJ45: 41832.173 | AK45: =IF(OR(AJ45="",AJ$16=0),"",AJ45/$AJ$16) -> 0.0016 | AL45: =IF(AK45="","",AI45-AK45) -> -0.0016 | AN45: =AM45/$D$16 -> 0 | AO45: 39274.091 | AP45: =IF(OR(AO45="",AO$16=0),"",AO45/$AO$16) -> 0.0016 | AQ45: =IF(AP45="","",AN45-AP45) -> -0.0016 | AS45: =AR45/$D$16 -> 0 | AT45: 38973.14 | AU45: =IF(OR(AT45="",AT$16=0),"",AT45/$AT$16) -> 0.0016 | AV45: =IF(AU45="","",AS45-AU45) -> -0.0016 | AX45: =AW45/$D$16 -> 0 | AY45: 41380.747 | AZ45: =IF(OR(AY45="",AY$16=0),"",AY45/$AY$16) -> 0.0016 | BA45: =IF(AZ45="","",AX45-AZ45) -> -0.0016 | BC45: =BB45/$D$16 -> 0 | BD45: 40327.419 | BE45: =IF(OR(BD45="",BD$16=0),"",BD45/$BD$16) -> 0.0016 | BF45: =IF(BE45="","",BC45-BE45) -> -0.0016 | BH45: =BG45/$D$16 -> 0 | BI45: 45293.109 | BJ45: =IF(OR(BI45="",BI$16=0),"",BI45/$BI$16) -> 0.0016 | BK45: =IF(BJ45="","",BH45-BJ45) -> -0.0016 | BL45: =SUM(D45,I45,N45,S45,X45,AC45,AH45,AM45,AR45,AW45,BB45,BG45) -> 37081.17 | BM45: =BL45/$BL$16 -> 0.00083362703 | BN45: =F45+K45+P45+U45+Z45+AE45+AJ45+AO45+AT45+AY45+BD45+BI45 -> 473049.55 | BO45: =IF(BN45="","",BN45/$BN$16) -> 0.0016 | BP45: =IF(BO45="","",BM45-BO45) -> -0.00076637297 | BQ45: 403590.85 | BR45: =BQ45/$BQ$16 -> 0.0014702087
A46: Almoxarifado | C46: ( - ) Almoxarifado | D46: =SUMIF(DESPESA!$E$4:$E$140,"Almoxarifado",DESPESA!$I$4:$I$140) -> 241419.66 | E46: =D46/$D$16 -> 0.010323086 | F46: 211323.33 | G46: =IF(OR(F46="",F$16=0),"",F46/$F$16) -> 0.01 | H46: =IF(G46="","",E46-G46) -> 0.00032308563 | I46: =SUMIF(DESPESA!$E$4:$E$140,"Almoxarifado",DESPESA!$J$4:$J$140) -> 168908.44 | J46: =I46/$I$16 -> 0.0080069072 | K46: 222891.75 | L46: =IF(OR(K46="",K$16=0),"",K46/$K$16) -> 0.01 | M46: =IF(L46="","",J46-L46) -> -0.0019930928 | O46: =IFERROR(N46/$N$16,"") | P46: 235117.88 | Q46: =IF(OR(P46="",P$16=0),"",P46/$P$16) -> 0.01 | R46: =N46-P46 -> -235117.88 | T46: =S46/$D$16 -> 0 | U46: 244522.6 | V46: =IF(OR(U46="",U$16=0),"",U46/$U$16) -> 0.01 | W46: =IF(V46="","",T46-V46) -> -0.01 | Y46: =X46/$D$16 -> 0 | Z46: 253927.31 | AA46: =IF(OR(Z46="",Z$16=0),"",Z46/$Z$16) -> 0.01 | AB46: =IF(AA46="","",Y46-AA46) -> -0.01 | AD46: =AC46/$D$16 -> 0 | AE46: 244522.6 | AF46: =IF(OR(AE46="",AE$16=0),"",AE46/$AE$16) -> 0.01 | AG46: =IF(AF46="","",AD46-AF46) -> -0.01 | AI46: =AH46/$D$16 -> 0 | AJ46: 261451.08 | AK46: =IF(OR(AJ46="",AJ$16=0),"",AJ46/$AJ$16) -> 0.01 | AL46: =IF(AK46="","",AI46-AK46) -> -0.01 | AN46: =AM46/$D$16 -> 0 | AO46: 245463.07 | AP46: =IF(OR(AO46="",AO$16=0),"",AO46/$AO$16) -> 0.01 | AQ46: =IF(AP46="","",AN46-AP46) -> -0.01 | AS46: =AR46/$D$16 -> 0 | AT46: 243582.12 | AU46: =IF(OR(AT46="",AT$16=0),"",AT46/$AT$16) -> 0.01 | AV46: =IF(AU46="","",AS46-AU46) -> -0.01 | AX46: =AW46/$D$16 -> 0 | AY46: 258629.67 | AZ46: =IF(OR(AY46="",AY$16=0),"",AY46/$AY$16) -> 0.01 | BA46: =IF(AZ46="","",AX46-AZ46) -> -0.01 | BC46: =BB46/$D$16 -> 0 | BD46: 252046.37 | BE46: =IF(OR(BD46="",BD$16=0),"",BD46/$BD$16) -> 0.01 | BF46: =IF(BE46="","",BC46-BE46) -> -0.01 | BH46: =BG46/$D$16 -> 0 | BI46: 283081.93 | BJ46: =IF(OR(BI46="",BI$16=0),"",BI46/$BI$16) -> 0.01 | BK46: =IF(BJ46="","",BH46-BJ46) -> -0.01 | BL46: =SUM(D46,I46,N46,S46,X46,AC46,AH46,AM46,AR46,AW46,BB46,BG46) -> 410328.1 | BM46: =BL46/$BL$16 -> 0.0092246441 | BN46: =F46+K46+P46+U46+Z46+AE46+AJ46+AO46+AT46+AY46+BD46+BI46 -> 2956559.7 | BO46: =IF(BN46="","",BN46/$BN$16) -> 0.01 | BP46: =IF(BO46="","",BM46-BO46) -> -0.00077535588 | BQ46: 2770268.3 | BR46: =BQ46/$BQ$16 -> 0.010091588
A47: Cheque | C47: ( - ) Cheques Compensandos | D47: =SUMIF(DESPESA!$E$4:$E$140,"Cheque",DESPESA!$I$4:$I$140) -> 0 | E47: =D47/$D$16 -> 0 | F47: 0 | G47: =IF(OR(F47="",F$16=0),"",F47/$F$16) -> 0 | H47: =IF(G47="","",E47-G47) -> 0 | I47: =SUMIF(DESPESA!$E$4:$E$140,"Cheque",DESPESA!$J$4:$J$140) -> 13333 | J47: =I47/$I$16 -> 0.00063203528 | K47: 0 | L47: =IF(OR(K47="",K$16=0),"",K47/$K$16) -> 0 | M47: =IF(L47="","",J47-L47) -> 0.00063203528 | O47: =IFERROR(N47/$N$16,"") | P47: 0 | Q47: =IF(OR(P47="",P$16=0),"",P47/$P$16) -> 0 | R47: =N47-P47 -> 0 | T47: =S47/$D$16 -> 0 | U47: 0 | V47: =IF(OR(U47="",U$16=0),"",U47/$U$16) -> 0 | W47: =IF(V47="","",T47-V47) -> 0 | Y47: =X47/$D$16 -> 0 | Z47: 0 | AA47: =IF(OR(Z47="",Z$16=0),"",Z47/$Z$16) -> 0 | AB47: =IF(AA47="","",Y47-AA47) -> 0 | AD47: =AC47/$D$16 -> 0 | AE47: 0 | AF47: =IF(OR(AE47="",AE$16=0),"",AE47/$AE$16) -> 0 | AG47: =IF(AF47="","",AD47-AF47) -> 0 | AI47: =AH47/$D$16 -> 0 | AJ47: 0 | AK47: =IF(OR(AJ47="",AJ$16=0),"",AJ47/$AJ$16) -> 0 | AL47: =IF(AK47="","",AI47-AK47) -> 0 | AN47: =AM47/$D$16 -> 0 | AO47: 0 | AP47: =IF(OR(AO47="",AO$16=0),"",AO47/$AO$16) -> 0 | AQ47: =IF(AP47="","",AN47-AP47) -> 0 | AS47: =AR47/$D$16 -> 0 | AT47: 0 | AU47: =IF(OR(AT47="",AT$16=0),"",AT47/$AT$16) -> 0 | AV47: =IF(AU47="","",AS47-AU47) -> 0 | AX47: =AW47/$D$16 -> 0 | AY47: 0 | AZ47: =IF(OR(AY47="",AY$16=0),"",AY47/$AY$16) -> 0 | BA47: =IF(AZ47="","",AX47-AZ47) -> 0 | BC47: =BB47/$D$16 -> 0 | BD47: 0 | BE47: =IF(OR(BD47="",BD$16=0),"",BD47/$BD$16) -> 0 | BF47: =IF(BE47="","",BC47-BE47) -> 0 | BH47: =BG47/$D$16 -> 0 | BI47: 0 | BJ47: =IF(OR(BI47="",BI$16=0),"",BI47/$BI$16) -> 0 | BK47: =IF(BJ47="","",BH47-BJ47) -> 0 | BL47: =SUM(D47,I47,N47,S47,X47,AC47,AH47,AM47,AR47,AW47,BB47,BG47) -> 13333 | BM47: =BL47/$BL$16 -> 0.00029974106 | BN47: =F47+K47+P47+U47+Z47+AE47+AJ47+AO47+AT47+AY47+BD47+BI47 -> 0 | BO47: =IF(BN47="","",BN47/$BN$16) -> 0 | BP47: =IF(BO47="","",BM47-BO47) -> 0.00029974106 | BQ47: 35000 | BR47: =BQ47/$BQ$16 -> 0.00012749869
A48: Taxa | C48: ( - ) Taxas Adm de Cartões | D48: =SUMIF(EXTRATO!$F$14:$F$194,"Taxa",EXTRATO!$I$14:$I$194) -> 217326.28 | E48: =D48/$D$16 -> 0.0092928546 | F48: 181738.06 | G48: =IF(OR(F48="",F$16=0),"",F48/$F$16) -> 0.0086 | H48: =IF(G48="","",E48-G48) -> 0.0006928546 | I48: =SUMIF(EXTRATO!$F$14:$F$194,"Taxa",EXTRATO!$J$14:$J$194) -> 162977.46 | J48: =I48/$I$16 -> 0.007725756 | K48: 191686.91 | L48: =IF(OR(K48="",K$16=0),"",K48/$K$16) -> 0.0086 | M48: =IF(L48="","",J48-L48) -> -0.000874244 | O48: =IFERROR(N48/$N$16,"") | P48: 202201.38 | Q48: =IF(OR(P48="",P$16=0),"",P48/$P$16) -> 0.0086 | R48: =N48-P48 -> -202201.38 | T48: =S48/$D$16 -> 0 | U48: 210289.43 | V48: =IF(OR(U48="",U$16=0),"",U48/$U$16) -> 0.0086 | W48: =IF(V48="","",T48-V48) -> -0.0086 | Y48: =X48/$D$16 -> 0 | Z48: 218377.49 | AA48: =IF(OR(Z48="",Z$16=0),"",Z48/$Z$16) -> 0.0086 | AB48: =IF(AA48="","",Y48-AA48) -> -0.0086 | AD48: =AC48/$D$16 -> 0 | AE48: 210289.43 | AF48: =IF(OR(AE48="",AE$16=0),"",AE48/$AE$16) -> 0.0086 | AG48: =IF(AF48="","",AD48-AF48) -> -0.0086 | AI48: =AH48/$D$16 -> 0 | AJ48: 224847.93 | AK48: =IF(OR(AJ48="",AJ$16=0),"",AJ48/$AJ$16) -> 0.0086 | AL48: =IF(AK48="","",AI48-AK48) -> -0.0086 | AN48: =AM48/$D$16 -> 0 | AO48: 211098.24 | AP48: =IF(OR(AO48="",AO$16=0),"",AO48/$AO$16) -> 0.0086 | AQ48: =IF(AP48="","",AN48-AP48) -> -0.0086 | AS48: =AR48/$D$16 -> 0 | AT48: 209480.63 | AU48: =IF(OR(AT48="",AT$16=0),"",AT48/$AT$16) -> 0.0086 | AV48: =IF(AU48="","",AS48-AU48) -> -0.0086 | AX48: =AW48/$D$16 -> 0 | AY48: 222421.52 | AZ48: =IF(OR(AY48="",AY$16=0),"",AY48/$AY$16) -> 0.0086 | BA48: =IF(AZ48="","",AX48-AZ48) -> -0.0086 | BC48: =BB48/$D$16 -> 0 | BD48: 216759.88 | BE48: =IF(OR(BD48="",BD$16=0),"",BD48/$BD$16) -> 0.0086 | BF48: =IF(BE48="","",BC48-BE48) -> -0.0086 | BH48: =BG48/$D$16 -> 0 | BI48: 243450.46 | BJ48: =IF(OR(BI48="",BI$16=0),"",BI48/$BI$16) -> 0.0086 | BK48: =IF(BJ48="","",BH48-BJ48) -> -0.0086 | BL48: =SUM(D48,I48,N48,S48,X48,AC48,AH48,AM48,AR48,AW48,BB48,BG48) -> 380303.74 | BM48: =BL48/$BL$16 -> 0.0085496622 | BN48: =F48+K48+P48+U48+Z48+AE48+AJ48+AO48+AT48+AY48+BD48+BI48 -> 2542641.3 | BO48: =IF(BN48="","",BN48/$BN$16) -> 0.0086 | BP48: =IF(BO48="","",BM48-BO48) -> -5.0337768e-05 | BQ48: 2372976.7 | BR48: =BQ48/$BQ$16 -> 0.0086443262
A49: Aluguel | C49: ( - ) Aluguel | D49: =SUMIF(EXTRATO!$F$14:$F$194,"Aluguel",EXTRATO!$I$14:$I$194) -> 111005.61 | E49: =D49/$D$16 -> 0.0047465911 | F49: 84529.331 | G49: =IF(OR(F49="",F$16=0),"",F49/$F$16) -> 0.004 | H49: =IF(G49="","",E49-G49) -> 0.00074659113 | I49: =SUMIF(EXTRATO!$F$14:$F$194,"Aluguel",EXTRATO!$J$14:$J$194) -> 112035.61 | J49: =I49/$I$16 -> 0.0053109171 | K49: 89156.7 | L49: =IF(OR(K49="",K$16=0),"",K49/$K$16) -> 0.004 | M49: =IF(L49="","",J49-L49) -> 0.0013109171 | O49: =IFERROR(N49/$N$16,"") | P49: 112000 | Q49: =IF(OR(P49="",P$16=0),"",P49/$P$16) -> 0.0047635679 | R49: =N49-P49 -> -112000 | T49: =S49/$D$16 -> 0 | U49: 97809.038 | V49: =IF(OR(U49="",U$16=0),"",U49/$U$16) -> 0.004 | W49: =IF(V49="","",T49-V49) -> -0.004 | Y49: =X49/$D$16 -> 0 | Z49: 101570.92 | AA49: =IF(OR(Z49="",Z$16=0),"",Z49/$Z$16) -> 0.004 | AB49: =IF(AA49="","",Y49-AA49) -> -0.004 | AD49: =AC49/$D$16 -> 0 | AE49: 97809.038 | AF49: =IF(OR(AE49="",AE$16=0),"",AE49/$AE$16) -> 0.004 | AG49: =IF(AF49="","",AD49-AF49) -> -0.004 | AI49: =AH49/$D$16 -> 0 | AJ49: 104580.43 | AK49: =IF(OR(AJ49="",AJ$16=0),"",AJ49/$AJ$16) -> 0.004 | AL49: =IF(AK49="","",AI49-AK49) -> -0.004 | AN49: =AM49/$D$16 -> 0 | AO49: 98185.227 | AP49: =IF(OR(AO49="",AO$16=0),"",AO49/$AO$16) -> 0.004 | AQ49: =IF(AP49="","",AN49-AP49) -> -0.004 | AS49: =AR49/$D$16 -> 0 | AT49: 97432.85 | AU49: =IF(OR(AT49="",AT$16=0),"",AT49/$AT$16) -> 0.004 | AV49: =IF(AU49="","",AS49-AU49) -> -0.004 | AX49: =AW49/$D$16 -> 0 | AY49: 103451.87 | AZ49: =IF(OR(AY49="",AY$16=0),"",AY49/$AY$16) -> 0.004 | BA49: =IF(AZ49="","",AX49-AZ49) -> -0.004 | BC49: =BB49/$D$16 -> 0 | BD49: 100818.55 | BE49: =IF(OR(BD49="",BD$16=0),"",BD49/$BD$16) -> 0.004 | BF49: =IF(BE49="","",BC49-BE49) -> -0.004 | BH49: =BG49/$D$16 -> 0 | BI49: 113232.77 | BJ49: =IF(OR(BI49="",BI$16=0),"",BI49/$BI$16) -> 0.004 | BK49: =IF(BJ49="","",BH49-BJ49) -> -0.004 | BL49: =SUM(D49,I49,N49,S49,X49,AC49,AH49,AM49,AR49,AW49,BB49,BG49) -> 223041.22 | BM49: =BL49/$BL$16 -> 0.0050142213 | BN49: =F49+K49+P49+U49+Z49+AE49+AJ49+AO49+AT49+AY49+BD49+BI49 -> 1200576.7 | BO49: =IF(BN49="","",BN49/$BN$16) -> 0.0040607221 | BP49: =IF(BO49="","",BM49-BO49) -> 0.00095349916 | BQ49: 1111057.5 | BR49: =BQ49/$BQ$16 -> 0.004047382
A50: Seguros | C50: ( - ) Seguros | D50: =SUMIF(EXTRATO!$F$14:$F$194,"Seguros",EXTRATO!$I$14:$I$194) -> 13138.92 | E50: =D50/$D$16 -> 0.00056181918 | F50: 10566.166 | G50: =IF(OR(F50="",F$16=0),"",F50/$F$16) -> 0.0005 | H50: =IF(G50="","",E50-G50) -> 6.1819183e-05 | I50: =SUMIF(EXTRATO!$F$14:$F$194,"Seguros",EXTRATO!$J$14:$J$194) -> 10861.85 | J50: =I50/$I$16 -> 0.0005148933 | K50: 11144.588 | L50: =IF(OR(K50="",K$16=0),"",K50/$K$16) -> 0.0005 | M50: =IF(L50="","",J50-L50) -> 1.4893304e-05 | O50: =IFERROR(N50/$N$16,"") | P50: 11755.894 | Q50: =IF(OR(P50="",P$16=0),"",P50/$P$16) -> 0.0005 | R50: =N50-P50 -> -11755.894 | T50: =S50/$D$16 -> 0 | U50: 12226.13 | V50: =IF(OR(U50="",U$16=0),"",U50/$U$16) -> 0.0005 | W50: =IF(V50="","",T50-V50) -> -0.0005 | Y50: =X50/$D$16 -> 0 | Z50: 12696.366 | AA50: =IF(OR(Z50="",Z$16=0),"",Z50/$Z$16) -> 0.0005 | AB50: =IF(AA50="","",Y50-AA50) -> -0.0005 | AD50: =AC50/$D$16 -> 0 | AE50: 12226.13 | AF50: =IF(OR(AE50="",AE$16=0),"",AE50/$AE$16) -> 0.0005 | AG50: =IF(AF50="","",AD50-AF50) -> -0.0005 | AI50: =AH50/$D$16 -> 0 | AJ50: 13072.554 | AK50: =IF(OR(AJ50="",AJ$16=0),"",AJ50/$AJ$16) -> 0.0005 | AL50: =IF(AK50="","",AI50-AK50) -> -0.0005 | AN50: =AM50/$D$16 -> 0 | AO50: 12273.153 | AP50: =IF(OR(AO50="",AO$16=0),"",AO50/$AO$16) -> 0.0005 | AQ50: =IF(AP50="","",AN50-AP50) -> -0.0005 | AS50: =AR50/$D$16 -> 0 | AT50: 12179.106 | AU50: =IF(OR(AT50="",AT$16=0),"",AT50/$AT$16) -> 0.0005 | AV50: =IF(AU50="","",AS50-AU50) -> -0.0005 | AX50: =AW50/$D$16 -> 0 | AY50: 12931.483 | AZ50: =IF(OR(AY50="",AY$16=0),"",AY50/$AY$16) -> 0.0005 | BA50: =IF(AZ50="","",AX50-AZ50) -> -0.0005 | BC50: =BB50/$D$16 -> 0 | BD50: 12602.318 | BE50: =IF(OR(BD50="",BD$16=0),"",BD50/$BD$16) -> 0.0005 | BF50: =IF(BE50="","",BC50-BE50) -> -0.0005 | BH50: =BG50/$D$16 -> 0 | BI50: 14154.096 | BJ50: =IF(OR(BI50="",BI$16=0),"",BI50/$BI$16) -> 0.0005 | BK50: =IF(BJ50="","",BH50-BJ50) -> -0.0005 | BL50: =SUM(D50,I50,N50,S50,X50,AC50,AH50,AM50,AR50,AW50,BB50,BG50) -> 24000.77 | BM50: =BL50/$BL$16 -> 0.00053956471 | BN50: =F50+K50+P50+U50+Z50+AE50+AJ50+AO50+AT50+AY50+BD50+BI50 -> 147827.99 | BO50: =IF(BN50="","",BN50/$BN$16) -> 0.0005 | BP50: =IF(BO50="","",BM50-BO50) -> 3.9564709e-05 | BQ50: 136500.86 | BR50: =BQ50/$BQ$16 -> 0.00049724802
C51: ( = )Total de custos operacionais | D51: =IF(SUM(D29:D50)=0,"",SUM(D29:D50)) -> 2643424.8 | E51: =SUM(E29:E50) -> 0.11303263 | F51: =IF(SUM(F29:F50)=0,"",SUM(F29:F50)) -> 2533766.7 | G51: =IF(F51="","",SUM(G29:G50)) -> 0.1199 | H51: =IF(G51="","",E51-G51) -> -0.0068673661 | I51: =IF(SUM(I29:I50)=0,"",SUM(I29:I50)) -> 2103362.8 | J51: =SUM(J29:J50) -> 0.099707455 | K51: =IF(SUM(K29:K50)=0,"",SUM(K29:K50)) -> 2672472.1 | L51: =IF(K51="","",SUM(L29:L50)) -> 0.1199 | M51: =IF(L51="","",J51-L51) -> -0.020192545 | N51: =IF(SUM(N29:N50)=0,"",SUM(N29:N50)) | O51: =IFERROR(SUM(O29:O50),"") -> 0 | P51: =IF(SUM(P29:P50)=0,"",SUM(P29:P50)) -> 2884274.9 | Q51: =IF(P51="","",SUM(Q29:Q50)) -> 0.12267357 | R51: =IFERROR(IF(Q51="","",O51-Q51),"") -> -0.12267357 | S51: =IF(SUM(S29:S50)=0,"",SUM(S29:S50)) | T51: =SUM(T29:T50) -> 0 | U51: =IF(SUM(U29:U50)=0,"",SUM(U29:U50)) -> 2980975 | V51: =IF(U51="","",SUM(V29:V50)) -> 0.12191 | W51: =IF(V51="","",T51-V51) -> -0.12191 | X51: =IF(SUM(X29:X50)=0,"",SUM(X29:X50)) | Y51: =SUM(Y29:Y50) -> 0 | Z51: =IF(SUM(Z29:Z50)=0,"",SUM(Z29:Z50)) -> 3095627.9 | AA51: =IF(Z51="","",SUM(AA29:AA50)) -> 0.12191 | AB51: =IF(AA51="","",Y51-AA51) -> -0.12191 | AC51: =IF(SUM(AC29:AC50)=0,"",SUM(AC29:AC50)) | AD51: =SUM(AD29:AD50) -> 0 | AE51: =IF(SUM(AE29:AE50)=0,"",SUM(AE29:AE50)) -> 2980975 | AF51: =IF(AE51="","",SUM(AF29:AF50)) -> 0.12191 | AG51: =IF(AF51="","",AD51-AF51) -> -0.12191 | AH51: =IF(SUM(AH29:AH50)=0,"",SUM(AH29:AH50)) | AI51: =SUM(AI29:AI50) -> 0 | AJ51: =IF(SUM(AJ29:AJ50)=0,"",SUM(AJ29:AJ50)) -> 3187350.2 | AK51: =IF(AJ51="","",SUM(AK29:AK50)) -> 0.12191 | AL51: =IF(AK51="","",AI51-AK51) -> -0.12191 | AM51: =IF(SUM(AM29:AM50)=0,"",SUM(AM29:AM50)) | AN51: =SUM(AN29:AN50) -> 0 | AO51: =IF(SUM(AO29:AO50)=0,"",SUM(AO29:AO50)) -> 2992440.3 | AP51: =IF(AO51="","",SUM(AP29:AP50)) -> 0.12191 | AQ51: =IF(AP51="","",AN51-AP51) -> -0.12191 | AR51: =IF(SUM(AR29:AR50)=0,"",SUM(AR29:AR50)) | AS51: =SUM(AS29:AS50) -> 0 | AT51: =IF(SUM(AT29:AT50)=0,"",SUM(AT29:AT50)) -> 2969509.7 | AU51: =IF(AT51="","",SUM(AU29:AU50)) -> 0.12191 | AV51: =IF(AU51="","",AS51-AU51) -> -0.12191 | AW51: =IF(SUM(AW29:AW50)=0,"",SUM(AW29:AW50)) | AX51: =SUM(AX29:AX50) -> 0 | AY51: =IF(SUM(AY29:AY50)=0,"",SUM(AY29:AY50)) -> 3152954.3 | AZ51: =IF(AY51="","",SUM(AZ29:AZ50)) -> 0.12191 | BA51: =IF(AZ51="","",AX51-AZ51) -> -0.12191 | BB51: =IF(SUM(BB29:BB50)=0,"",SUM(BB29:BB50)) | BC51: =SUM(BC29:BC50) -> 0 | BD51: =IF(SUM(BD29:BD50)=0,"",SUM(BD29:BD50)) -> 3072697.3 | BE51: =IF(BD51="","",SUM(BE29:BE50)) -> 0.12191 | BF51: =IF(BE51="","",BC51-BE51) -> -0.12191 | BG51: =IF(SUM(BG29:BG50)=0,"",SUM(BG29:BG50)) | BH51: =SUM(BH29:BH50) -> 0 | BI51: =IF(SUM(BI29:BI50)=0,"",SUM(BI29:BI50)) -> 3451051.8 | BJ51: =IF(BI51="","",SUM(BJ29:BJ50)) -> 0.12191 | BK51: =IF(BJ51="","",BH51-BJ51) -> -0.12191 | BL51: =IF(SUM(BL29:BL50)=0,"",SUM(BL29:BL50)) -> 4746787.5 | BM51: =SUM(BM29:BM50) -> 0.1067132 | BN51: =IF(SUM(BN29:BN50)=0,"",SUM(BN29:BN50)) -> 35974095 | BO51: =IF(BN51="","",SUM(BO29:BO50)) -> 0.12167552 | BP51: =IF(BO51="","",BM51-BO51) -> -0.014962321 | BQ51: =IF(SUM(BQ29:BQ50)=0,"",SUM(BQ29:BQ50)) -> 34734766 | BR51: =SUM(BR29:BR50) -> 0.12653249
C52: Lucro das operações (EBITDA) | D52: =IFERROR(D26-D51,"") -> 1344087.2 | E52: =E26-E51 -> 0.057473063 | F52: =IFERROR(F26-F51,"") -> 1751938.9 | G52: =IF(OR(F52="",$F$16=0),"",F52/$F$16) -> 0.082903241 | H52: =IF(G52="","",E52-G52) -> -0.025430178 | I52: =IFERROR(I26-I51,"") -> 1502534.9 | J52: =J26-J51 -> 0.071225913 | K52: =IFERROR(K26-K51,"") -> 1847844.8 | L52: =IF(OR(K52="",$K$16=0),"",K52/$K$16) -> 0.082903241 | M52: =IF(L52="","",J52-L52) -> -0.011677328 | N52: =IFERROR(N26-N51,"") | O52: =IFERROR(O26-O51,"") | P52: =IFERROR(P26-P51,"") -> 1883991.9 | Q52: =IF(OR(P52="",$P$16=0),"",P52/$P$16) -> 0.080129673 | R52: =IFERROR(IF(Q52="","",O52-Q52),"") | S52: =IFERROR(S26-S51,"") | T52: =T26-T51 -> 0 | U52: =IFERROR(U26-U51,"") -> 1978022.5 | V52: =IF(OR(U52="",$U$16=0),"",U52/$U$16) -> 0.080893241 | W52: =IF(V52="","",T52-V52) -> -0.080893241 | X52: =IFERROR(X26-X51,"") | Y52: =Y26-Y51 -> 0 | Z52: =IFERROR(Z26-Z51,"") -> 2054100.3 | AA52: =IF(OR(Z52="",$Z$16=0),"",Z52/$Z$16) -> 0.080893241 | AB52: =IF(AA52="","",Y52-AA52) -> -0.080893241 | AC52: =IFERROR(AC26-AC51,"") | AD52: =AD26-AD51 -> 0 | AE52: =IFERROR(AE26-AE51,"") -> 1978022.5 | AF52: =IF(OR(AE52="",$AE$16=0),"",AE52/$AE$16) -> 0.080893241 | AG52: =IF(AF52="","",AD52-AF52) -> -0.080893241 | AH52: =IFERROR(AH26-AH51,"") | AI52: =AI26-AI51 -> 0 | AJ52: =IFERROR(AJ26-AJ51,"") -> 2114962.5 | AK52: =IF(OR(AJ52="",$AJ$16=0),"",AJ52/$AJ$16) -> 0.080893241 | AL52: =IF(AK52="","",AI52-AK52) -> -0.080893241 | AM52: =IFERROR(AM26-AM51,"") | AN52: =AN26-AN51 -> 0 | AO52: =IFERROR(AO26-AO51,"") -> 1985630.3 | AP52: =IF(OR(AO52="",$AO$16=0),"",AO52/$AO$16) -> 0.080893241 | AQ52: =IF(AP52="","",AN52-AP52) -> -0.080893241 | AR52: =IFERROR(AR26-AR51,"") | AS52: =AS26-AS51 -> 0 | AT52: =IFERROR(AT26-AT51,"") -> 1970414.7 | AU52: =IF(OR(AT52="",$AT$16=0),"",AT52/$AT$16) -> 0.080893241 | AV52: =IF(AU52="","",AS52-AU52) -> -0.080893241 | AW52: =IFERROR(AW26-AW51,"") | AX52: =AX26-AX51 -> 0 | AY52: =IFERROR(AY26-AY51,"") -> 2092139.2 | AZ52: =IF(OR(AY52="",$AY$16=0),"",AY52/$AY$16) -> 0.080893241 | BA52: =IF(AZ52="","",AX52-AZ52) -> -0.080893241 | BB52: =IFERROR(BB26-BB51,"") | BC52: =BC26-BC51 -> 0 | BD52: =IFERROR(BD26-BD51,"") -> 2038884.8 | BE52: =IF(OR(BD52="",$BD$16=0),"",BD52/$BD$16) -> 0.080893241 | BF52: =IF(BE52="","",BC52-BE52) -> -0.080893241 | BG52: =IFERROR(BG26-BG51,"") | BH52: =BH26-BH51 -> 0 | BI52: =IFERROR(BI26-BI51,"") -> 2289941.5 | BJ52: =IF(OR(BI52="",$BI$16=0),"",BI52/$BI$16) -> 0.080893241 | BK52: =IF(BJ52="","",BH52-BJ52) -> -0.080893241 | BL52: =IFERROR(BL26-BL51,"") -> 2846622.1 | BM52: =BM26-BM51 -> 0.064330845 | BN52: =IFERROR(BN26-BN51,"") -> 23985894 | BO52: =IF(BN52="","",BO26-BO51) -> 0.081127717 | BP52: =IF(BO52="","",BM52-BO52) -> -0.016796872 | BQ52: =IFERROR(BQ26-BQ51,"") -> 13393674 | BR52: =BR26-BR51 -> 0.04879074
C54: Mvto Financeiro | D54: =IFERROR(D55-D56,"") -> 24862.13 | E54: =D54/$D$16 -> 0.0010631027 | F54: =IFERROR(F55-F56,"") -> -11000 | H54: =D54-F54 -> 35862.13 | I54: =IFERROR(I55-I56,"") -> 33291.32 | J54: =I54/$I$16 -> 0.0015781361 | K54: =IFERROR(K55-K56,"") -> -11000 | M54: =I54-K54 -> 44291.32 | N54: =IFERROR(N55-N56,"") -> 0 | O54: =IFERROR(N54/$N$16,"") | P54: =IFERROR(P55-P56,"") -> -11000 | Q54: =IFERROR(Q55-Q56,"") -> -0.00046785042 | R54: =N54-P54 -> 11000 | S54: =IFERROR(S55-S56,"") -> 0 | T54: =S54/$D$16 -> 0 | U54: =IFERROR(U55-U56,"") -> -11000 | W54: =S54-U54 -> 11000 | X54: =IFERROR(X55-X56,"") -> 0 | Y54: =X54/$D$16 -> 0 | Z54: =IFERROR(Z55-Z56,"") -> -11000 | AB54: =X54-Z54 -> 11000 | AC54: =IFERROR(AC55-AC56,"") -> 0 | AD54: =AC54/$D$16 -> 0 | AE54: =IFERROR(AE55-AE56,"") -> -11000 | AG54: =AC54-AE54 -> 11000 | AH54: =IFERROR(AH55-AH56,"") -> 0 | AI54: =AH54/$D$16 -> 0 | AJ54: =IFERROR(AJ55-AJ56,"") -> -11000 | AL54: =AH54-AJ54 -> 11000 | AM54: =IFERROR(AM55-AM56,"") -> 0 | AN54: =AM54/$D$16 -> 0 | AO54: =IFERROR(AO55-AO56,"") -> -11000 | AQ54: =AM54-AO54 -> 11000 | AR54: =IFERROR(AR55-AR56,"") -> 0 | AS54: =AR54/$D$16 -> 0 | AT54: =IFERROR(AT55-AT56,"") -> -11000 | AV54: =AR54-AT54 -> 11000 | AW54: =IFERROR(AW55-AW56,"") -> 0 | AX54: =AW54/$D$16 -> 0 | AY54: =IFERROR(AY55-AY56,"") -> -11000 | BA54: =AW54-AY54 -> 11000 | BB54: =IFERROR(BB55-BB56,"") -> 0 | BC54: =BB54/$D$16 -> 0 | BD54: =IFERROR(BD55-BD56,"") -> -11000 | BF54: =BB54-BD54 -> 11000 | BG54: =IFERROR(BG55-BG56,"") -> 0 | BH54: =BG54/$D$16 -> 0 | BI54: =IFERROR(BI55-BI56,"") -> -11000 | BK54: =BG54-BI54 -> 11000 | BL54: =IFERROR(BL55-BL56,"") -> 58153.45 | BM54: =BL54/$BL$16 -> 0.0013073559 | BN54: =F54+K54+P54+U54+Z54+AE54+AJ54+AO54+AT54+AY54+BD54+BI54 -> -132000 | BP54: =BL54-BN54 -> 190153.45 | BQ54: =IFERROR(BQ55-BQ56,"") -> 697567.38 | BR54: =BQ54/$BQ$16 -> 0.0025411122
A55: Ganho | C55: ( + ) Ganhos Financeiros | D55: =SUMIF(EXTRATO!$F$14:$F$194,"Ganho",EXTRATO!$I$14:$I$194) -> 34820.24 | E55: =D55/$D$16 -> 0.0014889107 | F55: 4000 | H55: =D55-F55 -> 30820.24 | I55: =SUMIF(EXTRATO!$F$14:$F$194,"Ganho",EXTRATO!$J$14:$J$194) -> 39503.32 | J55: =I55/$I$16 -> 0.0018726087 | K55: =4000 -> 4000 | M55: =I55-K55 -> 35503.32 | O55: =IFERROR(N55/$N$16,"") | P55: =4000 -> 4000 | Q55: =IF(P55="","",P55/$P$16) -> 0.00017012743 | R55: =N55-P55 -> -4000 | T55: =S55/$D$16 -> 0 | U55: =4000 -> 4000 | W55: =S55-U55 -> -4000 | Y55: =X55/$D$16 -> 0 | Z55: =4000 -> 4000 | AB55: =X55-Z55 -> -4000 | AD55: =AC55/$D$16 -> 0 | AE55: =4000 -> 4000 | AG55: =AC55-AE55 -> -4000 | AI55: =AH55/$D$16 -> 0 | AJ55: =4000 -> 4000 | AL55: =AH55-AJ55 -> -4000 | AN55: =AM55/$D$16 -> 0 | AO55: =4000 -> 4000 | AQ55: =AM55-AO55 -> -4000 | AS55: =AR55/$D$16 -> 0 | AT55: =4000 -> 4000 | AV55: =AR55-AT55 -> -4000 | AX55: =AW55/$D$16 -> 0 | AY55: =4000 -> 4000 | BA55: =AW55-AY55 -> -4000 | BC55: =BB55/$D$16 -> 0 | BD55: =4000 -> 4000 | BF55: =BB55-BD55 -> -4000 | BH55: =BG55/$D$16 -> 0 | BI55: =4000 -> 4000 | BK55: =BG55-BI55 -> -4000 | BL55: =SUM(D55,I55,N55,S55,X55,AC55,AH55,AM55,AR55,AW55,BB55,BG55) -> 74323.56 | BM55: =BL55/$BL$16 -> 0.0016708785 | BN55: =F55+K55+P55+U55+Z55+AE55+AJ55+AO55+AT55+AY55+BD55+BI55 -> 48000 | BP55: =BL55-BN55 -> 26323.56 | BQ55: 784897.85 | BR55: =BQ55/$BQ$16 -> 0.0028592413
A56: Gasto | C56: ( - ) Gastos Financeiros | D56: =SUMIF(EXTRATO!$F$14:$F$194,"Gasto",EXTRATO!$I$14:$I$194) -> 9958.11 | E56: =D56/$D$16 -> 0.000425808 | F56: 15000 | H56: =D56-F56 -> -5041.89 | I56: =SUMIF(EXTRATO!$F$14:$F$194,"Gasto",EXTRATO!$J$14:$J$194) -> 6212 | J56: =I56/$I$16 -> 0.0002944726 | K56: =15000 -> 15000 | M56: =I56-K56 -> -8788 | O56: =IFERROR(N56/$N$16,"") | P56: =15000 -> 15000 | Q56: =IF(P56="","",P56/$P$16) -> 0.00063797785 | R56: =N56-P56 -> -15000 | T56: =S56/$D$16 -> 0 | U56: =15000 -> 15000 | W56: =S56-U56 -> -15000 | Y56: =X56/$D$16 -> 0 | Z56: =15000 -> 15000 | AB56: =X56-Z56 -> -15000 | AD56: =AC56/$D$16 -> 0 | AE56: =15000 -> 15000 | AG56: =AC56-AE56 -> -15000 | AI56: =AH56/$D$16 -> 0 | AJ56: =15000 -> 15000 | AL56: =AH56-AJ56 -> -15000 | AN56: =AM56/$D$16 -> 0 | AO56: =15000 -> 15000 | AQ56: =AM56-AO56 -> -15000 | AS56: =AR56/$D$16 -> 0 | AT56: =15000 -> 15000 | AV56: =AR56-AT56 -> -15000 | AX56: =AW56/$D$16 -> 0 | AY56: =15000 -> 15000 | BA56: =AW56-AY56 -> -15000 | BC56: =BB56/$D$16 -> 0 | BD56: =15000 -> 15000 | BF56: =BB56-BD56 -> -15000 | BH56: =BG56/$D$16 -> 0 | BI56: =15000 -> 15000 | BK56: =BG56-BI56 -> -15000 | BL56: =SUM(D56,I56,N56,S56,X56,AC56,AH56,AM56,AR56,AW56,BB56,BG56) -> 16170.11 | BM56: =BL56/$BL$16 -> 0.00036352253 | BN56: =F56+K56+P56+U56+Z56+AE56+AJ56+AO56+AT56+AY56+BD56+BI56 -> 180000 | BP56: =BL56-BN56 -> -163829.89 | BQ56: 87330.47 | BR56: =BQ56/$BQ$16 -> 0.00031812915
C58: Lucro antes do Imposto de Renda | D58: =IFERROR(D52+D54,"") -> 1368949.3 | E58: =E52+E54 -> 0.058536165 | F58: =IFERROR(F52+F54,"") -> 1740938.9 | H58: =D58-F58 -> -371989.55 | I58: =IFERROR(I52+I54,"") -> 1535826.3 | J58: =J52+J54 -> 0.072804049 | K58: =IFERROR(K52+K54,"") -> 1836844.8 | M58: =I58-K58 -> -301018.59 | N58: =IFERROR(N52+N54,"") | O58: =IFERROR(O52+O54,"") | P58: =IFERROR(P52+P54,"") -> 1872991.9 | Q58: =IF(P58="","",P58/$P$16) -> 0.079661822 | R58: =N58-P58 -> #VALUE! | S58: =IFERROR(S52+S54,"") | T58: =T52+T54 -> 0 | U58: =IFERROR(U52+U54,"") -> 1967022.5 | W58: =S58-U58 -> #VALUE! | X58: =IFERROR(X52+X54,"") | Y58: =Y52+Y54 -> 0 | Z58: =IFERROR(Z52+Z54,"") -> 2043100.3 | AB58: =X58-Z58 -> #VALUE! | AC58: =IFERROR(AC52+AC54,"") | AD58: =AD52+AD54 -> 0 | AE58: =IFERROR(AE52+AE54,"") -> 1967022.5 | AG58: =AC58-AE58 -> #VALUE! | AH58: =IFERROR(AH52+AH54,"") | AI58: =AI52+AI54 -> 0 | AJ58: =IFERROR(AJ52+AJ54,"") -> 2103962.5 | AL58: =AH58-AJ58 -> #VALUE! | AM58: =IFERROR(AM52+AM54,"") | AN58: =AN52+AN54 -> 0 | AO58: =IFERROR(AO52+AO54,"") -> 1974630.3 | AQ58: =AM58-AO58 -> #VALUE! | AR58: =IFERROR(AR52+AR54,"") | AS58: =AS52+AS54 -> 0 | AT58: =IFERROR(AT52+AT54,"") -> 1959414.7 | AV58: =AR58-AT58 -> #VALUE! | AW58: =IFERROR(AW52+AW54,"") | AX58: =AX52+AX54 -> 0 | AY58: =IFERROR(AY52+AY54,"") -> 2081139.2 | BA58: =AW58-AY58 -> #VALUE! | BB58: =IFERROR(BB52+BB54,"") | BC58: =BC52+BC54 -> 0 | BD58: =IFERROR(BD52+BD54,"") -> 2027884.8 | BF58: =BB58-BD58 -> #VALUE! | BG58: =IFERROR(BG52+BG54,"") | BH58: =BH52+BH54 -> 0 | BI58: =IFERROR(BI52+BI54,"") -> 2278941.5 | BK58: =BG58-BI58 -> #VALUE! | BL58: =IFERROR(BL52+BL54,"") -> 2904775.6 | BM58: =BM52+BM54 -> 0.065638201 | BN58: =F58+K58+P58+U58+Z58+AE58+AJ58+AO58+AT58+AY58+BD58+BI58 -> 23853894 | BP58: =BL58-BN58 -> -20949118 | BQ58: =IFERROR(BQ52+BQ54,"") -> 14091242 | BR58: =BR52+BR54 -> 0.051331852
C59: ( - ) Despesa de Imposto de Renda | D59: =SUMIF(EXTRATO!$F$14:$F$194,"IR",EXTRATO!$I$14:$I$194) -> 100511.66 | E59: =D59/$D$16 -> 0.0042978707 | F59: =F16*2% -> 422646.66 | G59: 3.015 | H59: =D59-F59 -> -322135 | I59: =SUMIF(EXTRATO!$F$14:$F$194,"IR",EXTRATO!$J$14:$J$194) -> 533781.89 | J59: =I59/$I$16 -> 0.025303307 | K59: =K16*2% -> 445783.5 | L59: 4.015 | M59: =I59-K59 -> 87998.388 | O59: =IFERROR(N59/$N$16,"") | P59: =P16*2% -> 470235.76 | Q59: =IF(P59="","",P59/$P$16) -> 0.02 | R59: =N59-P59 -> -470235.76 | T59: =S59/$D$16 -> 0 | U59: =U16*2% -> 489045.19 | V59: 6.015 | W59: =S59-U59 -> -489045.19 | Y59: =X59/$D$16 -> 0 | Z59: =Z16*2% -> 507854.62 | AA59: 7.015 | AB59: =X59-Z59 -> -507854.62 | AD59: =AC59/$D$16 -> 0 | AE59: =AE16*2% -> 489045.19 | AF59: 8.015 | AG59: =AC59-AE59 -> -489045.19 | AI59: =AH59/$D$16 -> 0 | AJ59: =AJ16*2% -> 522902.17 | AK59: 9.015 | AL59: =AH59-AJ59 -> -522902.17 | AN59: =AM59/$D$16 -> 0 | AO59: =AO16*2% -> 490926.13 | AP59: 10.015 | AQ59: =AM59-AO59 -> -490926.13 | AS59: =AR59/$D$16 -> 0 | AT59: =AT16*2% -> 487164.25 | AU59: 11.015 | AV59: =AR59-AT59 -> -487164.25 | AX59: =AW59/$D$16 -> 0 | AY59: =AY16*2% -> 517259.34 | AZ59: 12.015 | BA59: =AW59-AY59 -> -517259.34 | BC59: =BB59/$D$16 -> 0 | BD59: =BD16*2% -> 504092.74 | BE59: 13.015 | BF59: =BB59-BD59 -> -504092.74 | BH59: =BG59/$D$16 -> 0 | BI59: =BI16*2% -> 566163.86 | BJ59: 14.015 | BK59: =BG59-BI59 -> -566163.86 | BL59: =SUM(D59,I59,N59,S59,X59,AC59,AH59,AM59,AR59,AW59,BB59,BG59) -> 634293.55 | BM59: =BL59/$BL$16 -> 0.014259643 | BN59: =F59+K59+P59+U59+Z59+AE59+AJ59+AO59+AT59+AY59+BD59+BI59 -> 5913119.4 | BO59: 14.015 | BP59: =BL59-BN59 -> -5278825.9 | BQ59: 4559643 | BR59: =BQ59/$BQ$16 -> 0.016609957
C60: Lucro líquido | D60: =IFERROR(D58-D59,"") -> 1268437.7 | E60: =D60/$D$16 -> 0.054238295 | F60: =IFERROR(F58-F59,"") -> 1318292.2 | G60: =IFERROR(F60/$F$16,"") -> 0.062382711 | H60: =D60-F60 -> -49854.549 | I60: =IFERROR(I58-I59,"") -> 1002044.4 | J60: =I60/$I$16 -> 0.047500742 | K60: =IFERROR(K58-K59,"") -> 1391061.3 | L60: =IFERROR(K60/$K$16,"") -> 0.062409728 | M60: =I60-K60 -> -389016.97 | N60: =IFERROR(N58-N59,"") | O60: =N60/$N$16 -> #VALUE! | P60: =IFERROR(P58-P59,"") -> 1402756.1 | Q60: =P60/P16 -> 0.059661822 | R60: =N60-P60 -> #VALUE! | S60: =IFERROR(S58-S59,"") | T60: =S60/$D$16 -> #VALUE! | U60: =IFERROR(U58-U59,"") -> 1477977.3 | V60: =IFERROR(U60/$U$16,"") -> 0.060443384 | W60: =S60-U60 -> #VALUE! | X60: =IFERROR(X58-X59,"") | Y60: =X60/$D$16 -> #VALUE! | Z60: =IFERROR(Z58-Z59,"") -> 1535245.7 | AA60: =IFERROR(Z60/$Z$16,"") -> 0.060460046 | AB60: =X60-Z60 -> #VALUE! | AC60: =IFERROR(AC58-AC59,"") | AD60: =AC60/$D$16 -> #VALUE! | AE60: =IFERROR(AE58-AE59,"") -> 1477977.3 | AF60: =IFERROR(AE60/$AE$16,"") -> 0.060443384 | AG60: =AC60-AE60 -> #VALUE! | AH60: =IFERROR(AH58-AH59,"") | AI60: =AH60/$D$16 -> #VALUE! | AJ60: =IFERROR(AJ58-AJ59,"") -> 1581060.4 | AK60: =IFERROR(AJ60/$AJ$16,"") -> 0.060472512 | AL60: =AH60-AJ60 -> #VALUE! | AM60: =IFERROR(AM58-AM59,"") | AN60: =AM60/$D$16 -> #VALUE! | AO60: =IFERROR(AO58-AO59,"") -> 1483704.2 | AP60: =IFERROR(AO60/$AO$16,"") -> 0.060445108 | AQ60: =AM60-AO60 -> #VALUE! | AR60: =IFERROR(AR58-AR59,"") | AS60: =AR60/$D$16 -> #VALUE! | AT60: =IFERROR(AT58-AT59,"") -> 1472250.5 | AU60: =IFERROR(AT60/$AT$16,"") -> 0.060441648 | AV60: =AR60-AT60 -> #VALUE! | AW60: =IFERROR(AW58-AW59,"") | AX60: =AW60/$D$16 -> #VALUE! | AY60: =IFERROR(AY58-AY59,"") -> 1563879.9 | AZ60: =IFERROR(AY60/$AY$16,"") -> 0.060467922 | BA60: =AW60-AY60 -> #VALUE! | BB60: =IFERROR(BB58-BB59,"") | BC60: =BB60/$D$16 -> #VALUE! | BD60: =IFERROR(BD58-BD59,"") -> 1523792 | BE60: =IFERROR(BD60/$BD$16,"") -> 0.060456813 | BF60: =BB60-BD60 -> #VALUE! | BG60: =IFERROR(BG58-BG59,"") | BH60: =BG60/$D$16 -> #VALUE! | BI60: =IFERROR(BI58-BI59,"") -> 1712777.6 | BJ60: =IFERROR(BI60/$BI$16,"") -> 0.060504661 | BK60: =BG60-BI60 -> #VALUE! | BL60: =IFERROR(BL58-BL59,"") -> 2270482 | BM60: =BL60/$BL$16 -> 0.051043028 | BN60: =F60+K60+P60+U60+Z60+AE60+AJ60+AO60+AT60+AY60+BD60+BI60 -> 17940775 | BO60: =IFERROR(BN60/$BN$16,"") -> 0.060681252 | BP60: =BL60-BN60 -> -15670292 | BQ60: =IFERROR(BQ58-BQ59,"") -> 9531598.7 | BR60: =BQ60/$BQ$16 -> 0.034721895
C62: Investimentos e Financiamentos | D62: =IFERROR(D63-D68,"") -> 611090.32 | E62: =D62/$D$16 -> 0.026130174 | F62: =IFERROR(F63-F68,"") -> 140378 | G62: =IFERROR(F62/$F$16,"") -> 0.0066428066 | H62: =E62-G62 -> 0.019487367 | I62: =IFERROR(I63-I68,"") -> 584699.79 | J62: =I62/$I$16 -> 0.02771701 | K62: =IFERROR(K63-K68,"") -> 140378 | L62: =IFERROR(K62/$K$16,"") -> 0.0062980348 | M62: =J62-L62 -> 0.021418975 | N62: =IFERROR(N63-N68,"") -> 0 | O62: =IFERROR(N62/$N$16,"") | P62: =IFERROR(P63-P68,"") -> 140378 | Q62: =P62/P16 -> 0.005970537 | R62: =IFERROR(O62-Q62,"") | S62: =IFERROR(S63-S68,"") -> 0 | T62: =S62/$D$16 -> 0 | U62: =IFERROR(U63-U68,"") -> 140378 | V62: =IFERROR(U62/$U$16,"") -> 0.0057409009 | W62: =T62-V62 -> -0.0057409009 | X62: =IFERROR(X63-X68,"") -> 0 | Y62: =X62/$D$16 -> 0 | Z62: =IFERROR(Z63-Z68,"") -> 140378 | AA62: =IFERROR(Z62/$Z$16,"") -> 0.005528275 | AB62: =Y62-AA62 -> -0.005528275 | AC62: =IFERROR(AC63-AC68,"") -> 0 | AD62: =AC62/$D$16 -> 0 | AE62: =IFERROR(AE63-AE68,"") -> 140378 | AF62: =IFERROR(AE62/$AE$16,"") -> 0.0057409009 | AG62: =AD62-AF62 -> -0.0057409009 | AH62: =IFERROR(AH63-AH68,"") -> 0 | AI62: =AH62/$D$16 -> 0 | AJ62: =IFERROR(AJ63-AJ68,"") -> 140378 | AK62: =IFERROR(AJ62/$AJ$16,"") -> 0.0053691879 | AL62: =AI62-AK62 -> -0.0053691879 | AM62: =IFERROR(AM63-AM68,"") -> 0 | AN62: =AM62/$D$16 -> 0 | AO62: =IFERROR(AO63-AO68,"") -> 140378 | AP62: =IFERROR(AO62/$AO$16,"") -> 0.0057189051 | AQ62: =AN62-AP62 -> -0.0057189051 | AR62: =IFERROR(AR63-AR68,"") -> 0 | AS62: =AR62/$D$16 -> 0 | AT62: =IFERROR(AT63-AT68,"") -> 140378 | AU62: =IFERROR(AT62/$AT$16,"") -> 0.0057630666 | AV62: =AS62-AU62 -> -0.0057630666 | AW62: =IFERROR(AW63-AW68,"") -> 0 | AX62: =AW62/$D$16 -> 0 | AY62: =IFERROR(AY63-AY68,"") -> 140378 | AZ62: =IFERROR(AY62/$AY$16,"") -> 0.0054277609 | BA62: =AX62-AZ62 -> -0.0054277609 | BB62: =IFERROR(BB63-BB68,"") -> 0 | BC62: =BB62/$D$16 -> 0 | BD62: =IFERROR(BD63-BD68,"") -> 140378 | BE62: =IFERROR(BD62/$BD$16,"") -> 0.0055695308 | BF62: =BC62-BE62 -> -0.0055695308 | BG62: =IFERROR(BG63-BG68,"") -> 0 | BH62: =BG62/$D$16 -> 0 | BI62: =IFERROR(BI63-BI68,"") -> 140378 | BJ62: =IFERROR(BI62/$BI$16,"") -> 0.0049589178 | BK62: =BH62-BJ62 -> -0.0049589178 | BL62: =IFERROR(BL63-BL68,"") -> 1195790.1 | BM62: =BL62/$BL$16 -> 0.026882727 | BN62: =F62+K62+P62+U62+Z62+AE62+AJ62+AO62+AT62+AY62+BD62+BI62 -> 1684536 | BO62: =IFERROR(BN62/$BN$16,"") -> 0.0056976221 | BP62: =BM62-BO62 -> 0.021185105 | BQ62: =IFERROR(BQ63-BQ68,"") -> 10235031 | BR62: =BQ62/$BQ$16 -> 0.037284372
C63: Saídas | D63: =SUM(D64:D67) -> 611090.32 | E63: =SUM(E64:E67) -> 0.026130174 | F63: =IF(SUM(F64:F65)=0,"",SUM(F64:F65)) -> 140378 | H63: =D63-F63 -> 470712.32 | I63: =SUM(I64:I67) -> 584699.79 | J63: =SUM(J64:J67) -> 0.02771701 | K63: =IF(SUM(K64:K65)=0,"",SUM(K64:K65)) -> 140378 | M63: =I63-K63 -> 444321.79 | N63: =SUM(N64:N67) -> 0 | O63: =IFERROR(SUM(O64:O67),"") -> 0 | P63: =IF(SUM(P64:P65)=0,"",SUM(P64:P65)) -> 140378 | Q63: =IF(P63="","",P63/$P$16) -> 0.005970537 | R63: =N63-P63 -> -140378 | S63: =SUM(S64:S67) -> 0 | T63: =SUM(T64:T67) -> 0 | U63: =IF(SUM(U64:U65)=0,"",SUM(U64:U65)) -> 140378 | W63: =S63-U63 -> -140378 | X63: =SUM(X64:X67) -> 0 | Y63: =SUM(Y64:Y67) -> 0 | Z63: =IF(SUM(Z64:Z65)=0,"",SUM(Z64:Z65)) -> 140378 | AB63: =X63-Z63 -> -140378 | AC63: =SUM(AC64:AC67) -> 0 | AD63: =SUM(AD64:AD67) -> 0 | AE63: =IF(SUM(AE64:AE65)=0,"",SUM(AE64:AE65)) -> 140378 | AG63: =AC63-AE63 -> -140378 | AH63: =SUM(AH64:AH67) -> 0 | AI63: =SUM(AI64:AI67) -> 0 | AJ63: =IF(SUM(AJ64:AJ65)=0,"",SUM(AJ64:AJ65)) -> 140378 | AL63: =AH63-AJ63 -> -140378 | AM63: =SUM(AM64:AM67) -> 0 | AN63: =SUM(AN64:AN67) -> 0 | AO63: =IF(SUM(AO64:AO65)=0,"",SUM(AO64:AO65)) -> 140378 | AQ63: =AM63-AO63 -> -140378 | AR63: =SUM(AR64:AR67) -> 0 | AS63: =SUM(AS64:AS67) -> 0 | AT63: =IF(SUM(AT64:AT65)=0,"",SUM(AT64:AT65)) -> 140378 | AV63: =AR63-AT63 -> -140378 | AW63: =SUM(AW64:AW67) -> 0 | AX63: =SUM(AX64:AX67) -> 0 | AY63: =IF(SUM(AY64:AY65)=0,"",SUM(AY64:AY65)) -> 140378 | BA63: =AW63-AY63 -> -140378 | BB63: =SUM(BB64:BB67) -> 0 | BC63: =SUM(BC64:BC67) -> 0 | BD63: =IF(SUM(BD64:BD65)=0,"",SUM(BD64:BD65)) -> 140378 | BF63: =BB63-BD63 -> -140378 | BG63: =SUM(BG64:BG67) -> 0 | BH63: =SUM(BH64:BH67) -> 0 | BI63: =IF(SUM(BI64:BI65)=0,"",SUM(BI64:BI65)) -> 140378 | BK63: =BG63-BI63 -> -140378 | BL63: =SUM(BL64:BL67) -> 1195790.1 | BM63: =SUM(BM64:BM67) -> 0.026882727 | BN63: =F63+K63+P63+U63+Z63+AE63+AJ63+AO63+AT63+AY63+BD63+BI63 -> 1684536 | BP63: =BL63-BN63 -> -488745.89 | BQ63: =SUM(BQ64:BQ67) -> 10235031 | BR63: =SUM(BR64:BR67) -> 0.037284372
A64: Emp_S | B64: Emp_E | C64: ( - ) Empréstimos | D64: =SUMIF(EXTRATO!$F$14:$F$194,"EMP_S",EXTRATO!$I$14:$I$194) -> 55762.52 | E64: =D64/$D$16 -> 0.002384401 | F64: 20378 | H64: =D64-F64 -> 35384.52 | I64: =SUMIF(EXTRATO!$F$14:$F$194,"EMP_S",EXTRATO!$J$14:$J$194) -> 55370.18 | J64: =I64/$I$16 -> 0.0026247587 | K64: =20378 -> 20378 | M64: =I64-K64 -> 34992.18 | O64: =IFERROR(N64/$N$16,"") | P64: =20378 -> 20378 | Q64: =IF(P64="","",P64/$P$16) -> 0.00086671418 | R64: =N64-P64 -> -20378 | T64: =S64/$D$16 -> 0 | U64: =20378 -> 20378 | W64: =S64-U64 -> -20378 | Y64: =X64/$D$16 -> 0 | Z64: =20378 -> 20378 | AB64: =X64-Z64 -> -20378 | AD64: =AC64/$D$16 -> 0 | AE64: =20378 -> 20378 | AG64: =AC64-AE64 -> -20378 | AI64: =AH64/$D$16 -> 0 | AJ64: =20378 -> 20378 | AL64: =AH64-AJ64 -> -20378 | AN64: =AM64/$D$16 -> 0 | AO64: =20378 -> 20378 | AQ64: =AM64-AO64 -> -20378 | AS64: =AR64/$D$16 -> 0 | AT64: =20378 -> 20378 | AV64: =AR64-AT64 -> -20378 | AX64: =AW64/$D$16 -> 0 | AY64: =20378 -> 20378 | BA64: =AW64-AY64 -> -20378 | BC64: =BB64/$D$16 -> 0 | BD64: =20378 -> 20378 | BF64: =BB64-BD64 -> -20378 | BH64: =BG64/$D$16 -> 0 | BI64: =20378 -> 20378 | BK64: =BG64-BI64 -> -20378 | BL64: =SUM(D64,I64,N64,S64,X64,AC64,AH64,AM64,AR64,AW64,BB64,BG64) -> 111132.7 | BM64: =BL64/$BL$16 -> 0.00249839 | BN64: =F64+K64+P64+U64+Z64+AE64+AJ64+AO64+AT64+AY64+BD64+BI64 -> 244536 | BP64: =BL64-BN64 -> -133403.3 | BQ64: 878274.1 | BR64: =BQ64/$BQ$16 -> 0.0031993942
A65: Imobilizado | C65: ( - ) Investimentos/Imobilizado | D65: =SUMIF(EXTRATO!$F$14:$F$194,"Imobilizado",EXTRATO!$I$14:$I$194)+SUMIF(DESPESA!$E$4:$E$140,"Imobilizado",DESPESA!$I$4:$I$140) -> 290508.28 | E65: =D65/$D$16 -> 0.012422111 | F65: 120000 | H65: =D65-F65 -> 170508.28 | I65: =SUMIF(EXTRATO!$F$14:$F$194,"Imobilizado",EXTRATO!$J$14:$J$194)+SUMIF(DESPESA!$E$4:$E$140,"Imobilizado",DESPESA!$J$4:$J$140) -> 363863.57 | J65: =I65/$I$16 -> 0.017248527 | K65: =120000 -> 120000 | M65: =I65-K65 -> 243863.57 | O65: =IFERROR(N65/$N$16,"") | P65: =120000 -> 120000 | Q65: =IF(P65="","",P65/$P$16) -> 0.0051038228 | R65: =N65-P65 -> -120000 | T65: =S65/$D$16 -> 0 | U65: =120000 -> 120000 | W65: =S65-U65 -> -120000 | Y65: =X65/$D$16 -> 0 | Z65: =120000 -> 120000 | AB65: =X65-Z65 -> -120000 | AD65: =AC65/$D$16 -> 0 | AE65: =120000 -> 120000 | AG65: =AC65-AE65 -> -120000 | AI65: =AH65/$D$16 -> 0 | AJ65: =120000 -> 120000 | AL65: =AH65-AJ65 -> -120000 | AN65: =AM65/$D$16 -> 0 | AO65: =120000 -> 120000 | AQ65: =AM65-AO65 -> -120000 | AS65: =AR65/$D$16 -> 0 | AT65: =120000 -> 120000 | AV65: =AR65-AT65 -> -120000 | AX65: =AW65/$D$16 -> 0 | AY65: =120000 -> 120000 | BA65: =AW65-AY65 -> -120000 | BC65: =BB65/$D$16 -> 0 | BD65: =120000 -> 120000 | BF65: =BB65-BD65 -> -120000 | BH65: =BG65/$D$16 -> 0 | BI65: =120000 -> 120000 | BK65: =BG65-BI65 -> -120000 | BL65: =SUM(D65,I65,N65,S65,X65,AC65,AH65,AM65,AR65,AW65,BB65,BG65) -> 654371.85 | BM65: =BL65/$BL$16 -> 0.014711026 | BN65: =F65+K65+P65+U65+Z65+AE65+AJ65+AO65+AT65+AY65+BD65+BI65 -> 1440000 | BP65: =BL65-BN65 -> -785628.15 | BQ65: 3716768.9 | BR65: =BQ65/$BQ$16 -> 0.013539519
C66: ( - ) Juros/IOF S/ Empréstimos | D66: =SUMIF(EXTRATO!$F$14:$F$194,"EMPJ_S",EXTRATO!$I$14:$I$194)-SUMIF(EXTRATO!$F$14:$F$194,"EMPJ_E",EXTRATO!$I$14:$I$194) -> -511.81 | E66: =D66/$D$16 -> -2.1884955e-05 | I66: =SUMIF(EXTRATO!$F$14:$F$194,"EMPJ_S",EXTRATO!$J$14:$J$194)-SUMIF(EXTRATO!$F$14:$F$194,"EMPJ_E",EXTRATO!$J$14:$J$194) -> -911.85 | J66: =I66/$I$16 -> -4.3225183e-05 | O66: =IFERROR(N66/$N$16,"") | Q66: =IF(P66="","",P66/$P$16) | R66: =N66-P66 -> 0 | T66: =S66/$D$16 -> 0 | Y66: =X66/$D$16 -> 0 | AD66: =AC66/$D$16 -> 0 | AI66: =AH66/$D$16 -> 0 | AN66: =AM66/$D$16 -> 0 | AS66: =AR66/$D$16 -> 0 | AX66: =AW66/$D$16 -> 0 | BC66: =BB66/$D$16 -> 0 | BH66: =BG66/$D$16 -> 0 | BL66: =SUM(D66,I66,N66,S66,X66,AC66,AH66,AM66,AR66,AW66,BB66,BG66) -> -1423.66 | BM66: =BL66/$BL$16 -> -3.2005502e-05 | BQ66: -12073.43 | BR66: =BQ66/$BQ$16 -> -4.3981328e-05
A67: Adto_S | C67: ( - ) Adiantamentos Efetuados | D67: =SUMIF(DESPESA!$E$4:$E$140,"Adto_S",DESPESA!$I$4:$I$140) -> 265331.33 | E67: =D67/$D$16 -> 0.011345547 | I67: =SUMIF(DESPESA!$E$4:$E$140,"Adto_S",DESPESA!$J$4:$J$140) -> 166377.89 | J67: =I67/$I$16 -> 0.0078869494 | O67: =IFERROR(N67/$N$16,"") | Q67: =IF(P67="","",P67/$P$16) | R67: =N67-P67 -> 0 | T67: =S67/$D$16 -> 0 | Y67: =X67/$D$16 -> 0 | AD67: =AC67/$D$16 -> 0 | AI67: =AH67/$D$16 -> 0 | AN67: =AM67/$D$16 -> 0 | AS67: =AR67/$D$16 -> 0 | AX67: =AW67/$D$16 -> 0 | BC67: =BB67/$D$16 -> 0 | BH67: =BG67/$D$16 -> 0 | BL67: =SUM(D67,I67,N67,S67,X67,AC67,AH67,AM67,AR67,AW67,BB67,BG67) -> 431709.22 | BM67: =BL67/$BL$16 -> 0.0097053161 | BQ67: 5652061.5 | BR67: =BQ67/$BQ$16 -> 0.020589441
C68: Entradas | D68: =IF(SUM(D69:D70)=0,0,SUM(D69:D70)) -> 0 | F68: =IF(SUM(F69:F70)=0,0,SUM(F69:F70)) -> 0 | H68: =D68-F68 -> 0 | I68: =IF(SUM(I69:I70)=0,0,SUM(I69:I70)) -> 0 | K68: =IF(SUM(K69:K70)=0,0,SUM(K69:K70)) -> 0 | M68: =I68-K68 -> 0 | N68: =IF(SUM(N69:N70)=0,0,SUM(N69:N70)) -> 0 | P68: =IF(SUM(P69:P70)=0,0,SUM(P69:P70)) -> 0 | Q68: =IF(P68="","",P68/$P$16) -> 0 | R68: =N68-P68 -> 0 | S68: =IF(SUM(S69:S70)=0,0,SUM(S69:S70)) -> 0 | U68: =IF(SUM(U69:U70)=0,0,SUM(U69:U70)) -> 0 | W68: =S68-U68 -> 0 | X68: =IF(SUM(X69:X70)=0,0,SUM(X69:X70)) -> 0 | Z68: =IF(SUM(Z69:Z70)=0,0,SUM(Z69:Z70)) -> 0 | AB68: =X68-Z68 -> 0 | AC68: =IF(SUM(AC69:AC70)=0,0,SUM(AC69:AC70)) -> 0 | AE68: =IF(SUM(AE69:AE70)=0,0,SUM(AE69:AE70)) -> 0 | AG68: =AC68-AE68 -> 0 | AH68: =IF(SUM(AH69:AH70)=0,0,SUM(AH69:AH70)) -> 0 | AJ68: =IF(SUM(AJ69:AJ70)=0,0,SUM(AJ69:AJ70)) -> 0 | AL68: =AH68-AJ68 -> 0 | AM68: =IF(SUM(AM69:AM70)=0,0,SUM(AM69:AM70)) -> 0 | AO68: =IF(SUM(AO69:AO70)=0,0,SUM(AO69:AO70)) -> 0 | AQ68: =AM68-AO68 -> 0 | AR68: =IF(SUM(AR69:AR70)=0,0,SUM(AR69:AR70)) -> 0 | AT68: =IF(SUM(AT69:AT70)=0,0,SUM(AT69:AT70)) -> 0 | AV68: =AR68-AT68 -> 0 | AW68: =IF(SUM(AW69:AW70)=0,0,SUM(AW69:AW70)) -> 0 | AY68: =IF(SUM(AY69:AY70)=0,0,SUM(AY69:AY70)) -> 0 | BA68: =AW68-AY68 -> 0 | BB68: =IF(SUM(BB69:BB70)=0,0,SUM(BB69:BB70)) -> 0 | BD68: =IF(SUM(BD69:BD70)=0,0,SUM(BD69:BD70)) -> 0 | BF68: =BB68-BD68 -> 0 | BG68: =IF(SUM(BG69:BG70)=0,0,SUM(BG69:BG70)) -> 0 | BI68: =IF(SUM(BI69:BI70)=0,0,SUM(BI69:BI70)) -> 0 | BK68: =BG68-BI68 -> 0 | BL68: =IF(SUM(BL69:BL70)=0,0,SUM(BL69:BL70)) -> 0 | BN68: =F68+K68+P68+U68+Z68+AE68+AJ68+AO68+AT68+AY68+BD68+BI68 -> 0 | BP68: =BL68-BN68 -> 0 | BQ68: =IF(SUM(BQ69:BQ70)=0,0,SUM(BQ69:BQ70)) -> 0
C69: Empréstimos | F69: 0 | H69: =D69-F69 -> 0 | K69: =0 -> 0 | M69: =I69-K69 -> 0 | P69: =0 -> 0 | Q69: =IF(P69="","",P69/$P$16) -> 0 | R69: =N69-P69 -> 0 | U69: =0 -> 0 | W69: =S69-U69 -> 0 | Z69: =0 -> 0 | AB69: =X69-Z69 -> 0 | AE69: =0 -> 0 | AG69: =AC69-AE69 -> 0 | AJ69: =0 -> 0 | AL69: =AH69-AJ69 -> 0 | AO69: =0 -> 0 | AQ69: =AM69-AO69 -> 0 | AT69: =0 -> 0 | AV69: =AR69-AT69 -> 0 | AY69: =0 -> 0 | BA69: =AW69-AY69 -> 0 | BD69: =0 -> 0 | BF69: =BB69-BD69 -> 0 | BI69: =0 -> 0 | BK69: =BG69-BI69 -> 0 | BN69: =F69+K69+P69+U69+Z69+AE69+AJ69+AO69+AT69+AY69+BD69+BI69 -> 0 | BP69: =BL69-BN69 -> 0
C70: Investimento/Imobilizado | F70: 0 | H70: =D70-F70 -> 0 | K70: =0 -> 0 | M70: =I70-K70 -> 0 | P70: =0 -> 0 | Q70: =IF(P70="","",P70/$P$16) -> 0 | R70: =N70-P70 -> 0 | U70: =0 -> 0 | W70: =S70-U70 -> 0 | Z70: =0 -> 0 | AB70: =X70-Z70 -> 0 | AE70: =0 -> 0 | AG70: =AC70-AE70 -> 0 | AJ70: =0 -> 0 | AL70: =AH70-AJ70 -> 0 | AO70: =0 -> 0 | AQ70: =AM70-AO70 -> 0 | AT70: =0 -> 0 | AV70: =AR70-AT70 -> 0 | AY70: =0 -> 0 | BA70: =AW70-AY70 -> 0 | BD70: =0 -> 0 | BF70: =BB70-BD70 -> 0 | BI70: =0 -> 0 | BK70: =BG70-BI70 -> 0 | BN70: =F70+K70+P70+U70+Z70+AE70+AJ70+AO70+AT70+AY70+BD70+BI70 -> 0 | BP70: =BL70-BN70 -> 0
C71: NCG 1 | D71: =IFERROR(D60-D62,"") -> 657347.35 | E71: =D71/$D$16 -> 0.028108121 | F71: =IFERROR(F60-F62,"") -> 1177914.2 | G71: =IFERROR(F71/$F$16,"") -> 0.055739905 | H71: =E71-G71 -> -0.027631784 | I71: =IFERROR(I60-I62,"") -> 417344.58 | J71: =I71/$I$16 -> 0.019783732 | K71: =IFERROR(K60-K62,"") -> 1250683.3 | L71: =IFERROR(K71/$K$16,"") -> 0.056111693 | M71: =J71-L71 -> -0.036327961 | N71: =IFERROR(N60-N62,"") | O71: =IFERROR(N71/$N$16,"") | P71: =IFERROR(P60-P62,"") -> 1262378.1 | Q71: =P71/P16 -> 0.053691285 | R71: =O71-Q71 -> #VALUE! | S71: =IFERROR(S60-S62,"") | T71: =S71/$D$16 -> #VALUE! | U71: =IFERROR(U60-U62,"") -> 1337599.3 | V71: =IFERROR(U71/$U$16,"") -> 0.054702484 | W71: =T71-V71 -> #VALUE! | X71: =IFERROR(X60-X62,"") | Y71: =X71/$D$16 -> #VALUE! | Z71: =IFERROR(Z60-Z62,"") -> 1394867.7 | AA71: =IFERROR(Z71/$Z$16,"") -> 0.054931771 | AB71: =Y71-AA71 -> #VALUE! | AC71: =IFERROR(AC60-AC62,"") | AD71: =AC71/$D$16 -> #VALUE! | AE71: =IFERROR(AE60-AE62,"") -> 1337599.3 | AF71: =IFERROR(AE71/$AE$16,"") -> 0.054702484 | AG71: =AD71-AF71 -> #VALUE! | AH71: =IFERROR(AH60-AH62,"") | AI71: =AH71/$D$16 -> #VALUE! | AJ71: =IFERROR(AJ60-AJ62,"") -> 1440682.4 | AK71: =IFERROR(AJ71/$AJ$16,"") -> 0.055103324 | AL71: =AI71-AK71 -> #VALUE! | AM71: =IFERROR(AM60-AM62,"") | AN71: =AM71/$D$16 -> #VALUE! | AO71: =IFERROR(AO60-AO62,"") -> 1343326.2 | AP71: =IFERROR(AO71/$AO$16,"") -> 0.054726203 | AQ71: =AN71-AP71 -> #VALUE! | AR71: =IFERROR(AR60-AR62,"") | AS71: =AR71/$D$16 -> #VALUE! | AT71: =IFERROR(AT60-AT62,"") -> 1331872.5 | AU71: =IFERROR(AT71/$AT$16,"") -> 0.054678581 | AV71: =AS71-AU71 -> #VALUE! | AW71: =IFERROR(AW60-AW62,"") | AX71: =AW71/$D$16 -> #VALUE! | AY71: =IFERROR(AY60-AY62,"") -> 1423501.9 | AZ71: =IFERROR(AY71/$AY$16,"") -> 0.055040161 | BA71: =AX71-AZ71 -> #VALUE! | BB71: =IFERROR(BB60-BB62,"") | BC71: =BB71/$D$16 -> #VALUE! | BD71: =IFERROR(BD60-BD62,"") -> 1383414 | BE71: =IFERROR(BD71/$BD$16,"") -> 0.054887282 | BF71: =BC71-BE71 -> #VALUE! | BG71: =IFERROR(BG60-BG62,"") | BH71: =BG71/$D$16 -> #VALUE! | BI71: =IFERROR(BI60-BI62,"") -> 1572399.6 | BJ71: =IFERROR(BI71/$BI$16,"") -> 0.055545743 | BK71: =BH71-BJ71 -> #VALUE! | BL71: =IFERROR(BL60-BL62,"") -> 1074691.9 | BM71: =BL71/$BL$16 -> 0.024160301 | BN71: =F71+K71+P71+U71+Z71+AE71+AJ71+AO71+AT71+AY71+BD71+BI71 -> 16256239 | BO71: =IFERROR(BN71/$BN$16,"") -> 0.05498363 | BP71: =BM71-BO71 -> -0.030823329 | BQ71: =IFERROR(BQ60-BQ62,"") -> -703432.35 | BR71: =BQ71/$BQ$16 -> -0.0025624772
A72: Socios | C72: ( - ) Sócios | D72: =SUMIF(EXTRATO!$F$14:$F$194,"socios",EXTRATO!$I$14:$I$194) -> 404076.15 | E72: =D72/$D$16 -> 0.017278264 | F72: 50003 | I72: =SUMIF(EXTRATO!$F$14:$F$194,"socios",EXTRATO!$J$14:$J$194) -> 327411.76 | J72: =I72/$I$16 -> 0.015520572 | K72: =50003 -> 50003 | O72: =IFERROR(N72/$N$16,"") | P72: =50003 -> 50003 | R72: =N72-P72 -> -50003 | T72: =S72/$D$16 -> 0 | U72: =50003 -> 50003 | Y72: =X72/$D$16 -> 0 | Z72: =50003 -> 50003 | AD72: =AC72/$D$16 -> 0 | AE72: =50003 -> 50003 | AI72: =AH72/$D$16 -> 0 | AJ72: =50003 -> 50003 | AN72: =AM72/$D$16 -> 0 | AO72: =50003 -> 50003 | AS72: =AR72/$D$16 -> 0 | AT72: =50003 -> 50003 | AX72: =AW72/$D$16 -> 0 | AY72: =50003 -> 50003 | BC72: =BB72/$D$16 -> 0 | BD72: =50003 -> 50003 | BH72: =BG72/$D$16 -> 0 | BI72: =50003 -> 50003 | BL72: =SUM(D72,I72,N72,S72,X72,AC72,AH72,AM72,AR72,AW72,BB72,BG72) -> 731487.91 | BM72: =BL72/$BL$16 -> 0.016444683 | BN72: =F72+K72+P72+U72+Z72+AE72+AJ72+AO72+AT72+AY72+BD72+BI72 -> 600036 | BQ72: 2904239.7 | BR72: =BQ72/$BQ$16 -> 0.010579621
A73: Ligadas_S | C73: ( - ) Coligadas | D73: =SUMIF(EXTRATO!$F$14:$F$194,"ligadas_s",EXTRATO!$I$14:$I$194) -> 0 | E73: =D73/$D$16 -> 0 | I73: =SUMIF(EXTRATO!$F$14:$F$194,"ligadas_s",EXTRATO!$J$14:$J$194) -> 0 | J73: =I73/$I$16 -> 0 | O73: =IFERROR(N73/$N$16,"") | R73: =N73-P73 -> 0 | T73: =S73/$D$16 -> 0 | Y73: =X73/$D$16 -> 0 | AD73: =AC73/$D$16 -> 0 | AI73: =AH73/$D$16 -> 0 | AN73: =AM73/$D$16 -> 0 | AS73: =AR73/$D$16 -> 0 | AX73: =AW73/$D$16 -> 0 | BC73: =BB73/$D$16 -> 0 | BH73: =BG73/$D$16 -> 0 | BL73: =SUM(D73,I73,N73,S73,X73,AC73,AH73,AM73,AR73,AW73,BB73,BG73) -> 0 | BM73: =BL73/$BL$16 -> 0 | BQ73: 250000 | BR73: =BQ73/$BQ$16 -> 0.00091070491
C74: NCG 2 | D74: =D71-D72-D73 -> 253271.2 | E74: =D74/$D$16 -> 0.010829857 | F74: =IFERROR(F71-F72-F73,"") -> 1127911.2 | G74: =IFERROR(F74/$F$16,"") -> 0.05337372 | H74: =E74-G74 -> -0.042543864 | I74: =I71-I72-I73 -> 89932.82 | J74: =I74/$I$16 -> 0.0042631602 | K74: =IFERROR(K71-K72-K73,"") -> 1200680.3 | L74: =IFERROR(K74/$K$16,"") -> 0.053868317 | M74: =J74-L74 -> -0.049605157 | N74: =N71-N72-N73 -> #VALUE! | O74: =IFERROR(N74/$N$16,"") | P74: =IFERROR(P71-P72-P73,"") -> 1212375.1 | Q74: =P74/P16 -> 0.051564565 | R74: =O74-Q74 -> #VALUE! | S74: =S71-S72-S73 -> #VALUE! | T74: =S74/$D$16 -> #VALUE! | U74: =IFERROR(U71-U72-U73,"") -> 1287596.3 | V74: =IFERROR(U74/$U$16,"") -> 0.05265756 | W74: =T74-V74 -> #VALUE! | X74: =X71-X72-X73 -> #VALUE! | Y74: =X74/$D$16 -> #VALUE! | Z74: =IFERROR(Z71-Z72-Z73,"") -> 1344864.7 | AA74: =IFERROR(Z74/$Z$16,"") -> 0.052962585 | AB74: =Y74-AA74 -> #VALUE! | AC74: =AC71-AC72-AC73 -> #VALUE! | AD74: =AC74/$D$16 -> #VALUE! | AE74: =IFERROR(AE71-AE72-AE73,"") -> 1287596.3 | AF74: =IFERROR(AE74/$AE$16,"") -> 0.05265756 | AG74: =AD74-AF74 -> #VALUE! | AH74: =AH71-AH72-AH73 -> #VALUE! | AI74: =AH74/$D$16 -> #VALUE! | AJ74: =IFERROR(AJ71-AJ72-AJ73,"") -> 1390679.4 | AK74: =IFERROR(AJ74/$AJ$16,"") -> 0.053190806 | AL74: =AI74-AK74 -> #VALUE! | AM74: =AM71-AM72-AM73 -> #VALUE! | AN74: =AM74/$D$16 -> #VALUE! | AO74: =IFERROR(AO71-AO72-AO73,"") -> 1293323.2 | AP74: =IFERROR(AO74/$AO$16,"") -> 0.052689114 | AQ74: =AN74-AP74 -> #VALUE! | AR74: =AR71-AR72-AR73 -> #VALUE! | AS74: =AR74/$D$16 -> #VALUE! | AT74: =IFERROR(AT71-AT72-AT73,"") -> 1281869.5 | AU74: =IFERROR(AT74/$AT$16,"") -> 0.052625762 | AV74: =AS74-AU74 -> #VALUE! | AW74: =AW71-AW72-AW73 -> #VALUE! | AX74: =AW74/$D$16 -> #VALUE! | AY74: =IFERROR(AY71-AY72-AY73,"") -> 1373498.9 | AZ74: =IFERROR(AY74/$AY$16,"") -> 0.053106779 | BA74: =AX74-AZ74 -> #VALUE! | BB74: =BB71-BB72-BB73 -> #VALUE! | BC74: =BB74/$D$16 -> #VALUE! | BD74: =IFERROR(BD71-BD72-BD73,"") -> 1333411 | BE74: =IFERROR(BD74/$BD$16,"") -> 0.052903401 | BF74: =BC74-BE74 -> #VALUE! | BG74: =BG71-BG72-BG73 -> #VALUE! | BH74: =BG74/$D$16 -> #VALUE! | BI74: =IFERROR(BI71-BI72-BI73,"") -> 1522396.6 | BJ74: =IFERROR(BI74/$BI$16,"") -> 0.053779364 | BK74: =BH74-BJ74 -> #VALUE! | BL74: =BL71-BL72-BL73 -> 343204.02 | BM74: =BL74/$BL$16 -> 0.0077156182 | BN74: =F74+K74+P74+U74+Z74+AE74+AJ74+AO74+AT74+AY74+BD74+BI74 -> 15656203 | BO74: =IFERROR(BN74/$BN$16,"") -> 0.052954123 | BP74: =BM74-BO74 -> -0.045238505 | BQ74: =BQ71-BQ72-BQ73 -> -3857672 | BR74: =BQ74/$BQ$16 -> -0.014052803
C75: Resgate | BL75: =SUM(D75,I75,N75,S75,X75,AC75,AH75,AM75,AR75,AW75,BB75,BG75) -> 0 | BQ75: 0
C76: Aplicações | BL76: =SUM(D76,I76,N76,S76,X76,AC76,AH76,AM76,AR76,AW76,BB76,BG76) -> 0 | BQ76: 0
A77: Recarga | C77: Terceiros | D77: =SUMIF(EXTRATO!$F$14:$F$194,"Recarga_S",EXTRATO!$I$14:$I$194) -> 3585 | I77: =SUMIF(EXTRATO!$F$14:$F$194,"Recarga_S",EXTRATO!$J$14:$J$194) -> 3125 | BL77: =SUM(D77,I77,N77,S77,X77,AC77,AH77,AM77,AR77,AW77,BB77,BG77) -> 6710 | BQ77: 40125
A78: Trans_S | C78: (+/-) Mvto Transitório | D78: =SUMIF(DESPESA!$E$4:$E$140,"Trans_S",DESPESA!$I$4:$I$140) -> 4465.42 | I78: =SUMIF(DESPESA!$E$4:$E$140,"Trans_S",DESPESA!$J$4:$J$140) -> 2509.7 | BL78: =SUM(D78,I78,N78,S78,X78,AC78,AH78,AM78,AR78,AW78,BB78,BG78) -> 6975.12 | BQ78: 25912.88
C79: Variação de Saldos | D79: =D74+D75-D76-D77-D78 -> 245220.78 | F79: =SUM(F74:F78) -> 1127911.2 | I79: =I74+I75-I76-I77-I78 -> 84298.12 | K79: =SUM(K74:K78) -> 1200680.3 | N79: =N74+N75-N76-N77-N78 -> #VALUE! | P79: =SUM(P74:P78) -> 1212375.1 | S79: =S74+S75-S76-S77-S78 -> #VALUE! | U79: =SUM(U74:U78) -> 1287596.3 | X79: =X74+X75-X76-X77-X78 -> #VALUE! | Z79: =SUM(Z74:Z78) -> 1344864.7 | AC79: =AC74+AC75-AC76-AC77-AC78 -> #VALUE! | AE79: =SUM(AE74:AE78) -> 1287596.3 | AH79: =AH74+AH75-AH76-AH77-AH78 -> #VALUE! | AJ79: =SUM(AJ74:AJ78) -> 1390679.4 | AM79: =AM74+AM75-AM76-AM77-AM78 -> #VALUE! | AO79: =SUM(AO74:AO78) -> 1293323.2 | AR79: =AR74+AR75-AR76-AR77-AR78 -> #VALUE! | AT79: =SUM(AT74:AT78) -> 1281869.5 | AW79: =AW74+AW75-AW76-AW77-AW78 -> #VALUE! | AY79: =SUM(AY74:AY78) -> 1373498.9 | BB79: =BB74+BB75-BB76-BB77-BB78 -> #VALUE! | BD79: =SUM(BD74:BD78) -> 1333411 | BG79: =BG74+BG75-BG76-BG77-BG78 -> #VALUE! | BI79: =SUM(BI74:BI78) -> 1522396.6 | BL79: =BL74+BL75-BL76-BL77-BL78 -> 329518.9 | BN79: =F79+K79+P79+U79+Z79+AE79+AJ79+AO79+AT79+AY79+BD79+BI79 -> 15656203 | BQ79: =BQ74+BQ75-BQ76-BQ77-BQ78 -> -3923709.9
I82: =I79-'E-25'!J10 -> 224071.69

Sheet DASHBOARD (2)
B2: 📊 ANÁLISE ORÇAMENTÁRIA 2026 | E2: 📅 MÊS: | F2: Fevereiro | Q2: =F2 -> Fevereiro | W2: =IFERROR(MATCH(Q2,V197:V208,0),3) -> 2
B3: ="Mês de referência: "&Q2&" | Fonte: CLAUD 2026 | Atualizado Dinamicamente" -> Mês de referência: Fevereiro | Fonte: CLAUD 2026 | Atualizado Dinamicamente | W3: {=IFERROR(INDEX(X197:X208,W2),14)} -> 9
B4: ★ = Valores projetados (sem realizado informado no mês selecionado) | W4: {=IFERROR(INDEX(Y197:Y208,W2),16)} -> 11
B5: ="▶ INDICADORES DO MÊS — "&Q2 -> ▶ INDICADORES DO MÊS — Fevereiro | N5: 📋 LEGENDA — RATING DE ASSERTIVIDADE
B6: INDICADOR | C6: ✅ REALIZADO | D6: 🎯 ORÇADO | E6: ↔ GAP R$ | F6: GAP % | G6: ★ RATING | H6: █ PROGRESSO | I6: 📈 REAL. ACUM. | J6: 🎯 ORC. ACUM. | K6: GAP% ACUM. | L6: ★ RATING ACUM. | M6: █ PROGRESSO ACUM. | N6: ⭐ | O6: GAP > 30% | P6: Crítico — desvio muito alto
B7: ─── RESULTADO GERAL | H7: =IF(OR(D7="",D7=0),"",_xlfn.LET(_xlpm.real,IF(C7="",0,C7),_xlpm.orc,D7,_xlpm.pct,MIN(MAX(_xlpm.real/_xlpm.orc,0),1.5),_xlpm.bars,ROUND(MIN(_xlpm.pct,1)*10,0),TEXT(ROUND(_xlpm.pct*100,0),"0")&"% "&REPT("█",_xlpm.bars)&REPT("░",MAX(0,10-_xlpm.bars)))) | N7: ⭐⭐ | O7: 20% < GAP ≤ 30% | P7: Ruim — desvio alto
B8: 💰 Receita Líquida | C8: {=IFERROR(IF(INDEX(CLAUDE!16:16,1,$W$3)=0,"",TEXT(ROUND(INDEX(CLAUDE!16:16,1,$W$3),0),"#.##0")),"─")} -> 21.095.341 | D8: {=IFERROR(TEXT(ROUND(INDEX(CLAUDE!16:16,1,$W$4),0),"#.##0"),"─")} -> 22.289.175 | E8: =IF(U8=0,"",IF(U8-V8>=0,"+","-")&TEXT(ABS(ROUND(U8-V8,0)),"#.##0")) -> -1.193.834 | F8: =IF(OR(U8=0,V8=0),"",TEXT(ABS(U8/V8-1),"0,0%")&IF(U8>=V8,"↑","↓")) -> 5,4%↓ | G8: =IF(OR(U8=0,V8=0),"",IF(ABS(U8/V8-1)>0.3,"⭐",IF(ABS(U8/V8-1)>0.2,"⭐⭐",IF(ABS(U8/V8-1)>0.1,"⭐⭐⭐",IF(ABS(U8/V8-1)>0.05,"⭐⭐⭐⭐","⭐⭐⭐⭐⭐"))))) -> ⭐⭐⭐⭐ | H8: =IF(OR(D8="",D8=0),"",IF(C8="","⏳ sem dados ░░░░░░░░░░░░",_xlfn.LET(_xlpm.pct,C8/D8,_xlpm.filled,MIN(ROUND(MIN(_xlpm.pct,1)*12,0),12),IF(_xlpm.pct>=1,"✓","!")&" "&TEXT(ROUND(_xlpm.pct*100,1),"0.0")&"% "&REPT("█",_xlpm.filled)&REPT("░",MAX(0,12-_xlpm.filled))))) -> ! 95% ███████████░ | I8: =IF(AB8=0,"─",TEXT(ROUND(AB8,0),"#.##0")) -> 44.481.727 | J8: =IF(AC8=0,"─",TEXT(ROUND(AC8,0),"#.##0")) -> 43.421.508 | K8: =IF(OR(AB8=0,AC8=0),"",TEXT(ABS(AB8/AC8-1),"0,0%")&IF(AB8>=AC8,"↑","↓")) -> 2,4%↑ | L8: =IF(OR(AB8=0,AC8=0),"",IF(ABS(AB8/AC8-1)>0.3,"⭐",IF(ABS(AB8/AC8-1)>0.2,"⭐⭐",IF(ABS(AB8/AC8-1)>0.1,"⭐⭐⭐",IF(ABS(AB8/AC8-1)>0.05,"⭐⭐⭐⭐","⭐⭐⭐⭐⭐"))))) -> ⭐⭐⭐⭐⭐ | M8: =IF(OR(AC8=0),"",IF(AB8=0,"⏳ sem dados ░░░░░░░░░░░░",_xlfn.LET(_xlpm.pct,AB8/AC8,_xlpm.filled,MIN(ROUND(MIN(_xlpm.pct,1)*12,0),12),TEXT(ROUND(_xlpm.pct*100,1),"0.0")&"% "&REPT("█",_xlpm.filled)&REPT("░",MAX(0,12-_xlpm.filled))))) -> 102% ████████████ | N8: ⭐⭐⭐ | O8: 10% < GAP ≤ 20% | P8: Regular — desvio moderado | U8: {=IFERROR(VALUE(INDEX(CLAUDE!16:16,1,$W$3)),0)} -> 21095341 | V8: {=IFERROR(VALUE(INDEX(CLAUDE!16:16,1,$W$4)),0)} -> 22289175 | AB8: =IF($W$2>=1,IFERROR(VALUE(INDEX(CLAUDE!16:16,1,4)),0),0)+IF($W$2>=2,IFERROR(VALUE(INDEX(CLAUDE!16:16,1,9)),0),0)+IF($W$2>=3,IFERROR(VALUE(INDEX(CLAUDE!16:16,1,14)),0),0)+IF($W$2>=4,IFERROR(VALUE(INDEX(CLAUDE!16:16,1,19)),0),0)+IF($W$2>=5,IFERROR(VALUE(INDEX(CLAUDE!16:16,1,24)),0),0)+IF($W$2>=6,IFERROR(VALUE(INDEX(CLAUDE!16:16,1,29)),0),0)+IF($W$2>=7,IFERROR(VALUE(INDEX(CLAUDE!16:16,1,34)),0),0)+IF($W$2>=8,IFERROR(VALUE(INDEX(CLAUDE!16:16,1,39)),0),0)+IF($W$2>=9,IFERROR(VALUE(INDEX(CLAUDE!16:16,1,44)),0),0)+IF($W$2>=10,IFERROR(VALUE(INDEX(CLAUDE!16:16,1,49)),0),0)+IF($W$2>=11,IFERROR(VALUE(INDEX(CLAUDE!16:16,1,54)),0),0)+IF($W$2>=12,IFERROR(VALUE(INDEX(CLAUDE!16:16,1,59)),0),0) -> 44481727 | AC8: =IF($W$2>=1,IFERROR(VALUE(INDEX(CLAUDE!16:16,1,6)),0),0)+IF($W$2>=2,IFERROR(VALUE(INDEX(CLAUDE!16:16,1,11)),0),0)+IF($W$2>=3,IFERROR(VALUE(INDEX(CLAUDE!16:16,1,16)),0),0)+IF($W$2>=4,IFERROR(VALUE(INDEX(CLAUDE!16:16,1,21)),0),0)+IF($W$2>=5,IFERROR(VALUE(INDEX(CLAUDE!16:16,1,26)),0),0)+IF($W$2>=6,IFERROR(VALUE(INDEX(CLAUDE!16:16,1,31)),0),0)+IF($W$2>=7,IFERROR(VALUE(INDEX(CLAUDE!16:16,1,36)),0),0)+IF($W$2>=8,IFERROR(VALUE(INDEX(CLAUDE!16:16,1,41)),0),0)+IF($W$2>=9,IFERROR(VALUE(INDEX(CLAUDE!16:16,1,46)),0),0)+IF($W$2>=10,IFERROR(VALUE(INDEX(CLAUDE!16:16,1,51)),0),0)+IF($W$2>=11,IFERROR(VALUE(INDEX(CLAUDE!16:16,1,56)),0),0)+IF($W$2>=12,IFERROR(VALUE(INDEX(CLAUDE!16:16,1,61)),0),0) -> 43421508
B9: 📦 Compras | C9: {=IFERROR(IF(INDEX(CLAUDE!17:17,1,$W$3)=0,"",TEXT(ROUND(INDEX(CLAUDE!17:17,1,$W$3),0),"#.##0")),"─")} -> 16.679.785 | D9: {=IFERROR(TEXT(ROUND(INDEX(CLAUDE!17:17,1,$W$4),0),"#.##0"),"─")} -> 16.716.881 | E9: =IF(U9=0,"",IF(U9-V9>=0,"+","-")&TEXT(ABS(ROUND(U9-V9,0)),"#.##0")) -> -37.097 | F9: =IF(OR(U9=0,V9=0),"",TEXT(ABS(U9/V9-1),"0,0%")&IF(U9>=V9,"↑","↓")) -> 0,2%↓ | G9: =IF(OR(U9=0,V9=0),"",IF(ABS(U9/V9-1)>0.3,"⭐",IF(ABS(U9/V9-1)>0.2,"⭐⭐",IF(ABS(U9/V9-1)>0.1,"⭐⭐⭐",IF(ABS(U9/V9-1)>0.05,"⭐⭐⭐⭐","⭐⭐⭐⭐⭐"))))) -> ⭐⭐⭐⭐⭐ | H9: =IF(OR(D9="",D9=0),"",IF(C9="","⏳ sem dados ░░░░░░░░░░░░",_xlfn.LET(_xlpm.pct,C9/D9,_xlpm.filled,MIN(ROUND(MIN(_xlpm.pct,1)*12,0),12),IF(_xlpm.pct<=1,"✓","⚠")&" "&TEXT(ROUND(_xlpm.pct*100,1),"0.0")&"% "&REPT("█",_xlpm.filled)&REPT("░",MAX(0,12-_xlpm.filled))))) -> ✓ 100% ████████████ | I9: =IF(AB9=0,"─",TEXT(ROUND(AB9,0),"#.##0")) -> 35.205.581 | J9: =IF(AC9=0,"─",TEXT(ROUND(AC9,0),"#.##0")) -> 32.566.131 | K9: =IF(OR(AB9=0,AC9=0),"",TEXT(ABS(AB9/AC9-1),"0,0%")&IF(AB9>=AC9,"↑","↓")) -> 8,1%↑ | L9: =IF(OR(AB9=0,AC9=0),"",IF(ABS(AB9/AC9-1)>0.3,"⭐",IF(ABS(AB9/AC9-1)>0.2,"⭐⭐",IF(ABS(AB9/AC9-1)>0.1,"⭐⭐⭐",IF(ABS(AB9/AC9-1)>0.05,"⭐⭐⭐⭐","⭐⭐⭐⭐⭐"))))) -> ⭐⭐⭐⭐ | M9: =IF(OR(AC9=0),"",IF(AB9=0,"⏳ sem dados ░░░░░░░░░░░░",_xlfn.LET(_xlpm.pct,AB9/AC9,_xlpm.filled,MIN(ROUND(MIN(_xlpm.pct,1)*12,0),12),TEXT(ROUND(_xlpm.pct*100,1),"0.0")&"% "&REPT("█",_xlpm.filled)&REPT("░",MAX(0,12-_xlpm.filled))))) -> 108% ████████████ | N9: ⭐⭐⭐⭐ | O9: 5% < GAP ≤ 10% | P9: Bom — desvio pequeno | U9: {=IFERROR(VALUE(INDEX(CLAUDE!17:17,1,$W$3)),0)} -> 16679785 | V9: {=IFERROR(VALUE(INDEX(CLAUDE!17:17,1,$W$4)),0)} -> 16716881 | AB9: =IF($W$2>=1,IFERROR(VALUE(INDEX(CLAUDE!17:17,1,4)),0),0)+IF($W$2>=2,IFERROR(VALUE(INDEX(CLAUDE!17:17,1,9)),0),0)+IF($W$2>=3,IFERROR(VALUE(INDEX(CLAUDE!17:17,1,14)),0),0)+IF($W$2>=4,IFERROR(VALUE(INDEX(CLAUDE!17:17,1,19)),0),0)+IF($W$2>=5,IFERROR(VALUE(INDEX(CLAUDE!17:17,1,24)),0),0)+IF($W$2>=6,IFERROR(VALUE(INDEX(CLAUDE!17:17,1,29)),0),0)+IF($W$2>=7,IFERROR(VALUE(INDEX(CLAUDE!17:17,1,34)),0),0)+IF($W$2>=8,IFERROR(VALUE(INDEX(CLAUDE!17:17,1,39)),0),0)+IF($W$2>=9,IFERROR(VALUE(INDEX(CLAUDE!17:17,1,44)),0),0)+IF($W$2>=10,IFERROR(VALUE(INDEX(CLAUDE!17:17,1,49)),0),0)+IF($W$2>=11,IFERROR(VALUE(INDEX(CLAUDE!17:17,1,54)),0),0)+IF($W$2>=12,IFERROR(VALUE(INDEX(CLAUDE!17:17,1,59)),0),0) -> 35205581 | AC9: =IF($W$2>=1,IFERROR(VALUE(INDEX(CLAUDE!17:17,1,6)),0),0)+IF($W$2>=2,IFERROR(VALUE(INDEX(CLAUDE!17:17,1,11)),0),0)+IF($W$2>=3,IFERROR(VALUE(INDEX(CLAUDE!17:17,1,16)),0),0)+IF($W$2>=4,IFERROR(VALUE(INDEX(CLAUDE!17:17,1,21)),0),0)+IF($W$2>=5,IFERROR(VALUE(INDEX(CLAUDE!17:17,1,26)),0),0)+IF($W$2>=6,IFERROR(VALUE(INDEX(CLAUDE!17:17,1,31)),0),0)+IF($W$2>=7,IFERROR(VALUE(INDEX(CLAUDE!17:17,1,36)),0),0)+IF($W$2>=8,IFERROR(VALUE(INDEX(CLAUDE!17:17,1,41)),0),0)+IF($W$2>=9,IFERROR(VALUE(INDEX(CLAUDE!17:17,1,46)),0),0)+IF($W$2>=10,IFERROR(VALUE(INDEX(CLAUDE!17:17,1,51)),0),0)+IF($W$2>=11,IFERROR(VALUE(INDEX(CLAUDE!17:17,1,56)),0),0)+IF($W$2>=12,IFERROR(VALUE(INDEX(CLAUDE!17:17,1,61)),0),0) -> 32566131
B10: 📈 Margem de Venda | C10: {=IFERROR(IF(INDEX(CLAUDE!18:18,1,$W$3)=0,"",TEXT(ROUND(INDEX(CLAUDE!18:18,1,$W$3),0),"#.##0")),"─")} -> 4.415.557 | D10: {=IFERROR(TEXT(ROUND(INDEX(CLAUDE!18:18,1,$W$4),0),"#.##0"),"─")} -> 5.572.294 | E10: =IF(U10=0,"",IF(U10-V10>=0,"+","-")&TEXT(ABS(ROUND(U10-V10,0)),"#.##0")) -> -1.156.737 | F10: =IF(OR(U10=0,V10=0),"",TEXT(ABS(U10/V10-1),"0,0%")&IF(U10>=V10,"↑","↓")) -> 20,8%↓ | G10: =IF(OR(U10=0,V10=0),"",IF(ABS(U10/V10-1)>0.3,"⭐",IF(ABS(U10/V10-1)>0.2,"⭐⭐",IF(ABS(U10/V10-1)>0.1,"⭐⭐⭐",IF(ABS(U10/V10-1)>0.05,"⭐⭐⭐⭐","⭐⭐⭐⭐⭐"))))) -> ⭐⭐ | H10: =IF(OR(D10="",D10=0),"",IF(C10="","⏳ sem dados ░░░░░░░░░░░░",_xlfn.LET(_xlpm.pct,C10/D10,_xlpm.filled,MIN(ROUND(MIN(_xlpm.pct,1)*12,0),12),IF(_xlpm.pct>=1,"✓","!")&" "&TEXT(ROUND(_xlpm.pct*100,1),"0.0")&"% "&REPT("█",_xlpm.filled)&REPT("░",MAX(0,12-_xlpm.filled))))) -> ! 79% ██████████░░ | I10: =IF(AB10=0,"─",TEXT(ROUND(AB10,0),"#.##0")) -> 9.276.146 | J10: =IF(AC10=0,"─",TEXT(ROUND(AC10,0),"#.##0")) -> 10.855.377 | K10: =IF(OR(AB10=0,AC10=0),"",TEXT(ABS(AB10/AC10-1),"0,0%")&IF(AB10>=AC10,"↑","↓")) -> 14,5%↓ | L10: =IF(OR(AB10=0,AC10=0),"",IF(ABS(AB10/AC10-1)>0.3,"⭐",IF(ABS(AB10/AC10-1)>0.2,"⭐⭐",IF(ABS(AB10/AC10-1)>0.1,"⭐⭐⭐",IF(ABS(AB10/AC10-1)>0.05,"⭐⭐⭐⭐","⭐⭐⭐⭐⭐"))))) -> ⭐⭐⭐ | M10: =IF(OR(AC10=0),"",IF(AB10=0,"⏳ sem dados ░░░░░░░░░░░░",_xlfn.LET(_xlpm.pct,AB10/AC10,_xlpm.filled,MIN(ROUND(MIN(_xlpm.pct,1)*12,0),12),TEXT(ROUND(_xlpm.pct*100,1),"0.0")&"% "&REPT("█",_xlpm.filled)&REPT("░",MAX(0,12-_xlpm.filled))))) -> 86% ██████████░░ | N10: ⭐⭐⭐⭐⭐ | O10: GAP ≤ 5% | P10: Excelente — alta assertividade | U10: {=IFERROR(VALUE(INDEX(CLAUDE!18:18,1,$W$3)),0)} -> 4415556.7 | V10: {=IFERROR(VALUE(INDEX(CLAUDE!18:18,1,$W$4)),0)} -> 5572293.8 | AB10: =IF($W$2>=1,IFERROR(VALUE(INDEX(CLAUDE!18:18,1,4)),0),0)+IF($W$2>=2,IFERROR(VALUE(INDEX(CLAUDE!18:18,1,9)),0),0)+IF($W$2>=3,IFERROR(VALUE(INDEX(CLAUDE!18:18,1,14)),0),0)+IF($W$2>=4,IFERROR(VALUE(INDEX(CLAUDE!18:18,1,19)),0),0)+IF($W$2>=5,IFERROR(VALUE(INDEX(CLAUDE!18:18,1,24)),0),0)+IF($W$2>=6,IFERROR(VALUE(INDEX(CLAUDE!18:18,1,29)),0),0)+IF($W$2>=7,IFERROR(VALUE(INDEX(CLAUDE!18:18,1,34)),0),0)+IF($W$2>=8,IFERROR(VALUE(INDEX(CLAUDE!18:18,1,39)),0),0)+IF($W$2>=9,IFERROR(VALUE(INDEX(CLAUDE!18:18,1,44)),0),0)+IF($W$2>=10,IFERROR(VALUE(INDEX(CLAUDE!18:18,1,49)),0),0)+IF($W$2>=11,IFERROR(VALUE(INDEX(CLAUDE!18:18,1,54)),0),0)+IF($W$2>=12,IFERROR(VALUE(INDEX(CLAUDE!18:18,1,59)),0),0) -> 9276146.1 | AC10: =IF($W$2>=1,IFERROR(VALUE(INDEX(CLAUDE!18:18,1,6)),0),0)+IF($W$2>=2,IFERROR(VALUE(INDEX(CLAUDE!18:18,1,11)),0),0)+IF($W$2>=3,IFERROR(VALUE(INDEX(CLAUDE!18:18,1,16)),0),0)+IF($W$2>=4,IFERROR(VALUE(INDEX(CLAUDE!18:18,1,21)),0),0)+IF($W$2>=5,IFERROR(VALUE(INDEX(CLAUDE!18:18,1,26)),0),0)+IF($W$2>=6,IFERROR(VALUE(INDEX(CLAUDE!18:18,1,31)),0),0)+IF($W$2>=7,IFERROR(VALUE(INDEX(CLAUDE!18:18,1,36)),0),0)+IF($W$2>=8,IFERROR(VALUE(INDEX(CLAUDE!18:18,1,41)),0),0)+IF($W$2>=9,IFERROR(VALUE(INDEX(CLAUDE!18:18,1,46)),0),0)+IF($W$2>=10,IFERROR(VALUE(INDEX(CLAUDE!18:18,1,51)),0),0)+IF($W$2>=11,IFERROR(VALUE(INDEX(CLAUDE!18:18,1,56)),0),0)+IF($W$2>=12,IFERROR(VALUE(INDEX(CLAUDE!18:18,1,61)),0),0) -> 10855377
B11: 🏷️ Impostos s/ Vendas | C11: {=IFERROR(IF(INDEX(CLAUDE!19:19,1,$W$3)=0,"",TEXT(ROUND(INDEX(CLAUDE!19:19,1,$W$3),0),"#.##0")),"─")} -> 1.215.044 | D11: {=IFERROR(TEXT(ROUND(INDEX(CLAUDE!19:19,1,$W$4),0),"#.##0"),"─")} -> 1.448.796 | E11: =IF(U11=0,"",IF(U11-V11>=0,"+","-")&TEXT(ABS(ROUND(U11-V11,0)),"#.##0")) -> -233.753 | F11: =IF(OR(U11=0,V11=0),"",TEXT(ABS(U11/V11-1),"0,0%")&IF(U11>=V11,"↑","↓")) -> 16,1%↓ | G11: =IF(OR(U11=0,V11=0),"",IF(ABS(U11/V11-1)>0.3,"⭐",IF(ABS(U11/V11-1)>0.2,"⭐⭐",IF(ABS(U11/V11-1)>0.1,"⭐⭐⭐",IF(ABS(U11/V11-1)>0.05,"⭐⭐⭐⭐","⭐⭐⭐⭐⭐"))))) -> ⭐⭐⭐ | H11: =IF(OR(D11="",D11=0),"",IF(C11="","⏳ sem dados ░░░░░░░░░░░░",_xlfn.LET(_xlpm.pct,C11/D11,_xlpm.filled,MIN(ROUND(MIN(_xlpm.pct,1)*12,0),12),IF(_xlpm.pct<=1,"✓","⚠")&" "&TEXT(ROUND(_xlpm.pct*100,1),"0.0")&"% "&REPT("█",_xlpm.filled)&REPT("░",MAX(0,12-_xlpm.filled))))) -> ✓ 84% ██████████░░ | I11: =IF(AB11=0,"─",TEXT(ROUND(AB11,0),"#.##0")) -> 2.726.279 | J11: =IF(AC11=0,"─",TEXT(ROUND(AC11,0),"#.##0")) -> 2.822.398 | K11: =IF(OR(AB11=0,AC11=0),"",TEXT(ABS(AB11/AC11-1),"0,0%")&IF(AB11>=AC11,"↑","↓")) -> 3,4%↓ | L11: =IF(OR(AB11=0,AC11=0),"",IF(ABS(AB11/AC11-1)>0.3,"⭐",IF(ABS(AB11/AC11-1)>0.2,"⭐⭐",IF(ABS(AB11/AC11-1)>0.1,"⭐⭐⭐",IF(ABS(AB11/AC11-1)>0.05,"⭐⭐⭐⭐","⭐⭐⭐⭐⭐"))))) -> ⭐⭐⭐⭐⭐ | M11: =IF(OR(AC11=0),"",IF(AB11=0,"⏳ sem dados ░░░░░░░░░░░░",_xlfn.LET(_xlpm.pct,AB11/AC11,_xlpm.filled,MIN(ROUND(MIN(_xlpm.pct,1)*12,0),12),TEXT(ROUND(_xlpm.pct*100,1),"0.0")&"% "&REPT("█",_xlpm.filled)&REPT("░",MAX(0,12-_xlpm.filled))))) -> 97% ████████████ | U11: {=IFERROR(VALUE(INDEX(CLAUDE!19:19,1,$W$3)),0)} -> 1215043.8 | V11: {=IFERROR(VALUE(INDEX(CLAUDE!19:19,1,$W$4)),0)} -> 1448796.4 | AB11: =IF($W$2>=1,IFERROR(VALUE(INDEX(CLAUDE!19:19,1,4)),0),0)+IF($W$2>=2,IFERROR(VALUE(INDEX(CLAUDE!19:19,1,9)),0),0)+IF($W$2>=3,IFERROR(VALUE(INDEX(CLAUDE!19:19,1,14)),0),0)+IF($W$2>=4,IFERROR(VALUE(INDEX(CLAUDE!19:19,1,19)),0),0)+IF($W$2>=5,IFERROR(VALUE(INDEX(CLAUDE!19:19,1,24)),0),0)+IF($W$2>=6,IFERROR(VALUE(INDEX(CLAUDE!19:19,1,29)),0),0)+IF($W$2>=7,IFERROR(VALUE(INDEX(CLAUDE!19:19,1,34)),0),0)+IF($W$2>=8,IFERROR(VALUE(INDEX(CLAUDE!19:19,1,39)),0),0)+IF($W$2>=9,IFERROR(VALUE(INDEX(CLAUDE!19:19,1,44)),0),0)+IF($W$2>=10,IFERROR(VALUE(INDEX(CLAUDE!19:19,1,49)),0),0)+IF($W$2>=11,IFERROR(VALUE(INDEX(CLAUDE!19:19,1,54)),0),0)+IF($W$2>=12,IFERROR(VALUE(INDEX(CLAUDE!19:19,1,59)),0),0) -> 2726279.1 | AC11: =IF($W$2>=1,IFERROR(VALUE(INDEX(CLAUDE!19:19,1,6)),0),0)+IF($W$2>=2,IFERROR(VALUE(INDEX(CLAUDE!19:19,1,11)),0),0)+IF($W$2>=3,IFERROR(VALUE(INDEX(CLAUDE!19:19,1,16)),0),0)+IF($W$2>=4,IFERROR(VALUE(INDEX(CLAUDE!19:19,1,21)),0),0)+IF($W$2>=5,IFERROR(VALUE(INDEX(CLAUDE!19:19,1,26)),0),0)+IF($W$2>=6,IFERROR(VALUE(INDEX(CLAUDE!19:19,1,31)),0),0)+IF($W$2>=7,IFERROR(VALUE(INDEX(CLAUDE!19:19,1,36)),0),0)+IF($W$2>=8,IFERROR(VALUE(INDEX(CLAUDE!19:19,1,41)),0),0)+IF($W$2>=9,IFERROR(VALUE(INDEX(CLAUDE!19:19,1,46)),0),0)+IF($W$2>=10,IFERROR(VALUE(INDEX(CLAUDE!19:19,1,51)),0),0)+IF($W$2>=11,IFERROR(VALUE(INDEX(CLAUDE!19:19,1,56)),0),0)+IF($W$2>=12,IFERROR(VALUE(INDEX(CLAUDE!19:19,1,61)),0),0) -> 2822398
B12: 💵 Margem Financeira | C12: {=IFERROR(IF(INDEX(CLAUDE!20:20,1,$W$3)=0,"",TEXT(ROUND(INDEX(CLAUDE!20:20,1,$W$3),0),"#.##0")),"─")} -> 3.200.513 | D12: {=IFERROR(TEXT(ROUND(INDEX(CLAUDE!20:20,1,$W$4),0),"#.##0"),"─")} -> 4.123.497 | E12: =IF(U12=0,"",IF(U12-V12>=0,"+","-")&TEXT(ABS(ROUND(U12-V12,0)),"#.##0")) -> -922.984 | F12: =IF(OR(U12=0,V12=0),"",TEXT(ABS(U12/V12-1),"0,0%")&IF(U12>=V12,"↑","↓")) -> 22,4%↓ | G12: =IF(OR(U12=0,V12=0),"",IF(ABS(U12/V12-1)>0.3,"⭐",IF(ABS(U12/V12-1)>0.2,"⭐⭐",IF(ABS(U12/V12-1)>0.1,"⭐⭐⭐",IF(ABS(U12/V12-1)>0.05,"⭐⭐⭐⭐","⭐⭐⭐⭐⭐"))))) -> ⭐⭐ | H12: =IF(OR(D12="",D12=0),"",IF(C12="","⏳ sem dados ░░░░░░░░░░░░",_xlfn.LET(_xlpm.pct,C12/D12,_xlpm.filled,MIN(ROUND(MIN(_xlpm.pct,1)*12,0),12),IF(_xlpm.pct>=1,"✓","!")&" "&TEXT(ROUND(_xlpm.pct*100,1),"0.0")&"% "&REPT("█",_xlpm.filled)&REPT("░",MAX(0,12-_xlpm.filled))))) -> ! 78% █████████░░░ | I12: =IF(AB12=0,"─",TEXT(ROUND(AB12,0),"#.##0")) -> 6.549.867 | J12: =IF(AC12=0,"─",TEXT(ROUND(AC12,0),"#.##0")) -> 8.032.979 | K12: =IF(OR(AB12=0,AC12=0),"",TEXT(ABS(AB12/AC12-1),"0,0%")&IF(AB12>=AC12,"↑","↓")) -> 18,5%↓ | L12: =IF(OR(AB12=0,AC12=0),"",IF(ABS(AB12/AC12-1)>0.3,"⭐",IF(ABS(AB12/AC12-1)>0.2,"⭐⭐",IF(ABS(AB12/AC12-1)>0.1,"⭐⭐⭐",IF(ABS(AB12/AC12-1)>0.05,"⭐⭐⭐⭐","⭐⭐⭐⭐⭐"))))) -> ⭐⭐⭐ | M12: =IF(OR(AC12=0),"",IF(AB12=0,"⏳ sem dados ░░░░░░░░░░░░",_xlfn.LET(_xlpm.pct,AB12/AC12,_xlpm.filled,MIN(ROUND(MIN(_xlpm.pct,1)*12,0),12),TEXT(ROUND(_xlpm.pct*100,1),"0.0")&"% "&REPT("█",_xlpm.filled)&REPT("░",MAX(0,12-_xlpm.filled))))) -> 82% ██████████░░ | U12: {=IFERROR(VALUE(INDEX(CLAUDE!20:20,1,$W$3)),0)} -> 3200513 | V12: {=IFERROR(VALUE(INDEX(CLAUDE!20:20,1,$W$4)),0)} -> 4123497.4 | AB12: =IF($W$2>=1,IFERROR(VALUE(INDEX(CLAUDE!20:20,1,4)),0),0)+IF($W$2>=2,IFERROR(VALUE(INDEX(CLAUDE!20:20,1,9)),0),0)+IF($W$2>=3,IFERROR(VALUE(INDEX(CLAUDE!20:20,1,14)),0),0)+IF($W$2>=4,IFERROR(VALUE(INDEX(CLAUDE!20:20,1,19)),0),0)+IF($W$2>=5,IFERROR(VALUE(INDEX(CLAUDE!20:20,1,24)),0),0)+IF($W$2>=6,IFERROR(VALUE(INDEX(CLAUDE!20:20,1,29)),0),0)+IF($W$2>=7,IFERROR(VALUE(INDEX(CLAUDE!20:20,1,34)),0),0)+IF($W$2>=8,IFERROR(VALUE(INDEX(CLAUDE!20:20,1,39)),0),0)+IF($W$2>=9,IFERROR(VALUE(INDEX(CLAUDE!20:20,1,44)),0),0)+IF($W$2>=10,IFERROR(VALUE(INDEX(CLAUDE!20:20,1,49)),0),0)+IF($W$2>=11,IFERROR(VALUE(INDEX(CLAUDE!20:20,1,54)),0),0)+IF($W$2>=12,IFERROR(VALUE(INDEX(CLAUDE!20:20,1,59)),0),0) -> 6549867 | AC12: =IF($W$2>=1,IFERROR(VALUE(INDEX(CLAUDE!20:20,1,6)),0),0)+IF($W$2>=2,IFERROR(VALUE(INDEX(CLAUDE!20:20,1,11)),0),0)+IF($W$2>=3,IFERROR(VALUE(INDEX(CLAUDE!20:20,1,16)),0),0)+IF($W$2>=4,IFERROR(VALUE(INDEX(CLAUDE!20:20,1,21)),0),0)+IF($W$2>=5,IFERROR(VALUE(INDEX(CLAUDE!20:20,1,26)),0),0)+IF($W$2>=6,IFERROR(VALUE(INDEX(CLAUDE!20:20,1,31)),0),0)+IF($W$2>=7,IFERROR(VALUE(INDEX(CLAUDE!20:20,1,36)),0),0)+IF($W$2>=8,IFERROR(VALUE(INDEX(CLAUDE!20:20,1,41)),0),0)+IF($W$2>=9,IFERROR(VALUE(INDEX(CLAUDE!20:20,1,46)),0),0)+IF($W$2>=10,IFERROR(VALUE(INDEX(CLAUDE!20:20,1,51)),0),0)+IF($W$2>=11,IFERROR(VALUE(INDEX(CLAUDE!20:20,1,56)),0),0)+IF($W$2>=12,IFERROR(VALUE(INDEX(CLAUDE!20:20,1,61)),0),0) -> 8032979
B13: 🤝 Créd. Fornecedores | C13: {=IFERROR(IF(INDEX(CLAUDE!24:24,1,$W$3)=0,"",TEXT(ROUND(INDEX(CLAUDE!24:24,1,$W$3),0),"#.##0")),"─")} -> 402.875 | D13: {=IFERROR(TEXT(ROUND(INDEX(CLAUDE!24:24,1,$W$4),0),"#.##0"),"─")} -> 371.863 | E13: =IF(U13=0,"",IF(U13-V13>=0,"+","-")&TEXT(ABS(ROUND(U13-V13,0)),"#.##0")) -> +31.013 | F13: =IF(OR(U13=0,V13=0),"",TEXT(ABS(U13/V13-1),"0,0%")&IF(U13>=V13,"↑","↓")) -> 8,3%↑ | G13: =IF(OR(U13=0,V13=0),"",IF(ABS(U13/V13-1)>0.3,"⭐",IF(ABS(U13/V13-1)>0.2,"⭐⭐",IF(ABS(U13/V13-1)>0.1,"⭐⭐⭐",IF(ABS(U13/V13-1)>0.05,"⭐⭐⭐⭐","⭐⭐⭐⭐⭐"))))) -> ⭐⭐⭐⭐ | H13: =IF(OR(D13="",D13=0),"",IF(C13="","⏳ sem dados ░░░░░░░░░░░░",_xlfn.LET(_xlpm.pct,C13/D13,_xlpm.filled,MIN(ROUND(MIN(_xlpm.pct,1)*12,0),12),IF(_xlpm.pct>=1,"✓","!")&" "&TEXT(ROUND(_xlpm.pct*100,1),"0.0")&"% "&REPT("█",_xlpm.filled)&REPT("░",MAX(0,12-_xlpm.filled))))) -> ✓ 108% ████████████ | I13: =IF(AB13=0,"─",TEXT(ROUND(AB13,0),"#.##0")) -> 849.176 | J13: =IF(AC13=0,"─",TEXT(ROUND(AC13,0),"#.##0")) -> 724.425 | K13: =IF(OR(AB13=0,AC13=0),"",TEXT(ABS(AB13/AC13-1),"0,0%")&IF(AB13>=AC13,"↑","↓")) -> 17,2%↑ | L13: =IF(OR(AB13=0,AC13=0),"",IF(ABS(AB13/AC13-1)>0.3,"⭐",IF(ABS(AB13/AC13-1)>0.2,"⭐⭐",IF(ABS(AB13/AC13-1)>0.1,"⭐⭐⭐",IF(ABS(AB13/AC13-1)>0.05,"⭐⭐⭐⭐","⭐⭐⭐⭐⭐"))))) -> ⭐⭐⭐ | M13: =IF(OR(AC13=0),"",IF(AB13=0,"⏳ sem dados ░░░░░░░░░░░░",_xlfn.LET(_xlpm.pct,AB13/AC13,_xlpm.filled,MIN(ROUND(MIN(_xlpm.pct,1)*12,0),12),TEXT(ROUND(_xlpm.pct*100,1),"0.0")&"% "&REPT("█",_xlpm.filled)&REPT("░",MAX(0,12-_xlpm.filled))))) -> 117% ████████████ | U13: {=IFERROR(VALUE(INDEX(CLAUDE!24:24,1,$W$3)),0)} -> 402875.35 | V13: {=IFERROR(VALUE(INDEX(CLAUDE!24:24,1,$W$4)),0)} -> 371862.76 | AB13: =IF($W$2>=1,IFERROR(VALUE(INDEX(CLAUDE!24:24,1,4)),0),0)+IF($W$2>=2,IFERROR(VALUE(INDEX(CLAUDE!24:24,1,9)),0),0)+IF($W$2>=3,IFERROR(VALUE(INDEX(CLAUDE!24:24,1,14)),0),0)+IF($W$2>=4,IFERROR(VALUE(INDEX(CLAUDE!24:24,1,19)),0),0)+IF($W$2>=5,IFERROR(VALUE(INDEX(CLAUDE!24:24,1,24)),0),0)+IF($W$2>=6,IFERROR(VALUE(INDEX(CLAUDE!24:24,1,29)),0),0)+IF($W$2>=7,IFERROR(VALUE(INDEX(CLAUDE!24:24,1,34)),0),0)+IF($W$2>=8,IFERROR(VALUE(INDEX(CLAUDE!24:24,1,39)),0),0)+IF($W$2>=9,IFERROR(VALUE(INDEX(CLAUDE!24:24,1,44)),0),0)+IF($W$2>=10,IFERROR(VALUE(INDEX(CLAUDE!24:24,1,49)),0),0)+IF($W$2>=11,IFERROR(VALUE(INDEX(CLAUDE!24:24,1,54)),0),0)+IF($W$2>=12,IFERROR(VALUE(INDEX(CLAUDE!24:24,1,59)),0),0) -> 849175.78 | AC13: =IF($W$2>=1,IFERROR(VALUE(INDEX(CLAUDE!24:24,1,6)),0),0)+IF($W$2>=2,IFERROR(VALUE(INDEX(CLAUDE!24:24,1,11)),0),0)+IF($W$2>=3,IFERROR(VALUE(INDEX(CLAUDE!24:24,1,16)),0),0)+IF($W$2>=4,IFERROR(VALUE(INDEX(CLAUDE!24:24,1,21)),0),0)+IF($W$2>=5,IFERROR(VALUE(INDEX(CLAUDE!24:24,1,26)),0),0)+IF($W$2>=6,IFERROR(VALUE(INDEX(CLAUDE!24:24,1,31)),0),0)+IF($W$2>=7,IFERROR(VALUE(INDEX(CLAUDE!24:24,1,36)),0),0)+IF($W$2>=8,IFERROR(VALUE(INDEX(CLAUDE!24:24,1,41)),0),0)+IF($W$2>=9,IFERROR(VALUE(INDEX(CLAUDE!24:24,1,46)),0),0)+IF($W$2>=10,IFERROR(VALUE(INDEX(CLAUDE!24:24,1,51)),0),0)+IF($W$2>=11,IFERROR(VALUE(INDEX(CLAUDE!24:24,1,56)),0),0)+IF($W$2>=12,IFERROR(VALUE(INDEX(CLAUDE!24:24,1,61)),0),0) -> 724425.28
B14: 🏷️ Lucro Bruto | C14: {=IFERROR(IF(INDEX(CLAUDE!26:26,1,$W$3)=0,"",TEXT(ROUND(INDEX(CLAUDE!26:26,1,$W$3),0),"#.##0")),"─")} -> 3.605.898 | D14: {=IFERROR(TEXT(ROUND(INDEX(CLAUDE!26:26,1,$W$4),0),"#.##0"),"─")} -> 4.520.317 | E14: =IF(U14=0,"",IF(U14-V14>=0,"+","-")&TEXT(ABS(ROUND(U14-V14,0)),"#.##0")) -> -914.419 | F14: =IF(OR(U14=0,V14=0),"",TEXT(ABS(U14/V14-1),"0,0%")&IF(U14>=V14,"↑","↓")) -> 20,2%↓ | G14: =IF(OR(U14=0,V14=0),"",IF(ABS(U14/V14-1)>0.3,"⭐",IF(ABS(U14/V14-1)>0.2,"⭐⭐",IF(ABS(U14/V14-1)>0.1,"⭐⭐⭐",IF(ABS(U14/V14-1)>0.05,"⭐⭐⭐⭐","⭐⭐⭐⭐⭐"))))) -> ⭐⭐ | H14: =IF(OR(D14="",D14=0),"",IF(C14="","⏳ sem dados ░░░░░░░░░░░░",_xlfn.LET(_xlpm.pct,C14/D14,_xlpm.filled,MIN(ROUND(MIN(_xlpm.pct,1)*12,0),12),IF(_xlpm.pct>=1,"✓","!")&" "&TEXT(ROUND(_xlpm.pct*100,1),"0.0")&"% "&REPT("█",_xlpm.filled)&REPT("░",MAX(0,12-_xlpm.filled))))) -> ! 80% ██████████░░ | I14: =IF(AB14=0,"─",TEXT(ROUND(AB14,0),"#.##0")) -> 7.593.410 | J14: =IF(AC14=0,"─",TEXT(ROUND(AC14,0),"#.##0")) -> 8.806.023 | K14: =IF(OR(AB14=0,AC14=0),"",TEXT(ABS(AB14/AC14-1),"0,0%")&IF(AB14>=AC14,"↑","↓")) -> 13,8%↓ | L14: =IF(OR(AB14=0,AC14=0),"",IF(ABS(AB14/AC14-1)>0.3,"⭐",IF(ABS(AB14/AC14-1)>0.2,"⭐⭐",IF(ABS(AB14/AC14-1)>0.1,"⭐⭐⭐",IF(ABS(AB14/AC14-1)>0.05,"⭐⭐⭐⭐","⭐⭐⭐⭐⭐"))))) -> ⭐⭐⭐ | M14: =IF(OR(AC14=0),"",IF(AB14=0,"⏳ sem dados ░░░░░░░░░░░░",_xlfn.LET(_xlpm.pct,AB14/AC14,_xlpm.filled,MIN(ROUND(MIN(_xlpm.pct,1)*12,0),12),TEXT(ROUND(_xlpm.pct*100,1),"0.0")&"% "&REPT("█",_xlpm.filled)&REPT("░",MAX(0,12-_xlpm.filled))))) -> 86% ██████████░░ | U14: {=IFERROR(VALUE(INDEX(CLAUDE!26:26,1,$W$3)),0)} -> 3605897.7 | V14: {=IFERROR(VALUE(INDEX(CLAUDE!26:26,1,$W$4)),0)} -> 4520316.9 | AB14: =IF($W$2>=1,IFERROR(VALUE(INDEX(CLAUDE!26:26,1,4)),0),0)+IF($W$2>=2,IFERROR(VALUE(INDEX(CLAUDE!26:26,1,9)),0),0)+IF($W$2>=3,IFERROR(VALUE(INDEX(CLAUDE!26:26,1,14)),0),0)+IF($W$2>=4,IFERROR(VALUE(INDEX(CLAUDE!26:26,1,19)),0),0)+IF($W$2>=5,IFERROR(VALUE(INDEX(CLAUDE!26:26,1,24)),0),0)+IF($W$2>=6,IFERROR(VALUE(INDEX(CLAUDE!26:26,1,29)),0),0)+IF($W$2>=7,IFERROR(VALUE(INDEX(CLAUDE!26:26,1,34)),0),0)+IF($W$2>=8,IFERROR(VALUE(INDEX(CLAUDE!26:26,1,39)),0),0)+IF($W$2>=9,IFERROR(VALUE(INDEX(CLAUDE!26:26,1,44)),0),0)+IF($W$2>=10,IFERROR(VALUE(INDEX(CLAUDE!26:26,1,49)),0),0)+IF($W$2>=11,IFERROR(VALUE(INDEX(CLAUDE!26:26,1,54)),0),0)+IF($W$2>=12,IFERROR(VALUE(INDEX(CLAUDE!26:26,1,59)),0),0) -> 7593409.7 | AC14: =IF($W$2>=1,IFERROR(VALUE(INDEX(CLAUDE!26:26,1,6)),0),0)+IF($W$2>=2,IFERROR(VALUE(INDEX(CLAUDE!26:26,1,11)),0),0)+IF($W$2>=3,IFERROR(VALUE(INDEX(CLAUDE!26:26,1,16)),0),0)+IF($W$2>=4,IFERROR(VALUE(INDEX(CLAUDE!26:26,1,21)),0),0)+IF($W$2>=5,IFERROR(VALUE(INDEX(CLAUDE!26:26,1,26)),0),0)+IF($W$2>=6,IFERROR(VALUE(INDEX(CLAUDE!26:26,1,31)),0),0)+IF($W$2>=7,IFERROR(VALUE(INDEX(CLAUDE!26:26,1,36)),0),0)+IF($W$2>=8,IFERROR(VALUE(INDEX(CLAUDE!26:26,1,41)),0),0)+IF($W$2>=9,IFERROR(VALUE(INDEX(CLAUDE!26:26,1,46)),0),0)+IF($W$2>=10,IFERROR(VALUE(INDEX(CLAUDE!26:26,1,51)),0),0)+IF($W$2>=11,IFERROR(VALUE(INDEX(CLAUDE!26:26,1,56)),0),0)+IF($W$2>=12,IFERROR(VALUE(INDEX(CLAUDE!26:26,1,61)),0),0) -> 8806022.5
B15: ⚡ EBITDA | C15: =IF(U15=0,"─",TEXT(ROUND(U15,0),"#.##0")) -> 778.053 | D15: =TEXT(ROUND(V15,0),"#.##0") -> 1.811.498 | E15: =IF(U15=0,"─",IF(U15-V15>=0,"+","-")&TEXT(ABS(ROUND(U15-V15,0)),"#.##0")) -> -1.033.446 | F15: =IF(OR(U15=0,V15=0),"─",TEXT(ABS(U15/V15-1),"0,0%")&IF(U15>=V15,"↑","↓")) -> 57,0%↓ | G15: =IF(OR(U15=0,V15=0),"",IF(ABS(U15/V15-1)>0.3,"⭐",IF(ABS(U15/V15-1)>0.2,"⭐⭐",IF(ABS(U15/V15-1)>0.1,"⭐⭐⭐",IF(ABS(U15/V15-1)>0.05,"⭐⭐⭐⭐","⭐⭐⭐⭐⭐"))))) -> ⭐ | H15: =IF(OR(V15=0),"",IF(U15=0,"⏳ sem dados ░░░░░░░░░░░░",_xlfn.LET(_xlpm.pct,U15/V15,_xlpm.filled,MIN(ROUND(MIN(_xlpm.pct,1)*12,0),12),IF(_xlpm.pct>=1,"✓","!")&" "&TEXT(ROUND(_xlpm.pct*100,1),"0,0")&"% "&REPT("█",_xlpm.filled)&REPT("░",MAX(0,12-_xlpm.filled))))) -> ! 43,0% █████░░░░░░░ | I15: =IF(AB15=0,"─",TEXT(ROUND(AB15,0),"#.##0")) -> 1.373.470 | J15: =IF(AC15=0,"─",TEXT(ROUND(AC15,0),"#.##0")) -> 3.262.555 | K15: =IF(OR(AB15=0,AC15=0),"",TEXT(ABS(AB15/AC15-1),"0,0%")&IF(AB15>=AC15,"↑","↓")) -> 57,9%↓ | L15: =IF(OR(AB15=0,AC15=0),"",IF(ABS(AB15/AC15-1)>0.3,"⭐",IF(ABS(AB15/AC15-1)>0.2,"⭐⭐",IF(ABS(AB15/AC15-1)>0.1,"⭐⭐⭐",IF(ABS(AB15/AC15-1)>0.05,"⭐⭐⭐⭐","⭐⭐⭐⭐⭐"))))) -> ⭐ | M15: =IF(OR(AC15=0),"",IF(AB15=0,"⏳ sem dados ░░░░░░░░░░░░",_xlfn.LET(_xlpm.pct,AB15/AC15,_xlpm.filled,MIN(ROUND(MIN(_xlpm.pct,1)*12,0),12),TEXT(ROUND(_xlpm.pct*100,1),"0.0")&"% "&REPT("█",_xlpm.filled)&REPT("░",MAX(0,12-_xlpm.filled))))) -> 42% █████░░░░░░░ | U15: {=IFERROR(VALUE(INDEX(CLAUDE!59:59,1,$W$3)),0)} -> 778052.57 | V15: {=IFERROR(VALUE(INDEX(CLAUDE!59:59,1,$W$4)),0)} -> 1811498.4 | AB15: =IF($W$2>=1,IFERROR(VALUE(INDEX(CLAUDE!59:59,1,4)),0),0)+IF($W$2>=2,IFERROR(VALUE(INDEX(CLAUDE!59:59,1,9)),0),0)+IF($W$2>=3,IFERROR(VALUE(INDEX(CLAUDE!59:59,1,14)),0),0)+IF($W$2>=4,IFERROR(VALUE(INDEX(CLAUDE!59:59,1,19)),0),0)+IF($W$2>=5,IFERROR(VALUE(INDEX(CLAUDE!59:59,1,24)),0),0)+IF($W$2>=6,IFERROR(VALUE(INDEX(CLAUDE!59:59,1,29)),0),0)+IF($W$2>=7,IFERROR(VALUE(INDEX(CLAUDE!59:59,1,34)),0),0)+IF($W$2>=8,IFERROR(VALUE(INDEX(CLAUDE!59:59,1,39)),0),0)+IF($W$2>=9,IFERROR(VALUE(INDEX(CLAUDE!59:59,1,44)),0),0)+IF($W$2>=10,IFERROR(VALUE(INDEX(CLAUDE!59:59,1,49)),0),0)+IF($W$2>=11,IFERROR(VALUE(INDEX(CLAUDE!59:59,1,54)),0),0)+IF($W$2>=12,IFERROR(VALUE(INDEX(CLAUDE!59:59,1,59)),0),0) -> 1373469.9 | AC15: =IF($W$2>=1,IFERROR(VALUE(INDEX(CLAUDE!59:59,1,6)),0),0)+IF($W$2>=2,IFERROR(VALUE(INDEX(CLAUDE!59:59,1,11)),0),0)+IF($W$2>=3,IFERROR(VALUE(INDEX(CLAUDE!59:59,1,16)),0),0)+IF($W$2>=4,IFERROR(VALUE(INDEX(CLAUDE!59:59,1,21)),0),0)+IF($W$2>=5,IFERROR(VALUE(INDEX(CLAUDE!59:59,1,26)),0),0)+IF($W$2>=6,IFERROR(VALUE(INDEX(CLAUDE!59:59,1,31)),0),0)+IF($W$2>=7,IFERROR(VALUE(INDEX(CLAUDE!59:59,1,36)),0),0)+IF($W$2>=8,IFERROR(VALUE(INDEX(CLAUDE!59:59,1,41)),0),0)+IF($W$2>=9,IFERROR(VALUE(INDEX(CLAUDE!59:59,1,46)),0),0)+IF($W$2>=10,IFERROR(VALUE(INDEX(CLAUDE!59:59,1,51)),0),0)+IF($W$2>=11,IFERROR(VALUE(INDEX(CLAUDE!59:59,1,56)),0),0)+IF($W$2>=12,IFERROR(VALUE(INDEX(CLAUDE!59:59,1,61)),0),0) -> 3262554.9
B16: ─── CUSTOS OPERACIONAIS | H16: =IF(OR(D16="",D16=0),"",_xlfn.LET(_xlpm.real,IF(C16="",0,C16),_xlpm.orc,D16,_xlpm.pct,MIN(MAX(_xlpm.real/_xlpm.orc,0),1.5),_xlpm.bars,ROUND(MIN(_xlpm.pct,1)*10,0),TEXT(ROUND(_xlpm.pct*100,0),"0")&"% "&REPT("█",_xlpm.bars)&REPT("░",MAX(0,10-_xlpm.bars))))
B17: 👥 Pessoal / Folha | C17: {=IFERROR(IF(INDEX(CLAUDE!29:29,1,$W$3)=0,"",TEXT(ROUND(INDEX(CLAUDE!29:29,1,$W$3),0),"#.##0")),"─")} -> 670.372 | D17: {=IFERROR(TEXT(ROUND(INDEX(CLAUDE!29:29,1,$W$4),0),"#.##0"),"─")} -> 1.181.326 | E17: =IF(U17=0,"",IF(U17-V17>=0,"+","-")&TEXT(ABS(ROUND(U17-V17,0)),"#.##0")) -> -510.954 | F17: =IF(OR(U17=0,V17=0),"",TEXT(ABS(U17/V17-1),"0,0%")&IF(U17>=V17,"↑","↓")) -> 43,3%↓ | G17: =IF(OR(U17=0,V17=0),"",IF(ABS(U17/V17-1)>0.3,"⭐",IF(ABS(U17/V17-1)>0.2,"⭐⭐",IF(ABS(U17/V17-1)>0.1,"⭐⭐⭐",IF(ABS(U17/V17-1)>0.05,"⭐⭐⭐⭐","⭐⭐⭐⭐⭐"))))) -> ⭐ | H17: =IF(OR(D17="",D17=0),"",IF(C17="","⏳ sem dados ░░░░░░░░░░░░",_xlfn.LET(_xlpm.pct,C17/D17,_xlpm.filled,MIN(ROUND(MIN(_xlpm.pct,1)*12,0),12),IF(_xlpm.pct<=1,"✓","⚠")&" "&TEXT(ROUND(_xlpm.pct*100,1),"0.0")&"% "&REPT("█",_xlpm.filled)&REPT("░",MAX(0,12-_xlpm.filled))))) -> ✓ 57% ███████░░░░░ | I17: =IF(AB17=0,"─",TEXT(ROUND(AB17,0),"#.##0")) -> 1.342.598 | J17: =IF(AC17=0,"─",TEXT(ROUND(AC17,0),"#.##0")) -> 1.858.028 | K17: =IF(OR(AB17=0,AC17=0),"",TEXT(ABS(AB17/AC17-1),"0,0%")&IF(AB17>=AC17,"↑","↓")) -> 27,7%↓ | L17: =IF(OR(AB17=0,AC17=0),"",IF(ABS(AB17/AC17-1)>0.3,"⭐",IF(ABS(AB17/AC17-1)>0.2,"⭐⭐",IF(ABS(AB17/AC17-1)>0.1,"⭐⭐⭐",IF(ABS(AB17/AC17-1)>0.05,"⭐⭐⭐⭐","⭐⭐⭐⭐⭐"))))) -> ⭐⭐ | M17: =IF(OR(AC17=0),"",IF(AB17=0,"⏳ sem dados ░░░░░░░░░░░░",_xlfn.LET(_xlpm.pct,AB17/AC17,_xlpm.filled,MIN(ROUND(MIN(_xlpm.pct,1)*12,0),12),TEXT(ROUND(_xlpm.pct*100,1),"0.0")&"% "&REPT("█",_xlpm.filled)&REPT("░",MAX(0,12-_xlpm.filled))))) -> 72% █████████░░░ | U17: {=IFERROR(VALUE(INDEX(CLAUDE!29:29,1,$W$3)),0)} -> 670371.83 | V17: {=IFERROR(VALUE(INDEX(CLAUDE!29:29,1,$W$4)),0)} -> 1181326.3 | AB17: =IF($W$2>=1,IFERROR(VALUE(INDEX(CLAUDE!29:29,1,4)),0),0)+IF($W$2>=2,IFERROR(VALUE(INDEX(CLAUDE!29:29,1,9)),0),0)+IF($W$2>=3,IFERROR(VALUE(INDEX(CLAUDE!29:29,1,14)),0),0)+IF($W$2>=4,IFERROR(VALUE(INDEX(CLAUDE!29:29,1,19)),0),0)+IF($W$2>=5,IFERROR(VALUE(INDEX(CLAUDE!29:29,1,24)),0),0)+IF($W$2>=6,IFERROR(VALUE(INDEX(CLAUDE!29:29,1,29)),0),0)+IF($W$2>=7,IFERROR(VALUE(INDEX(CLAUDE!29:29,1,34)),0),0)+IF($W$2>=8,IFERROR(VALUE(INDEX(CLAUDE!29:29,1,39)),0),0)+IF($W$2>=9,IFERROR(VALUE(INDEX(CLAUDE!29:29,1,44)),0),0)+IF($W$2>=10,IFERROR(VALUE(INDEX(CLAUDE!29:29,1,49)),0),0)+IF($W$2>=11,IFERROR(VALUE(INDEX(CLAUDE!29:29,1,54)),0),0)+IF($W$2>=12,IFERROR(VALUE(INDEX(CLAUDE!29:29,1,59)),0),0) -> 1342598 | AC17: =IF($W$2>=1,IFERROR(VALUE(INDEX(CLAUDE!29:29,1,6)),0),0)+IF($W$2>=2,IFERROR(VALUE(INDEX(CLAUDE!29:29,1,11)),0),0)+IF($W$2>=3,IFERROR(VALUE(INDEX(CLAUDE!29:29,1,16)),0),0)+IF($W$2>=4,IFERROR(VALUE(INDEX(CLAUDE!29:29,1,21)),0),0)+IF($W$2>=5,IFERROR(VALUE(INDEX(CLAUDE!29:29,1,26)),0),0)+IF($W$2>=6,IFERROR(VALUE(INDEX(CLAUDE!29:29,1,31)),0),0)+IF($W$2>=7,IFERROR(VALUE(INDEX(CLAUDE!29:29,1,36)),0),0)+IF($W$2>=8,IFERROR(VALUE(INDEX(CLAUDE!29:29,1,41)),0),0)+IF($W$2>=9,IFERROR(VALUE(INDEX(CLAUDE!29:29,1,46)),0),0)+IF($W$2>=10,IFERROR(VALUE(INDEX(CLAUDE!29:29,1,51)),0),0)+IF($W$2>=11,IFERROR(VALUE(INDEX(CLAUDE!29:29,1,56)),0),0)+IF($W$2>=12,IFERROR(VALUE(INDEX(CLAUDE!29:29,1,61)),0),0) -> 1858028
B18: 🏛️ Tributária | C18: {=IFERROR(IF(INDEX(CLAUDE!37:37,1,$W$3)=0,"",TEXT(ROUND(INDEX(CLAUDE!37:37,1,$W$3),0),"#.##0")),"─")} -> 28.998 | D18: {=IFERROR(TEXT(ROUND(INDEX(CLAUDE!37:37,1,$W$4),0),"#.##0"),"─")} -> 0 | E18: =IF(U18=0,"",IF(U18-V18>=0,"+","-")&TEXT(ABS(ROUND(U18-V18,0)),"#.##0")) -> +28.998 | F18: =IF(OR(U18=0,V18=0),"",TEXT(ABS(U18/V18-1),"0,0%")&IF(U18>=V18,"↑","↓")) | G18: =IF(OR(U18=0,V18=0),"",IF(ABS(U18/V18-1)>0.3,"⭐",IF(ABS(U18/V18-1)>0.2,"⭐⭐",IF(ABS(U18/V18-1)>0.1,"⭐⭐⭐",IF(ABS(U18/V18-1)>0.05,"⭐⭐⭐⭐","⭐⭐⭐⭐⭐"))))) | H18: =IF(OR(J18="─",J18="",AC18=0),"─",IF(AB18=0,"⏳ sem dados ░░░░░░░░░░░░",_xlfn.LET(_xlpm.pct,AB18/AC18,_xlpm.filled,MIN(ROUND(MIN(_xlpm.pct,1)*12,0),12),IF(_xlpm.pct<=1,"✓","⚠")&" "&TEXT(ROUND(_xlpm.pct*100,1),"0.0")&"% "&REPT("█",_xlpm.filled)&REPT("░",MAX(0,12-_xlpm.filled))))) -> ─ | I18: =IF(AB18=0,"─",TEXT(ROUND(AB18,0),"#.##0")) -> 380.117 | J18: =IF(AC18=0,"─",TEXT(ROUND(AC18,0),"#.##0")) -> ─ | K18: =IF(OR(AB18=0,AC18=0),"",TEXT(ABS(AB18/AC18-1),"0,0%")&IF(AB18>=AC18,"↑","↓")) | L18: =IF(OR(AB18=0,AC18=0),"",IF(ABS(AB18/AC18-1)>0.3,"⭐",IF(ABS(AB18/AC18-1)>0.2,"⭐⭐",IF(ABS(AB18/AC18-1)>0.1,"⭐⭐⭐",IF(ABS(AB18/AC18-1)>0.05,"⭐⭐⭐⭐","⭐⭐⭐⭐⭐"))))) | M18: =IF(OR(AC18=0),"",IF(AB18=0,"⏳ sem dados ░░░░░░░░░░░░",_xlfn.LET(_xlpm.pct,AB18/AC18,_xlpm.filled,MIN(ROUND(MIN(_xlpm.pct,1)*12,0),12),TEXT(ROUND(_xlpm.pct*100,1),"0.0")&"% "&REPT("█",_xlpm.filled)&REPT("░",MAX(0,12-_xlpm.filled))))) | U18: {=IFERROR(VALUE(INDEX(CLAUDE!37:37,1,$W$3)),0)} -> 28998.06 | V18: {=IFERROR(VALUE(INDEX(CLAUDE!37:37,1,$W$4)),0)} -> 0 | AB18: =IF($W$2>=1,IFERROR(VALUE(INDEX(CLAUDE!37:37,1,4)),0),0)+IF($W$2>=2,IFERROR(VALUE(INDEX(CLAUDE!37:37,1,9)),0),0)+IF($W$2>=3,IFERROR(VALUE(INDEX(CLAUDE!37:37,1,14)),0),0)+IF($W$2>=4,IFERROR(VALUE(INDEX(CLAUDE!37:37,1,19)),0),0)+IF($W$2>=5,IFERROR(VALUE(INDEX(CLAUDE!37:37,1,24)),0),0)+IF($W$2>=6,IFERROR(VALUE(INDEX(CLAUDE!37:37,1,29)),0),0)+IF($W$2>=7,IFERROR(VALUE(INDEX(CLAUDE!37:37,1,34)),0),0)+IF($W$2>=8,IFERROR(VALUE(INDEX(CLAUDE!37:37,1,39)),0),0)+IF($W$2>=9,IFERROR(VALUE(INDEX(CLAUDE!37:37,1,44)),0),0)+IF($W$2>=10,IFERROR(VALUE(INDEX(CLAUDE!37:37,1,49)),0),0)+IF($W$2>=11,IFERROR(VALUE(INDEX(CLAUDE!37:37,1,54)),0),0)+IF($W$2>=12,IFERROR(VALUE(INDEX(CLAUDE!37:37,1,59)),0),0) -> 380117.18 | AC18: =IF($W$2>=1,IFERROR(VALUE(INDEX(CLAUDE!37:37,1,6)),0),0)+IF($W$2>=2,IFERROR(VALUE(INDEX(CLAUDE!37:37,1,11)),0),0)+IF($W$2>=3,IFERROR(VALUE(INDEX(CLAUDE!37:37,1,16)),0),0)+IF($W$2>=4,IFERROR(VALUE(INDEX(CLAUDE!37:37,1,21)),0),0)+IF($W$2>=5,IFERROR(VALUE(INDEX(CLAUDE!37:37,1,26)),0),0)+IF($W$2>=6,IFERROR(VALUE(INDEX(CLAUDE!37:37,1,31)),0),0)+IF($W$2>=7,IFERROR(VALUE(INDEX(CLAUDE!37:37,1,36)),0),0)+IF($W$2>=8,IFERROR(VALUE(INDEX(CLAUDE!37:37,1,41)),0),0)+IF($W$2>=9,IFERROR(VALUE(INDEX(CLAUDE!37:37,1,46)),0),0)+IF($W$2>=10,IFERROR(VALUE(INDEX(CLAUDE!37:37,1,51)),0),0)+IF($W$2>=11,IFERROR(VALUE(INDEX(CLAUDE!37:37,1,56)),0),0)+IF($W$2>=12,IFERROR(VALUE(INDEX(CLAUDE!37:37,1,61)),0),0) -> 0
B19: ⚡ Energia Elétrica | C19: {=IFERROR(IF(INDEX(CLAUDE!38:38,1,$W$3)=0,"",TEXT(ROUND(INDEX(CLAUDE!38:38,1,$W$3),0),"#.##0")),"─")} -> 136.573 | D19: {=IFERROR(TEXT(ROUND(INDEX(CLAUDE!38:38,1,$W$4),0),"#.##0"),"─")} -> 106.988 | E19: =IF(U19=0,"",IF(U19-V19>=0,"+","-")&TEXT(ABS(ROUND(U19-V19,0)),"#.##0")) -> +29.585 | F19: =IF(OR(U19=0,V19=0),"",TEXT(ABS(U19/V19-1),"0,0%")&IF(U19>=V19,"↑","↓")) -> 27,7%↑ | G19: =IF(OR(U19=0,V19=0),"",IF(ABS(U19/V19-1)>0.3,"⭐",IF(ABS(U19/V19-1)>0.2,"⭐⭐",IF(ABS(U19/V19-1)>0.1,"⭐⭐⭐",IF(ABS(U19/V19-1)>0.05,"⭐⭐⭐⭐","⭐⭐⭐⭐⭐"))))) -> ⭐⭐ | H19: =IF(OR(D19="",D19=0),"",IF(C19="","⏳ sem dados ░░░░░░░░░░░░",_xlfn.LET(_xlpm.pct,C19/D19,_xlpm.filled,MIN(ROUND(MIN(_xlpm.pct,1)*12,0),12),IF(_xlpm.pct<=1,"✓","⚠")&" "&TEXT(ROUND(_xlpm.pct*100,1),"0.0")&"% "&REPT("█",_xlpm.filled)&REPT("░",MAX(0,12-_xlpm.filled))))) -> ⚠ 128% ████████████ | I19: =IF(AB19=0,"─",TEXT(ROUND(AB19,0),"#.##0")) -> 269.353 | J19: =IF(AC19=0,"─",TEXT(ROUND(AC19,0),"#.##0")) -> 208.423 | K19: =IF(OR(AB19=0,AC19=0),"",TEXT(ABS(AB19/AC19-1),"0,0%")&IF(AB19>=AC19,"↑","↓")) -> 29,2%↑ | L19: =IF(OR(AB19=0,AC19=0),"",IF(ABS(AB19/AC19-1)>0.3,"⭐",IF(ABS(AB19/AC19-1)>0.2,"⭐⭐",IF(ABS(AB19/AC19-1)>0.1,"⭐⭐⭐",IF(ABS(AB19/AC19-1)>0.05,"⭐⭐⭐⭐","⭐⭐⭐⭐⭐"))))) -> ⭐⭐ | M19: =IF(OR(AC19=0),"",IF(AB19=0,"⏳ sem dados ░░░░░░░░░░░░",_xlfn.LET(_xlpm.pct,AB19/AC19,_xlpm.filled,MIN(ROUND(MIN(_xlpm.pct,1)*12,0),12),TEXT(ROUND(_xlpm.pct*100,1),"0.0")&"% "&REPT("█",_xlpm.filled)&REPT("░",MAX(0,12-_xlpm.filled))))) -> 129% ████████████ | U19: {=IFERROR(VALUE(INDEX(CLAUDE!38:38,1,$W$3)),0)} -> 136572.56 | V19: {=IFERROR(VALUE(INDEX(CLAUDE!38:38,1,$W$4)),0)} -> 106988.04 | AB19: =IF($W$2>=1,IFERROR(VALUE(INDEX(CLAUDE!38:38,1,4)),0),0)+IF($W$2>=2,IFERROR(VALUE(INDEX(CLAUDE!38:38,1,9)),0),0)+IF($W$2>=3,IFERROR(VALUE(INDEX(CLAUDE!38:38,1,14)),0),0)+IF($W$2>=4,IFERROR(VALUE(INDEX(CLAUDE!38:38,1,19)),0),0)+IF($W$2>=5,IFERROR(VALUE(INDEX(CLAUDE!38:38,1,24)),0),0)+IF($W$2>=6,IFERROR(VALUE(INDEX(CLAUDE!38:38,1,29)),0),0)+IF($W$2>=7,IFERROR(VALUE(INDEX(CLAUDE!38:38,1,34)),0),0)+IF($W$2>=8,IFERROR(VALUE(INDEX(CLAUDE!38:38,1,39)),0),0)+IF($W$2>=9,IFERROR(VALUE(INDEX(CLAUDE!38:38,1,44)),0),0)+IF($W$2>=10,IFERROR(VALUE(INDEX(CLAUDE!38:38,1,49)),0),0)+IF($W$2>=11,IFERROR(VALUE(INDEX(CLAUDE!38:38,1,54)),0),0)+IF($W$2>=12,IFERROR(VALUE(INDEX(CLAUDE!38:38,1,59)),0),0) -> 269352.68 | AC19: =IF($W$2>=1,IFERROR(VALUE(INDEX(CLAUDE!38:38,1,6)),0),0)+IF($W$2>=2,IFERROR(VALUE(INDEX(CLAUDE!38:38,1,11)),0),0)+IF($W$2>=3,IFERROR(VALUE(INDEX(CLAUDE!38:38,1,16)),0),0)+IF($W$2>=4,IFERROR(VALUE(INDEX(CLAUDE!38:38,1,21)),0),0)+IF($W$2>=5,IFERROR(VALUE(INDEX(CLAUDE!38:38,1,26)),0),0)+IF($W$2>=6,IFERROR(VALUE(INDEX(CLAUDE!38:38,1,31)),0),0)+IF($W$2>=7,IFERROR(VALUE(INDEX(CLAUDE!38:38,1,36)),0),0)+IF($W$2>=8,IFERROR(VALUE(INDEX(CLAUDE!38:38,1,41)),0),0)+IF($W$2>=9,IFERROR(VALUE(INDEX(CLAUDE!38:38,1,46)),0),0)+IF($W$2>=10,IFERROR(VALUE(INDEX(CLAUDE!38:38,1,51)),0),0)+IF($W$2>=11,IFERROR(VALUE(INDEX(CLAUDE!38:38,1,56)),0),0)+IF($W$2>=12,IFERROR(VALUE(INDEX(CLAUDE!38:38,1,61)),0),0) -> 208423.24
B20: 🔧 Utilidades / Serv. | C20: {=IFERROR(IF(INDEX(CLAUDE!39:39,1,$W$3)=0,"",TEXT(ROUND(INDEX(CLAUDE!39:39,1,$W$3),0),"#.##0")),"─")} -> 43.095 | D20: {=IFERROR(TEXT(ROUND(INDEX(CLAUDE!39:39,1,$W$4),0),"#.##0"),"─")} -> 64.639 | E20: =IF(U20=0,"",IF(U20-V20>=0,"+","-")&TEXT(ABS(ROUND(U20-V20,0)),"#.##0")) -> -21.544 | F20: =IF(OR(U20=0,V20=0),"",TEXT(ABS(U20/V20-1),"0,0%")&IF(U20>=V20,"↑","↓")) -> 33,3%↓ | G20: =IF(OR(U20=0,V20=0),"",IF(ABS(U20/V20-1)>0.3,"⭐",IF(ABS(U20/V20-1)>0.2,"⭐⭐",IF(ABS(U20/V20-1)>0.1,"⭐⭐⭐",IF(ABS(U20/V20-1)>0.05,"⭐⭐⭐⭐","⭐⭐⭐⭐⭐"))))) -> ⭐ | H20: =IF(OR(D20="",D20=0),"",IF(C20="","⏳ sem dados ░░░░░░░░░░░░",_xlfn.LET(_xlpm.pct,C20/D20,_xlpm.filled,MIN(ROUND(MIN(_xlpm.pct,1)*12,0),12),IF(_xlpm.pct<=1,"✓","⚠")&" "&TEXT(ROUND(_xlpm.pct*100,1),"0.0")&"% "&REPT("█",_xlpm.filled)&REPT("░",MAX(0,12-_xlpm.filled))))) -> ✓ 67% ████████░░░░ | I20: =IF(AB20=0,"─",TEXT(ROUND(AB20,0),"#.##0")) -> 107.413 | J20: =IF(AC20=0,"─",TEXT(ROUND(AC20,0),"#.##0")) -> 125.922 | K20: =IF(OR(AB20=0,AC20=0),"",TEXT(ABS(AB20/AC20-1),"0,0%")&IF(AB20>=AC20,"↑","↓")) -> 14,7%↓ | L20: =IF(OR(AB20=0,AC20=0),"",IF(ABS(AB20/AC20-1)>0.3,"⭐",IF(ABS(AB20/AC20-1)>0.2,"⭐⭐",IF(ABS(AB20/AC20-1)>0.1,"⭐⭐⭐",IF(ABS(AB20/AC20-1)>0.05,"⭐⭐⭐⭐","⭐⭐⭐⭐⭐"))))) -> ⭐⭐⭐ | M20: =IF(OR(AC20=0),"",IF(AB20=0,"⏳ sem dados ░░░░░░░░░░░░",_xlfn.LET(_xlpm.pct,AB20/AC20,_xlpm.filled,MIN(ROUND(MIN(_xlpm.pct,1)*12,0),12),TEXT(ROUND(_xlpm.pct*100,1),"0.0")&"% "&REPT("█",_xlpm.filled)&REPT("░",MAX(0,12-_xlpm.filled))))) -> 85% ██████████░░ | U20: {=IFERROR(VALUE(INDEX(CLAUDE!39:39,1,$W$3)),0)} -> 43094.68 | V20: {=IFERROR(VALUE(INDEX(CLAUDE!39:39,1,$W$4)),0)} -> 64638.608 | AB20: =IF($W$2>=1,IFERROR(VALUE(INDEX(CLAUDE!39:39,1,4)),0),0)+IF($W$2>=2,IFERROR(VALUE(INDEX(CLAUDE!39:39,1,9)),0),0)+IF($W$2>=3,IFERROR(VALUE(INDEX(CLAUDE!39:39,1,14)),0),0)+IF($W$2>=4,IFERROR(VALUE(INDEX(CLAUDE!39:39,1,19)),0),0)+IF($W$2>=5,IFERROR(VALUE(INDEX(CLAUDE!39:39,1,24)),0),0)+IF($W$2>=6,IFERROR(VALUE(INDEX(CLAUDE!39:39,1,29)),0),0)+IF($W$2>=7,IFERROR(VALUE(INDEX(CLAUDE!39:39,1,34)),0),0)+IF($W$2>=8,IFERROR(VALUE(INDEX(CLAUDE!39:39,1,39)),0),0)+IF($W$2>=9,IFERROR(VALUE(INDEX(CLAUDE!39:39,1,44)),0),0)+IF($W$2>=10,IFERROR(VALUE(INDEX(CLAUDE!39:39,1,49)),0),0)+IF($W$2>=11,IFERROR(VALUE(INDEX(CLAUDE!39:39,1,54)),0),0)+IF($W$2>=12,IFERROR(VALUE(INDEX(CLAUDE!39:39,1,59)),0),0) -> 107413.29 | AC20: =IF($W$2>=1,IFERROR(VALUE(INDEX(CLAUDE!39:39,1,6)),0),0)+IF($W$2>=2,IFERROR(VALUE(INDEX(CLAUDE!39:39,1,11)),0),0)+IF($W$2>=3,IFERROR(VALUE(INDEX(CLAUDE!39:39,1,16)),0),0)+IF($W$2>=4,IFERROR(VALUE(INDEX(CLAUDE!39:39,1,21)),0),0)+IF($W$2>=5,IFERROR(VALUE(INDEX(CLAUDE!39:39,1,26)),0),0)+IF($W$2>=6,IFERROR(VALUE(INDEX(CLAUDE!39:39,1,31)),0),0)+IF($W$2>=7,IFERROR(VALUE(INDEX(CLAUDE!39:39,1,36)),0),0)+IF($W$2>=8,IFERROR(VALUE(INDEX(CLAUDE!39:39,1,41)),0),0)+IF($W$2>=9,IFERROR(VALUE(INDEX(CLAUDE!39:39,1,46)),0),0)+IF($W$2>=10,IFERROR(VALUE(INDEX(CLAUDE!39:39,1,51)),0),0)+IF($W$2>=11,IFERROR(VALUE(INDEX(CLAUDE!39:39,1,56)),0),0)+IF($W$2>=12,IFERROR(VALUE(INDEX(CLAUDE!39:39,1,61)),0),0) -> 125922.37
B21: 🔩 Manutenções | C21: {=IFERROR(IF(INDEX(CLAUDE!40:40,1,$W$3)=0,"",TEXT(ROUND(INDEX(CLAUDE!40:40,1,$W$3),0),"#.##0")),"─")} -> 64.909 | D21: {=IFERROR(TEXT(ROUND(INDEX(CLAUDE!40:40,1,$W$4),0),"#.##0"),"─")} -> 69.096 | E21: =IF(U21=0,"",IF(U21-V21>=0,"+","-")&TEXT(ABS(ROUND(U21-V21,0)),"#.##0")) -> -4.188 | F21: =IF(OR(U21=0,V21=0),"",TEXT(ABS(U21/V21-1),"0,0%")&IF(U21>=V21,"↑","↓")) -> 6,1%↓ | G21: =IF(OR(U21=0,V21=0),"",IF(ABS(U21/V21-1)>0.3,"⭐",IF(ABS(U21/V21-1)>0.2,"⭐⭐",IF(ABS(U21/V21-1)>0.1,"⭐⭐⭐",IF(ABS(U21/V21-1)>0.05,"⭐⭐⭐⭐","⭐⭐⭐⭐⭐"))))) -> ⭐⭐⭐⭐ | H21: =IF(OR(D21="",D21=0),"",IF(C21="","⏳ sem dados ░░░░░░░░░░░░",_xlfn.LET(_xlpm.pct,C21/D21,_xlpm.filled,MIN(ROUND(MIN(_xlpm.pct,1)*12,0),12),IF(_xlpm.pct<=1,"✓","⚠")&" "&TEXT(ROUND(_xlpm.pct*100,1),"0.0")&"% "&REPT("█",_xlpm.filled)&REPT("░",MAX(0,12-_xlpm.filled))))) -> ✓ 94% ███████████░ | I21: =IF(AB21=0,"─",TEXT(ROUND(AB21,0),"#.##0")) -> 153.393 | J21: =IF(AC21=0,"─",TEXT(ROUND(AC21,0),"#.##0")) -> 134.607 | K21: =IF(OR(AB21=0,AC21=0),"",TEXT(ABS(AB21/AC21-1),"0,0%")&IF(AB21>=AC21,"↑","↓")) -> 14,0%↑ | L21: =IF(OR(AB21=0,AC21=0),"",IF(ABS(AB21/AC21-1)>0.3,"⭐",IF(ABS(AB21/AC21-1)>0.2,"⭐⭐",IF(ABS(AB21/AC21-1)>0.1,"⭐⭐⭐",IF(ABS(AB21/AC21-1)>0.05,"⭐⭐⭐⭐","⭐⭐⭐⭐⭐"))))) -> ⭐⭐⭐ | M21: =IF(OR(AC21=0),"",IF(AB21=0,"⏳ sem dados ░░░░░░░░░░░░",_xlfn.LET(_xlpm.pct,AB21/AC21,_xlpm.filled,MIN(ROUND(MIN(_xlpm.pct,1)*12,0),12),TEXT(ROUND(_xlpm.pct*100,1),"0.0")&"% "&REPT("█",_xlpm.filled)&REPT("░",MAX(0,12-_xlpm.filled))))) -> 114% ████████████ | U21: {=IFERROR(VALUE(INDEX(CLAUDE!40:40,1,$W$3)),0)} -> 64908.81 | V21: {=IFERROR(VALUE(INDEX(CLAUDE!40:40,1,$W$4)),0)} -> 69096.443 | AB21: =IF($W$2>=1,IFERROR(VALUE(INDEX(CLAUDE!40:40,1,4)),0),0)+IF($W$2>=2,IFERROR(VALUE(INDEX(CLAUDE!40:40,1,9)),0),0)+IF($W$2>=3,IFERROR(VALUE(INDEX(CLAUDE!40:40,1,14)),0),0)+IF($W$2>=4,IFERROR(VALUE(INDEX(CLAUDE!40:40,1,19)),0),0)+IF($W$2>=5,IFERROR(VALUE(INDEX(CLAUDE!40:40,1,24)),0),0)+IF($W$2>=6,IFERROR(VALUE(INDEX(CLAUDE!40:40,1,29)),0),0)+IF($W$2>=7,IFERROR(VALUE(INDEX(CLAUDE!40:40,1,34)),0),0)+IF($W$2>=8,IFERROR(VALUE(INDEX(CLAUDE!40:40,1,39)),0),0)+IF($W$2>=9,IFERROR(VALUE(INDEX(CLAUDE!40:40,1,44)),0),0)+IF($W$2>=10,IFERROR(VALUE(INDEX(CLAUDE!40:40,1,49)),0),0)+IF($W$2>=11,IFERROR(VALUE(INDEX(CLAUDE!40:40,1,54)),0),0)+IF($W$2>=12,IFERROR(VALUE(INDEX(CLAUDE!40:40,1,59)),0),0) -> 153392.91 | AC21: =IF($W$2>=1,IFERROR(VALUE(INDEX(CLAUDE!40:40,1,6)),0),0)+IF($W$2>=2,IFERROR(VALUE(INDEX(CLAUDE!40:40,1,11)),0),0)+IF($W$2>=3,IFERROR(VALUE(INDEX(CLAUDE!40:40,1,16)),0),0)+IF($W$2>=4,IFERROR(VALUE(INDEX(CLAUDE!40:40,1,21)),0),0)+IF($W$2>=5,IFERROR(VALUE(INDEX(CLAUDE!40:40,1,26)),0),0)+IF($W$2>=6,IFERROR(VALUE(INDEX(CLAUDE!40:40,1,31)),0),0)+IF($W$2>=7,IFERROR(VALUE(INDEX(CLAUDE!40:40,1,36)),0),0)+IF($W$2>=8,IFERROR(VALUE(INDEX(CLAUDE!40:40,1,41)),0),0)+IF($W$2>=9,IFERROR(VALUE(INDEX(CLAUDE!40:40,1,46)),0),0)+IF($W$2>=10,IFERROR(VALUE(INDEX(CLAUDE!40:40,1,51)),0),0)+IF($W$2>=11,IFERROR(VALUE(INDEX(CLAUDE!40:40,1,56)),0),0)+IF($W$2>=12,IFERROR(VALUE(INDEX(CLAUDE!40:40,1,61)),0),0) -> 134606.67
B22: 🚗 Veículos | C22: {=IFERROR(IF(INDEX(CLAUDE!41:41,1,$W$3)=0,"",TEXT(ROUND(INDEX(CLAUDE!41:41,1,$W$3),0),"#.##0")),"─")} -> 61.821 | D22: {=IFERROR(TEXT(ROUND(INDEX(CLAUDE!41:41,1,$W$4),0),"#.##0"),"─")} -> 100.301 | E22: =IF(U22=0,"",IF(U22-V22>=0,"+","-")&TEXT(ABS(ROUND(U22-V22,0)),"#.##0")) -> -38.481 | F22: =IF(OR(U22=0,V22=0),"",TEXT(ABS(U22/V22-1),"0,0%")&IF(U22>=V22,"↑","↓")) -> 38,4%↓ | G22: =IF(OR(U22=0,V22=0),"",IF(ABS(U22/V22-1)>0.3,"⭐",IF(ABS(U22/V22-1)>0.2,"⭐⭐",IF(ABS(U22/V22-1)>0.1,"⭐⭐⭐",IF(ABS(U22/V22-1)>0.05,"⭐⭐⭐⭐","⭐⭐⭐⭐⭐"))))) -> ⭐ | H22: =IF(OR(D22="",D22=0),"",IF(C22="","⏳ sem dados ░░░░░░░░░░░░",_xlfn.LET(_xlpm.pct,C22/D22,_xlpm.filled,MIN(ROUND(MIN(_xlpm.pct,1)*12,0),12),IF(_xlpm.pct<=1,"✓","⚠")&" "&TEXT(ROUND(_xlpm.pct*100,1),"0.0")&"% "&REPT("█",_xlpm.filled)&REPT("░",MAX(0,12-_xlpm.filled))))) -> ✓ 62% ███████░░░░░ | I22: =IF(AB22=0,"─",TEXT(ROUND(AB22,0),"#.##0")) -> 178.640 | J22: =IF(AC22=0,"─",TEXT(ROUND(AC22,0),"#.##0")) -> 195.397 | K22: =IF(OR(AB22=0,AC22=0),"",TEXT(ABS(AB22/AC22-1),"0,0%")&IF(AB22>=AC22,"↑","↓")) -> 8,6%↓ | L22: =IF(OR(AB22=0,AC22=0),"",IF(ABS(AB22/AC22-1)>0.3,"⭐",IF(ABS(AB22/AC22-1)>0.2,"⭐⭐",IF(ABS(AB22/AC22-1)>0.1,"⭐⭐⭐",IF(ABS(AB22/AC22-1)>0.05,"⭐⭐⭐⭐","⭐⭐⭐⭐⭐"))))) -> ⭐⭐⭐⭐ | M22: =IF(OR(AC22=0),"",IF(AB22=0,"⏳ sem dados ░░░░░░░░░░░░",_xlfn.LET(_xlpm.pct,AB22/AC22,_xlpm.filled,MIN(ROUND(MIN(_xlpm.pct,1)*12,0),12),TEXT(ROUND(_xlpm.pct*100,1),"0.0")&"% "&REPT("█",_xlpm.filled)&REPT("░",MAX(0,12-_xlpm.filled))))) -> 91% ███████████░ | U22: {=IFERROR(VALUE(INDEX(CLAUDE!41:41,1,$W$3)),0)} -> 61820.73 | V22: {=IFERROR(VALUE(INDEX(CLAUDE!41:41,1,$W$4)),0)} -> 100301.29 | AB22: =IF($W$2>=1,IFERROR(VALUE(INDEX(CLAUDE!41:41,1,4)),0),0)+IF($W$2>=2,IFERROR(VALUE(INDEX(CLAUDE!41:41,1,9)),0),0)+IF($W$2>=3,IFERROR(VALUE(INDEX(CLAUDE!41:41,1,14)),0),0)+IF($W$2>=4,IFERROR(VALUE(INDEX(CLAUDE!41:41,1,19)),0),0)+IF($W$2>=5,IFERROR(VALUE(INDEX(CLAUDE!41:41,1,24)),0),0)+IF($W$2>=6,IFERROR(VALUE(INDEX(CLAUDE!41:41,1,29)),0),0)+IF($W$2>=7,IFERROR(VALUE(INDEX(CLAUDE!41:41,1,34)),0),0)+IF($W$2>=8,IFERROR(VALUE(INDEX(CLAUDE!41:41,1,39)),0),0)+IF($W$2>=9,IFERROR(VALUE(INDEX(CLAUDE!41:41,1,44)),0),0)+IF($W$2>=10,IFERROR(VALUE(INDEX(CLAUDE!41:41,1,49)),0),0)+IF($W$2>=11,IFERROR(VALUE(INDEX(CLAUDE!41:41,1,54)),0),0)+IF($W$2>=12,IFERROR(VALUE(INDEX(CLAUDE!41:41,1,59)),0),0) -> 178640.46 | AC22: =IF($W$2>=1,IFERROR(VALUE(INDEX(CLAUDE!41:41,1,6)),0),0)+IF($W$2>=2,IFERROR(VALUE(INDEX(CLAUDE!41:41,1,11)),0),0)+IF($W$2>=3,IFERROR(VALUE(INDEX(CLAUDE!41:41,1,16)),0),0)+IF($W$2>=4,IFERROR(VALUE(INDEX(CLAUDE!41:41,1,21)),0),0)+IF($W$2>=5,IFERROR(VALUE(INDEX(CLAUDE!41:41,1,26)),0),0)+IF($W$2>=6,IFERROR(VALUE(INDEX(CLAUDE!41:41,1,31)),0),0)+IF($W$2>=7,IFERROR(VALUE(INDEX(CLAUDE!41:41,1,36)),0),0)+IF($W$2>=8,IFERROR(VALUE(INDEX(CLAUDE!41:41,1,41)),0),0)+IF($W$2>=9,IFERROR(VALUE(INDEX(CLAUDE!41:41,1,46)),0),0)+IF($W$2>=10,IFERROR(VALUE(INDEX(CLAUDE!41:41,1,51)),0),0)+IF($W$2>=11,IFERROR(VALUE(INDEX(CLAUDE!41:41,1,56)),0),0)+IF($W$2>=12,IFERROR(VALUE(INDEX(CLAUDE!41:41,1,61)),0),0) -> 195396.79
B23: 🏠 Manut. Imóveis | C23: {=IFERROR(IF(INDEX(CLAUDE!42:42,1,$W$3)=0,"",TEXT(ROUND(INDEX(CLAUDE!42:42,1,$W$3),0),"#.##0")),"─")} -> 33.401 | D23: {=IFERROR(TEXT(ROUND(INDEX(CLAUDE!42:42,1,$W$4),0),"#.##0"),"─")} -> 24.518 | E23: =IF(U23=0,"",IF(U23-V23>=0,"+","-")&TEXT(ABS(ROUND(U23-V23,0)),"#.##0")) -> +8.883 | F23: =IF(OR(U23=0,V23=0),"",TEXT(ABS(U23/V23-1),"0,0%")&IF(U23>=V23,"↑","↓")) -> 36,2%↑ | G23: =IF(OR(U23=0,V23=0),"",IF(ABS(U23/V23-1)>0.3,"⭐",IF(ABS(U23/V23-1)>0.2,"⭐⭐",IF(ABS(U23/V23-1)>0.1,"⭐⭐⭐",IF(ABS(U23/V23-1)>0.05,"⭐⭐⭐⭐","⭐⭐⭐⭐⭐"))))) -> ⭐ | H23: =IF(OR(D23="",D23=0),"",IF(C23="","⏳ sem dados ░░░░░░░░░░░░",_xlfn.LET(_xlpm.pct,C23/D23,_xlpm.filled,MIN(ROUND(MIN(_xlpm.pct,1)*12,0),12),IF(_xlpm.pct<=1,"✓","⚠")&" "&TEXT(ROUND(_xlpm.pct*100,1),"0.0")&"% "&REPT("█",_xlpm.filled)&REPT("░",MAX(0,12-_xlpm.filled))))) -> ⚠ 136% ████████████ | I23: =IF(AB23=0,"─",TEXT(ROUND(AB23,0),"#.##0")) -> 44.989 | J23: =IF(AC23=0,"─",TEXT(ROUND(AC23,0),"#.##0")) -> 47.764 | K23: =IF(OR(AB23=0,AC23=0),"",TEXT(ABS(AB23/AC23-1),"0,0%")&IF(AB23>=AC23,"↑","↓")) -> 5,8%↓ | L23: =IF(OR(AB23=0,AC23=0),"",IF(ABS(AB23/AC23-1)>0.3,"⭐",IF(ABS(AB23/AC23-1)>0.2,"⭐⭐",IF(ABS(AB23/AC23-1)>0.1,"⭐⭐⭐",IF(ABS(AB23/AC23-1)>0.05,"⭐⭐⭐⭐","⭐⭐⭐⭐⭐"))))) -> ⭐⭐⭐⭐ | M23: =IF(OR(AC23=0),"",IF(AB23=0,"⏳ sem dados ░░░░░░░░░░░░",_xlfn.LET(_xlpm.pct,AB23/AC23,_xlpm.filled,MIN(ROUND(MIN(_xlpm.pct,1)*12,0),12),TEXT(ROUND(_xlpm.pct*100,1),"0.0")&"% "&REPT("█",_xlpm.filled)&REPT("░",MAX(0,12-_xlpm.filled))))) -> 94% ███████████░ | U23: {=IFERROR(VALUE(INDEX(CLAUDE!42:42,1,$W$3)),0)} -> 33400.69 | V23: {=IFERROR(VALUE(INDEX(CLAUDE!42:42,1,$W$4)),0)} -> 24518.093 | AB23: =IF($W$2>=1,IFERROR(VALUE(INDEX(CLAUDE!42:42,1,4)),0),0)+IF($W$2>=2,IFERROR(VALUE(INDEX(CLAUDE!42:42,1,9)),0),0)+IF($W$2>=3,IFERROR(VALUE(INDEX(CLAUDE!42:42,1,14)),0),0)+IF($W$2>=4,IFERROR(VALUE(INDEX(CLAUDE!42:42,1,19)),0),0)+IF($W$2>=5,IFERROR(VALUE(INDEX(CLAUDE!42:42,1,24)),0),0)+IF($W$2>=6,IFERROR(VALUE(INDEX(CLAUDE!42:42,1,29)),0),0)+IF($W$2>=7,IFERROR(VALUE(INDEX(CLAUDE!42:42,1,34)),0),0)+IF($W$2>=8,IFERROR(VALUE(INDEX(CLAUDE!42:42,1,39)),0),0)+IF($W$2>=9,IFERROR(VALUE(INDEX(CLAUDE!42:42,1,44)),0),0)+IF($W$2>=10,IFERROR(VALUE(INDEX(CLAUDE!42:42,1,49)),0),0)+IF($W$2>=11,IFERROR(VALUE(INDEX(CLAUDE!42:42,1,54)),0),0)+IF($W$2>=12,IFERROR(VALUE(INDEX(CLAUDE!42:42,1,59)),0),0) -> 44988.95 | AC23: =IF($W$2>=1,IFERROR(VALUE(INDEX(CLAUDE!42:42,1,6)),0),0)+IF($W$2>=2,IFERROR(VALUE(INDEX(CLAUDE!42:42,1,11)),0),0)+IF($W$2>=3,IFERROR(VALUE(INDEX(CLAUDE!42:42,1,16)),0),0)+IF($W$2>=4,IFERROR(VALUE(INDEX(CLAUDE!42:42,1,21)),0),0)+IF($W$2>=5,IFERROR(VALUE(INDEX(CLAUDE!42:42,1,26)),0),0)+IF($W$2>=6,IFERROR(VALUE(INDEX(CLAUDE!42:42,1,31)),0),0)+IF($W$2>=7,IFERROR(VALUE(INDEX(CLAUDE!42:42,1,36)),0),0)+IF($W$2>=8,IFERROR(VALUE(INDEX(CLAUDE!42:42,1,41)),0),0)+IF($W$2>=9,IFERROR(VALUE(INDEX(CLAUDE!42:42,1,46)),0),0)+IF($W$2>=10,IFERROR(VALUE(INDEX(CLAUDE!42:42,1,51)),0),0)+IF($W$2>=11,IFERROR(VALUE(INDEX(CLAUDE!42:42,1,56)),0),0)+IF($W$2>=12,IFERROR(VALUE(INDEX(CLAUDE!42:42,1,61)),0),0) -> 47763.659
B24: 📢 Marketing | C24: {=IFERROR(IF(INDEX(CLAUDE!43:43,1,$W$3)=0,"",TEXT(ROUND(INDEX(CLAUDE!43:43,1,$W$3),0),"#.##0")),"─")} -> 32.165 | D24: {=IFERROR(TEXT(ROUND(INDEX(CLAUDE!43:43,1,$W$4),0),"#.##0"),"─")} -> 37.892 | E24: =IF(U24=0,"",IF(U24-V24>=0,"+","-")&TEXT(ABS(ROUND(U24-V24,0)),"#.##0")) -> -5.726 | F24: =IF(OR(U24=0,V24=0),"",TEXT(ABS(U24/V24-1),"0,0%")&IF(U24>=V24,"↑","↓")) -> 15,1%↓ | G24: =IF(OR(U24=0,V24=0),"",IF(ABS(U24/V24-1)>0.3,"⭐",IF(ABS(U24/V24-1)>0.2,"⭐⭐",IF(ABS(U24/V24-1)>0.1,"⭐⭐⭐",IF(ABS(U24/V24-1)>0.05,"⭐⭐⭐⭐","⭐⭐⭐⭐⭐"))))) -> ⭐⭐⭐ | H24: =IF(OR(D24="",D24=0),"",IF(C24="","⏳ sem dados ░░░░░░░░░░░░",_xlfn.LET(_xlpm.pct,C24/D24,_xlpm.filled,MIN(ROUND(MIN(_xlpm.pct,1)*12,0),12),IF(_xlpm.pct<=1,"✓","⚠")&" "&TEXT(ROUND(_xlpm.pct*100,1),"0.0")&"% "&REPT("█",_xlpm.filled)&REPT("░",MAX(0,12-_xlpm.filled))))) -> ✓ 85% ██████████░░ | I24: =IF(AB24=0,"─",TEXT(ROUND(AB24,0),"#.##0")) -> 66.190 | J24: =IF(AC24=0,"─",TEXT(ROUND(AC24,0),"#.##0")) -> 73.817 | K24: =IF(OR(AB24=0,AC24=0),"",TEXT(ABS(AB24/AC24-1),"0,0%")&IF(AB24>=AC24,"↑","↓")) -> 10,3%↓ | L24: =IF(OR(AB24=0,AC24=0),"",IF(ABS(AB24/AC24-1)>0.3,"⭐",IF(ABS(AB24/AC24-1)>0.2,"⭐⭐",IF(ABS(AB24/AC24-1)>0.1,"⭐⭐⭐",IF(ABS(AB24/AC24-1)>0.05,"⭐⭐⭐⭐","⭐⭐⭐⭐⭐"))))) -> ⭐⭐⭐ | M24: =IF(OR(AC24=0),"",IF(AB24=0,"⏳ sem dados ░░░░░░░░░░░░",_xlfn.LET(_xlpm.pct,AB24/AC24,_xlpm.filled,MIN(ROUND(MIN(_xlpm.pct,1)*12,0),12),TEXT(ROUND(_xlpm.pct*100,1),"0.0")&"% "&REPT("█",_xlpm.filled)&REPT("░",MAX(0,12-_xlpm.filled))))) -> 90% ███████████░ | U24: {=IFERROR(VALUE(INDEX(CLAUDE!43:43,1,$W$3)),0)} -> 32165.39 | V24: {=IFERROR(VALUE(INDEX(CLAUDE!43:43,1,$W$4)),0)} -> 37891.598 | AB24: =IF($W$2>=1,IFERROR(VALUE(INDEX(CLAUDE!43:43,1,4)),0),0)+IF($W$2>=2,IFERROR(VALUE(INDEX(CLAUDE!43:43,1,9)),0),0)+IF($W$2>=3,IFERROR(VALUE(INDEX(CLAUDE!43:43,1,14)),0),0)+IF($W$2>=4,IFERROR(VALUE(INDEX(CLAUDE!43:43,1,19)),0),0)+IF($W$2>=5,IFERROR(VALUE(INDEX(CLAUDE!43:43,1,24)),0),0)+IF($W$2>=6,IFERROR(VALUE(INDEX(CLAUDE!43:43,1,29)),0),0)+IF($W$2>=7,IFERROR(VALUE(INDEX(CLAUDE!43:43,1,34)),0),0)+IF($W$2>=8,IFERROR(VALUE(INDEX(CLAUDE!43:43,1,39)),0),0)+IF($W$2>=9,IFERROR(VALUE(INDEX(CLAUDE!43:43,1,44)),0),0)+IF($W$2>=10,IFERROR(VALUE(INDEX(CLAUDE!43:43,1,49)),0),0)+IF($W$2>=11,IFERROR(VALUE(INDEX(CLAUDE!43:43,1,54)),0),0)+IF($W$2>=12,IFERROR(VALUE(INDEX(CLAUDE!43:43,1,59)),0),0) -> 66189.78 | AC24: =IF($W$2>=1,IFERROR(VALUE(INDEX(CLAUDE!43:43,1,6)),0),0)+IF($W$2>=2,IFERROR(VALUE(INDEX(CLAUDE!43:43,1,11)),0),0)+IF($W$2>=3,IFERROR(VALUE(INDEX(CLAUDE!43:43,1,16)),0),0)+IF($W$2>=4,IFERROR(VALUE(INDEX(CLAUDE!43:43,1,21)),0),0)+IF($W$2>=5,IFERROR(VALUE(INDEX(CLAUDE!43:43,1,26)),0),0)+IF($W$2>=6,IFERROR(VALUE(INDEX(CLAUDE!43:43,1,31)),0),0)+IF($W$2>=7,IFERROR(VALUE(INDEX(CLAUDE!43:43,1,36)),0),0)+IF($W$2>=8,IFERROR(VALUE(INDEX(CLAUDE!43:43,1,41)),0),0)+IF($W$2>=9,IFERROR(VALUE(INDEX(CLAUDE!43:43,1,46)),0),0)+IF($W$2>=10,IFERROR(VALUE(INDEX(CLAUDE!43:43,1,51)),0),0)+IF($W$2>=11,IFERROR(VALUE(INDEX(CLAUDE!43:43,1,56)),0),0)+IF($W$2>=12,IFERROR(VALUE(INDEX(CLAUDE!43:43,1,61)),0),0) -> 73816.564
B25: 💻 Informática | C25: {=IFERROR(IF(INDEX(CLAUDE!44:44,1,$W$3)=0,"",TEXT(ROUND(INDEX(CLAUDE!44:44,1,$W$3),0),"#.##0")),"─")} -> 54.332 | D25: {=IFERROR(TEXT(ROUND(INDEX(CLAUDE!44:44,1,$W$4),0),"#.##0"),"─")} -> 49.036 | E25: =IF(U25=0,"",IF(U25-V25>=0,"+","-")&TEXT(ABS(ROUND(U25-V25,0)),"#.##0")) -> +5.296 | F25: =IF(OR(U25=0,V25=0),"",TEXT(ABS(U25/V25-1),"0,0%")&IF(U25>=V25,"↑","↓")) -> 10,8%↑ | G25: =IF(OR(U25=0,V25=0),"",IF(ABS(U25/V25-1)>0.3,"⭐",IF(ABS(U25/V25-1)>0.2,"⭐⭐",IF(ABS(U25/V25-1)>0.1,"⭐⭐⭐",IF(ABS(U25/V25-1)>0.05,"⭐⭐⭐⭐","⭐⭐⭐⭐⭐"))))) -> ⭐⭐⭐ | H25: =IF(OR(D25="",D25=0),"",IF(C25="","⏳ sem dados ░░░░░░░░░░░░",_xlfn.LET(_xlpm.pct,C25/D25,_xlpm.filled,MIN(ROUND(MIN(_xlpm.pct,1)*12,0),12),IF(_xlpm.pct<=1,"✓","⚠")&" "&TEXT(ROUND(_xlpm.pct*100,1),"0.0")&"% "&REPT("█",_xlpm.filled)&REPT("░",MAX(0,12-_xlpm.filled))))) -> ⚠ 111% ████████████ | I25: =IF(AB25=0,"─",TEXT(ROUND(AB25,0),"#.##0")) -> 115.832 | J25: =IF(AC25=0,"─",TEXT(ROUND(AC25,0),"#.##0")) -> 95.527 | K25: =IF(OR(AB25=0,AC25=0),"",TEXT(ABS(AB25/AC25-1),"0,0%")&IF(AB25>=AC25,"↑","↓")) -> 21,3%↑ | L25: =IF(OR(AB25=0,AC25=0),"",IF(ABS(AB25/AC25-1)>0.3,"⭐",IF(ABS(AB25/AC25-1)>0.2,"⭐⭐",IF(ABS(AB25/AC25-1)>0.1,"⭐⭐⭐",IF(ABS(AB25/AC25-1)>0.05,"⭐⭐⭐⭐","⭐⭐⭐⭐⭐"))))) -> ⭐⭐ | M25: =IF(OR(AC25=0),"",IF(AB25=0,"⏳ sem dados ░░░░░░░░░░░░",_xlfn.LET(_xlpm.pct,AB25/AC25,_xlpm.filled,MIN(ROUND(MIN(_xlpm.pct,1)*12,0),12),TEXT(ROUND(_xlpm.pct*100,1),"0.0")&"% "&REPT("█",_xlpm.filled)&REPT("░",MAX(0,12-_xlpm.filled))))) -> 121% ████████████ | U25: {=IFERROR(VALUE(INDEX(CLAUDE!44:44,1,$W$3)),0)} -> 54331.93 | V25: {=IFERROR(VALUE(INDEX(CLAUDE!44:44,1,$W$4)),0)} -> 49036.185 | AB25: =IF($W$2>=1,IFERROR(VALUE(INDEX(CLAUDE!44:44,1,4)),0),0)+IF($W$2>=2,IFERROR(VALUE(INDEX(CLAUDE!44:44,1,9)),0),0)+IF($W$2>=3,IFERROR(VALUE(INDEX(CLAUDE!44:44,1,14)),0),0)+IF($W$2>=4,IFERROR(VALUE(INDEX(CLAUDE!44:44,1,19)),0),0)+IF($W$2>=5,IFERROR(VALUE(INDEX(CLAUDE!44:44,1,24)),0),0)+IF($W$2>=6,IFERROR(VALUE(INDEX(CLAUDE!44:44,1,29)),0),0)+IF($W$2>=7,IFERROR(VALUE(INDEX(CLAUDE!44:44,1,34)),0),0)+IF($W$2>=8,IFERROR(VALUE(INDEX(CLAUDE!44:44,1,39)),0),0)+IF($W$2>=9,IFERROR(VALUE(INDEX(CLAUDE!44:44,1,44)),0),0)+IF($W$2>=10,IFERROR(VALUE(INDEX(CLAUDE!44:44,1,49)),0),0)+IF($W$2>=11,IFERROR(VALUE(INDEX(CLAUDE!44:44,1,54)),0),0)+IF($W$2>=12,IFERROR(VALUE(INDEX(CLAUDE!44:44,1,59)),0),0) -> 115832.07 | AC25: =IF($W$2>=1,IFERROR(VALUE(INDEX(CLAUDE!44:44,1,6)),0),0)+IF($W$2>=2,IFERROR(VALUE(INDEX(CLAUDE!44:44,1,11)),0),0)+IF($W$2>=3,IFERROR(VALUE(INDEX(CLAUDE!44:44,1,16)),0),0)+IF($W$2>=4,IFERROR(VALUE(INDEX(CLAUDE!44:44,1,21)),0),0)+IF($W$2>=5,IFERROR(VALUE(INDEX(CLAUDE!44:44,1,26)),0),0)+IF($W$2>=6,IFERROR(VALUE(INDEX(CLAUDE!44:44,1,31)),0),0)+IF($W$2>=7,IFERROR(VALUE(INDEX(CLAUDE!44:44,1,36)),0),0)+IF($W$2>=8,IFERROR(VALUE(INDEX(CLAUDE!44:44,1,41)),0),0)+IF($W$2>=9,IFERROR(VALUE(INDEX(CLAUDE!44:44,1,46)),0),0)+IF($W$2>=10,IFERROR(VALUE(INDEX(CLAUDE!44:44,1,51)),0),0)+IF($W$2>=11,IFERROR(VALUE(INDEX(CLAUDE!44:44,1,56)),0),0)+IF($W$2>=12,IFERROR(VALUE(INDEX(CLAUDE!44:44,1,61)),0),0) -> 95527.317
